Workbook

Sheet 202202KSRheinbergerMühlen
A1: Projektname | B1: =IF(Projektinfo!B1="","",Projektinfo!B1) -> 2022-02_KS_Rheinberger/Mühlen
A2: MwSt.
A3: Typ | B3: Ordnungszahl | C3: Kurztext | D3: Langtext | E3: Menge | F3: Einheit | G3: Einheitspreis | H3: Gesamtpreis | I3: Nachlass | J3: Preis nach Nachlass | K3: MwSt.
A4: Leistungsbeschreibung | C4: 2022-02 Rheinberger Straße / Mühlenstraße Stadt Moers 2021-008
A5: Hinweistext | C5: Deckblatt_Stadt_Moers_und_ENNI | D5: Stadt Moers Fachbereich 8 - Fachdienst 8.2 - Straßen- und Verkehrsplanung und ENNI Stadt & Service Niederrhein AöR - Abteilung (LP) - Leitungsgebundene Aktivitäten Planung und Bau A n g e b o t über Straßen- und Kanalsanierung Mühlenstraße, Rheinberger Straße und Repelener Straße 1.BA -Mühlenstraße und Rheinberger Straße- | K5: ="" | M5: 996bdbb5-d876-4f8f-b35c-b8ea57e198eb
A6: Hinweistext | C6: Leistungsbeschreibung gemäß DIN 18299 | D6: Leistungsbeschreibung gemäß DIN 18299 | K6: ="" | M6: 8cf685e0-27ff-437b-988b-0d4d347fe30d
A7: Hinweistext | C7: Leistungsbeschreibung gemäß DIN 18299 | D7: Soweit in der Leistungsbeschreibung auf Technische Spezifikationen, z.B. nationale Normen, mit denen Europäische Normen umgesetzt werden, europäisch technische Bewertungen, gemeinsame technische Spezifikationen, Internationale Normen, Bezug genommen wird, werden auch ohne den ausdrücklichen Zusatz: "oder gleichwertig" immer gleichwertige Technische Spezifikationen in Bezug genommen. Digital werden dem Bieter folgende Unterlagen zur Verfügung gestellt: Leistungsbeschreibung Leistungsverzeichnis Ausführungspläne Baugrundgutachten Kampfmitteluntersuchung Verkehrskonzept Die Ausführungspläne ergänzen die vorliegenden Ausschreibungsunterlagen und sind bei der Angebotskalkulation vollständig zu berücksichtigen. Das im GAEB-Format verfügbare Leistungsverzeichnis wird dem Bieter zur Vereinfachung der Kalkulation zur Verfügung gestellt. Das Leistungsverzeichnis wurde vor Bereitstellung von der Stadt Moers hinsichtlich Fehlerhaftigkeit und Vollständigkeit geprüft. Sollten zwischen der pdf-Datei und der LV-Version im GAEB-Format dennoch Differenzen bestehen, so sind daraus keine Rechtsansprüche gegen die Stadt Moers bzw. ENNI Stadt & Service Niederrhein AöR abzuleiten. Es geht immer die übermittelte pdf-Datei der Ausschreibung rechtsverbindlich in die Wertung ein. Grundlage des zu schließenden Vertrags zwischen der Stadt Moers bzw. ENNI Stadt & Service Niederrhein AöR und dem zu beauftragenden Bieter ist die zum Zeitpunkt des Vertragsschlusses gültige Fassung der VOB/B und VOB/C. Die ZTV unter Punkt vier werden ebenfalls Vertragsbestandteil. | K7: ="" | M7: ba21e7ac-a2d6-470d-b9a2-9b4ac0f3f376
A8: Hinweistext | C8: 1. Angaben zur Baustelle | D8: 1. Angaben zur Baustelle | K8: ="" | M8: 525c6792-deb3-4538-8f1d-c3073714d80f
A9: Hinweistext | C9: 1.1 Lage der Baustelle, Umgebungsbedingungen, Zufahrtsmöglichkeiten | D9: 1.1 Lage der Baustelle, Umgebungsbedingungen, Zufahrtsmöglichkeiten, Einschränkungen Bei der Baumaßnahme handelt es sich um eine Straßen- und Kanalsanierungsmaßnahme der Straßen "Mühlenstraße und Rheinberger Straße". In beiden Straßen wird der gesamte Querschnitt (Fahrbahn + Nebenflächen) neu hergestellt, zusätzlich finden in diesen beiden Straßen Kanalsanierungen im Bereich der SW- und NW-Kanäle sowie im Bereich der Anschlussleitungen statt. Die genaue Lage ist aus dem Übersichtslageplan ersichtlich. Der Übersichtsplan liegt den Ausschreibungsunterlagen bei. | K9: ="" | M9: 600c3669-b445-46d7-b590-c8c7614ca62e
A10: Hinweistext | C10: 1.2 Besondere Belastungen aus Immissionen sowie bes. klimatische oder betriebliche Bedingungen | D10: 1.2 Besondere Belastungen aus Immissionen sowie bes. klimatische oder betriebliche Bedingungen Besondere Belastungen aus Immissionen sowie besondere klimatische oder betriebliche Bedingungen sind nicht bekannt. | K10: ="" | M10: 26b0ae1b-b92a-48c0-9a07-59d2c121c69a
A11: Hinweistext | C11: 1.3 Art und Lage der baulichen Anlagen | D11: 1.3 Art und Lage der baulichen Anlagen Gegenstand der Baumaßnahme ist die Erneuerung von Schmutz- und Regenwasserkanälen sowie die Erneuerung von öffentlichen Verkehrsflächen im Bereich der Mühlenstraße und Rheinberger Straße. Dabei sind insbesondere folgende Bauleistungen zu erbringen: DIN 18.300 Erdarbeiten DIN 18.301 Bohrarbeiten DIN 18.303 Verbauarbeiten DIN 18.305 Wasserhaltungsarbeiten DIN 18.306 Entwässerungskanalarbeiten DIN 18.317 Verkehrswegebauarbeiten, Oberbau aus Asphalt DIN 18.318 Verkehrswegebauarbeiten, Pflasterdecken DIN 18.329 Verkehrssicherungsarbeiten DIN 18.330 Maurerarbeiten DIN 18.331 Betonarbeiten Die Arbeiten haben etwa folgenden Umfang: 2246 m² Aufbruch bit. befestigte Straßenflächen, bis 15 cm 1723 m² Aufbruch bit. befestigte Straßenflächen, bis 30 cm 679 m³ Aufbruch Tragschicht, bis 22 cm, nach EBV 628 m Bordsteinanlage abbrechen und entsorgen 634 m Rinnenanlage abbrechen und entsorgen 762 m² Betonsteinpflaster aufnehmen und entsorgen 779 m² Gehwegplatten aufnehmen und entsorgen 652 m vorhandenen Kanäle abbrechen und entsorgen 15 m³ vorhandene Kanäle verdämmen 33 m vorhandene Kanalschächte abbrechen und entsorgen 647 m² Waagerechter Normverbau Anschlussleitungen 740 m² Waagerechter Normverbau Hauptkanäle 2660 m² Verbau mit Grabenverbaugerät 175 m² Stirnverbau 2288 m³ Grabenaushub 285 m Kanal DN/OD 160 PP 109 m Kanal DN 250 STZ 114 m Kanal DN 400 B 128 m Kanal DN 600 B 47 m Kanal DN 700 B 7 Stck Kanalschacht DN 1000 B 1 Stck Kanalschacht DN 1200 B 1 Stck Kanalschacht DN 1500 B 703 m² Schotter zur temporären Befestigung von Kanalgräben 17 Stck Straßenablauf 650 m Rinnenanlage 511 m Bordsteinanlage 1018 m³ Frostschutzkies 1042 m³ Schottertragschicht 2822 m² Verkehrsfläche aus Asphalt 2071 m² Verkehrsfläche aus Betonsteinpflaster Die Lage der baulichen Anlagen ist in den Ausführungsplänen angegeben. Gegenstand der Baumaßnahme ist der Neubau des vorhandenen Trennsystems der Kanalisation mit Hausanschlussleitungen inkl. provisorischer Herstellung der Straßenoberfläche (30 cm Auffüllungen und 20 cm Tragschichtmaterial sowie 10 cm Tragdeckschicht), sowie Straßensanierungsmaßnahmen. Im Rahmen der Straßensanierung werden die Fahrbahnen inklusive Nebenflächen neu hergestellt. Für den Ausbau der neu herzustellenden Verkehrsflächen in Asphaltbauweise ist für die genannten Straßen die Belastungsklasse Bk 10 maßgebend, der Oberbau erfolgt in Anlehnung an die RStO 12, Belastungsklasse 10 Tafel 1, Zeile 3 mit folgendem Oberbau: 4,0 cm Asphaltdeckschicht 8,0 cm Asphaltbinderschicht 10,0 cm Asphalttragschicht 20,0 cm Schottertragschicht 23,0 cm Frostschutzschicht 65,0 cm Gesamtaufbau Für den Ausbau der neu herzustellenden Bushalteflächen in Asphaltbauweise ist die Belastungsklasse Bk 32 maßgebend, der Oberbau erfolgt in Anlehnung an die RStO 12, Belastungsklasse 32 Tafel 1, Zeile 3 mit folgendem Oberbau: 3,0 cm Asphaltdeckschicht 9,0 cm Asphaltbinderschicht 14,0 cm Asphalttragschicht 20,0 cm Schottertragschicht 29,0 cm Frostschutzschicht 75,0 cm Gesamtaufbau Für den Ausbau der neu herzustellenden Nebenflächen in Pflasterbauweise erfolgt der Oberbau, falls es erforderlich ist diesen neu herzustellen, in Anlehnung an die RStO 12, Tafel 6, Zeile 1 mit folgendem Oberbau: 8,0 cm Betonsteinpflaster 4,0 cm Bettung 15,0 cm Schottertragschicht 13,0 cm Frostschutzschicht 40,0 cm Gesamtaufbau Für den Ausbau der neu herzustellenden Schwerlastzufahrten in Pflasterbauweise erfolgt der Oberbau, falls es erforderlich ist diesen neu herzustellen, in Anlehnung an die RStO 12, Tafel 6, Zeile 1 mit folgendem Oberbau: 8,0 cm Betonsteinpflaster 4,0 cm Bettung 20,0 cm Schottertragschicht 28,0 cm Frostschutzschicht 60,0 cm Gesamtaufbau | K11: ="" | M11: 188b21ae-2cb2-449a-a3bf-2d3c453b5ca5
A12: Hinweistext | C12: 1.4 Verkehrsverhältnisse auf der Baustelle, insbesondere Verkehrsbeschränkungen | D12: 1.4 Verkehrsverhältnisse auf der Baustelle, insbesondere Verkehrsbeschränkungen Das Baufeld liegt innerhalb öffentlicher Straßen. Die Baustelle ist über öffentliche Straßen erreichbar. Verkehrsbeschränkungen, die sich auf An- und Abfahrmöglichkeiten für Baustellenfahrzeuge auswirken, liegen nicht vor. Einschränkungen der Befahrbarkeit der Straßen im Baufeld infolge der Baumaßnahmen sind unter Punkt 2.2 (Besondere Erschwernisse) aufgeführt. | K12: ="" | M12: b80efa75-1c36-4a48-a6d9-06c7c3161c67
A13: Hinweistext | C13: 1.5 Für den Verkehr freizuhaltende Flächen | D13: 1.5 Für den Verkehr freizuhaltende Flächen Die Baumaßnahme ist so durchzuführen, dass Einschränkungen für den öffentlichen Verkehr auf ein Mindestmaß beschränkt werden. Wo Behinderungen unvermeidbar sind, sind geeignete Verkehrssicherungs- und -lenkungsmaßnahmen entsprechend dem abgestimmten Verkehrskonzept umzusetzen. Zur Reduzierung verkehrlicher Beeinträchtigungen ist die Maßnahme in vier aufeinanderfolgende Bauphasen untergliedert, wie im Verkehrskonzept dargestellt. Teilweise finden Arbeiten abschnittsweise oder parallel statt, z. B. der Straßenbau Rheinberger Straße (BP3) während des Kanalbaus in der Mühlenstraße (BP2). Das Verkehrskonzept wurde mit der Stadt Moers (FD 8.2 und FD 8.3), der Polizei, der Feuerwehr sowie den Verkehrsbetrieben (NIAG) abgestimmt und liegt den Ausschreibungsunterlagen bei. Es ersetzt nicht die unter Abschnitt 2.6 aufgeführten Pflichten zur Erstellung und Vorlage von Verkehrszeichenplänen und Umleitungsregelungen – diese sind durch den Auftragnehmer zusätzlich zu erbringen. Für alle Bauphasen ist aufgrund der innerstädtischen Lage und beengter Platzverhältnisse mit abschnittsweisen Sperrungen zu rechnen. Wo möglich, erfolgt die Ausführung in halbseitiger Bauweise mit einer Mindestrestfahrbahnbreite von ≥ 3,00 m. In Bauphasen mit temporärer Vollsperrung sind entsprechende Umleitungen gemäß Verkehrskonzept umzusetzen. Eine Gehwegseite ist über alle Bauphasen hinweg auf der Rheinberger Straße dauerhaft freizuhalten und begehbar zu halten. Die Grundstücke der Anwohner müssen während der gesamten Bauzeit fußläufig erreichbar sein. Die Erreichbarkeit mit Kraftfahrzeugen ist täglich vor Baubeginn und nach Bauende sicherzustellen. In Fällen, in denen dies vorübergehend nicht möglich ist, sind betroffene Anlieger frühzeitig zu informieren. Die Zugänglichkeit für Rettungsfahrzeuge, insbesondere Feuerwehrdrehleitern, muss jederzeit gewährleistet sein, besonders zu berücksichtigen sind dabei Haus-Nr. 32, 33, 34, 37, 55. Die Längen der nicht befahrbaren Abschnitte sind auf ein Maximum von 50 Metern zu beschränken. Offene Kanalbaugruben dürfen maximal 15 Meter lang sein. Die Feuerwehr muss bis zur Grubenkante andienen können. Anliegerzufahrten werden, soweit erforderlich, mit Hinweisschildern „Bitte in den fließenden Verkehr einordnen“ ausgestattet. Während der gesamten Maßnahme wird eine Baustellen-Lichtsignalanlage am Knotenpunkt Neuer Wall / Unterwallstraße / Wilhelm-Schröder-Straße vorgehalten. Diese ist koordiniert in Abhängigkeit mit der Baustellen-LSA am Knotenpunkt Rheinberger Straße / Mühlenstraße zu schalten. Dazu ist eine Abstimmung/Koordinierung mit den LSA Planern der Stadt Moers notwendig (Herr Baas (0 28 41 / 201-576 / carsten.baas@moers.de) und Herr Schlösser (0 28 41 / 201-552 / michael.schloesser@moers.de)). Zusätzlich ist ein temporärer Kreisverkehr während der gesamten Baumaßnahme im Bereich der Gabelsberger- & Seminarstraße einzurichten, die Gabelsbergerstraße wird dabei permanent gesperrt. Dieser dient zur Aufrechterhaltung des Verkehrsflusses und verhindert Rückstoß- und Wendefahrten. Die Mittelinsel wird mit Markierungen und einem Leitsystem (Bordsteinerhöhung, nicht überfahrbar) gekennzeichnet. Die Fahrbahnbreiten sind so ausgelegt, dass Busverkehr jederzeit ungehindert passieren kann. Die Verkehrssicherung obliegt dem Auftragnehmer. Der ausführende Bauunternehmer ist verpflichtet, die Feuerwehr Moers rechtzeitig per E-Mail an vb.feuerwehr@moers.de über folgende Ereignisse zu informieren: - Beginn und Einrichtung der Baustelle - Jede Änderung der Zufahrts-, Einfahrts- oder Sperrbereiche - Abschluss der Maßnahme Die Mitteilungen sind grundsätzlich mit aktuellem Übersichtsplan / Lageplan zu versehen. Beispiel: „In der kommenden Woche erfolgt eine Vollsperrung der Rheinberger Straße im Abschnitt zwischen Hausnummer 30 und 34. Zugang für Feuerwehr wird über Baerler Straße sichergestellt.“ Zusätzlich hat der ausführende Bauunternehmer die Polizei (dirgepwsued.wesel@polizei.nrw.de), Verkehrsbetriebe (NIAG: Grasshoff, Volker: volker.grasshoff@niag-online.de) sowie die Müllabfuhr (Frank Seemann: 017614744217; fseemann@enni.de / Friedel Baumann 01709137254 / fbaumann@enni.de) über die Sperrung einzelner Straßenabschnitte zu informieren. | K13: ="" | M13: 23a27da0-373c-4c63-b86b-2ea70fc48a0a
A14: Hinweistext | C14: 1.6 Nutzbarkeit von Transporteinrichtungen und Transportwegen | D14: 1.6 Art, Lage und Maße und Nutzbarkeit von Transporteinrichtungen und Transportwegen Keine Angaben. | K14: ="" | M14: e2a862de-780e-48fe-98e1-5fec04734873
A15: Hinweistext | C15: 1.7 Energieversorgung (Wasser, Strom, Abwasser) Bedingungen für das Ableiten von Abwässern | D15: 1.7 Energieversorgung (Wasser, Strom, Abwasser) Bedingungen für das Ableiten von Abwässern Der Auftragnehmer hat sich selbst über Lage, Art, Anschlusswert und Bedingungen für das Überlassen von Anschlüssen für Wasser und Strom zu erkundigen. Die Kosten für die Herstellung der Energieversorgung sowie für den Energieverbrauch sind in die Einheitspreise einzukalkulieren. Zur Entnahme des Wassers aus Hydranten dürfen nur Standrohre der ENNI Energie & Umwelt Niederrhein GmbH benutzt werden. Aufstauungen ohne vorherige Genehmigung des Kanalnetzbetriebes (Abteilung Technische Dienste Entwässerung) der ENNI AöR sind untersagt. Ansprechperson TEW: Yvonne Schwabe, Tel.: 0 28 41 – 104 - 763, E-mail: yschwabe@enni.de Im Falle von auftretenden Ereignissen ist außerhalb der Geschäftszeiten die ENNI Ingenieurbereitschaft unter 0160 - 90 14 11 01 zu kontaktieren. | K15: ="" | M15: e38c72b1-990b-416a-a84c-b9da77f033a6
A16: Hinweistext | C16: 1.8 Vom Auftraggeber zur Verfügung gestellte Flächen und Räume | D16: 1.8 Vom Auftraggeber zur Verfügung gestellte Flächen und Räume Der Auftraggeber stellt keine Flächen oder Räume zur Verfügung. Der Baubereich umfasst die Flächen der geplanten Bauwerke und die Bewegungsflächen für die zur Herstellung erforderlichen Baufahrzeuge und Geräte. Innerhalb des Baubereichs sollen sich nur die für die Bauarbeiten zwingend örtlich benötigten Teile der Baustelleneinrichtung und Materiallagerplätze befinden. Lager- und Arbeitsplätze innerhalb des Baubereichs entstehen entsprechend dem Bauablauf räumlich und zeitlich begrenzt am aktuellen Bauort. Alle übrigen Teile der Baustelleneinrichtung und Materiallagerplätze befinden sich außerhalb des Baubereichs. Hierzu gehören insbesondere Material- und Gerätecontainer, Lagerräume, Zwischenlagerfläche für separierten Boden mit unklarer Schadstoffbelastung, Waschräume, Toilettenanlage, Aufenthaltsräume, Baubüro, Anschlüsse für Strom und Wasser, sonstige Lager- und Arbeitsplätze, Verkehrssicherung und Schilder. Zusätzlich benötigte Flächen und Räume hat sich der Auftragnehmer rechtzeitig vor Baubeginn zu beschaffen, für die Dauer der Baumaßnahmen zu unterhalten und nach Beendigung der Arbeiten zu räumen. Die Genehmigung für die Nutzung von Flächen ist rechtzeitig vor Baubeginn von den Eigentümern einzuholen. Die Kosten sind in die Einheitspreise einzukalkulieren. Ansprechpartner für die Flächennutzungsplanung der Stadt Moers: Herr Sell Tel: 02841/201-416 Mail: Pascal.Sell@Moers.de | K16: ="" | M16: 7cef0235-9eeb-470b-b281-4a31820e5ad3
... A32: Hinweistext | C32: 2 Angaben zur Ausführung | D32: 2 Angaben zur Ausführung | K32: ="" | M32: 490bbd59-1bef-40c9-a8e5-5c6f0a6e4d3c
A33: Hinweistext | D33: 2.1 Bauablauf (Arbeitsabschnitte, -unterbrechungen und –beschränkungen) Der Bauablauf ist mit der Bauüberwachung der ENNI abzustimmen. Der Baubeginn ist verbindlich in der 14. KW 2026 vorzusehen. Vor Baubeginn erfolgt eine Standortbegehung gemeinsam mit der örtlichen Bauüberwachung / Bauoberleitung des AG. Arbeitsunterbrechungen sind nicht vorgesehen. Das Verkehrskonzept sieht die Aufteilung der Baumaßnahme in 4 Bauphasen vor: Bauphase 1: Kanalbau Rheinberger Straße Bauphase 2: Kanalbau Mühlenstraße Bauphase 3: Straßenbau Rheinberger Straße Bauphase 4: Straßenbau Mühlenstraße Bauphasenbeschreibung Bauphase 1 Der Baustart erfolgt im Kreuzungsbereich Rheinberger Straße/Mühlenstraße. Aufgrund der Lage des Kanals ist eine Vollsperrung notwendig. Die Arbeiten erfolgen von Süd nach Nord in Richtung Baerler Straße. Die Bauarbeiten sind so aufzuführen, dass die Erreichbarkeit der Hausnummern 36 bis 40 und die Andienung der Hausnummern 32, 33, 34, 37 und 55 mit Drehleiter sichergestellt ist. Eine Gehwegseite bleibt durchgängig begehbar. Neben den Arbeiten der ENNI beabsichtigt die Fernwärme Niederrhein die Herstellung von zwei Hausanschlüsse (bei Rheinberger Straße 41 und 49) in der ersten Bauphase. Abstimmungen zu den Arbeiten sind direkt mit der Fernwärme Niederrhein zu treffen (Kontaktdaten siehe Punkt 1.20). Die vorhandenen Senkenleitungen werden im Kanalgraben provisorisch mitgeführt und im Zuge des Straßenbaus neu angeschlossen. Der Kanalbau umfasst SW- und RW-Leitungen mit provisorischen und späteren endgültigen Anschlüssen. Der Schacht 32192S101 bildet den Übergabepunkt für das Provisorium aus der Mühlenstraße. Der Bau erfolgt gegen die Fließrichtung. Die Verbindung zur Baerler Straße bleibt möglichst lange offen. Die Arbeiten an der Kreuzung sollen innerhalb von 5 Wochen abgeschlossen sein, um die Verbindung Richtung Süden wiederherzustellen. Bauphase 2 Nach Abschluss der Kanalbauarbeiten in der Rheinberger Straße beginnt die Kanalbaukolonne mit dem Bau des SW-Kanals in der Mühlenstraße. Die Arbeiten starten im Kreuzungsbereich und verlaufen gegen die Fließrichtung Richtung Brücke. Bestehende Provisorien werden aufgenommen und ordnungsgemäß eingebunden. Der Bestandsschacht 32192S001 entfällt. Der RW-Kanal folgt im Anschluss, beginnend am Bestandsschacht 32192R206, dessen Anschluss angepasst wird. Die vorhandenen Senkenleitungen werden provisorisch mitgeführt. Während dieser Bauphase erfolgt bereits der Straßenbau Rheinberger Straße (Bauphase 3a) parallel. Der Zufahrt für Rettungsfahrzeuge ist zu jeder Zeit sicherzustellen.Eine Gehwegseite bleibt durchgängig begehbar. Bauphase 3 Nach Abschluss der Kanalbauarbeiten im Kreuzungsbereich Rheinberger/Mühlenstraße beginnt der Straßenbau in der Rheinberger Straße. Die Arbeiten erfolgen in drei Abschnitten (3a Westseite, 3b/3c Ostseite) in halbseitiger Bauweise. Eine Vollsperrung ist nicht vorgesehen. Der Verkehr wird während der gesamten Bauphase 3 als Einbahnstraße in Fahrtrichtung „stadtauswärts“ geführt. Südlich des KP Mühlenstraße / Rheinberger Straße ist eine Bedarfs-LSA für Fußgänger einzurichten. Damit Einsatzfahrzeuge und der ÖPNV entgegen der Einbahnstraße in Fahrtrichtung „stadteinwärts“ die Rheinberger Straße befahren können, ist nördlich des Baufeldes ein zusätzlicher Signalgeber vorzusehen. Dieser ist mit der südlichen Bedarfs-LSA zu koppeln. Jede Zufahrt im Baufeld ist mit einem Signalgeber auszustatten.In Bauphase 3c ist der Knotenpunkt Mühlenstraße / Rheinberger Straße mit einer Baustellen-LSA auszustatten. Diese ist weiterhin mit dem nördlichen Signal für Rettungsfahrzeuge und ÖPNV zu koppeln. Die Baumaßnahme ist so zu gestalten, dass eine durchgehende Restfahrbahnbreite ≥ 3,00 m gewährleistet wird. Die Bauarbeiten sind so aufzuführen, dass die Erreichbarkeit der Hausnummern 36 bis 40 und die Andienung der Hausnummern 32, 33, 34, 37 und 55 mit Drehleiter sichergestellt ist. Eine Gehwegseite bleibt durchgängig begehbar. Bauphase 4 Nach Abschluss der Arbeiten in Rheinberger Straße sowie des Kanalbaus in der Mühlenstraße erfolgt der Straßenbau in der Mühlenstraße. Auch hier erfolgt die Ausführung in zwei Teilabschnitten (Süd- und Nordseite) in halbseitiger Bauweise unter Aufrechterhaltung des Verkehrs mit LSA-Führung. Die Baufelder sind so zu wählen, dass die Zufahrt für Rettungsfahrzeuge jederzeit möglich sind. Anliegerzufahrten sind mit einem Hinweisschild "Bitte in den fließenden Verkehr einordnen" auszustatten. Eine Gehwegseite bleibt durchgängig begehbar. | K33: ="" | M33: 73562370-a84c-4136-9cbc-47b18baf6cce
A34: Hinweistext | C34: 2.2 Besondere Erschwernisse während der Ausführung, z.B. Arbeiten im Bereich von Verkehrswegen | D34: 2.2 Besondere Erschwernisse während der Ausführung, z.B. Arbeiten im Bereich von Verkehrswegen Verkehr: Den Anliegern ist die Erreichbarkeit der Grundstücke zu ermöglichen (insbesondere Rettungsfahrzeuge, Müllabfuhr, Anwohner, Lieferanten), siehe Punkt 1.5. Sollte dies temporär, aufgrund des Baufortschrittes, nicht möglich sein ist der AN angehalten dies mit den jeweiligen Anwohnern abzustimmen. Zumindest zum Feierabend müssen die Grundstücke anfahrbar sein. Dies ist ggf. durch das Verlegen von Stahlplatten oder das Herstellen von Anrampungen sicherzustellen. Eine fußläufige Erreichbarkeit der Grundstücke muss über den Zeitraum der Baumaßnahme gewährleistet werden. Müllabfuhr: Der AN hat während der Baumaßnahme der ENNI als Abfallentsorger die Zuwegung zu den Anliegern zu ermöglichen. Wird dies durch den Bauablauf behindert, so hat der AN mit der ENNI einen Übergabepunkt für die zu leerenden Mülltonnen festzulegen sowie den Hin- und Rücktransport der Mülltonnen (Restmülltonne, Blaue Tonne, Biotonne) sowie gelber Säcke/gelbe Tonne und Grünschnitt zu organisieren. Die jeweiligen Abfuhrtermine können auf der Webseite http://www.enni.de/stadt-service/abfall/abfallkalender eingesehen werden. Ansprechpartner ENNI Stadt und Service: Friedel Baumann: Tel. 01709137254 / Mail: fbaumann@enni.de Frank Seemann: Tel. 017614744217 / Mail: fseemann@enni.de Überleitung von Abwasser aus Kanälen: Während der gesamten Bauphase ist der Abwasserabfluss aufrecht zu erhalten. Bei Regenwetter ist in den Kanälen mit großen Abwassermengen und Einstau der Kanäle bis maximal zur Geländeoberkante zu rechnen. Wird ein vorhandener Kanal abgebrochen, so ist der Abwasserzufluss von oberhalb provisorisch überzuleiten und sämtliche Straßenablauf- und Hausanschlusskanäle bis zum endgültigen Anschluss an den neuen Kanal provisorisch zu übernehmen. Beim Anschluss an vorhandene Kanäle oder an den vorhandenen Graben ist die Baugrube gegen Rückstau zu sichern. Dabei ist die vorhandene Geländeoberkante als Rückstauebene anzunehmen. Die Überleitungs- und Sicherungsmaßnahmen sind entsprechend druckdicht auszuführen. Kanalgraben: Die Länge des offenen Kanalgrabens ist auf 15 m zu begrenzen. Die Feuerwehr muss die Grube jederzeit bis zur Kante anfahren können. Verfüllte Grabenabschnitte sind bis zur endgültigen Wiederherstellung der Straßenoberfläche provisorisch verkehrssicher zu befestigen und zu unterhalten. Lager- und Arbeitsplätze außerhalb des Baufeldes: Innerhalb des Baufeldes dürfen sich nur die für die Bauarbeiten zwingend örtlich benötigten Teile der Baustelleneinrichtung und Materiallagerplätze befinden. Lager- und Arbeitsplätze innerhalb des Baufeldes entstehen entsprechend dem Bauablauf räumlich und zeitlich begrenzt am aktuellen Bauort. Alle übrigen Teile der Baustelleneinrichtung und Materiallagerplätze dürfen sich nicht im Bereich des Baufeldes befinden. Kanaluntersuchung durch den Kanalnetzbetrieb der ENNI Stadt & Service Niederrhein AöR innerhalb der Bauzeit: Der Kanalnetzbetrieb der ENNI Stadt & Service Niederrhein AöR wird innerhalb der Bauzeit die fertiggestellten Kanäle untersuchen, siehe Punkt 2.1. Der Auftragnehmer hat diese Arbeiten zu dulden und selbst rechtzeitig eine Abstimmung mit dem Kanalnetzbetrieb der ENNI Stadt & Service Niederrhein AöR vorzunehmen. Die Kosten für die genannten besonderen Erschwernisse sind in die Einheitspreise einzukalkulieren, sofern sie nicht in Einzelpositionen des Leistungsverzeichnisses enthalten sind. | K34: ="" | M34: 64c94dab-9bb2-4c78-b8ab-5c5913adb3f3
A35: Hinweistext | C35: 2.3 Bauzeitenplan | D35: 2.3 Bauzeitenplan Für die gesamten geplanten Baumaßnahmen ist ein Bauzeitenplan zu erstellen (eine entsprechende Position ist Bestandteil des Leistungsverzeichnisses). Wenn unter Punkt 2.1 nichts Anderes ausdrücklich erwähnt ist, obliegt die Planung des Bauablaufes dem Ermessen des Auftragnehmers. Die detaillierten Ausführungstermine sind mit der örtlichen Bauüberwachung der ENNI und dem Verkehrssicherungsunternehmen abzustimmen. Beim Aufstellen des Bauzeitenplans sind alle Gewerke zu berücksichtigen. Die Darstellung hat mit einem Zeitraster von mindestens einer Woche zu erfolgen. Jeweils nach vier Wochen Bauzeit ist der Plan zu erneuern und der AG-Bauüberwachung vorzulegen. Der neue Bauzeitplan muss eine Darstellung des Soll-Ist-Vergleichs enthalten. Der erste Bauzeitenplan ist fünf Werktage vor Arbeitsbeginn unaufgefordert dem Bauüberwacher des AG zu übergeben. | K35: ="" | M35: bb12a4fc-7a50-4a50-b4b7-575c92365a36
A36: Hinweistext | C36: 2.4 Besondere Anforderungen für Arbeiten in kontaminierten Bereichen | D36: 2.4 Besondere Anforderungen für Arbeiten in kontaminierten Bereichen Es sind keine Schadstoffbelastungen im Baufeld bekannt, siehe Punkt 1.21. Besondere Anforderungen für die Arbeiten sind nicht vorgesehen. | K36: ="" | M36: 7eb8cbc5-9bda-48a7-8b3a-b37787fda4f5
A37: Hinweistext | C37: 2.5 Besondere Anforderungen an die Baustelleneinrichtung / Entsorgungseinrichtungen | D37: 2.5 Besondere Anforderungen an die Baustelleneinrichtung / Entsorgungseinrichtungen Besondere Anforderungen an die Baustelleneinrichtung können sich aus umweltrechtlichen Anforderungen ergeben (siehe Abschnitt 1.11). Die erforderlichen Ausrüstungen, Geräte und PSA sind Bestandteil der Baustelleneinrichtung und in den Einheitspreis einzukalkulieren. | K37: ="" | M37: 4db8584a-045a-46a4-9273-0479f6ad3f8b
A38: Hinweistext | C38: 2.6 Besonderheiten der Regelung und Sicherung des Verkehrs | D38: 2.6 Besonderheiten der Regelung und Sicherung des Verkehrs Die Sicherung des Verkehrs erfolgt durch den Auftragnehmer.Erforderliche Genehmigungen sind durch den AN einzuholen. Die Kosten hierfür sind in die Einheitspreise einzukalkulieren. Spätestens 4 Wochen vor Ausführung der verkehrslenkenden Maßnahmen ist ein Verkehrsführungs- und Beschilderungsplan in anordnungsfähiger Ausführung anzufertigen und bei dem zuständigen Fachdienst 8.3 - Straßen- und Verkehrsrecht der Stadt Moers einzureichen. Die Erstellung der Verkehrssicherungspläne hat in digitaler Form zu erfolgen. Die Sicherung des Verkehrs hat nach Vorgabe des Fachdienstes 8.3 - Straßen- und Verkehrsrecht durch ein fachlich qualifiziertes Unternehmen zu erfolgen. Erforderliche Genehmigungen sind durch den AN einzuholen. Die Kosten hierfür sind in die Einheitspreise einzukalkulieren. Die Planung der Beschilderung sowie die Abstimmung mit der ENNI Stadt & Service Niederrhein AöR, Nahverkehrsunternehmen, Feuerwehr, Rettungsdienste, Polizei und Entsorgungsunternehmen sind durch den AN durchzuführen. Auflagen der Behörden sind zu befolgen. Baustellen an oder in öffentlichen Verkehrsflächen sind durch stabile, entsprechend der Straßenverkehrsordnung rot-weiß gestreifte Absperrschranken nach ZTV-SA und RSA abzusichern. Die Kosten hierfür sind in die LV-Positionen einzurechnen. Zu beachten ist die Gebührenordnung für Anordnungen nach § 45 Abs. 6 StVO über Maßnahmen der Unternehmer im Straßenverkehr. Folgende Gebühren werden erhoben: für die Dauer von 1 Tag: 35,00 €, bei Verlängerung je Tag: 15,00 €; 2 Tage bis 1 Woche: 50,00 €, bei Verlängerung je Woche: 25,00 €; bis zu 3 Wochen: 100,00 €, bei (jeder) Verlängerung: 50,00 €; bis zu 6 Wochen: 150,00 €, bei (jeder) Verlängerung: 100,00 €; über 6 Wochen: 250,00 €, bei (jeder) Verlängerung: 100,00 €; über 3 Monate: 500,00 € bei (jeder) Verlängerung: 150,00 €; über 6 Monate: 767,00 € Zusätzlich zu a) –g) wenn ein Ortstermin erforderlich ist: 110,00 € Verwaltungsaufwand je angefangene Viertelstunde: 16,25 € Fahrtkosten je Kilometer: 0,30 € Eilzuschlag zusätzlich zu a) – e) (außer bei unvorhergesehenen Notfallarbeiten) wenn der Antrag - innerhalb von 2 Wochen vor Beginn der Arbeiten gestellt wird: - 25 % der Grundgebühr - innerhalb von 1 Woche vor Beginn der Arbeiten gestellt wird: - 50 % der Grundgebühr Nachkontrolle aufgrund von Mängeln: 50,00 € Das Außerkraftsetzen von Verkehrszeichen durch Klebebänder ist verboten. Bei Zuwiderhandlungen ist Ersatz für beschädigte Schilder zu leisten. Es können Schilderhüllen, Jute- oder Plastiksäcke verwendet werden. Wegweiser sind durch ein rotes Holzlattenkreuz in Abstimmung mit der Bauüberwachung außer Kraft zu setzen. Zu beachten ist, dass ein zertifiziertes Fachunternehmen die Verkehrssicherung durchführt. | K38: ="" | M38: 7b9fe972-fba3-4bf7-88df-76337518e90c
A39: Hinweistext | C39: 2.7 Besondere Anforderungen an das Auf- und Abbauen sowie Vorhalten von Gerüsten | D39: 2.7 Besondere Anforderungen an das Auf- und Abbauen sowie Vorhalten von Gerüsten Der Einsatz von Gerüsten, die keine Nebenleistung sind, ist nicht vorgesehen. | K39: ="" | M39: c27e5808-21a2-42cb-abe6-98247f9f3e16
A40: Hinweistext | C40: 2.8 Mitbenutzung fremder Gerüste, Hebezeuge, Aufzüge, Geräte, Einrichtungen und dergleichen | D40: 2.8 Mitbenutzung fremder Gerüste, Hebezeuge, Aufzüge, Geräte, Einrichtungen und dergleichen Nicht vorgesehen. | K40: ="" | M40: d1eadb5e-9c93-4879-b0a8-5d62d3980dec
A41: Hinweistext | C41: 2.9 Mitbenutzung eigener Geräte, Einrichtungen o. ä. durch Dritte; Dauer und Arbeiten | D41: 2.9 Mitbenutzung eigener Geräte, Einrichtungen o. ä. durch Dritte; Dauer und Arbeiten Nicht vorgesehen. | K41: ="" | M41: f9e3f3a9-6203-4169-9a0d-a9ecbc482e2d
A42: Hinweistext | C42: 2.10 Verwendung oder Mitverwendung von wiederaufbereiteten (Recycling-) Stoffen | D42: 2.10 Verwendung oder Mitverwendung von wiederaufbereiteten (Recycling-) Stoffen Wiederaufbereitetes Material darf nur verwendet werden, wenn die Verwendung im Positionstext beschrieben wird. | K42: ="" | M42: 786ceb22-c93b-4af4-ad91-b85f76bc5f64
A43: Hinweistext | C43: 2.11 Anforderungen an wiederaufbereitete (Recycling-)Stoffe und nicht genormte Stoffe und Bauteile | D43: 2.11 Anforderungen an wiederaufbereitete (Recycling-)Stoffe und nicht genormte Stoffe und Bauteile Es sind mit Ausnahme der ausgeschriebenen Recycling-Baustoffe grundsätzlich neuwertige Baustoffe einzubauen. | K43: ="" | M43: 2cfdc6f0-e3e7-4630-8d35-cdc2456d7151
A44: Hinweistext | C44: 2.12 Besondere Anforderungen an Art, Güte und Umweltverträglichkeit der Stoffe und Bauteile | D44: 2.12 Besondere Anforderungen an Art, Güte und Umweltverträglichkeit der Stoffe und Bauteile Siehe Vorbemerkungen und Positionstexte im LV zu Stoffen und Bauteilen. Beim Bau von Einsteigschächten aus Betonfertigteilen ist die Fugenzahl durch die Verwendung von Schachtringen größtmöglicher Bauhöhe zu minimieren. Zwischen Konus und Schachtabdeckung ist mindestens ein Ausgleichsring vorzusehen. | K44: ="" | M44: 94d4a85a-4e8b-45e8-bb50-6ba0b352e590
A45: Hinweistext | C45: 2.13 Art und Umfang der vom Auftraggeber verlangten Eignungs- und Gütenachweise | D45: 2.13 Art und Umfang der vom Auftraggeber verlangten Eignungs- und Gütenachweise Allgemeines: Eignungs- und Gütenachweise sind vollständig und nachvollziehbar zu dokumentieren. Die Dokumentation ist der Bauüberwachung zu übergeben. Probenahmen zur Eigenkontrolle, Bodenuntersuchungen und Prüfungen sind durch eine unabhängige Prüfstelle durchzuführen. Sämtliche hiermit verbundenen Kosten sind in die Einheitspreise einzukalkulieren, soweit sie nicht in Einzelpositionen beschrieben sind. Bodenverdichtung: Nachweis der Verdichtung im tiefen Bereich: Durch Sondierung mit der leichten Rammsonde nach DIN EN ISO 22476-2 (DPL 10) ist die Verdichtung des verfüllten Bodens im tiefen Bereich zu bestimmen. Einzuhalten sind die Grenzwerte der DIN EN ISO 22476-2 und der ZTV-E-StB 17.Ferner muss die erreichte Verdichtung mit der statischen Berechnung der Rohrleitungen übereinstimmen. Je angefangener 50 m Rohrgrabenlänge ist ein Nachweis zu führen. Die Vergütung erfolgt über Einzelpositionen des Leistungsverzeichnisses. Nachweis der Verdichtung im oberflächennahen Bereich: Durch Plattendruckversuch nach DIN 18134 ist die Verdichtung des verfüllten Bodens im oberflächennahen Bereich zu bestimmen. Einzuhalten sind die Grenzwerte nach RStO 12 für die jeweiligen Belastungsklassen, sowie nach ZTV Asphalt-StB 07/13, Normungen jeweils in der derzeit gültigen Fassung. Die Vergütung erfolgt über Einzelpositionen des Leistungsverzeichnisses. Dichtheitsprüfungen: Die Dichtheitsprüfungen von Freigefälleleitungen und Anschlussleitungen werden durch den AG durchgeführt. Nachbesserung, Wiederholung von Eignungs- und Gütenachweisen: Erfüllen Bauteile nicht die geforderten Eignungs- und Gütenachweise, sind Nachbesserungsmaßnahmen mit der Bauüberwachung abzustimmen. Nach erfolgter Nachbesserung sind die für die Eignungs- und Gütenachweise erforderlichen Probenahmen, Bodenuntersuchungen und Prüfungen zu wiederholen. Die Kosten für die Nachbesserungsmaßnahmen und die Wiederholung von Eignungs- und Gütenachweisen trägt der Auftragnehmer. | K45: ="" | M45: c14af6f9-4262-41d7-be11-ca08bc14d358
... A74: Hinweistext | C74: Vorbemerkungen (4. Zusätzliche Technische Vorschriften für die Verlegung von Entwässerungskanälen) | D74: 4. Zusätzliche Technische Vorschriften für die Verlegung von Entwässerungskanälen Richtung und Höhenlage (Ergänzungen zur DIN EN 1610) a) Die Höhenlage der Leitung ist vor dem Einbau der oberen Bettungsschicht vom AN als Eigenüberwachungsprüfung mittels Nivellement am Endpunkt sowie den 1/5 Punkten der Haltung zu kontrollieren. Das Nivellement ist von der Bauüberwachung der ENNI Stadt & Service Niederrhein AöR gegenzuzeichnen. Ebenso ist die Flucht der Haltung zwischen den angebundenen Schächten zu überprüfen. b) Bei Abweichungen der Ist-Neigung von der Soll-Neigung von mehr Gefälle der Haltung maximal zulässige Abweichung des Gefälles um I ≥ 0,3 % 0,05 Prozentpunkte 0,2 ≤ I< 0,3 % 0,04 Prozentpunkte 0,1 ≤ I< 0,2 % 0,03 Prozentpunkte I< 0,1 % 0,01 Prozentpunkte kann die ENNI Stadt & Service Niederrhein AöR die Auswechselung der Haltung und Herstellung der geforderten Sohlhöhen und Gefälleverhältnisse verlangen. Bei einem Verzicht wird eine Wertminderung im Verhältnis der tatsächlichen Leistungsfähigkeit zur theoretischen Leistungsfähigkeit bei Vollfüllung nach Prandtl-Colebrook errechnet. Berechnungsgrundlage sind die Baukosten der Haltung einschließlich der angebundenen Schächte. Baukosten, die nicht dieser oder anderen Haltungen oder Schächten zuzuordnen sind, wie Baustelleneinrichtung, Beschilderung, Verkehrssicherung, Stundenlohn etc., sind anteilig auf die Haltungslänge zu verteilen. Beispiel: a) Gefälle Soll: 0,5 % Gefälle lt. Abnahme = 0,46 % ist in Ordnung Gefälle lt. Abnahme = 0,43 % mangelbehaftet b) Gefälle: Soll 0,15 % Gefälle lt. Abnahme = 0,13 % ist in Ordnung Gefälle lt. Abnahme = 0,11 % mangelbehaftet c) Die Höhenangaben der Ausführungspläne sind einzuhalten. Mehrkosten durch vom AN zu verantwortenden Mehrtiefen werden nicht vergütet. Bei Mehr- oder Mindertiefen behält die ENNI Stadt & Service Niederrhein AöR sich Schadenersatz vor. | K74: ="" | M74: f3436363-932c-4a87-841f-52b1a6194cff
A75: Gruppe | B75: 1. | C75: Teil 1: Allgemeine Leistungen | K75: =""
A76: Gruppe | B76: 1.1. | C76: Vorbereitende Maßnahmen | K76: =""
A77: Gruppe | B77: 1.1.1. | C77: Baustelleneinrichtungsarbeiten | K77: =""
A78: Hinweistext | C78: Allgemeine Hinweise | D78: Alle, über die gesamte Bauzeit für die Ausführung der Arbeiten notwendigen Geräte und Maschinen, Bedienungspersonal, Hilfsmittel, Ausführung und damit verbundener Nebenarbeiten sowie die Lieferung aller erforderlichen Materialien sind in die Einheitspreise der entsprechenden Positionen zur Baustelleneinrichtung und Baustellenräumung einzurechnen, wenn nicht über andere LV-Positionen gesondert vergütet. Hierzu zählen insbesondere: Herrichten, Unterhalten, Wiederherstellen von Zufahrtswegen und Lagerplätzen. Aufstellen von Tagesunterkünften, Magazinen, Werkstätten etc. Herstellen und Unterhalten von notwendigen Strom- und Wasser- anschlüssen. Überwachung der Baustelle auch an Tagen ohne Arbeitseinsatz. Aufstellen, Unterhalten und das durch den Baufortschritt bedingte Umsetzen der Verkehrssicherungseinrichtung im gesamten Baustellenbereich gemäß Verkehrsrechtlicher Anordnung nach § 45 STVO und RSA in der jeweils gültigen Fassung. Nach Fertigstellung sind die Sicherungseinrichtungen wieder zu beseitigen. An Müllabfuhrtagen sind die Müllgefäße bzw. der Sperrmüll rechtzeitig vor dem Eintreffen der Müllfahrzeuge an die von ihnen anfahrbare Stelle zu befördern. Der AN hat während der Baumaßnahme die Mülltonnen aus den nicht anfahrbaren Bereichen des Baufeldes zur Abholung durch Müllfahrzeugen bis an die anfahrbaren Bereiche hin- und zurück zu trans- portieren. Nach der Entleerung sind die Gefäße unverzüglich zurückzubringen. Betrifft Müllgefäße und Müllsäcke sämtlicher von den Bauarbeiten betroffenen Anlieger. Die betroffenen Anlieger im Bereich der Baustelle sind mindestens 10 Tage vor Arbeitsbeginn schriftlich (Briefkasteneinwurf) über Einzelheiten der Baumaßnahme zu informieren. Aufrechterhaltung des Abwasserbetriebs. Säuberung der Schächte, Straßeneinläufe und Spülung der Kanäle soweit die Verschmutzungen durch die Bautätigkeit verursacht sind. Anlegen und Beseitigen von provisorischen Zufahrten und Zuwegungen. Sofern in den Leistungsbeschreibungen nicht besonders erwähnt, sind Erdaushub, Abbruchmaterialien sowie sonstiges Räumgut auf einer geeigneten Deponie als Abfall zu entsorgen. Kosten für die Verladung, Abfuhr, Entsorgung einschl. Deponiegebühren werden nicht extra vergütet und sind in die Einheitspreise der Bodenabfuhrpositionen einzurechnen. Die Baustelle ist so herzustellen und zu unterhalten, dass der Verkehr zu jederzeit nicht übermäßig beeinträchtigt wird. Dies gilt insbesondere für Fahrzeuge der Rettungsdienste, Polizei, Feuerwehr, Müllabfuhr, öffentlicher Personennahverkehr etc. Diese Vorgabe gilt für alle Titel des Leistungsverzeichnisses. Besondere Vorgaben für den Bauablauf: Vor Baubeginn ist der Feuerwehr ein Übersichtsplan der Planung zu übergeben. Das Baufeld im Bereich der Kanalbaugruben ist auf eine Länge von ca. 15,00 m zu begrenzen. Baufahrzeuge sind nach Feierabend aus dem öffentlichen Verkehrsbereich des Baufeldes zu entfernen. Parallel stattfindende Aufbrucharbeiten / Arbeitsabläufe (z.B. zwei Kanalbaukolonnen) sind im Vorfeld mit der Feuerwehr abzusprechen. Der ausführende Bauunternehmer ist vertraglich verpflichtet, die Feuerwehr wöchentlich über den Stand der Arbeiten und den geplanten Arbeitsfortschritt per E-mail an die Adresse vb.feuerwehr@moers.de zu unterrichten. Zusätzlich hat der Auftragnehmer die Polizei, Verkehrsbetriebe sowie die Müllabfuhr über die Sperrung einzelner Straßenabschnitte zu informieren. ( Es ist zu beachten, dass für die Müllabfuhr unterschiedliche Entsorgungsbetriebe zuständig sind ). Hierzu hat er vor Beginn der Arbeiten innerhalb eines Straßenabschnittes Auskunft über den Baubereich, sowie über die voraussichtliche Dauer der Sperrung zu geben. Änderungen am Baufeld sowie Verschiebungen im Bauablauf sind der Feuerwehr, der Polizei sowie der Müllabfuhr unverzüglich nach Bekanntwerden mitzuteilen. Die Kosten für Koordination und die Erschwernis der Arbeiten in einem eingeschränkten Baufeld sind in die Positionen des Leistungsverzeichnisses mit einzurechnen und werden nicht gesondert vergütet. | K78: ="" | M78: 3dfcec69-f7fb-4edf-879d-3c768e759696
A79: Position | B79: 1.1.1.01 | C79: Baustelleneinrichtung | D79: Antransportieren, aller für die Bauausführung erforderlichen Einrichtungen, Maschinen, Geräte, Werkzeuge, Bauwagen, Lagerschuppen, Aufenthaltsräume, Abortanlagen und Zäune entsprechend der Vorschriften der Berufsgenossenschaft und der Straßenverkehrsordnung. Vom Bieter ist nach Auftragserteilung ein detaillierter Baustelleneinrichtungsplan vorzulegen. Es sind, soweit vorgesehen, darzustellen: Baustromanschluss, Bauwasseranschluss Büro-, magazin-, Aufenthaltscontainer WC- und Wascheinrichtungen Oberboden und Aushublagerplätze Die erforderlichen Ver- und Entsorgungsanschlüsse herstellen einschließlich Zähler. Beschaffen, Mieten und Anlegen notwendiger Arbeits- und Lagerflächen sowie Zufahrtswege, die über die vom AG zur Verfügung gestellten Möglichkeiten hinausgehen. Bei Bedarf Zufahrtswege zur Baustelle sowie Lagerplätze, sonstige Platzbefestigungen und Wege im Baustellenbereich anlegen. Mutterbodenarbeiten und Beseitigung des Aufwuchses für die Baustelleneinrichtung, soweit erforderlich, werden nicht gesondert vergütet. Die Kosten für Vorhalten, Unterhalten und Betreiben der Geräte, Anlagen und Einrichtungen einschließlich Mieten, Pacht, Gebühren und dgl. sind in die Einheitspreise der betreffenden Teilleistungen einzurechnen. Für Rettungsmaßnahmen in umschlossenen Räumen von abwassertechnischen Anlagen muss eine Rettungsausrüstung vorhanden sein: ein frei tragbares, von der Umgebungsatmosphäre unabhängiges Atemschutzgerät mit Vollmaske, z.B Regenerationsgerät mit Drucksauerstoff bzw. chemisch gebundenem Sauerstoff ein Abseil- und Rettungshubgerät, zwei Sicherheitsleinen und Auffanggurt eine betriebsfertige, explosionsgeschützte Handleuchte ein Verbandskasten nach DIN 12 157 "Erste Hilfe Material", Verbandskasten C eine Löscheinrichtung (z.B. Handfeuerlöscher) Gasspürgerät / Gaswarner bzw. -melder Aufstellen von Leiteinrichtungen (z.B. Leitbaken, Absperrschranken, Schrammborde etc..) einschließlich der erforderlichen Beleuchtung innerhalb der Baustelle und des dazugehörigen Bereiches gemäß den Richtlinien für die Sicherung von Arbeitsstellen auf Straßen RSA und der ZTV-SA. | E79: 1 | F79: psch | G79: =SUMPRODUCT((Kalkulation!A2:A50000=B79)*Kalkulation!D2:D50000) -> 0 | H79: =G79*E79 -> 0 | J79: =H79*(1-I79) -> 0 | K79: =B2 -> 0 | L79: 68b12ec4-df45-4506-86b5-e1f50a53d190 | M79: f47f9614-c8cb-43c5-80eb-f23c38fd8144
A80: Position | B80: 1.1.1.02 | C80: Baustelleneinrichtung vorhalten | D80: Vorhaltung aller für die Bauausführung erforderlichen Einrichtungen wie Geräte, Maschinen, Bauwagen- bzw. -container, Abortanlagen, Waschcontainer, Absperrung und Beleuchtung der Baustelle sowie der Anschlüsse von Wasser, Gas, Strom und Telefon im Bereich der Baustelle sowie Unterhaltung von Lagerflächen und Arbeitsplätzen außerhalb des Baustellenbereiches. | E80: 1 | F80: psch | G80: =SUMPRODUCT((Kalkulation!A2:A50000=B80)*Kalkulation!D2:D50000) -> 0 | H80: =G80*E80 -> 0 | J80: =H80*(1-I80) -> 0 | K80: =B2 -> 0 | L80: 68b12ec4-df45-4506-86b5-e1f50a53d190 | M80: 19e7f877-72cb-4275-8df5-7cd8755c42a6
A81: Position | B81: 1.1.1.03 | C81: Baustellenräumung | D81: Baustelle von allen Geräten, Anlagen, Maschinen, Einrichtungen und dergleichen räumen. Benutzte Flächen und Wege entsprechend dem ursprünglichen Zustand unter Wahrung der landschaftlichen Belange ordnungsgemäß herrichten. Verunreinigungen beseitigen. Der ursprüngliche Zustand der Flächen ist wieder herzustellen und vom Auftraggeber schriftlich bestätigen zu lassen. | E81: 1 | F81: psch | G81: =SUMPRODUCT((Kalkulation!A2:A50000=B81)*Kalkulation!D2:D50000) -> 0 | H81: =G81*E81 -> 0 | J81: =H81*(1-I81) -> 0 | K81: =B2 -> 0 | L81: 68b12ec4-df45-4506-86b5-e1f50a53d190 | M81: 44e61555-7690-4ce3-941c-6715321ae607
A82: Position | B82: 1.1.1.04 | C82: Bauzeitenplan | D82: Erstellung eines Bauzeitenplans für die gesamte geplante Baumaßnahme. Beim Aufstellen des Bauzeitenplans sind alle Gewerke analog dem Leistungsverzeichnis zu berücksichtigen. Die Darstellung hat mit einem Zeitraster von einer Woche zu erfolgen. Die Anzahl der Kolonnen und deren Mitarbeiter ist einzutragen. Jeweils nach vier Wochen Bauzeit ist der Plan zu erneuern und aktualisieren. Der neue Bauzeitenplan muss eine Darstellung des Soll-Ist-Vergleichs enthalten. Der erste Bauzeitenplan ist fünf Werktage vor Arbeitsbeginn unaufgefordert der Bauüberwachung des AG zu übergeben. | E82: 1 | F82: psch | G82: =SUMPRODUCT((Kalkulation!A2:A50000=B82)*Kalkulation!D2:D50000) -> 0 | H82: =G82*E82 -> 0 | J82: =H82*(1-I82) -> 0 | K82: =B2 -> 0 | L82: 68b12ec4-df45-4506-86b5-e1f50a53d190 | M82: bf829549-6556-4912-a816-30d92d88ca26
A83: Position | B83: 1.1.1.05 | C83: Baustellenschild | D83: Bauschild nach Vorgabe des AG anfertigen, liefern, aufstellen, für die gesamte Bauzeit vorhalten und wieder entfernen und entsorgen. Das Schild ist aus einem stabilen Gerüst und einer standfesten Gründung nach statisch Erfordernissen herzustellen und sturmsicher aufzustellen. Größe des Bauschildes: Hauptschild b x h = 3,00 x 2,00 m. Höhe der Schildunterkante mind. 3,0 m über Gelände Folienträger und Beschriftung in wetterfester Ausführung Vorbereitung der Aufstellfläche und Fundamentierung nach statischer Erfordernis Gerüstabmessungen und Material nach statischer Erfordernis Aufstellort in Abstimmung mit dem AG. Lieferung der Druckvorlage durch den AG. In den Einheitspreis dieser Position sind die Kosten für den statischen Nachweis einzurechnen. | E83: 1 | F83: St | G83: =SUMPRODUCT((Kalkulation!A2:A50000=B83)*Kalkulation!D2:D50000) -> 0 | H83: =G83*E83 -> 0 | J83: =H83*(1-I83) -> 0 | K83: =B2 -> 0 | L83: 68b12ec4-df45-4506-86b5-e1f50a53d190 | M83: 76629818-a470-4657-a304-4df844132a26
A84: Position | B84: 1.1.1.06 | C84: Verkehrszeichen aller Art aufstellen | D84: Verkehrszeichen aller Art aufstellen, vorhalten und beseitigen für die Lenkung des öffentlichen und nichtöffentlichen Verkehrs im Baustellenbereich und auf den Umleitungsstrecken aufstellen, für die Dauer der vertraglichen Ausführungsfrist vorhalten und beseitigen. Zusätzlich auf Anordnung des AG. Für Verkehrszeichen aller Art, nicht aber Leiteinrichtungen wie Absperrbaken, Absperrgitter, Geländer. Derartige Leistungen sind in die Position Verkehrssicherung einzurechnen. | E84: 140 | F84: St | G84: =SUMPRODUCT((Kalkulation!A2:A50000=B84)*Kalkulation!D2:D50000) -> 0 | H84: =G84*E84 -> 0 | J84: =H84*(1-I84) -> 0 | K84: =B2 -> 0 | L84: 68b12ec4-df45-4506-86b5-e1f50a53d190 | M84: 6c734111-e033-4a8c-a461-8219fdf256be
A85: Position | B85: 1.1.1.07 | C85: Hinweisschilder abdecken | D85: Gebots-, Verbots- oder Hinweisschilder innerhalb und außerhalb des Baustellenbereiches auf Anordnung des Ordnungsamtes abdecken, während der Bauzeit den abgedeckten Zustand warten, und nach Beendigung der Arbeiten die Abdeckung wieder entfernen. | E85: 30 | F85: St | G85: =SUMPRODUCT((Kalkulation!A2:A50000=B85)*Kalkulation!D2:D50000) -> 0 | H85: =G85*E85 -> 0 | J85: =H85*(1-I85) -> 0 | K85: =B2 -> 0 | L85: 68b12ec4-df45-4506-86b5-e1f50a53d190 | M85: d5b22cc6-5101-4e2e-bbfb-e1fe7922460a
A86: Position | B86: 1.1.1.08 | C86: Auskreuzvorrichtung für Wegweiser | D86: Auskreuzvorrichtung für Wegweiser gem. RSA 21 zum außer Kraft setzten einzelner Zielangaben, Teilbereiche und Hinweise auf Wegweisern liefern, montieren, während der Bauzeit warten und nach Beendigung der Arbeiten wieder entfernen. | E86: 4 | F86: St | G86: =SUMPRODUCT((Kalkulation!A2:A50000=B86)*Kalkulation!D2:D50000) -> 0 | H86: =G86*E86 -> 0 | J86: =H86*(1-I86) -> 0 | K86: =B2 -> 0 | L86: 68b12ec4-df45-4506-86b5-e1f50a53d190 | M86: 434d27c2-1d0a-4b1f-92c7-8b3568609253
A87: Position | B87: 1.1.1.09 | C87: Bordsteinerhöhung für prov. Kreismittelinsel | D87: Bordsteinerhöhung(Frankfurter Hut) für Kreismittelinsel liefern, montieren, während der Bauzeit warten und nach Beendigung der Arbeiten wieder entfernen und Montagelöcher verfüllen. Einschließlich aller notwendigen Arbeiten, Montagematerial, Entsorgung des Bohrgutes und Füllmaterial. Höhe: 0,15 m Länge: 0,75 m Breite: 0,12 m Farbe: rot und weiß (werden im Wechsel montiert) Material: Recycling-Kunststoff | E87: 14 | F87: St | G87: =SUMPRODUCT((Kalkulation!A2:A50000=B87)*Kalkulation!D2:D50000) -> 0 | H87: =G87*E87 -> 0 | J87: =H87*(1-I87) -> 0 | K87: =B2 -> 0 | L87: 68b12ec4-df45-4506-86b5-e1f50a53d190 | M87: fb03a7ff-c5f8-4ebb-9256-1ce8f33b09e6
A88: Position | B88: 1.1.1.10 | C88: Anrampen vorh. Zufahrten zu den Grundstücken | D88: Anrampen vorh. Zufahrten zu den Grundstücken mit güteüberwachtem Tragschicht-Material nach Angabe des AG herstellen und Zug um Zug mit Baufortschritt an der Fahrbahnbefestigung wieder zurückbauen und entsorgen. Einzelflächen. Dicke bis 40 cm einschließlich aller erforderlichen Erd- und Nebenarbeiten. | E88: 132 | F88: m2 | G88: =SUMPRODUCT((Kalkulation!A2:A50000=B88)*Kalkulation!D2:D50000) -> 0 | H88: =G88*E88 -> 0 | J88: =H88*(1-I88) -> 0 | K88: =B2 -> 0 | L88: 68b12ec4-df45-4506-86b5-e1f50a53d190 | M88: c3d3d2af-e2bc-4554-8c25-02cead75234d
A89: Position | B89: 1.1.1.11 | C89: Anrampen vorh. Zufahrten zu den Straßen | D89: Anrampen vorh. Zufahrten zu den Straßen mit güteüberwachtem Tragschicht-Material nach Angabe des AG herstellen und Zug um Zug mit Baufortschritt an der Fahrbahnbefestigung wieder zurückbauen und entsorgen. Einzelflächen. Dicke bis 40 cm einschließlich aller erforderlichen Erd- und Nebenarbeiten. | E89: 170 | F89: m2 | G89: =SUMPRODUCT((Kalkulation!A2:A50000=B89)*Kalkulation!D2:D50000) -> 0 | H89: =G89*E89 -> 0 | J89: =H89*(1-I89) -> 0 | K89: =B2 -> 0 | L89: 68b12ec4-df45-4506-86b5-e1f50a53d190 | M89: 4707908d-f191-46b8-82a5-dabf9b8ceacc
A90: Position | B90: 1.1.1.12 | C90: Plantafel (Vorwegweiser) 125 x 160, mit 2 Vorwarnblinkern | D90: Plantafel (Vorwegweiser) nach RUB (Richtlinien für Umleitungsbeschilderungen), 125 x 160 cm, Folie Typ 1, mit Darstellung der Umleitungsstraße, nach den Auflagen des zuständigen Fachdienstes 8.3 "Straßen- und Verkehrsrecht" aufstellen, für die Dauer der vertraglichen Ausführungsfrist vorhalten, betreiben und beseitigen. Zur frühzeitigen Wahrnehmung durch den Verkehrs ist die Plantafel mit 2 gelben Vorwarnblinkern (oben links und rechts) auszustatten. Energieversorgung: Akku oder Solarbetrieb. | E90: 12 | F90: St | G90: =SUMPRODUCT((Kalkulation!A2:A50000=B90)*Kalkulation!D2:D50000) -> 0 | H90: =G90*E90 -> 0 | J90: =H90*(1-I90) -> 0 | K90: =B2 -> 0 | L90: 68b12ec4-df45-4506-86b5-e1f50a53d190 | M90: c79229fe-6213-447a-9bf2-f584665b579e
A91: Position | B91: 1.1.1.13 | C91: Plantafel (Vorwegweiser) 125 x 160 | D91: Plantafel (Vorwegweiser) nach RUB (Richtlinien für Umleitungsbeschilderungen), 125 x 160 cm, Folie Typ 1, mit Darstellung der Umleitungsstraße, nach den Auflagen des zuständigen Fachdienstes 8.3 "Straßen- und Verkehrsrecht" aufstellen, für die Dauer der vertraglichen Ausführungsfrist vorhalten und beseitigen. | E91: 22 | F91: St | G91: =SUMPRODUCT((Kalkulation!A2:A50000=B91)*Kalkulation!D2:D50000) -> 0 | H91: =G91*E91 -> 0 | J91: =H91*(1-I91) -> 0 | K91: =B2 -> 0 | L91: 68b12ec4-df45-4506-86b5-e1f50a53d190 | M91: f383d120-e26a-4237-88fa-7176a350370c
A92: Position | B92: 1.1.1.14 | C92: Verkehrssicherung | D92: Einrichtung zur Verkehrssicherung gemäß ZTV-SA und RSA, zur Verkehrsumleitung und Verkehrsregelung mit der erforderlichen Beschilderung, Beleuchtung, Leiteinricht- ungen, Baken, Markierungen, etc. in Abstimmung mit der Stadt Moers, Fachdienst 8.3 "Straßen- und Verkehrsrecht" (Herr Eller, 02841/201-484 bzw. Frau Sohl 02841/201-628) einschließlich Antransport, Vorhalten, Warten und Umsetzen der erforderlichen Absperrgeräte während der Bauzeit. Vorhandenen Verkehrszeichen im Bereich der Baustelle / Verkehrssicherung sind ggf. aufgrund der Verkehrssicherungsmaßnahmen und Einrichtung der Umleitungsstrecken während der Bauzeit außer Kraft zu setzen. Dies hat gemäß Punkt 2.6 wie folgt zu erfolgen. Das Außerkraftsetzen von Verkehrszeichen durch Klebebänder ist verboten. Bei Zuwiderhandlungen ist Ersatz für beschädigte Schilder zu leisten. Es können Schilderhüllen, Jute- oder Plastiksäcke verwendet werden. Wegweiser sind durch geeignete Auskreuzvorrichtung in Abstimmung mit der Bauüberwachung außer Kraft zu setzen. Nach Beendigung der Bauarbeiten aufgestellte Schilder, Leiteinrichtungen usw. abbauen, abfahren und benutzte Flächen in den ursprünglichen Zustand versetzen. Die Vergütung zur Einholung der verkehrlichen Anordnungen ist mit einzukalkulieren. Die Vergütung erfolgt entsprechend dem Baufortschritt. | E92: 1 | F92: psch | G92: =SUMPRODUCT((Kalkulation!A2:A50000=B92)*Kalkulation!D2:D50000) -> 0 | H92: =G92*E92 -> 0 | J92: =H92*(1-I92) -> 0 | K92: =B2 -> 0 | L92: 68b12ec4-df45-4506-86b5-e1f50a53d190 | M92: 556572bc-eb6a-478c-b939-d2df424e7d63
A93: Position | B93: 1.1.1.15 | C93: Vierseitige autom. Lichtsignalanlage | D93: Vierseitige autom. Lichtsignalanlage Transportable Lichtsignalanlage, Masten mit Auslegern, zur Regelung des Verkehrs aus 4 Richtungen inkl. Fußgänger- und Radfahrersignalisierung, mit bis zu 8 KFZ-Signalgruppen, 4 Radfahrer-Signalgruppen und 4 Fußgänger-Signalgruppen Verkehrsabhängig, funkuhrgesteuert Signalgeber, Schaltzeiten und Programme gemäß der TL Transportable Lichtsignalanlagen mit Signalsicherung nach RiLSA und VDE 0832, Eingangsspannung von 23OV I 50 Hz AC Stromversorgung erfolgt durch Anschluss an einen vom Auftragnehmer bereitgestellten Baustromverteiler inkl. der Einrichtung der erforderlichen Verkehrszeichen, anfahren, aufbauen, anschließen, entsprechend Bauphase mehrmalig, mindestens zweimalig umsetzen sowie erneut anschließen, Programmieren und nach Beendigung der Baumaßnahme wieder abbauen und abfahren. Die bis zu 4 Fußgänger-Signalgruppen sind mit einer Sehbehinderten Akustik auszustatten. Einschl. Luftverkabelung mehrmaliges Umsetzen während der einzelnen Bauphasen bei Verschiebungen im Baufeld bzw. erf. Änderung der Spurführung etc. einschließlich Erstellen der Verkehrstechnischen Unterlagen sowie Anpassung der Programmierung bei Verschiebungen im Baufeld. Vorhandene Signalgeber der stationären Anlage sind fachgerecht abzudecken. Die Verkehrsregelung ist im Einvernehmen mit der zuständigen Verkehrsbehörde durchzuführen. Eine entsprechende Anordnung ist durch den AN zu beantragen und bei Änderungen der LSA entsprechend anzupassen und erneut zu beantragen. Die Kosten für die verkehrsbehördliche Anordnung sind in den Einheitspreis einzukalkulieren. Die Signalanlage ist entsprechend der Örtlichkeit durch eine angepasste Verkehrsplanung (Schaltzeiten, Programm der LZA, Spurführung, Verkehrsaufkommen) zu betreiben. Werden nach Inbetriebnahme Probleme im Verkehrsablauf festgestellt, sind bis zu 4 Anpassungen in den Programmen im Einheitspreis enthalten. Anpassungen müssen vor Ort umsetzbar sein. Das Kleben, Vorhalten und Entfernen der erforderlichen gelben Fahrbahnmarkierung gem. RMS aus gelber reflektierender Folie 97 (Richtungspfeile, Führungs- und Haltestreifen, Demarkierungen) sowie die laufende Wartung bzw. Erneuerung der Streifen ist mit einzukalkulieren. 70 v.H. des Preises werden nach betriebsfertigem Aufstellen, der Rest nach Beseitigen vergütet. | E93: 1 | F93: St | G93: =SUMPRODUCT((Kalkulation!A2:A50000=B93)*Kalkulation!D2:D50000) -> 0 | H93: =G93*E93 -> 0 | J93: =H93*(1-I93) -> 0 | K93: =B2 -> 0 | L93: 68b12ec4-df45-4506-86b5-e1f50a53d190 | M93: 5c2cdfbc-504e-48d1-9677-4c4d6b177e16
A94: Position | B94: 1.1.1.16 | C94: Lichtsignalanlage vorhalten und betreiben | D94: Transportable Lichtsignalanlage gemäß Pos 1.1.1.15 vorhalten und durchgängig an allen Wochentagen einschließlich Sonn- und Feiertagen betreiben. Der Beginn, die Dauer des Betriebes und die Einstellung des Betriebes sind in den Tagesberichten festzuhalten. Reparaturkosten bei Defekten oder Ausfällen der Anlage sind in den Einheitspreis einzurechnen. | E94: 66 | F94: Wo | G94: =SUMPRODUCT((Kalkulation!A2:A50000=B94)*Kalkulation!D2:D50000) -> 0 | H94: =G94*E94 -> 0 | J94: =H94*(1-I94) -> 0 | K94: =B2 -> 0 | L94: 68b12ec4-df45-4506-86b5-e1f50a53d190 | M94: 1410da91-ea29-4ff6-a335-b434b3229b95
A95: Position | B95: 1.1.1.17 | C95: Zweiseitige Lichtsignalanlage (FG-Bedarfsampel) | D95: Transportable Lichtsignalanlage, zur Regelung des Verkehrs aus 2 Richtungen inkl. Fußgängersignalisierung mit 2 KFZ-Signalgruppen und 1 Fußgänger-Signalgruppe mit Bedarfsanforderung für Fußgänger. Signalgeber, Schaltzeiten und Programme gemäß der TL Transportable Lichtsignalanlagen mit Signalsicherung nach RiLSA und VDE 0832. Stromversorgung erfolgt durch Anschluss an einen vom Auftragnehmer bereitgestellten Baustromverteiler. Die Fußgänger-Signalgruppe ist mit einer Sehbehinderten Akustik auszustatten. Einschl. Luftverkabelung. Die Verkehrsregelung ist im Einvernehmen mit der zuständigen Verkehrsbehörde durchzuführen. Eine entsprechende Anordnung ist durch den AN zu beantragen und bei Änderungen der LSA entsprechend anzupassen und erneut zu beantragen. Die Kosten für die verkehrsbehördliche Anordnung sind in den Einheitspreis einzukalkulieren. Die Signalanlage ist entsprechend der Örtlichkeit durch eine angepasste Verkehrsplanung (Schaltzeiten, Programm der LZA, Spurführung, Verkehrsaufkommen) zu betreiben. Werden nach Inbetriebnahme Probleme im Verkehrsablauf festgestellt, sind bis zu 2 Anpassungen in den Programmen im Einheitspreis enthalten. Anpassungen müssen vor Ort umsetzbar sein. Das Kleben, Vorhalten und Entfernen der erforderlichen gelben Fahrbahnmarkierung gem. RMS aus gelber reflektierender Folie 97 (Richtungspfeile, Führungs- und Haltestreifen, Demarkierungen) sowie die laufende Wartung bzw. Erneuerung der Streifen ist mit einzukalkulieren. 70 v.H. des Preises werden nach betriebsfertigem Aufstellen, der Rest nach Beseitigen vergütet. | E95: 1 | F95: St | G95: =SUMPRODUCT((Kalkulation!A2:A50000=B95)*Kalkulation!D2:D50000) -> 0 | H95: =G95*E95 -> 0 | J95: =H95*(1-I95) -> 0 | K95: =B2 -> 0 | L95: 68b12ec4-df45-4506-86b5-e1f50a53d190 | M95: f75a467c-d4c6-4e53-bc9a-bce015c8be65
A96: Position | B96: 1.1.1.18 | C96: Lichtsignalanlage vorhalten und betreiben | D96: Transportable Lichtsignalanlage gemäß Pos. 1.1.1.17 vorhalten und durchgängig an allen Wochentagen einschließlich Sonn- und Feiertagen betreiben. Der Beginn, die Dauer des Betriebes und die Einstellung des Betriebes sind in den Tagesberichten festzuhalten. Reparaturkosten bei Defekten oder Ausfällen der Anlage sind in den Einheitspreis einzurechnen. | E96: 34 | F96: Wo | G96: =SUMPRODUCT((Kalkulation!A2:A50000=B96)*Kalkulation!D2:D50000) -> 0 | H96: =G96*E96 -> 0 | J96: =H96*(1-I96) -> 0 | K96: =B2 -> 0 | L96: 68b12ec4-df45-4506-86b5-e1f50a53d190 | M96: 4a7c8125-a717-4df1-9745-9020ce9653f0
A97: Position | B97: 1.1.1.19 | C97: Lichtsignalanlage für die Bauphasen 3a und 3b | D97: Lichtsignalanlage für die Bauphasen 3a und 3b Transportable Lichtsignalanlage, zur Sicherung der gegenläufigen Fahrbeziehung für Einsatzfahrzeuge und ÖPNV gegen die Einbahnregelung. Inkl. externer Anmeldung für Einsatzfahrzeuge und ÖPNV und mit bis zu 4 KFZ-Signalgruppen und einer Fußgänger-Signalgruppe mit Bedarfsanforderung für Fußgänger. Signalgeber, Schaltzeiten und Programme gemäß der TL Transportable Lichtsignalanlagen mit Signalsicherung nach RiLSA und VDE 0832, Eingangsspannung von 23OV I 50 Hz AC Stromversorgung erfolgt durch Anschluss an einen vom Auftragnehmer bereitgestellten Baustromverteiler inkl. der Einrichtung der erforderlichen Verkehrszeichen, anfahren, aufbauen, anschließen, entsprechend Bauphase umsetzen sowie erneut anschließen und nach Beendigung der Baumaßnahme wieder abbauen und abfahren. Die externe Anmeldung für Einsatzfahrzeuge und ÖPNV muss über eine Fahrzeughöhenerkennung, Anmeldung per Anruf und per Schlüsselschalter möglich sein. Im Zuge der Rheinberger Straße sind bis zu 10 Zufahrt in die Signalisierung einzubeziehen und mit Signalgebern auszustatten. Die Fußgänger-Signalgruppe ist mit einer Sehbehinderten Akustik auszustatten. Einschl. Luftverkabelung mehrmaliges Umsetzen während der einzelnen Bauphasen und bei Verschiebungen im Baufeld bzw. erf. Änderung der Spurführung etc. einschließlich Erstellen der Verkehrstechnischen Unterlagen sowie Anpassung der Programmierung bei Verschiebungen im Baufeld. Vorhandene Signalgeber der stationären Anlage sind fachgerecht abzudecken. Die Verkehrsregelung ist im Einvernehmen mit der zuständigen Verkehrsbehörde durchzuführen. Eine entsprechende Anordnung ist durch den AN zu beantragen und bei Änderungen der LSA entsprechend anzupassen und erneut zu beantragen. Die Kosten für die verkehrsbehördliche Anordnung sind in den Einheitspreis einzukalkulieren. Die Signalanlage ist entsprechend der Örtlichkeit durch eine angepasste Verkehrsplanung (Schaltzeiten, Programm der LZA, Spurführung, Verkehrsaufkommen) zu betreiben. Werden nach Inbetriebnahme Probleme im Verkehrsablauf festgestellt, sind bis zu 4 Anpassungen in den Programmen im Einheitspreis enthalten. Anpassungen müssen vor Ort umsetzbar sein. Das Kleben, Vorhalten und Entfernen der erforderlichen gelben Fahrbahnmarkierung gem. RMS aus gelber reflektierender Folie 97 (Richtungspfeile, Führungs- und Haltestreifen, Demarkierungen) sowie die laufende Wartung bzw. Erneuerung der Streifen ist mit einzukalkulieren. 70 v.H. des Preises werden nach betriebsfertigem Aufstellen, der Rest nach Beseitigen vergütet. | E97: 1 | F97: St | G97: =SUMPRODUCT((Kalkulation!A2:A50000=B97)*Kalkulation!D2:D50000) -> 0 | H97: =G97*E97 -> 0 | J97: =H97*(1-I97) -> 0 | K97: =B2 -> 0 | L97: 68b12ec4-df45-4506-86b5-e1f50a53d190 | M97: 6c23750a-e977-4812-ad4f-3b2e371b22c8
A98: Position | B98: 1.1.1.20 | C98: Lichtsignalanlage vorhalten und betreiben | D98: Transportable Lichtsignalanlage gemäß Pos. 1.1.1.19 vorhalten und durchgängig an allen Wochentagen einschließlich Sonn- und Feiertagen betreiben. Der Beginn, die Dauer des Betriebes und die Einstellung des Betriebes sind in den Tagesberichten festzuhalten. Reparaturkosten bei Defekten oder Ausfällen der Anlage sind in den Einheitspreis einzurechnen. | E98: 28 | F98: Wo | G98: =SUMPRODUCT((Kalkulation!A2:A50000=B98)*Kalkulation!D2:D50000) -> 0 | H98: =G98*E98 -> 0 | J98: =H98*(1-I98) -> 0 | K98: =B2 -> 0 | L98: 68b12ec4-df45-4506-86b5-e1f50a53d190 | M98: 9aa37964-4fcd-4ca2-a250-8b8790a885b1
A99: Position | B99: 1.1.1.21 | C99: Lichtsignalanlage für die Bauphase 3c | D99: Lichtsignalanlage für die Bauphase 3c Transportable Lichtsignalanlage, zur Regelung des Verkehrs aus 2 Richtungen und zur Sicherung der gegenläufigen Fahrbeziehung für Einsatzfahrzeuge und ÖPNV gegen die Einbahnregelung. Inkl. externer Anmeldung für Einsatzfahrzeuge und ÖPNV. Mit bis zu 6 KFZ-Signalgruppen und 2 Fußgänger-Signalgruppen mit Bedarfsanforderung für Fußgänger. Verkehrsabhängig, funkuhrgesteuert Signalgeber, Schaltzeiten und Programme gemäß der TL Transportable Lichtsignalanlagen mit Signalsicherung nach RiLSA und VDE 0832, Eingangsspannung von 23OV I 50 Hz AC Stromversorgung erfolgt durch Anschluss an einen vom Auftragnehmer bereitgestellten Baustromverteiler. Inkl. der Einrichtung der erforderlichen Verkehrszeichen, anfahren, aufbauen, anschließen, entsprechend Bauphase umsetzen sowie erneut anschließen und nach Beendigung der Baumaßnahme wieder abbauen und abfahren. Die externe Anmeldung für Einsatzfahrzeuge und ÖPNV muss über eine Fahrzeughöhenerkennung, Anmeldung per Anruf und per Schlüsselschalter möglich sein. Im Zuge der Rheinberger Straße sind bis zu 8 Zufahrt in die Signalisierung einzubeziehen und mit Signalgebern auszustatten. Die 2 Fußgänger-Signalgruppen sind mit einer Sehbehinderten Akustik auszustatten. Einschl. Luftverkabelung mehrmaliges Umsetzen während der Bauphase bei Verschiebungen im Baufeld bzw. erf. Änderung der Spurführung etc. einschließlich Erstellen der Verkehrstechnischen Unterlagen sowie Anpassung der Programmierung bei Verschiebungen im Baufeld. Vorhandene Signalgeber der stationären Anlage sind fachgerecht abzudecken. Die Verkehrsregelung ist im Einvernehmen mit der zuständigen Verkehrsbehörde durchzuführen. Eine entsprechende Anordnung ist durch den AN zu beantragen und bei Änderungen der LSA entsprechend anzupassen und erneut zu beantragen. Die Kosten für die verkehrsbehördliche Anordnung sind in den Einheitspreis einzukalkulieren. Die Signalanlage ist entsprechend der Örtlichkeit durch eine angepasste Verkehrsplanung (Schaltzeiten, Programm der LZA, Spurführung, Verkehrsaufkommen) zu betreiben. Werden nach Inbetriebnahme Probleme im Verkehrsablauf festgestellt, sind bis zu 4 Anpassungen in den Programmen im Einheitspreis enthalten. Anpassungen müssen vor Ort umsetzbar sein. Das Kleben, Vorhalten und Entfernen der erforderlichen gelben Fahrbahnmarkierung gem. RMS aus gelber reflektierender Folie 97 (Richtungspfeile, Führungs- und Haltestreifen, Demarkierungen) sowie die laufende Wartung bzw. Erneuerung der Streifen ist mit einzukalkulieren. 70 v.H. des Preises werden nach betriebsfertigem Aufstellen, der Rest nach Beseitigen vergütet. | E99: 1 | F99: St | G99: =SUMPRODUCT((Kalkulation!A2:A50000=B99)*Kalkulation!D2:D50000) -> 0 | H99: =G99*E99 -> 0 | J99: =H99*(1-I99) -> 0 | K99: =B2 -> 0 | L99: 68b12ec4-df45-4506-86b5-e1f50a53d190 | M99: f9bba7f2-dd7f-43cd-80fa-8261d3a199cd
A100: Position | B100: 1.1.1.22 | C100: Lichtsignalanlage vorhalten und betreiben | D100: Transportable Lichtsignalanlage gemäß Pos 1.1.1.21 vorhalten und durchgängig an allen Wochentagen einschließlich Sonn- und Feiertagen betreiben. Der Beginn, die Dauer des Betriebes und die Einstellung des Betriebes sind in den Tagesberichten festzuhalten. Reparaturkosten bei Defekten oder Ausfällen der Anlage sind in den Einheitspreis einzurechnen. | E100: 7 | F100: Wo | G100: =SUMPRODUCT((Kalkulation!A2:A50000=B100)*Kalkulation!D2:D50000) -> 0 | H100: =G100*E100 -> 0 | J100: =H100*(1-I100) -> 0 | K100: =B2 -> 0 | L100: 68b12ec4-df45-4506-86b5-e1f50a53d190 | M100: a0a805e2-5bde-40c3-ad05-b6573f5b500b
A101: Position | B101: 1.1.1.23 | C101: Lichtsignalanlage für die Bauphasen 4 a und 4 b | D101: Lichtsignalanlage für die Bauphasen 4a und 4b Transportable Lichtsignalanlage, zur Regelung des Verkehrs aus 3 Richtungen inkl. Fußgängersignalisierung, mit bis zu 6 KFZ-Signalgruppen und 3 Fußgänger-Signalgruppen. Verkehrsabhängig, funkuhrgesteuert Signalgeber, Schaltzeiten und Programme gemäß der TL Transportable Lichtsignalanlagen mit Signalsicherung nach RiLSA und VDE 0832, Eingangsspannung von 23OV I 50 Hz AC Stromversorgung erfolgt durch Anschluss an einen vom Auftragnehmer bereitgestellten Baustromverteiler inkl. der Einrichtung der erforderlichen Verkehrszeichen, anfahren, aufbauen, anschließen, entsprechend Bauphase mehrmalig, mindestens zweimalig umsetzen (siehe Verkehrskonzept) sowie erneut anschließen, Programmieren und nach Beendigung der Baumaßnahme wieder abbauen und abfahren. Die bis zu 3 Fußgänger-Signalgruppen sind mit einer Sehbehinderten Akustik auszustatten. Einschl. Luftverkabelung mehrmaliges Umsetzen während der einzelnen Bauphasen bei Verschiebungen im Baufeld bzw. erf. Änderung der Spurführung etc. einschließlich Erstellen der Verkehrstechnischen Unterlagen sowie Anpassung der Programmierung bei Verschiebungen im Baufeld. Vorhandene Signalgeber der stationären Anlage sind fachgerecht abzudecken. Die Verkehrsregelung ist im Einvernehmen mit der zuständigen Verkehrsbehörde durchzuführen. Eine entsprechende Anordnung ist durch den AN zu beantragen und bei Änderungen der LSA entsprechend anzupassen und erneut zu beantragen. Die Kosten für die verkehrsbehördliche Anordnung sind in den Einheitspreis einzukalkulieren. Die Signalanlage ist entsprechend der Örtlichkeit durch eine angepasste Verkehrsplanung (Schaltzeiten, Programm der LZA, Spurführung, Verkehrsaufkommen) zu betreiben. Werden nach Inbetriebnahme Probleme im Verkehrsablauf festgestellt, sind bis zu 4 Anpassungen in den Programmen im Einheitspreis enthalten. Anpassungen müssen vor Ort umsetzbar sein. Das Kleben, Vorhalten und Entfernen der erforderlichen gelben Fahrbahnmarkierung gem. RMS aus gelber reflektierender Folie 97 (Richtungspfeile, Führungs- und Haltestreifen, Demarkierungen) sowie die laufende Wartung bzw. Erneuerung der Streifen ist mit einzukalkulieren. 70 v.H. des Preises werden nach betriebsfertigem Aufstellen, der Rest nach Beseitigen vergütet. | E101: 1 | F101: St | G101: =SUMPRODUCT((Kalkulation!A2:A50000=B101)*Kalkulation!D2:D50000) -> 0 | H101: =G101*E101 -> 0 | J101: =H101*(1-I101) -> 0 | K101: =B2 -> 0 | L101: 68b12ec4-df45-4506-86b5-e1f50a53d190 | M101: 1278bf59-5287-47fc-bf86-060181de2250
A102: Position | B102: 1.1.1.24 | C102: Lichtsignalanlage vorhalten und betreiben | D102: Transportable Lichtsignalanlage gemäß Pos 1.1.1.23 vorhalten und durchgängig an allen Wochentagen einschließlich Sonn- und Feiertagen betreiben. Der Beginn, die Dauer des Betriebes und die Einstellung des Betriebes sind in den Tagesberichten festzuhalten. Reparaturkosten bei Defekten oder Ausfällen der Anlage sind in den Einheitspreis einzurechnen. | E102: 18 | F102: Wo | G102: =SUMPRODUCT((Kalkulation!A2:A50000=B102)*Kalkulation!D2:D50000) -> 0 | H102: =G102*E102 -> 0 | J102: =H102*(1-I102) -> 0 | K102: =B2 -> 0 | L102: 68b12ec4-df45-4506-86b5-e1f50a53d190 | M102: d0b24a78-999e-416a-98bd-08f7debc1318
A103: Position | B103: 1.1.1.25 | C103: Fußgänger-Behelfsbrücke umsetzen | D103: Fußgänger-Behelfsbrücke der Vorposition umsetzen und vorhalten. | E103: 23 | F103: St | G103: =SUMPRODUCT((Kalkulation!A2:A50000=B103)*Kalkulation!D2:D50000) -> 0 | H103: =G103*E103 -> 0 | J103: =H103*(1-I103) -> 0 | K103: =B2 -> 0 | L103: 68b12ec4-df45-4506-86b5-e1f50a53d190 | M103: 37162918-f744-4162-8e64-a62ab78c9ccc
A104: Position | B104: 1.1.1.26 | C104: Fußgänger-Behelfsbrücke | D104: Fußgängerbrücke mit einer lichten Breite von min. 1,00 m, rutschfreie Oberfläche, Geländer- und Zwischenholm sowie Tastenleiste herstellen, vorhalten und wieder abbauen. | E104: 2 | F104: St | G104: =SUMPRODUCT((Kalkulation!A2:A50000=B104)*Kalkulation!D2:D50000) -> 0 | H104: =G104*E104 -> 0 | J104: =H104*(1-I104) -> 0 | K104: =B2 -> 0 | L104: 68b12ec4-df45-4506-86b5-e1f50a53d190 | M104: f4f98a70-def6-4d0b-b419-07df36b1ce52
A105: Position | B105: 1.1.1.27 | C105: Abdeckungen mit Stahlplatten herstellen | D105: Abdeckung mit Stahlplatten (mindestens SLW 60) für Rohrgräben, Suchgräben (Kopflöcher) Hausanschlüsse u.ä. höhengleich und verschiebesicher einbauen, vorhalten und wieder ausbauen; einschl. entsprechender bituminöser Anrampungen. Abrechnung nach lichter, überdeckter Baugrube. | E105: 50 | F105: m2 | G105: =SUMPRODUCT((Kalkulation!A2:A50000=B105)*Kalkulation!D2:D50000) -> 0 | H105: =G105*E105 -> 0 | J105: =H105*(1-I105) -> 0 | K105: =B2 -> 0 | L105: 68b12ec4-df45-4506-86b5-e1f50a53d190 | M105: 401e6b39-d6d4-4d83-a935-ee3272acc7e0
A106: Position | B106: 1.1.1.28 | C106: Straßenreinigung durchführen | D106: Straßenreinigung der angrenzenden, baubedingt verunreinigten Straßen durchführen. Die Straßenreinigung ist je nach Erfordernis ggfs. auch mehrmals täglich durchzuführen. Alle hieraus resultierenden Kosten sind in den Einheitspreis mit einzukalkulieren. | E106: 1 | F106: psch | G106: =SUMPRODUCT((Kalkulation!A2:A50000=B106)*Kalkulation!D2:D50000) -> 0 | H106: =G106*E106 -> 0 | J106: =H106*(1-I106) -> 0 | K106: =B2 -> 0 | L106: 68b12ec4-df45-4506-86b5-e1f50a53d190 | M106: 925512ed-0e88-4cd2-a214-604a6e86a5cb
A107: Position | B107: 1.1.1.29 | C107: Beleuchtung entfernen, zwischenlagern und wieder aufstellen | D107: Vorhandenen Beleuchtungsmast bis LPH 10,00 m, vom Anschluss gemeinsam mit VU trennen. Lichtpunkthöhe bis 10,00 m. Mast aufnehmen und lagern, nach Abschluss der Arbeiten wieder in das neue zu erstellende Fundament in statisch ausreichender Dimensionierung, neu versetzen und wieder mit VU anschließen. Einschl. der erforderlichen Erdarbeiten und Abfuhr der verdrängten Erdmassen, Entsorgen des alten Fundaments und Verfüllen der alten Grube mit geeignetem Material. Einschl. neuem Fundament, Herstellung der Muffen- verbindung für den alten Anschluss und dem neuen Anschluss durch den AN. Mast einschl. Leuchtmittel bis LPH 10,00 m. Auslegerlänge: bis 2 * 2,00m | E107: 8 | F107: St | G107: =SUMPRODUCT((Kalkulation!A2:A50000=B107)*Kalkulation!D2:D50000) -> 0 | H107: =G107*E107 -> 0 | J107: =H107*(1-I107) -> 0 | K107: =B2 -> 0 | L107: 68b12ec4-df45-4506-86b5-e1f50a53d190 | M107: 06b65907-f4ac-4561-8298-589c5f6e29a0
A108: Hinweistext | C108: HINWEIS | D108: Schutzeinrichtungen nach Beendigung der Bauarbeiten abbauen, das Material ist von der Baustelle zu entfernen. Abrechnungsregelungen: Stammumfänge werden 1 m über Geländeoberkante gemessen. 80 v.H. der Einheitspreise werden nach Erstellung der Schutzvorrichtung, der Rest nach Entfernung der Schutzvorrichtung gezahlt. | K108: ="" | M108: 736e7cfc-48dc-4205-b47b-5a60111dbad5
A109: Position | B109: 1.1.1.30 | C109: Baumschutz Umfang von 1,00 m bis 1,50 m herstellen | D109: Wie vor Position , jedoch Stammumfang von 1,00 m - 1,50 m | E109: 1 | F109: St | G109: =SUMPRODUCT((Kalkulation!A2:A50000=B109)*Kalkulation!D2:D50000) -> 0 | H109: =G109*E109 -> 0 | J109: =H109*(1-I109) -> 0 | K109: =B2 -> 0 | L109: 68b12ec4-df45-4506-86b5-e1f50a53d190 | M109: d5bd84f1-5946-455d-825d-8fa4557ac250
A110: Position | B110: 1.1.1.31 | C110: Organisation Müllentsorgung, je Woche | D110: Während der Baumaßnahme hat der AN zwei bis drei Mal x wöchentlich die 2-Rad Mülltonen bis 240 l und 4-Rad Mülltonen bis 1100 l der Anwohner außerhalb des Baustellenbereiches zu den Leerungsterminen zu den Übergabepunkten aufzustellen. Ein Übergabepunkt ist mit der ENNI festzulegen. Nach erfolgter Leerung sind die Mülltonnen wieder auf die Grundstücke der Anwohner zu stellen. Zu dem sogenannten "Müll-Service" zählen: Restmülltonne Biotonne Blaue Tonne Gelbe Säcke Der AN hat sich rechtzeitig über die Abholtermine zu informieren. Verschiebungen der Abholtermine wegen möglicher Feiertage sind zu beachten. Einzurechnen sind bis zu 60 Mülltonnen pro Entsorgung, Transportweg bis Sammelstellplatz bis ca. 250 m. Ansprechpartner ENNI Stadt und Service: Friedel Baumann: Tel. 01709137254 / Mail: fbaumann@enni.de Frank Seemann: Tel. 017614744217 / Mail: fseemann@enni.de | E110: 66 | F110: Wo | G110: =SUMPRODUCT((Kalkulation!A2:A50000=B110)*Kalkulation!D2:D50000) -> 0 | H110: =G110*E110 -> 0 | J110: =H110*(1-I110) -> 0 | K110: =B2 -> 0 | L110: 68b12ec4-df45-4506-86b5-e1f50a53d190 | M110: 4f141306-d7b8-424b-84f5-d88a1d8ca354
A111: Position | B111: 1.1.1.32 | C111: Koordination Feuerwehr, je Woche | D111: Vor Arbeitsbeginn / Einrichtung der Baustelle ist die Feuerwehr über den Starttermin zu informieren. Während der Baumaßnahme ist der Auftragnehmer vertraglich verpflichtet der Feuerwehr wöchentliche Berichte über den Stand der Arbeiten und den geplanten Arbeitsfortschritt mitzuteilen. Rückmeldungen zu Straßensperrungen, insbesondere deren voraussichtliche Dauer sind von besonderer Wichtigkeit, diese sind vor Arbeitsbeginn bekannt zu geben. Desweiteren müssen noch Änderungen im geplanten Bauablauf unverzüglich nach Bekanntwerden mitgeteilt werden, diese sind dann mit der Feuerwehr bezüglich der Feuerwehrzufahrten im Baustellenbereich abzustimmen. "Änderungen" bedeuten in diesem Zusammenhang, dass sich Einfahrt-, Zufahrts- oder Einmündungsbereiche sowie Fahrtwege ändern, oder die Baustelle "weiterzieht". (Zum Beispiel: Nächste Woche Baugrube/Vollsperrung im Bereich Musterstraße zwischen Haus-Nr. 50a und 56 / 1 und 9). Die Mitteilung an die Feuerwehr muss grundsätzlich mit Zeichnung / Plan erfolgen. Mitteilung über Beendigung der Arbeiten an Feuerwehr übersenden. Weitere Informationen sind den Vorbemerkungen zu entnehmen. | E111: 66 | F111: Wo | G111: =SUMPRODUCT((Kalkulation!A2:A50000=B111)*Kalkulation!D2:D50000) -> 0 | H111: =G111*E111 -> 0 | J111: =H111*(1-I111) -> 0 | K111: =B2 -> 0 | L111: 68b12ec4-df45-4506-86b5-e1f50a53d190 | M111: bbb2bb34-f031-493e-9ae0-257f392552e1
A112: Summe Gruppe | B112: 1.1.1. | C112: Baustelleneinrichtungsarbeiten | H112: =SUMIF(L:L,"68b12ec4-df45-4506-86b5-e1f50a53d190",J:J) -> 0 | J112: =H112*(1-I112) -> 0 | L112: d539e62c-539c-4067-8aef-0a8af150ede8 | M112: 68b12ec4-df45-4506-86b5-e1f50a53d190
A113: Gruppe | B113: 1.1.2. | C113: Beweissicherung | K113: =""
A114: Position | B114: 1.1.2.01 | C114: Beweissicherung Gebäude von 001 bis 400 m² | D114: Beweissicherungsverfahren im Einflussbereich der Kanal- und Straßenbauarbeiten, für Gebäude durch Begehung, innen (einschl. priv. Wohnungen und Kellerräume) und außen, durchführen und dokumentieren. Es ist ein bei Gericht zugelassener Sachverständiger einzuschalten, der vom AN zu beauftragen ist. Die Beweissicherung ist vor Beginn der Arbeiten durchzuführen. Die Dokumentation ist in dreifacher Ausfertigung herzustellen. Beweissicherungsverfahren für Gebäude (Gewerbe, Arztpraxis und Wohngebäude, mehrstöckig inkl. Keller) mit einer Wohn- bzw. Nutzfläche von 001 m² bis 400 m²; einschl. der Abstimmung der Begehung mit den Eigentums- und/oder Mietparteien. Adressen: Rheinberger Straße Hausnummer 18 Rheinberger Straße Hausnummer 28 Rheinberger Straße Hausnummer 30 Rheinberger Straße Hausnummer 37 Rheinberger Straße Hausnummer 39a Rheinberger Straße Hausnummer 43 Rheinberger Straße Hausnummer 51 | E114: 7 | F114: St | G114: =SUMPRODUCT((Kalkulation!A2:A50000=B114)*Kalkulation!D2:D50000) -> 0 | H114: =G114*E114 -> 0 | J114: =H114*(1-I114) -> 0 | K114: =B2 -> 0 | L114: 5ab05861-6448-46e3-bee7-9c4493ab5bdf | M114: 8bb2c1e9-4d5c-4a35-9408-53fff88c31d8
A115: Position | B115: 1.1.2.02 | C115: Beweissicherung Gebäude von 400 bis 800 m² | D115: Beweissicherungsverfahren im Einflussbereich der Kanal- und Straßenbauarbeiten, für Gebäude durch Begehung, innen (einschl. priv. Wohnungen und Kellerräume) und außen, durchführen und dokumentieren. Es ist ein bei Gericht zugelassener Sachverständiger einzuschalten, der vom AN zu beauftragen ist. Die Beweissicherung ist vor Beginn der Arbeiten durchzuführen. Die Dokumentation ist in dreifacher Ausfertigung herzustellen. Beweissicherungsverfahren für Gebäude (Gewerbe, Arztpraxis und Wohngebäude, mehrstöckig inkl. Keller) mit einer Wohn- bzw. Nutzfläche von 400 m² bis 800 m²; einschl. der Abstimmung der Begehung mit den Eigentums- und/oder Mietparteien. Adressen: Rheinberger Straße Hausnummer 39 Rheinberger Straße Hausnummer 53 | E115: 2 | F115: St | G115: =SUMPRODUCT((Kalkulation!A2:A50000=B115)*Kalkulation!D2:D50000) -> 0 | H115: =G115*E115 -> 0 | J115: =H115*(1-I115) -> 0 | K115: =B2 -> 0 | L115: 5ab05861-6448-46e3-bee7-9c4493ab5bdf | M115: d7cfc1c8-c933-4e39-872a-13f2d694adfa
A116: Position | B116: 1.1.2.03 | C116: Beweissicherung Gebäude von 800 bis 1700 m² | D116: Beweissicherungsverfahren im Einflussbereich der Kanal- und Straßenbauarbeiten, für Gebäude durch Begehung, innen (einschl. priv. Wohnungen und Kellerräume) und außen, durchführen und dokumentieren. Es ist ein bei Gericht zugelassener Sachverständiger einzuschalten, der vom AN zu beauftragen ist. Die Beweissicherung ist vor Beginn der Arbeiten durchzuführen. Die Dokumentation ist in dreifacher Ausfertigung herzustellen. Beweissicherungsverfahren für Gebäude (Gewerbe, Arztpraxis und Wohngebäude, mehrstöckig inkl. Keller) mit einer Wohn- bzw. Nutzfläche von 800 m² bis 1700 m²; einschl. der Abstimmung der Begehung mit den Eigentums- und/oder Mietparteien. Adressen: Rheinberger Straße Hausnummer 33-35 Rheinberger Straße Hausnummer 41 Rheinberger Straße Hausnummer 47 Rheinberger Straße Hausnummer 55 a, b, c | E116: 4 | F116: St | G116: =SUMPRODUCT((Kalkulation!A2:A50000=B116)*Kalkulation!D2:D50000) -> 0 | H116: =G116*E116 -> 0 | J116: =H116*(1-I116) -> 0 | K116: =B2 -> 0 | L116: 5ab05861-6448-46e3-bee7-9c4493ab5bdf | M116: 469bbb2d-5aa9-47df-90a9-961c4582bdd0
A117: Position | B117: 1.1.2.04 | C117: Dokumentation Einfriedungen und Oberflächen | D117: Fotodokumentation der im Bereich der Kanal- und Straßenbauarbeiten beidseitig am Baufeld angrenzenden bzw. anbindenden privaten Oberflächen wie Parkplatzflächen, Vorgärten, Einfahrten etc. und Einfriedungen wie Mauern, Zäune, Hecken etc.. Die Fotodokumentation ist vor Beginn der Arbeiten durchzuführen mit Angaben des Datums. Die Dokumentation bzw. die Bilder müssen den Bestand mit ggf. vorhandenen Schäden wiedergeben, die Örtlichkeit muss eindeutig zugeordnet werden können. Die Dokumentation ist vor Beginn der Arbeiten dem AG zu übergeben. | E117: 1 | F117: psch | G117: =SUMPRODUCT((Kalkulation!A2:A50000=B117)*Kalkulation!D2:D50000) -> 0 | H117: =G117*E117 -> 0 | J117: =H117*(1-I117) -> 0 | K117: =B2 -> 0 | L117: 5ab05861-6448-46e3-bee7-9c4493ab5bdf | M117: 8bf4b15c-24cc-46f9-b8cb-39d8ef25ae62
A118: Summe Gruppe | B118: 1.1.2. | C118: Beweissicherung | H118: =SUMIF(L:L,"5ab05861-6448-46e3-bee7-9c4493ab5bdf",J:J) -> 0 | J118: =H118*(1-I118) -> 0 | L118: d539e62c-539c-4067-8aef-0a8af150ede8 | M118: 5ab05861-6448-46e3-bee7-9c4493ab5bdf
A119: Gruppe | B119: 1.1.3. | C119: Vorarbeiten | K119: =""
A120: Hinweistext | C120: Vortext Vorarbeiten | D120: Baustoffe, die zum Bauhof der ENNI Stadt & Service Niederrhein AöR (Am Jostenhof 15 in 47441 Moers) gefahren werden, sind dort gegen Quittung abzugeben. Der Auftragnehmer ist verpflichtet, alle anfallenden Rest- und Abfallstoffe, Böden, Aufbruchmaterialien fachgerecht zu entsorgen. Die entsprechenden Nachweise über die fachgerechte Entsorgung sind dem Auftraggeber unaufgefordert bei Rechnungsstellung vorzulegen. Entsprechend den Vorgaben des Kreislaufwirtschaftsgesetzes ist in jedem Fall der Verwertung Vorrang vor einer Beseitigung anfallender Materialien einzuräumen. Die für eine Verwertung oder Beseitigung entstehenden Kosten z. B. Deponiegebühren werden nicht gesondert vergütet und sind in die Einheitspreise einzukalkulieren. | K120: ="" | M120: f1df08f9-a1bc-4fe9-be01-4c807ce3b551
A121: Position | B121: 1.1.3.01 | C121: Verkehrsschildpfosten mit Verkehrszeichen aufnehmen und entsorgen | D121: Verkehrsschildpfosten mit Verkehrszeichen aufnehmen und entsorgen, Betonfundament abstemmen und beseitigen. Altes Fundamentloch mit geeignetem Material verfüllen und verdichten. Einschließlich der erforderlichen Erdarbeiten. | E121: 8 | F121: St | G121: =SUMPRODUCT((Kalkulation!A2:A50000=B121)*Kalkulation!D2:D50000) -> 0 | H121: =G121*E121 -> 0 | J121: =H121*(1-I121) -> 0 | K121: =B2 -> 0 | L121: 49d620c7-035a-45b3-b3c3-fc9136915b0f | M121: a6cb99c7-d222-4394-b5ac-a87017fbf1a1
A122: Position | B122: 1.1.3.02 | C122: Pfosten für Verkehrszeichen in Bodenhülse liefern und versetzen | D122: Pfosten für Verkehrszeichen 60,3 mm Durchmesser, stahl - Feuerverzinkt, Höhe bis 3.000 mm einschließlich Bodenhülse liefern und in Betonfundament versetzen, einschließlich der Erdarbeiten und Abfuhr des verdrängten Bodens, sowie Wiederherstellung der Oberfläche. Inklusive aller Erdarbeiten. | E122: 14 | F122: St | G122: =SUMPRODUCT((Kalkulation!A2:A50000=B122)*Kalkulation!D2:D50000) -> 0 | H122: =G122*E122 -> 0 | J122: =H122*(1-I122) -> 0 | K122: =B2 -> 0 | L122: 49d620c7-035a-45b3-b3c3-fc9136915b0f | M122: 7034dbad-b29a-4993-a52f-90616f0f7c18
A123: Position | B123: 1.1.3.03 | C123: Beschilderung sichern | D123: Beschilderung für die Dauer der Bauzeit vor Beschädigungen sichern. Kosten für Behinderungen durch die Beschilderung sind in die Position einzukalkulieren. Die Funktionstüchtigkeit wird nach Fertigstellung der Baumaßnahme durch den Auftraggeber überprüft. | E123: 3 | F123: St | G123: =SUMPRODUCT((Kalkulation!A2:A50000=B123)*Kalkulation!D2:D50000) -> 0 | H123: =G123*E123 -> 0 | J123: =H123*(1-I123) -> 0 | K123: =B2 -> 0 | L123: 49d620c7-035a-45b3-b3c3-fc9136915b0f | M123: 978c267d-12f5-4c15-aeb2-d5aff043c207
A124: Position | B124: 1.1.3.04 | C124: Vorhandene Verkehrsschilder demontieren, lagern und neu montieren | D124: Vorh. Verkehrsschilder (Verkehrszeichen, Straßennamen, etc.) demontieren, gegen Beschädigungen in Plastikhüllen geschützt innerhalb des Baufeldes zwischenlagern und an neuem Pfosten montieren. Die durch unsachgemäße Behandlung beschädigten Verkehrszeichen werden auf Kosten des AN ersetzt. | E124: 4 | F124: St | G124: =SUMPRODUCT((Kalkulation!A2:A50000=B124)*Kalkulation!D2:D50000) -> 0 | H124: =G124*E124 -> 0 | J124: =H124*(1-I124) -> 0 | K124: =B2 -> 0 | L124: 49d620c7-035a-45b3-b3c3-fc9136915b0f | M124: 21e3a7bf-de35-4e36-94da-8aa48d6af403
A125: Position | B125: 1.1.3.05 | C125: Verkehrsschildpfosten mit Verkehrszeichen aufnehmen, lagern und wieder einsetzen | D125: Verkehrsschildpfosten mit Verkehrszeichen aufnehmen, Betonfundament abstemmen und beseitigen. Verkehrszeichen gegen Beschädigungen in Plastikhülle o.ä. schützten und innerhalb des Baufeldes zwischenlagern. Altes Fundamentloch mit geeignetem Material verfüllen und verdichten. Verkehrsschildpfosten mit Verkehrszeichen in einem neu zu erstellendem Betonfundamenten wieder einsetzen. Die durch unsachgemäße Behandlung beschädigten Verkehrszeichen werden auf Kosten des AN ersetzt. Einschließlich der erforderlichen Erdarbeiten. | E125: 6 | F125: St | G125: =SUMPRODUCT((Kalkulation!A2:A50000=B125)*Kalkulation!D2:D50000) -> 0 | H125: =G125*E125 -> 0 | J125: =H125*(1-I125) -> 0 | K125: =B2 -> 0 | L125: 49d620c7-035a-45b3-b3c3-fc9136915b0f | M125: 834a73c7-8a77-47e2-9ee1-7820bfca2208
A126: Position | B126: 1.1.3.06 | C126: Großbeschilderung Vorwegweiser sichern | D126: Großbeschilderung Vorwegweiser für die Dauer der Bauzeit vor Beschädigungen sichern. Kosten für Behinderungen durch die Großbeschilderung sind in die Position einzukalkulieren. Die Funktionstüchtigkeit wird nach Fertigstellung der Baumaßnahme durch den Auftraggeber überprüft. | E126: 2 | F126: St | G126: =SUMPRODUCT((Kalkulation!A2:A50000=B126)*Kalkulation!D2:D50000) -> 0 | H126: =G126*E126 -> 0 | J126: =H126*(1-I126) -> 0 | K126: =B2 -> 0 | L126: 49d620c7-035a-45b3-b3c3-fc9136915b0f | M126: eb20a9e9-883f-4deb-ba9b-7802f36f8f13
A127: Position | B127: 1.1.3.07 | C127: Großbeschilderungspfosten Parkleitsystem überführen und montieren | D127: Der vorhandene Großbeschilderungspfosten (Parkleit- system) ist im Bauhof eingelagert. Der Pfosten ist vom Auftragnehmer fachgerecht beim Bauhof (Am Jostenhof) abzuholen, zu verladen, transportsicher zu befestigen und zur Baustelle zu überführen. An der Baustelle ist der Pfosten auf dem neu hergestellten Fundament gemäß 1.1.3.8 fachgerecht aufzustellen und zu montieren. Ausrichten und Befestigen entsprechend den Montagevorschriften des Herstellers. Alle erforderlichen Hilfs- und Nebenleistungen (z.B. Transport, Hebezeug, Montagepersonal, Schrauben, Verbindungsmittel) sind im Einheitspreis enthalten. | E127: 1 | F127: St | G127: =SUMPRODUCT((Kalkulation!A2:A50000=B127)*Kalkulation!D2:D50000) -> 0 | H127: =G127*E127 -> 0 | J127: =H127*(1-I127) -> 0 | K127: =B2 -> 0 | L127: 49d620c7-035a-45b3-b3c3-fc9136915b0f | M127: 8c049b67-f478-4ef8-9c3a-ad897cb3b3c2
A128: Position | B128: 1.1.3.08 | C128: Fundament für Parkleitsystem inklusive Mastanker herstellen | D128: Fundament für Parkleitsystem herstellen. Einschließlich aller Erd- und Nebenarbeiten, sowie Herstellung der notwendigen Schalung. Inkl. Kabelschutzrohr, kommend vom nächsten Schacht, seitlich in das Fundament einführen und mittig durch Mastanker bis OK führen und in Fundament einbauen. Abmessungen: 1500/1500/1000 mm Beton: C25/30 Höhe OK Fundament: -0,20 m, gemessen ab gepl. GOK Ausführungsdetails (Mastanker) sind der den Ausschreibungsunterlagen beiliegenden Anlage zu entnehmen (siehe Anlage_1). | E128: 1 | F128: St | G128: =SUMPRODUCT((Kalkulation!A2:A50000=B128)*Kalkulation!D2:D50000) -> 0 | H128: =G128*E128 -> 0 | J128: =H128*(1-I128) -> 0 | K128: =B2 -> 0 | L128: 49d620c7-035a-45b3-b3c3-fc9136915b0f | M128: 705161de-51bd-4527-84fb-9cc38c2cbcca
A129: Position | B129: 1.1.3.09 | C129: Fundament für Wartehalle herstellen | D129: Fundament für Wartehalle gemäß Anlage 2 (Fundamentplatte Wartehalle K8 - Statik) herstellen. Einschließlich aller Erd- und Nebenarbeiten. Abmessungen der Fundamentplatte: 2,00/5,00/0,20 m Beton: C30/37 Höhe OK Fundamentplatte: -0,20 m, gemessen ab gepl. GOK Die Platte ist in Waage herzustellen. | E129: 1 | F129: St | G129: =SUMPRODUCT((Kalkulation!A2:A50000=B129)*Kalkulation!D2:D50000) -> 0 | H129: =G129*E129 -> 0 | J129: =H129*(1-I129) -> 0 | K129: =B2 -> 0 | L129: 49d620c7-035a-45b3-b3c3-fc9136915b0f | M129: b6cea669-6af8-4632-bf4c-381ed53ac900
A130: Position | B130: 1.1.3.10 | C130: Befestigungen / Fundamente aus unbewehrtem Beton abbrechen | D130: Befestigungen / Fundamente aus unbewehrtem Beton ab- brechen. Aufbruchgut ist fachgerecht zu entsorgen. Einschließlich Entsorgungskosten. Erdvertiefungen mit geeignetem Füllboden auffüllen und verdichten, einschließlich Lieferung. | E130: 3 | F130: m3 | G130: =SUMPRODUCT((Kalkulation!A2:A50000=B130)*Kalkulation!D2:D50000) -> 0 | H130: =G130*E130 -> 0 | J130: =H130*(1-I130) -> 0 | K130: =B2 -> 0 | L130: 49d620c7-035a-45b3-b3c3-fc9136915b0f | M130: e0d1259f-9173-4f1c-847f-b30cb02b8c17
A131: Position | B131: 1.1.3.11 | C131: Befestigungen / Fundamente aus bewehrtem Beton abbrechen | D131: Befestigungen / Fundamente aus bewehrtem Beton ab- brechen. Aufbruchgut ist fachgerecht zu entsorgen. Einschließlich Entsorgungskosten. Erdvertiefungen mit geeignetem Füllboden auffüllen und verdichten, einschließlich Lieferung. | E131: 3 | F131: m3 | G131: =SUMPRODUCT((Kalkulation!A2:A50000=B131)*Kalkulation!D2:D50000) -> 0 | H131: =G131*E131 -> 0 | J131: =H131*(1-I131) -> 0 | K131: =B2 -> 0 | L131: 49d620c7-035a-45b3-b3c3-fc9136915b0f | M131: a976aded-1db1-4d15-891e-4f3d765fb94f
A132: Position | B132: 1.1.3.12 | C132: Schaltschrank sichern | D132: Schaltschrank für die Dauer der Bauzeit vor Beschädigungen sichern. Die Verdichtung im Bereich des Schaltschrankes hat besonders sorgfältig zu erfolgen, um spätere Setzungen zu vermeiden. Die Funktionstüchtigkeit wird nach dem Einbau durch den Auftraggeber überprüft. | E132: 8 | F132: St | G132: =SUMPRODUCT((Kalkulation!A2:A50000=B132)*Kalkulation!D2:D50000) -> 0 | H132: =G132*E132 -> 0 | J132: =H132*(1-I132) -> 0 | K132: =B2 -> 0 | L132: 49d620c7-035a-45b3-b3c3-fc9136915b0f | M132: 7ec05db5-7b47-4817-b547-e9ea55ab500a
A133: Position | B133: 1.1.3.13 | C133: Abfallbehälter aufnehmen, lagern und wiederversetzen | D133: Abfallbehälter aufnehmen, Betonfundament abstemmen und beseitigen. Abfallbehälter gegen Beschädigungen schützten und innerhalb des Baufeldes zwischenlagern. Altes Fundamentloch mit geeignetem Material verfüllen und verdichten. Abfallbehälter in einem neu zu erstellendem Betonfundamenten wieder versetzen. Durch unsachgemäße Behandlung entstandene Schäden werden auf Kosten des AN ersetzt. Einschließlich der erforderlichen Erdarbeiten. | E133: 1 | F133: St | G133: =SUMPRODUCT((Kalkulation!A2:A50000=B133)*Kalkulation!D2:D50000) -> 0 | H133: =G133*E133 -> 0 | J133: =H133*(1-I133) -> 0 | K133: =B2 -> 0 | L133: 49d620c7-035a-45b3-b3c3-fc9136915b0f | M133: 3163bbdd-6461-4a1a-b229-f429909efb80
A134: Summe Gruppe | B134: 1.1.3. | C134: Vorarbeiten | H134: =SUMIF(L:L,"49d620c7-035a-45b3-b3c3-fc9136915b0f",J:J) -> 0 | J134: =H134*(1-I134) -> 0 | L134: d539e62c-539c-4067-8aef-0a8af150ede8 | M134: 49d620c7-035a-45b3-b3c3-fc9136915b0f
A135: Gruppe | B135: 1.1.4. | C135: Technische Bearbeitung | K135: =""
A136: Position | B136: 1.1.4.01 | C136: Technische Bearbeitung, Überwachung | D136: Technische Bearbeitung - Ergebnisse der Eigenüberwachung gem. ZTV Asphalt, neueste Fassung, für den Straßenbau liefern. | E136: 1 | F136: psch | G136: =SUMPRODUCT((Kalkulation!A2:A50000=B136)*Kalkulation!D2:D50000) -> 0 | H136: =G136*E136 -> 0 | J136: =H136*(1-I136) -> 0 | K136: =B2 -> 0 | L136: 30cfe42b-c654-44f0-beb5-6f291b6f5846 | M136: 5f7be87f-9eac-439d-99c9-53fe814956a0
A137: Position | B137: 1.1.4.02 | C137: Lastplattendruckversuche | D137: Lastplattendruckversuch gemäß ZTVE-StB und DIN 18134 mit allen Nebenarbeiten und kompletter Feststellung der Verdichtung von einem anerkannten Laboratorium/Institut durchführen lassen. Die Gestellung aller erforderlichen Hilfskräfte und erforderlichen Geräte ist einzukalkulieren. Ergebnisse 3-fach protokollieren und der Bauleitung übergeben. Wird festgestellt, dass die Verdichtung nicht ausreicht, muss neu verdichtet und der Versuch so oft wiederholt werden, bis die ausreichende Verdichtung nachgewiesen wird. Die Kosten für die Wiederholungsprüfungen trägt der AN. Sie werden nicht vergütet. Die Position wird nur auf Anweisung der Bauleitung ausgeführt. Lastplattendruckversuche für die vom AN durchzuführende Eigenüberwachungsprüfungen gemäß ZTVE-StB und ZTV-SoB werden nicht gesondert vergütet. | E137: 8 | F137: St | G137: =SUMPRODUCT((Kalkulation!A2:A50000=B137)*Kalkulation!D2:D50000) -> 0 | H137: =G137*E137 -> 0 | J137: =H137*(1-I137) -> 0 | K137: =B2 -> 0 | L137: 30cfe42b-c654-44f0-beb5-6f291b6f5846 | M137: 2b284ff6-38e0-4d0a-aa51-131f4dd21266
A138: Position | B138: 1.1.4.03 | C138: Absteckungsarbeiten | D138: Die Absteckung der Bordsteinfluchten-/höhen und Fahrbahnachsen erfolgt durch den AN. Vor Beginn der Arbeiten durch das Setzen der Bord- und Rinnenanlage und der Fahrbahnachse vor Einbau der bituminös gebundenen Schichten eine höhen- und lagegerechte Absteckung herstellen und mit der Bauleitung des AG abstimmen. | E138: 1 | F138: psch | G138: =SUMPRODUCT((Kalkulation!A2:A50000=B138)*Kalkulation!D2:D50000) -> 0 | H138: =G138*E138 -> 0 | J138: =H138*(1-I138) -> 0 | K138: =B2 -> 0 | L138: 30cfe42b-c654-44f0-beb5-6f291b6f5846 | M138: 42fe6818-46bd-4919-a22f-d17017bdd3b8
A139: Position | B139: 1.1.4.04 | C139: Aufwandsentschädigung Kostenaufteilung | D139: Leistungen nach Vorgabe des Auftraggebers getrennt nach Kostenbereichen aufmessen und abrechnen. Folgende Kostenbereiche sind zu berücksichtigen: 1) Kanalbau RW Rheinberger Straße 2) Kanalbau SW Rheinberger Straße 3) Kanalbau RW Mühlenstraße 4) Kanalbau SW Mühlenstraße 5) Straßenbau investiv, Rheinberger Straße 6) Straßenbau investiv, Mühlenstraße 7) Leitungsverlegung Strom Für die Bereiche sind in den Lageplänen entsprechende Grenzen eingetragen worden. Die Kosten für die Baustelleneinrichtung und Verkehrs- sicherung sind prozentual auf die einzelnen Kostenbereiche umzulegen. | E139: 1 | F139: psch | G139: =SUMPRODUCT((Kalkulation!A2:A50000=B139)*Kalkulation!D2:D50000) -> 0 | H139: =G139*E139 -> 0 | J139: =H139*(1-I139) -> 0 | K139: =B2 -> 0 | L139: 30cfe42b-c654-44f0-beb5-6f291b6f5846 | M139: 39fbc3a5-2f11-47e3-8665-c10ce5b5ce38
A140: Position | B140: 1.1.4.05 | C140: Geländevermessung nach Beendigung der Bauarbeiten (Schlussvermessung) | D140: Geländevermessung nach Abschluss der Bauarbeiten, d. h. nach Wiederandeckung des Oberbodens bzw. Herstellung aller Oberflächen. Anforderungsprofil Aufzunehmen sind in einem Raster von max. 10m: • HK Rinnenbahn/Bordsteinkante • HK Bordstein • HK Gehweg/Grundstückseinfassung/Häuserfronten • Fahrbahnmitte bzw. Fahrbahnachse Zusätzlich zum o. a. Raster sind aufzunehmen: • alle Einfahrten (Flügelstein Anfang/Ende), sonst wie oben • alle Grundstückszugänge- und Zufahrten • alle an Grundstücksgrenzen angrenzenden Hauseingänge • alle in den Straßenraum ragenden Stufen (unten, unterste Stufe auch oben) • alle Müll-/Lichtschächte • alle offensichtlichen Hoch- und Tiefpunkte der Verkehrsführung außerhalb des Rasters Aufzunehmende Topographie mit Höhe: • alle Schachtabdeckungen, Straßenabläufe, Straßen kappen, Unterflurhydranten, Einfassungen von Grünflächen und Bäumen, etc. in der Fahrbahn und auf dem Gehweg • alle Straßenmarkierungen (Parkplatzflächen etc.) • alle Häuserfronten, die direkt an den öffentlichen Verkehrsraum angrenzen Aufzunehmende Topographie/Verkehrsfläche ohne Höhe: • alle Baumstandorte mit Angabe Stammumfang • alle Verkehrszeichen, Beleuchtung und Schalt schränke (mit Abmessungen), sowie sonstige Einbauten im Gehwegbereich • alle Grundstückseinfassungen (Mauerwerk, Holzzaun, Stahlzaun, Hecken, etc.) • alle Oberflächenarten mit Materialwechselkanten Alle aufgenommen Verkehrsanlagen, Höhenpunkte und Topographiepunkte sind in einen Bestandslageplan (DWG-Datei, passend für AutoCAD Civil 3D 2018), ohne Berücksichtigung der Zonenbenennung “32“, mit entsprechenden Layern für jede Objektklasse einzufügen und zu übergeben. Höhenangaben sind bitte in Klammern, kursiv und deutlich lesbar auszugeben. Zusätzlich ist die Ausgabe der Höhenangaben über die Ansteuerung des gemessenen Punktes zu ermöglichen. Für die Erstellung eines digitalen Geländemodells sind alle höhenmäßig aufgemessenen Punkt- und Linienobjekte als 3D-Objekte in der DWG-Datei darzustellen. Grundstückseinfassungen, Grundstückszugänge- und Zufahrten, Flügelsteine bei Zugängen und Zufahrten, Hauseingänge und Oberflächenarten sind zu benennen. Es ist ein Lageplan (PDF-Datei) in Maßstab 1:500 sowie eine Textdatei mit Punktnummer, Rechtswert, Hochwert und Höhe (mit Kommatrennung), ohne Berücksichtigung der Zonenbenennung “32“, zu übergeben. Zum Beispiel: Punktnummer,Rechtswert,Hochwert,Höhe 400001,332672.364,5698268.381,31.76 400002,332672.412,5698268.376,31.67 400003,332674.380,5698271.241,31.74 | E140: 1 | F140: psch | G140: =SUMPRODUCT((Kalkulation!A2:A50000=B140)*Kalkulation!D2:D50000) -> 0 | H140: =G140*E140 -> 0 | J140: =H140*(1-I140) -> 0 | K140: =B2 -> 0 | L140: 30cfe42b-c654-44f0-beb5-6f291b6f5846 | M140: 0f484f1c-000f-49e2-8cdf-1709577903c9
A141: Summe Gruppe | B141: 1.1.4. | C141: Technische Bearbeitung | H141: =SUMIF(L:L,"30cfe42b-c654-44f0-beb5-6f291b6f5846",J:J) -> 0 | J141: =H141*(1-I141) -> 0 | L141: d539e62c-539c-4067-8aef-0a8af150ede8 | M141: 30cfe42b-c654-44f0-beb5-6f291b6f5846
A142: Summe Gruppe | B142: 1.1. | C142: Vorbereitende Maßnahmen | H142: =SUMIF(L:L,"d539e62c-539c-4067-8aef-0a8af150ede8",J:J) -> 0 | J142: =H142*(1-I142) -> 0 | L142: ad62aed4-32d5-4743-9859-f5d1938a2163 | M142: d539e62c-539c-4067-8aef-0a8af150ede8
A143: Summe Gruppe | B143: 1. | C143: Teil 1: Allgemeine Leistungen | H143: =SUMIF(L:L,"ad62aed4-32d5-4743-9859-f5d1938a2163",J:J) -> 0 | J143: =H143*(1-I143) -> 0 | L143: 05713836-9d56-4fff-9799-826b94d961d6 | M143: ad62aed4-32d5-4743-9859-f5d1938a2163
...

Sheet Projektinfo
A1: Projektname | B1: 2022-02_KS_Rheinberger/Mühlen
A2: Einheitspreisanteile
A4: Käufer
A5: Name
A6: Straße
A7: Postleitzahl
A8: Stadt
A9: Land
A10: Kontaktperson
A11: Email
A12: Telefon
A15: Bieter
A16: Name
... A26: Telefon

Sheet Kalkulation
A1: Ordnungszahl | B1: Kommentar | C1: Einheitspreisanteil | D1: Ergebnis | E1: Einheit | F1: 1.1.1.01
A2: 1.1.1.01 | E2: =IF(ISBLANK(A2),"",IF(ISNA(VLOOKUP(A2,'202202KSRheinbergerMühlen'!$B$4:$F$575,5,FALSE)),"",VLOOKUP(A2,'202202KSRheinbergerMühlen'!$B$4:$F$575,5,FALSE))&"") -> psch | F2: 1.1.1.02
A3: 1.1.1.02 | E3: =IF(ISBLANK(A3),"",IF(ISNA(VLOOKUP(A3,'202202KSRheinbergerMühlen'!$B$4:$F$575,5,FALSE)),"",VLOOKUP(A3,'202202KSRheinbergerMühlen'!$B$4:$F$575,5,FALSE))&"") -> psch | F3: 1.1.1.03
A4: 1.1.1.03 | E4: =IF(ISBLANK(A4),"",IF(ISNA(VLOOKUP(A4,'202202KSRheinbergerMühlen'!$B$4:$F$575,5,FALSE)),"",VLOOKUP(A4,'202202KSRheinbergerMühlen'!$B$4:$F$575,5,FALSE))&"") -> psch | F4: 1.1.1.04
A5: 1.1.1.04 | E5: =IF(ISBLANK(A5),"",IF(ISNA(VLOOKUP(A5,'202202KSRheinbergerMühlen'!$B$4:$F$575,5,FALSE)),"",VLOOKUP(A5,'202202KSRheinbergerMühlen'!$B$4:$F$575,5,FALSE))&"") -> psch | F5: 1.1.1.05
A6: 1.1.1.05 | E6: =IF(ISBLANK(A6),"",IF(ISNA(VLOOKUP(A6,'202202KSRheinbergerMühlen'!$B$4:$F$575,5,FALSE)),"",VLOOKUP(A6,'202202KSRheinbergerMühlen'!$B$4:$F$575,5,FALSE))&"") -> St | F6: 1.1.1.06
A7: 1.1.1.06 | E7: =IF(ISBLANK(A7),"",IF(ISNA(VLOOKUP(A7,'202202KSRheinbergerMühlen'!$B$4:$F$575,5,FALSE)),"",VLOOKUP(A7,'202202KSRheinbergerMühlen'!$B$4:$F$575,5,FALSE))&"") -> St | F7: 1.1.1.07
A8: 1.1.1.07 | E8: =IF(ISBLANK(A8),"",IF(ISNA(VLOOKUP(A8,'202202KSRheinbergerMühlen'!$B$4:$F$575,5,FALSE)),"",VLOOKUP(A8,'202202KSRheinbergerMühlen'!$B$4:$F$575,5,FALSE))&"") -> St | F8: 1.1.1.08
A9: 1.1.1.08 | E9: =IF(ISBLANK(A9),"",IF(ISNA(VLOOKUP(A9,'202202KSRheinbergerMühlen'!$B$4:$F$575,5,FALSE)),"",VLOOKUP(A9,'202202KSRheinbergerMühlen'!$B$4:$F$575,5,FALSE))&"") -> St | F9: 1.1.1.09
A10: 1.1.1.09 | E10: =IF(ISBLANK(A10),"",IF(ISNA(VLOOKUP(A10,'202202KSRheinbergerMühlen'!$B$4:$F$575,5,FALSE)),"",VLOOKUP(A10,'202202KSRheinbergerMühlen'!$B$4:$F$575,5,FALSE))&"") -> St | F10: 1.1.1.10
A11: 1.1.1.10 | E11: =IF(ISBLANK(A11),"",IF(ISNA(VLOOKUP(A11,'202202KSRheinbergerMühlen'!$B$4:$F$575,5,FALSE)),"",VLOOKUP(A11,'202202KSRheinbergerMühlen'!$B$4:$F$575,5,FALSE))&"") -> m2 | F11: 1.1.1.11
A12: 1.1.1.11 | E12: =IF(ISBLANK(A12),"",IF(ISNA(VLOOKUP(A12,'202202KSRheinbergerMühlen'!$B$4:$F$575,5,FALSE)),"",VLOOKUP(A12,'202202KSRheinbergerMühlen'!$B$4:$F$575,5,FALSE))&"") -> m2 | F12: 1.1.1.12
A13: 1.1.1.12 | E13: =IF(ISBLANK(A13),"",IF(ISNA(VLOOKUP(A13,'202202KSRheinbergerMühlen'!$B$4:$F$575,5,FALSE)),"",VLOOKUP(A13,'202202KSRheinbergerMühlen'!$B$4:$F$575,5,FALSE))&"") -> St | F13: 1.1.1.13
... A344: 6.3.5. | E344: =IF(ISBLANK(A344),"",IF(ISNA(VLOOKUP(A344,'202202KSRheinbergerMühlen'!$B$4:$F$575,5,FALSE)),"",VLOOKUP(A344,'202202KSRheinbergerMühlen'!$B$4:$F$575,5,FALSE))&"") -> St | F344: 6.3.6.
A345: 6.3.6. | E345: =IF(ISBLANK(A345),"",IF(ISNA(VLOOKUP(A345,'202202KSRheinbergerMühlen'!$B$4:$F$575,5,FALSE)),"",VLOOKUP(A345,'202202KSRheinbergerMühlen'!$B$4:$F$575,5,FALSE))&"") -> St

Sheet Config
A1: Configuration Version | B1: 2
A2: Service Specification Index | B2: 0
A3: Dangl.AVA.Converter www.dangl-it.com V2.28.9 ©2026
A4: Worksheetname Overview | B4: 202202KSRheinbergerMühlen
A5: Worksheetname ProjectInfo | B5: Projektinfo
A6: Worksheetname Calculation | B6: Kalkulation
A7: Dieses Arbeitsblatt enthält Konfigurationsdaten, die dem späteren Einlesen als GAEB Datei dienen. Bitte ändern Sie keine Werte.
A8: This worksheet contains configuration data needed so the file can be read again as GAEB file. Please do not modify any values.
A9: Created at 13.01.2026 18:47 (UTC) | B9: 46035.783
A11: 1000:82F7A4D6C284B390C5801C0B51EA54C2B64096A0B41B8EABBDC3DF49C170443B:ED854DAB3B14A49DFB28BF2B36DC4373:0nOeojpf49rwOuu9HPG2W/ZITHyBtwHtl9/DgWw0tPlqSj9JNY0JWa4/NokbFdWzBhNUISTwFfTpHwgmR11mdTXqFmPz8Q9qjw0dDjE4Yip3yEHC/GZ2nDIWK+CIVijoN5RnP5uldkUrvs55D7dQoJiPZnu33EDx5/GON0Ip7Gb5J4kyrYPkTJ/J6txUGuqlWrKwGsveGttpcBAz1KiZg7raWE0zC8OaJaamJp+IcPWQYUp+UHHojBm0h3gGT3uEx4HcMSRXAYbqLlEjyFkjtwM4/t886eHFsnlrwUzs1gpgTGiBUtqNEMEhearfGAIHuQq94D4pmo7Xjhr+fNnRM/R6s6kJT3llWq5PUnyuDYl7eZEDy1fAIKMUj12anTpHJb5Rx4c9Ez9+KX0Cwcx4bRY/G7ocK5C+CXLX8UPLmYRk/1iFIr7aXIORDU1FEsw/FFd1PpwtkplSHlRPxGksasWxwWCc+p0o9olBEWp484cokWLNfT0p/G+38e8FkatoFHf7yz2SlrdbawzD5EAz2P+LxCCx7Oi/BJ0WgdiLE5Rs3YWYj8GRRwvGIme6bzX76NlH74neaMbgbfljrNWLoIfYpU5vIsYD72SxdMoPaejSlhsQFmPXLpXFNFBoDtrxg8h/meyKH24tWrDL19QdPr52u3K6Lozqt8rJoJStCmHhdj1tDGCuh7syYb3e2mzQ5FaKVpBOUlyTb4M00+83MpiVHLOnTFzZs9ig6zjM+v+9T4Ci4jq0X17WZEVIngb9M0bSerjCXkJf6UbWYoqNbiItjiVOKEiX/ZK2YVyDRYVHCrX+AEpBYGdH/qZFMnK0NBQCVxWBtGpDwmi8VBTMQbCZTIIymqdJbm55F+gOThJr3OTFO10kFcb8z4Yk92Sz7dNYTQMOBu2gznEUy1PdNMp/rHjNWDQxoFO6zmg/qkUCLKCpJAwwzXu3sE8P1plJO2CH+Sk2xWIBT6H4fH6nxjQmmuMPuTck+1AjYZXs0io6et/qCYj69pSxsd9KZRHbv7pz+ltVJzvguvUIOkUlY86BpmfzHw9ac03FTUJpB+aFq49moREXoqbmAbaSpV2c0hR35Pg3ql3GILNh8ImTtSJ4sw1DHyH16CpKtjKFX7ANndCyxS2twsDDRxftF/bDLweh2NHU42IET+Rq6AvRaMbBH3KP7ZgDLmAGu3R0g1h7hZTN+GZgYK+zbVAjxJsMxpszEpWEa26XslUKCIdYb/zlZORAzrNfM5cKzhnELAJkG9rcvRAj//AW0lAuHV5quFAtgYE6QAqLEG3DX7WO8TEuqmpqWAHjH3WMLGgxa3dV4/6HcNdcfbMr3TKYjLGtfkFLb5ysF9yOHL6Ad2R7WFE5ZLbT6XQELdfL+jeIlSyNEFpU5nMu4Mtw49egXAn7vuZFdXLqf1sdRGY1XdeOBeQwktJeSq+xtNr8oYyydxNJzDoHlTMISqmqnJd4D+mfB960E5bozk7Bx65MVNoprSd7qolL1UAxLvo8tAOik+NuxNfzzfH6z8Z85v+s8Bg8ZFTykanzJUG3eerPJMYKLI3DbUBzzbE9LWd3+l7wKwsttU27mDim5LH2jzkw+6+AeHY+Y0g9S8rCUY5Kgvs5x1V/gD1cHFY6usBZcAqG1e4qMXxAk4ugaqtk2y5r7xbCLnggCv5gKB9gTtCTV75b5twuhBuQAb+ZckPWF3bJ2HXkQ0Q2IXIoXn1qXtS8tCeaSe+fEXMesdMAm+OgVv2jn7O/weAp9dj8PTy0k1K6vgg9PGSGaJvtokniSzpvFLB9s9Rn6pbocJbW1GtzTsEI+WlDKSNRroYRz5DuGQBZETxxPYEwxr+xAMESrLk4+xWG/ncnb4ozqwVLWVx8khudVuklYlnBkQCY8/uEhn808DHJOHIyDmdM2wZYxowoIeS5dfHXd7P0/UgUM7H5ugoTbIxSb4trY4NPbLcq0uKCkGR3cUK9aO/AokqdCF1FYU1+bAxm5b+k9MGVgtlWj4vB7+AiKgG4296bl7cTy1R/uL+IXDMV/BMZc+Nc6dlSnGRSS67hId8QNHhtEHwEiPFiJnen/JUq6ZNeE/D7BgXAHt+779MRwslsInLkpafFTVLmnVkcvaJNYfidANxH6PqEl3ZyY5i2VNxnMFJsfw+z2EEj+Y7q/ioIIDAeCyeYEcMByhi7ufPeQSeMl52MSyOkKSKQlR1ssgsb7Nui2WFnhGkHNorE+p/wAwORng4MTZN6mx7cPdHdQnRkZTX9/Ezdc9A47+8x1ziec++eSGiT+8eU8Dt6c7Oi/0/JRF0PgL1HBX7pjfTJVAnqNQ+SvTCPzlISk22vNnb46Lcto2+iM47BvlzRByjNQdLbVIUE7noe8nvmeCTN6+Oo3XJYo1r32wfQBIlfzAoF6FNm2TRJNMCc0/GO6cU3Bv6yhjl0ugw1AP7o4Rydk5ksEipYhf8bgJEW09ibYLyCoqj0fH6GpURIvOOv6B1WK3RceS3NQKjCz/fI1SzL+uyUzwt4SXvBcJXCv71Lkarp2QzpReuL7QwSFbwr0Q+1B8fbbvvWYYTWHGJakInhiDzaGz7a1onY3jzHuQUJeKBycGWKKS8zU9qRvl2ZcvJ9knCfA4g41g/DZoyLVpwhg7fAz+cNAbszIkw9zj78WVTksc+CeUPS/xd/NFWmY8jVVtbYRJxhQhO8nF+jWvfQTgAvfiwZVh8ryc/Zd8nkiQaZkh8msXKeHcpv3kruzfzbXNT66TBRCbWla9t2XRik+3gPndJLLc8SRfM+UoW2BKXSQwkcgfvLd/22YSMp+8a/z5NQoAw62g15d8yY/giGj339FYInTTuLs5YpVoU6tomXoyBQ1fdi/zn8I3x6RYnvHnmRL6XJ0wO5HsJ6fpZiWvH2/BomZ+23slzXE/SxN2cCkRMIWgcRAFTh1gAvwdmVVySx4+zBgX8xfkWrf28dMNoHlLA8R3gxxQmealjei5tZ87IDJrDvEfor6OEUJIT7s3vFLbqV4X5PZOIZ8kVVE4RPJSYEnDylizTK7UlyZQOKSKbGqFDgI1bS3ww+oscSEzy3kClMmS2fkcAAwfDtcfkGhsArY7rK2iHRJ+DnEFEfkOhWs35PiKrYCQnPXJtiOyJcprn4P0FMuulK4GykkzaHyxrTvOX6U//2sIR+L4i8+KJcuCja4lLr0ZD2kAD+/0WIKJvu9f4iTT22iucMoIWVstQUp0NYkxeans+OQ+uZz4jqhHY6YI4W6ArTnuyQ6EaCUS0sxuVv2CmrrHitMn8sVMzmuMWYAt1w0fdN5rpUcIfa1T4ESw/1tvzD6yzCXtqBsgyC5cpM6sHweTIOlXjTaJib2CxCY4mboiDe+PusnK7kJ88uDzbsxbM/aqf4by6fVC5/OCwnKkQnPPtazlj4mNj8F51+DBczRhIVlYk6Ov1bJSPeqbfnmAd+YSU4ezueI2/rTTfh8IPaI0CzJLcpGTw6CcUFYqX1ZVNl21DGyiMq5ulvXtUUeENfRByaW6jVAPco8dcyPY19PAbVbrI7uP6rKrK3uMUsuv7TUhTwCmr1XDiDX483thBA8icWLjA5Ty/C5sOyEi42+cUqBncOo/ENu7ySXvXyO/OtGJpZ0R2cCSyMGAsI7h2g7t0dL+HEyYxDJZS0ahwLWFMc8OQz0W7Ek1qxvFm3KpHy2yMsXLUL0WlWX0ecpmwbYf7k0jxSP+6jafE3udA/2M1Q8dH1ZhGiilwLib5sOVNsnUQBZrVIJQOgkoeQi9849q6bSbsJdE9piBLoJtEqJxdPqy4ztko1LyOWKczJGDUUMRGLG++ptvjJ1Z4Mm4ooAg4tDma4RXq8mxsnGgO3YdBHJXSZ224VPWzOXjMgkPpQqRncCwuTuaTtPdr7BAbYW5ASyXttsom4vZoE2rcDMGrWu4Q0UO2Or7TDNe6c6bVH4Gk7AmEMWhs1Pa4fNWehPmHGiAUJt7s+2VtK3LDoOj331wKD3VUgh63Mq7npD9kodlpYO1OzhnyViQU4rdEjm30QiSvxNnNgIfn7ljlw/lFwGDLEjatB0JudUFvFqAnvBqlLMsSZOQbEBGAKSNCdl8BvveFdkYrcmnaE5cU/r3lhqOasF6Fgxg+EoGv7p+sJxmTaOaz9/+ANjFocAgHInXsfMq/ybTVxffunUYVvDPh33m5ofbFA3DWzCgJ1H5MjUBdwf8W0IadoUMsUzwAGk9xbCGjEy7LBOQ9olG5mktzC0VFlRscSSqc98s2uaiCYasldhvyy0e6CjwgP3RHAMuqNb97sY5d1Zdk7eutjCP2x+4JVlcNcLdlmV6p4JKkuXlC3oeIZwcGd4iDb9qbcajqjKJOBpqA/pTNFlm7AOv4611kytgxve8qH/0upTluT2WzI8ioqO7Tp/XmV2yfpHjyiwz2aA+oMwHBlTmQZE5nMHjbajGBWB/myiin89WHVLa4ls78tfedlg3vx8SN+jFZauRqVk0LPh/kVef6HbQBOX6tUXXLAByVqRoVGJWFi2NEK2DzJ0wFjtCbkDJx1JH9uZqnVvjZO32W+jxBJ4x6HSlFlRf08xuqbk1UkNztSH93fMt0VQQtsk6x1VsuvqK9aQoxIarmFfyMQdhfm0PSchkh3RtYLJ8Yehn/z+lnz21u4ZsNnpvIykzMK8M7SgAFrUf4WNr1r3uKAAMrbWNbAe2NDdy7nEd+sLJOaK2fds6L+fdwapAIHHNwfdVXlT/Xb8bVQ89KWLvh67w37TZAKFSfaQXslMNs12PAbmGRnoZ+C2tHu+xDMDXYsGym+yoq4ecipdgCz9Jm6rNjjONR/qeq2KGd84I6qII+FyOI8Uoo0nH+2QtDmx68aIQVMq1Yj7tN9h1qiCPS8dvvyrJUvk8L0TBwDet/san30hdWGOsSjkZNynN18KWOoNxjzOE+TvaZEDXs7JkmJJK4Zrf8sHRwThpM6e6xSJN5mnQIKu589MWgNmGT9u/1cpyL8+JqnbTJ9AgOsQz3Sa1J3dwjMahDDSRTkKRT3/9uAxohoOO12cA0GTo4fNM93Uz/q5ShY+gt/vhl10GSYEr24+Aq7dQj71DSfXAB0kGB5B2COWv7Y6ILYj+/RS/SwJskwfnmhrn5psQeNBjT+4mUpTWa5nx7DzZeV9hCIgD6zERsn3XXO/jeNqbgyQltsaa32DY8IirroSawE2XaApoLZE+CSYOA65AjmhImqjyRDlS2m2/jkn0wwpu+Pucvxd1atIBCzsdJ0+N2AIyvQF4mjIAEdd345d7ckCrPeOipV1jjt/8ZqJqbDc8gXTObKadeAPrHRToxsnguD8wtoYpQ82EY1bR8p9lsT9F4K/OM8PdGkEyZsG47xYF6uvgg4Es+fsajHiZaaCAouVk0zhgoIOU5f+Cx0gQet0avvon4R5+ue6SYGF59FGEhbnZruvUqUwz0dX+0zFE2z79DYbKIiISQtmP/203olXEBjllzIhcN43Ou1DE+xQU9SN06hV4oGe4nunZS1wTLKMAcjay7PNudJXZ5tjNDbbFXxpFw79FqNAgttkv5D0aIJh2TFJx2lciRpYD8fzRnYEiVEPtG50A1cx8G1kkAv+u6efKV9i0tbskxJYTF4cEogTW0wAfIPtnjHw6X/esp+RkPStr37RA9QEmS0agMSp+UbEdT7vE3d9rp7Yhw85SXv4xCb4N7UBAucWxM1JFPG+BFBvvRU2eoPVdo3gWoRbtwi2pOmxoS9ai8Gp8GYQaKa/9mxNbqRchaMr98dNDSOGe9IBhU2CMda+Q4TrmHnBSLC1kT1/wtC3fZONSDa5FFm3b1G1fmItglSUsmJzQMP0n/xpRM/dCrwrzLlQv0dsWznDFg/C0cTQWT9Yn5FIS2DU77CNlNBfHUWvr+QV/zU2Rfny8wB9I3UMlDBzW5MnUBH9EUAGrY6LkFq9GqybSPXDETuqO2Bms/60RUY80poK2WdfrYXQF7v3KkdrBxY//ZhwpmMoo6KqU5wdohuPLrN/eZwNY1GKMBFnqUao3V3AHqdQYwvN6GpQdJZdHBzR7YXnfjhpD1ZexfN9mMjbmBE/JSZzDfuBfvtX5139OOtxPA1ow7fr66XkdEaQlGLwddcHoZ+RhxOU9ZYCCaFJ61w9ZIXk1OQhwZC9beKE4IDYPDhgXcSd+zN1fS7uudwd2ryah6/aT+zX01Y5IprDafa2Ux6mZzB3MLe6TFzi8AJrd2SM3JxTTIjQAScddB1mx/PsIK4KIEPyawZaSerD0vwpFile0v8/G6qvx0OxNwvMu/7bumrszqRj3LFSq+dL/lEFn7UOnoXu5OAYXGEBaywkJ6Gvmbqg8DQ1m+y9RTTaqsAPV3wYt1f9p0AcWc3onIQDNsaH91WY3Tr6Lv/ywUIzVhzbzRmaEfsDuJKPhSG3NuRVmoGp6r1cTrqphfcsKt4WQNb0H+qRVrEsUq6bVCZUSgF/wGLE8iGysmQzkuDPVHN7LMz2uD5BmEk+LrTVGJFPVtBAm1x3/6TJpgjpsSKnu39sIqrBwynilwlfCeiO5XUg6cdXCR2PgC2TvBvn0/DwBi5o5L81iXK48rDhKxUBujzjuIj0gzSjX7XhhrIE3TVsa75rw9VI12E8NUoV52+fzwyAnh+EXNtuBcUMMbHe2BKIfZeIpZavMRrT5Bj+2BfhbKWR7x4SG9gkBIhwPJd+qC0CWlsvjg4NPrkEDRRZC6hOKqZP3FO0QNE5AWqqQcIzQh3qhbpIZujc2LQbuVJRf8kqypH0h1KVIuohhEkgP3rARTjKZxnXvXZByVrdkn2OD5Jq68GCNL0ogGU/5L8GVayTaxkIcCH9R7zO3BGpjhX5EIznuKE+MdbNw16aC+Je+ADH1vVAbUpX424oJEXr9DFGimVv0zIpfJk8zQw2PPZHQ2/fOEEGpAVC7ilSJQqB/3Dn1gQs39Pnz1XdVJ0UhyObh0/FYqNgHzGKchQGoJyqfUgUJsrNBYEqZL9Wov/JENuCBoJfPj0wLL6wWXfFr1E8lg9n+hZOqOhym8enh/vlE1NZUrPsbrYhlxvHqUNqLklTmqZeobPSZMbPdBuS07xbN4tdz9PMqGYglo8+AoUvkiF1GtfB4/0gVNV91PWbFiuAev6lnUCFwo2zsmyUYsA6627J/BrDi1+i1FPDW0mJN2mmJJ5E32HF05ijvfnEX8iUHazK2VSoC7Y8Tw5FpayRhoJe+Nu/Ic+mjahVhILkoOJGhcppG7RJR4Ay7R3NM791yfdPohsSnIDShoN26HDQF1p5wgAtlgvJ2w9ob9msISW7b1o4OpCBoWlbgKFPruPtzMMYsU1P7bRsxof/Jx0fKD1PmuSi1oHQj6ZyP3GTmQrogTYNugh+nbiND7sKWJSRzBNdaTyW9B0FvHJ8g37atJlJsKSRrzC6HIqCJwmshPEvzaj3efrUydjyiQu2yfZX42ig6gBXjozOIL6D9AbwXhzomSEgBu9sQGKbfvoqLhz2JTIP4LVC+My60AjRXGc+YQr8hemk7JQedizmLFzbL0jTW486TFBQ6iXRJySxZyyxNAUxd5JvU5VE4NkcPOuo/op5RNMX06fZglapWth061b9gdElnChRK28/uy2O3SjvP/V85BiS8TQLvYTAKYQc6t/KQMI76y6dGtzxkWu+wdjOHu+Y/7uPkV40s9o0x+PhKg+KJ/CO9u+MTLbuKM8Szf57lEvmDqNmZ+gCdM6qcGjZoslg8aYKKM8SJVxlSG2OxWBLPJO/Zy6W2Rrt5oARHCcgvXhdCydkDQGvoYr0pg4IWEbi6qAT+HKlGmxomcDJKkQXtR434RqpNXBAm7BMPVoy3HvV6D/1jBGolXvLf1RXstWHZxynEWV/1s2kNxP8eVlZABEJlCmyUs+pJYQfaPbl+YmH8/JtUGt8zmNum1mYxvcmuCrlJujptxXiQaD+Dp1BdEsTjZG6nI4bWT4kMEYo10NaTw/ScafrhoioxrVuFKyoLse7zVLlqCfXonPHfSFbMWpkE5Y0RhWYQtGpNg56+aT+rwDCE76KDpB65EKywrn1azKSuHqYeu3dnvqJA6/4EXsLW2T65RPaJREba6yCQpOch/issO7qUchR41CtlcZASsHQMRG2Sv5ePMp3MAZgvM2vjx9H8neA5v8oQ50XDq61AQ2mtpP1ZUsdOHHkPCPeCdry/4IQjXLU6PCqxqY/69s+xKIXBLr3O1+l80zLDoEt/EAesmpCRE42iKRU6H15jFWpH+xy2qfQLprdxzXy/q0pVqeFdETeOtu54mDxJ40kI37QsZNaE66sNehn/MfdHsHm6dkLcHXD/HAcd98Ncm9hLwZ2bOXmgn8SzlSZqH58prKiLJWokpdIf92BljvLIXISpMRmD/Mg6NINSU9MklQsRchO0L4ctFhRqU5I0BIfze2iatt0VNIpZ2PWCP3psd2O5S8CpZ9YJi8Ho0N+DWQR7M8xIMW7DqK2X/l+rlqCBrdpyCizpamLmi2PdVmbCtElvc0C0nt9hMlCZnO3fFTz/HYIsYCR9E7bmYrK92oW6oHITpdLhYHwEaPCX7qEwolgktsJtMmF5sVRCLTBHS30BcXsD6JLUD3GL9ywwqVJDwYIF786fL7B6sjqSEJbW3sg8a8dfWRfU4Je5J9DhCsSLqZmV3y5Ur01yoQHedHuiK2dsdvVtkSBZhHDlPH4PXDQIDbupPOeC7OKxYNsOWTd9U5UvFjrW/0VhA5iZHZRYTfvXWp2lQY7tCzCqnGMAF8bEtZqx3U73gY38gDQ7lkANx7uVYcClS9pHwNjWaDKCscyQFiB5jGELPWVcprx89keb1TSI3l99kzWl5uyR/5+gWC+SJ9VObbTX2Kj4qosHtaM0tPG6gCr9HG7ylkEnMlqd4i57zvBbB2yTfis1Cs5EFwbDq5BdeCHa6zCQpH3NFZb8mobTsw+crnEW0VAggTH3sfDPD7Gg7Ybd91ZeYv7X73iRv97bbe8h+kmGf4Ttnp+HRi6RDzeqqBR1lM3EvAMJHBdEutY1LUw9HMi8PbnjhXgq1Ys1Db/qAXFR9mF1QbtKiO30egr4aA2O130hQpiFLjDruaAJIUjVNiA98ZUXbuZQW4DubcEZOvy5eRwMJuz5q5PDtwfFJ87LDKEYhkQnVR8txLRI1XlCa8rU3xtDWB5BmgnrkvuIahX6alLnuCy1aIG9x/Fj5EqmAy3kzxA1EM1gVmbBmeEAXvHbqpoV724dO39mly5vxw397gRqqPENW9ONQPmoAXlY98PrK21JnJvhU3Q8Rguh2FIucqTixozmqzIfUJTVcbcZaXupfCFSI+ZoaJe/3YWBUimHZUp98OOlBSUZkgFprfQFUKAqt+GN8jELXizt6Ify/dQ8iv4pUlN7v7JOBaFLWwKMt5Jj1qUnH70sjY743MsEOawUip9AMoQfSAuhbrNTus2+lDSbYnwpiGDuupUW1HEO4oOFX2wGHI0/1GV/IsYQmJkTTgEimIvt1HOn6e6izPkzEzSnaHBJLurbJNLgj5Y9mrbrRLdO0tbOY4PR7d8CGihX7R8NeUviQZO7vW8rHi+zB0Fm1oNdDguEqcUWAOSohOCVSggGqbn4PCiH7ytNtCMSrFhxaPXz/3NEs+BAIjVUG0fshQ2DnOM2yhhxD+S31Ru81Ldltz3hb7Jl5fO7CNnxeSAmGTWz2ZkPVZJquX3FN8M1jKvl020+kKYqMgpU3D0+bGYOxfxQwv5WA4viQvJ1qrqSe9gyZ339KQsSN+j299+7HICH0k++Pxps8+KifWBkQyEJhNYIvhDi357jTgHWxZ/v+5ng/ezmF/gNnjR0nsE1FyNjcKVx6YFBtUKcRi0FG6QlBRDBKcvBOHD5cJGtU4zNg/fis0uyAvpcbhPlWxWDNntch0iRJ1CcpFRRkM6M6U+ki0Y1BPZdFarukMgzhsiaYuAEoudqUXR0nCnfwVdU7JfnQoZNf6uWa9IcwQd5k7drc4E9tsls6qan958R8vfySfTFxwTtxj0Z49kQyuBsuHgZlb/uZprPpqS8kp2jB3do0vCe31BRUTMj5/UbWMWAatBsqh6xONRAZZeXMCk/4BJ/BZQiwYAhiEhAurt6TtXWTBoaoUZ0oDNFPQouewj4HHodcpDkzCWxpnxASIO9t3yjMJQm1OtXu9sYim9sWHiHupCjuSnVe/9fRkzdI+hYYYsWLD8Q0DeDY/ibgQG/RuOmXVLRh5YFEw4dkFM1a5zoGSHEsfQvHSiuLRcbmyfiUIFMWuRzfQaR3Rfm3HF72qlQB3MrfFwop+Lp6I9pxagkTyfnPh4iSwCdkBfrbPD6m0fuLqzWSGFSTrr1V4fZUwG2X25pO6Ulw1xjdfkKKlG2ZT/MQjFLHoU8qcmW08DGTfhZQhZZOApgC3iealzYT6qQ6vvrCBs2P0AbOubhS9L9GGKSeNqWP8wKycBGu7Y3HEHXuiK5eY0ez1n5oCZMHc631iZJhc1lyKZxdVE6ip4Na9boIEMDnzSf4U8kJcc9ZElPYWEqf9Jhy15BgyiiheOyekNKAayiemTVKc9rjP4W6DIB7r5PjD/U4bx5PEODJHx4wv9B4eJ/FMbe5RHsYvPSjCpyWlQMVXvXKXzKLsnqs1mNz6/P/hh5ErF08pM9yFoeZnIEt104ugHisSVX9bV9E5A2C0Va9X/XHwSQa3onXtRodCiivelAylBdl30s5qTQiEVuGHOUIR62Y1JmfTCGk+Z0FJ3gKMacmh/61EiAWka300JXgnVeY0n1D84Xy1Is/FgPulO9fnMDz/5U/He1YYhsnXQVKwZ3Nf/PqMOTEc+O2kahLLbTjz9LyHDMJy/pgwFT+eGf0D6AD5HgwF/PXvNEqXvemjq8B8ukkupi1Sd9WNyqayBYvl/ZX9Ic74LCL04HF7O+Rnrmrv5gwxMIlbRb9I5YIg3rIOMFrOj7EmGa425YOPgxDZ8unDQ6f9i3WQnhmdpwYUBSLMNIXvUyDRadB5NVszIa9VEfpyN0OvE/n96byunk8HvIP2FPuln5ICiVnOZQfy8viop4Qg5UUisX1W8uuiRCGwLbpwNbz/HT4hC565Moq7Pkzkfv+63z6p0KxY1Npsf6sonD8YQWINeVIzMHGST6J47DVkNByLm30+n10I7Eunsd1uNKN49R06CdATc4S9MHfaT9zi3tnZm66ic5Fwv/r16/GiTvtCuQkkGgx7OFY+hF0Mkzmob0MbhLX+NgsjsWdyil650aV7HbaM7RLCURN/42Juo3NCgEmF0ZQfYcIr5Gw3IsR6lmzozfHYoxNbko/3YpwLxPYpAz80B/qVSQYOCzqKGmGrU8bvqt3CFgz+jfMss2rpLdjRM+B/8q7zv7eUPO7rZZhnqyxa6otFj6YiZ/kLiVL0+6A39j5lLctV9M95Jfkq+GAVwsFMB3TYcFKmhcdnd+VapJWlOoGBwgsQ/Rj6+gA30V2J3ps64tQ+wCA1RxyxW5mnKlq4U0zkE1FJKGp0aQGy2lnc2D1pxUD6I3uIwzMBnQzo9hpFbriVRX8KZNoP27jPR+8ol1AQIX65TnQnFbpb90XavX1bYL48uLH4SENlU/G9AslKT3nY1tXeg0EhLDJaLmjtTsQfTtG4ZCBf0h1wF8DJVi6/DHCCjbg2X9qhldco6tQ/zCHYHUyIqURUo6sp6EzZziYtSP7NxM1d0u3iCDZbtBqE/PPwjJ2mIrUV+eUPt0n2FBALSVrvSSzniJXGW7dbvSnBoY5R+ZY75NSO1gvDWZB1+SzhyEQYvLEspvXgYowEGUDQwx6gen7XUPnJTBFxLGLLmTfmfYUAZJ+e9QXplFKuK+droygdnjjfyXz6rqFUeDwG7Q1lXUqib5DPRvsVK5NYpHcan+OGrIjCLDvjYSkVVutJ4uNKLK9Yv+1x9AwaAbXa4BU3jf/eT4dFTOdApXWg10wDYtOvpZCuTBP1MrQsPCYZabEkdIIIoVsM0Ug4zPx2F/OIsfDiEOijWgvZLyubRf+jzhiHhd65e7ARoivC4Uyi6nSwcXiwF6cFAgcxjaBjMqeKBB2gjWSGAEdTwRm6rPSRpIPA3pXCAYSb1Ud5jR1FtBsUUCOzlWbawU9FLF8lusrIU/JfGqgnSNlt6I9nHFbwe8LafFhhRdHDtciXOcJ+Yso761x+lLpRj6JWL4oirmp3L4uS0y0xw3+ucuCH65+igSFuQnda7Ktl9rW9biEt8RSilKqw4rCMAuXelnPqSLobh0Dl7N7qoqZ34jvxgr1gB11ptiJ0ZLfRF0Hos8LbcqChIYode580Rwy39Iy5ULhYwaNnJ3vMbzxXxJh2/tXpx0FV6upybRQvDUPuz/ULVe4OjZkPOwslPOwK/zAg8jdcVeGq2Cs+bZ6YOOHtTJ5LN1tJe3FWTa4oqWVQnTQ0ovUUo/dSw4eabt8pGuZJcAvgqGd6rHxz7vCfwhsiuw28ALnyTOuZvzIfqyiHd6SqilDE08Ce5zDQ1/81DVdynr1CF+CDEiuhQoBA16GEZOPB9SCIi+Tz1k5gwn2sKutgUL4Wyihbym4WldOPrbLzf8tpFpYsVQk0/J1MSR6M37w/5Q5HIgta7qOoZYdzG5itNxU9hw0z80WlplPqxWRA9STNGGIzXXc2DX21Jq53vbp6IteaauA5nN3JJtt/Ypk+PjZTJJQbzBkfx+2tb3yJathpLdvW9CngNN7tkYHPZDoOUNt5VxXRDKtsZ+iwVmvaPkY5gQZv4kgXkq252mOju05gjqLPc01dgnEReML4YRw8bn4+rjulaYCoTXLEc158xbPrPYPfuNbkVDaG0aEKKj6wX601VurFDKJvqkqqaMTYWmSjx/FDAeWCAUUAzZewU/XiCQRJ6VPHySf86gCLIoQIL7dWPsow0v0sn9SKCebpaMswhchXkSdkaARkQORkrQ45fkP1272gZq2ne8tOZAjqwcUKa41udgTDujkeXty5gPMy3L5guWZNkvE6tGjUZXsocCEguCcRGi+thmNts3m41FZqRXkmXpNmKrnB/BTPq4sYqEWNGVcIG3bKlzQtLwlqzu+/dBkzEByK9fRxRDuJhF11aaJ8kj6ce/MW6k/0bA2nzKq/dVjCD9uMQPeZBHjawGlYDHzrJ77CWDqgAMUH3Zo3emr1omxqLWV76HWWyAcSehXblfEcIf5f6GbUwK28tLLmTqYSPbZqdNY8q2Ne6/X1xo5/4iulkXrNdc+eKqfbRpJhvRhoTLkOcqJjl+SOX6q2Rx5co1avlWTZSU0zinDUlJRyJC/jNwUWcNNYmftaddCzOxWWVF8yD+5oCmczJez5FzX47SZ4LxX2eW+MBAghdm5TTVj5qTVM1u7LxUqCe4FmmcM2vYy/RZI1i7pMlHpBQqLYh29KyYj1tqhumE7UowZ4TQWI8UASCgguD08DYi5WUaWOx5JDq+J23xheuW7+g+5g8ca7FQcXg8pg+P+NI9rOLDEK1wsy9fYDzjAC/Ojyj3Qkprmm40DHKtyprbPu37S16bPI8YRmSpulwDIubbUJeFkETT8VExpK2kEYakNaa7n9Bc1SPRaV4ACs4q25owl3rBttnQJ6wQ0KX4RJBK5njBpm0xzyuEJ0ngp80TKs5/zydGQDUjpqY4iUdiqyl+NCiB9j4/+lGarGsrUP6wdmMkDdgMa+lOAhBPTyn4poYpI9bG0BFkoOjqQlg3fIJQlUQrD3wWpbJQ9T03vT8dKUSgk8PYEmIIjxilmii92+NtUNPJqDSlP26urECE1tNQhkcZsh2xuqNwVmJwMzRM9S6BjUheOKzaEI471ydkRRoWl3lEzQu+7+gNk4RY+/PGblMCMPIFOPiE6sPFJIvl+4kSgyqHXAdh4Q7fTMm63txlqkkgHsE+AHEZWVqf+UXwe5OUXo4deaoXn/G3dGzEdawmX1qubWMy+I11HmSIjCXJf8p8nzV+AWJRLBM+CukqbEqQPXF1MD1M0GAoRbyNRbknvU27PqZK+umqHD3tICSGG/GTWhdhRL8yHV7nP0NQjU1/Vg8YIGVSw5VvtCwi/gTr3OQUQve1ke2HJjP08CVhqQTy3OacZJRYmon6ZS5EJhKcMLeReZxU7e2IuiLkSFjH8YqbZXB9O61CIu4F6ueRPWx8LmP5u7nWd4SVqb1tWynCiqq+OPw7UoU2coboDg7ahduU/S2CJYbEhWs0GxbjnXFuvtfZ914yY5Y4rklvPF+VPNvE0QNSEAdKnA9zI46z7lkA8tS/AUXElFgpoO8ltOWU7eddHGDvRc9TkvLCBFpDWA9XyDMwBdCOsPO0R7ti+opBdqDynwMnGRg5Y++S8/vvFP52dVy8mZptxc1ypBY59Tfh4S673bEI77Lsw3AFVhrxVKVIZQhmFdO+4u+kgoxWk8UfNT+haVEaRSD9KzZd9lixkFm1skM0uOdXflrGfl5epUYGcHacd86FN8cRqt6KYW8uRK5e4PVLpe8kKWSpz/p/Ec4paUckgh0p4J75C/C9s5xGsQxbOhiqrm2O5sfYEzgVaW9dcrjtTuzwypIWuP+QI75SGyfJAPBnUWSQEqcWgUUczHuCeG7KIdSKULNFWESF5JlLwRhOvqbrlryl7+KUV0CDxCcykifFikJFCB8k9iqRADqR16BGUQU1QRNLM3DJE6M/qhBiivfI6XFeG6qMnw7F7r91+Y5raDO+dRYczzQ4JTcQ2iyuHpAlaRhs/mLce0+VL/ASfXTGzgQRjh+Qjw3eIO5XGn1L69NVSEf/AI5t2CDb+1Di7Gev7h3HI7bs/U3hRe0Z41PwTkq+WuKJbCKjGTrkZpZuFsR3EcSTxdoxuzbNtDZG9qO5vzSZPpb53S/7It4XHNEgizcySc6fyG4pAd/rM635nWPDcjF4gU2v6VqgHQxsGIzC0AR366A57PoqKqkxM6brecP4gZKd0C8cEO5ZG5UWaEmIbW1l3ZAWUQ2wfRVlj6vSHi5raDA2EA5Pm/TypJK9KRERnsLjjalO9tVqCA5niVrVPsO2VBbvMk28VYiBb0a1Syt7pMD7eQ6oCYUiZhtluLPkILjzn9jIyh0WBOhmyr/p0JxGpWQpUNjdVQ1htDaU7+GS3jepbVqFSfkC5Ubea9obhxkqoGNmxcO/tXBm4Km6pi52+jshzPpcmoQ4xhuiZG6RxVeyEYWd3VaLdUFejGKx6Eqb19GhLt7OPeo9fizlZYhrZWz2qnlZ7NV1TVM2sBiTcdGyLMiZ1AfXzkumFHROQ1p2FVpsyxbwYXcJIvpv2Cazj7IWnz5QXI5ZsPuw4nhSjiRrftWrMaodeGZ1vQPuA5RodHLe7f1h3fmDVR9sxUNjvhXeuJ8Eep+8/lZSoAeeSFOQej9UpoQz2l1kj6dXlb7/uXAldwWQV8UtLsYP5A7tBX43EHpP1H6om5YKeOKFmKbcjyudEqj3w5mDJhu9QBVXq8OdXSkyoBPI2TenSlolgGOqpb93M2TGd9hS54f0d56vnigDlxMrFM74boFySDWIWNESZQU4xnQVlEkwTLsAKgAuZrUPkmwAR/WZVYIXljVy5Dmis/YitM7eHYd/H7q/Gc92I9zHD8A6H73G7l+uwWXwHEMzqGTy2aF+n1AdHO0OH1wQUwcnqaS+926BowNoCSSs5yTs380IVnBgIo76s0gnFPlprqe2VAbBh0TKGgQNZlr8OUXZZ7EevlQDEsiqMTf1xJIn64+r8GdOgQt8KTQ1CAA3HcnN6BK9l7Tv5sKFw4P87OSGhLZ6luBYT5iDJzy7BNfXyB8Dpmg+Qghy6FXwB2uXXL195xqt38deTiEptzjGpkwSqMYBtYatEYkjfmEGprCj9kU+50ZqDis3Bww6Xh9qTftoj+gQSVnXSb+exjIdZJLU4bgB9YAvBT8GLz9Ayivi44TMRs1Eex1uZjEBTFehCjlZaYg8O6CpG9uSf2QuM9QC6MGjkLBOEscpO36lo01F4mbQRIeDb6pkc8mBT6sVbI9yyj8mmiINtcVq01iQRHhtfrHCryMAkgvnFpzwQTNd3yV19RCvVdLoow1aQaqFdJjGbGS8q5HukztXqiGN/tpvBG3Zy4TTTKDG9VpV1PhR67QyG41SZ06dOIGpstax6zRCjOe6GjHh7S3Fd/b9t2XbdDWyXIIUnTBurQknwv5tU+QgP7T2B2eO6Z7H2MePTo3Um9OxifWR93akbuNxSftb558/czPIik2IgGrKPO45AUZty+j9Ab+qxLcjV7KfZqS0fvSXqLA92qBII91m4PLpoPSx/yDBlA8US4mV5six4yg//q0EaOGI6IRZP4mXbUJNjZhJngRbfpo/VcAhagLJq+7CALkb7/E2gDfcCR6jfR/HqV20JVQgXWTSni4qc6TMhfN6ZerZTSFNm24soi9qGOJjduSwG2PwG97QmAT1aIlcQhG931lXz4xs1B+gYhWY7x+6fhiiGxHMGJp8bn3vGolOnN68sdMNLMkA8HIIIE2eZvcrhdEIrryefRCZsN5E4Nwqa/5QbCxKhfV6cL25C72Itij91e61vLiP7k3zxxaURUMMKGvfRE3ImH2kB7gOjTQL13u34XyOX2oQrNFX1m9ldGOSA8vQAY3TWVVQPDN6v6vm9c1jrQOwE4+qVkZo4dNtc/lBd/Eu0Zv21KYhHRElySPobr39TbyzUgJHTiT87rrxzAnOQl2ChQwbYT/sCJ+otpBKDZDQluRA1F4zqDvT7jrA8Jk7quGJH9E25aH/8huWrkiBybvDzdAPbuYdfZkzc+QmEVpiOuz1iTfJnLZ1lzJgvG0cPVw/t92LeiiYIEje1eDwREVujbX44MXgKoi/IuzBHeXSWtBSBBgib2bhWXgTs3KUeQRoYc9MHCLXshiGlFnaaRHz4NKY+JjgPz9VBJ2EsmNLkjKAqKVV+AK+axkP3azvQ2TwR5uVniFUHOHgnPpT0kUGw5QrXeqX0PO1w4ZzustyPpN41sgB9leTJ1raZkvGHrpVM0WrReTNz11tuN2ldgcRQHgg7BjruOAc/PuAtbqmETvvDM1fkXnjVUd2b8ZKAfqMF+qwNeIRjy/1ecfeaFwst0SBTZP2Wf3ljJ11pH2MLGEoMinSeWZcRgSD1yM8nbIxOz8PmsL9x0LZu++cbmjDsyl965O0Sbi+fJEY5VaX3KCKAG/2ZQASBwegKjYLDZtfuzySk8CAglxMt8n4oQnIz5BlHU9/AYJaROwDV58UOEzFa7jol5gn1FjEicPAst2ZhYcNOsO82lmwUSjf9P4H5kiwAecC6jBiqaAAPK4+4qpvMDn3EAphL3iYVCYhdvDgyPkTzzocgZku1Z3RjfkgsrSySK28LAUUnX1hA45vlsz5tC9icKz7uyj5ebKNjKh232sbOzdUUonDZYy2AtfaV0gvPUBJHIGMJgF+ZXgjkzHgmSncMJxzPlNago1226IZ5OBgPttQAJH5XkmmLQNAT+/tFUHZYrE7Mma8opHoqcxZ/biRfQpU0dA9YAPR+4IiUClH63YWOPytRQ9sXif/5ldd3ujdfwTy2IesOJg+v7MUVHq/QKTlCCxgJmN7JPfCYc5L7Ld7wHGlhpWYrmvae+2SLqxgVvCzI7FzJsZxMudCeaDDW5KM11+BtgiLDw6jnhmC6ydp5ixrkCbppZNQWcxA/19UpOuqmkXAkbs33pc3qvWJSuHQlS7HbiHU3q5EqJMaHUfRYsAWagDlb2BJpquxYoAbMd+1iYtsqJWQ/X/aDEqBBLDm1NSg/jZanABG1m58YYIYMuA5E1HwBEIuE3ww+XVoUucdfri9wRNWaxcdFx07AUbiEk56iEEAJcPpYWvpLAMrPucR+hAt3P/17iUH376Kd4Xx+BO/U/QVP1OaQyX24KQKK5RSa7i7FxRII8cRW8d/Klq2Raw6KlnoZLXXymSJXNINYgghgc4D/Y67cRV7aeIHgurxwyamRqXi2hcIXw+7vwNke6WLLAf28CQ//8gAZPeyfCzhy0kWwzzQ6OtF+iCL481koX4FtsnTsWg1CArOEMByHyboOVGnUVCXGTBGXmkJ4dVKkWI+RACaAL4ZtWxFMCu61RHlmeNZC7ndSCJO75kwoZSUexqcp03E3OfyKhrwzv1RUwy9kjcDaWiJWNaIrojZYymqbknRzmohUEBlxCtoK7V9hSfKTLtns2oyXZ7DRmz9moTxGQ/iBvQPnaJv3fp+jlGHBPq1no6n5ppXExa+8ZzPS5KdH7MlZv6AUiAdVVC4vbsLSpvsSpqriYnP0J6n/wBJr6+KwiNoSgZtA8GkDdA0HDC7loHTXhQAbbvm/vSMq2Rms3mGDi5IyiSe8CsZWHFYiO4tMqnVeuOvVpOGYiHjQoGq0txivRNeNzN1VG4+v6Q+fywSwUaKDCM/g79P5bbj8vvpljNPXVDh0SPIOz6tUKxEz4sRDQ3hTRxLMJNG22s+VIvjs7bzghLflGY71jCtKA9TSeSxjYZDcxoDPatxggneInO/ox7kiJjRNSelhMt4bj1mrGDeUDYkvraw+QbjEO7CnPxEobr4OaRYzJWZmobzvUZkE1LP1Qgb4nXe+92HMpG80kXVcKazihziuuoSNDw96RaUJ0XBN64a25o0nUO/pPjKx7VXWDUrp12rHnSgJA3uBe6CUg60jqD12qkomojzNGqJk/bQfnEOGT0H3glz5oGmVIh8TLSSYGR7H/Bta2M4id5uqBWuOCsIKX4GTiqwRJl+012GWXr/nHysJgkbBSn4x1rIosc1U5S0S/nL01DaGw0yXcXHnOkQSj4QBrSlKAJ4VOMdX7wOJIEG5Wx94ixPrIzpVMrumDkYUnidQzSg7MZT5iX23BLMLORrPvluxg8T+c6ooTRmavA3PfGZoeTXgrM7cOl4ddyjvfkSrcw+oxr/pmObCAWA4USpqQoxBkfinKkDpIBLtDAoiOPNOhzy4a7WsBMBiwv9CPemrF3Xzyfle7Tzf6xOEQESaYQNAdN3UQLJr6IyhSHP0lJgpqV3HA0iBzEUWF+aj38XkJoOUXP/CT0muLLSxeiMFnols/T1NDPfM0mdB8ktaP9Bf+k0vWedub7RPC6Y9d94wAn7NX0oCgBUVwlIv1tRob0vV1ok9HoToROEksIeMfvij4xLHpDNqd9Od62vVIRKV9OO0eFM8AvsGCwgaPl/YZlTf3csK8oNPNKeOuZ4hQGHuZ9NEewKhDyleTEef4tLrY1uKBlwVzKxks2z8KoZAju+kPF1VEgDnNeyiohfoiAIwTUp8ZjETijgczYlH//dag/euxtTVnbqpjSpmeYc5ESdOZGMmhedcV35GhRq9yTK705nW4tU9TeIktL0ZRnRL7IcCqbxKykn83bCIkrVuifwz5DV5vHGxoPN+nCqBiyCCrGhpuTrpK9/Xeytp3j3fvp1Tyy+LBcytTGB2ikCof/5X3x/Iqy/v5OdpRLCrfJRxNAVLUlAovBTPmzkl4LzucqlZPRkizvG3Ct+01B1H6RLTOy2M8bqMlxjCPp06vG1ZzLUeGQcvkNpTFjdiQmxyGEX8tvJbzQAoEn8PxF4wY3PoSrO9nxMp6DRiC2e1G881ZzOuv3xrByRJMn6yDZecK79EMxWkoEsoGXBI8JxdXdum8xpZIxzmM1xBI010ppZ3mNYIacYvLJPoo94ROPHBH62ssI21ZCwGTElM3H6jYTS6dsnfZ0+M4s+pv/GV+wm3JO+a+FDU92+UdjK9RiPcVcjgq93+FqtLKhfpnx51J1oWku9h6z+KivuCoT6z+namVaRe2QlKBlFHJhaBMMkVCvfz680MBcvL2utFFA++KjLUhGDjM2Pyb04NliDMDvLr0/1JHFoXnn3FoyykPYq2CCA6TWJ6SyYRnTbXZqJJdVl/HWehj/84lnxdCqv92HiSZ8FSGYzxt0J8yRWUyBO2rIXTNtnwTRL57q4/g4izIrJaf90KfIynQ9sxeyO10Rzvo5flXj9vFWLR5WMoHIYcTwG+toC34gY92Ks3KiS8MdnJ+wL1E6yco7WSSqjWeX4Wry9vs/R366Vdai4alpNkCYwgq08dvdRenRT9VlUg1AbK1dTwmX0voXcwdfoY2AMAlW9JHeJdYBY+lmlyat0aox9F/FO1ArbXvOaeCO7iPw6gmBWD62e05//4d3IUe01udrCCJRM32TOoMwaPBPymU5JUJGtSSdX0sHfe646LWn6TNTiWT7GnrDwMNrPmek7gXuoIUhKwBuMa+V6ffuKApSi8lQiiHB+n13fnBKeib/E1p87X10bpb4c4B8ap/Byc8PkZnKov23eEetXBpsjkC8tl+KOri5JEO9Apm8QBCijwXk/hxVHL7Vys7Npnel1iqpDuzPoQV7S8Ayi9tvBugBVmBPdPdzJGVwhBVo9GxHSBlW34KvjHWaqbbsLUcYKC9+Qqchaf8NGzCZtDSVxO7VaHTQ3vblK1jutp9KkwrAXX2eaz2nPV37+j8BLOj+Is0n5RuKe+LF/FeoQ8YX+8WL22Wq3O3LIjxDnC3NdMlf1sQERhErbEXFh/e39EtfO9akLySIMpyjBZDq/vEB9Vr0L7a9bYfvSpb2gLnHQtrk/hvQIX5g0MHhQmD/oSMfVGEhONyYTPE5xLEA4DbTBW4zNvq+Lp1DEicvZVMmwr/b2el7sJz1vS8EDAbru4Pm3cboeISPm6sFVMLhwHzQIpYry2l5aJFRxHvwnO5yEv6d8quSRdlOl0rKzNHN3V+ZZSIB04lzj3fP3JsGN090YPBtWocaV8lPgTeXl8h8vgyNp72qxZ4LchELTVChBbiN8lAyV9Usszfj4kxi7Kto1jK7pYTyJeTgBlpM+nhdznqqZ0AE/ug2Qf3tZ74YfQCEaXTOb5ZPPLI2c5EtWToP0Cmba0TXRvUqg2qyo+OJy0uZq0WTFvdeBPlzN6MeTQQJFKh2M2OUIXFn1NKmE+6oc+ZOMiMapw5sq2ouVlzRYau/V0rTYO1IqQ7X5g5bM5QRZECvxLsBine2snfkT0GOP75HrXD2GtX9wZTf1NlAGk1/62Djb9fT9LUW7Xzn6VGAwGq6agvJQIWMziDa4DwhMzJQOiMmcqf6/Cm8XTolGujkRDRaoOBSTrBu+eJmWNZfP0AdEI6CmvCYx1imqMWZk+240tn5EZqTZKYfZcRe1h3YVMgtsvhkv7HOSYx8ngbXIAF/7pH5/23QX9KaxNACCfhQJmLeErovi5tNWRuvsoLImDwPI5QUdIqcwdWdtKm2J+Wc2qCP7dBMCLAmcvGZ5o1tfj36NJd2PT4sRSQ9oGkf2GUmxNZYPISznD877F5E4M5clUWMFG9slPkL+mw9TACgRSjqqnVQBsNZyDghlCfr6W9Wq+yfXxEJMIj374/D8JDf6wvyFvw5NwdhRtCoDJb7zpj8nr7uUeh3XhzC/YqiRHVQViWbfl61CzhTM1AfW//u/4glQ9xvR/xH6WdySdjqCUK6S6HNP3BCJvEE7Uib9fjgyB56KJH6uItPzmJNe37oukmArKU2VNvXtWYaEXg7j10oVRBgz5GhkbafRDuT3iIW5QXOQSgxErrfoBQQPOMgpytTKUv3+syXkDvGo4NF8TT0csT1kqUK4dq9XwwjpjrBwQxtICmjWmYoIKPz8zD8CYdNWQrdy457FswpM/HE2AYGcEgzDAUHsBR8dHk0Qou7m1Qh+c/AnqcTUdj7L/MNgZRp+YbNx82TB51308dDgxt/MVOe/a0l316MHVIkbMjI4pWmDXrdB7auKVFw+PWwVZ7ImTc0mljacdBMylPtqB0zd5g9BnXZEWTFJvLiFodZsz9Oj9qP/mGTSjLBxLhUMxSPvyeEyihVXvN8P0gmzEHokijCXlbpmVwXwfkKrwdW1iac9GIOwUMjtl+P5HD6Va+6tFmzLZ+haLVPKTJwCIh+8rfRnLeG00Zdt9qThbehvWJghfc8GCC5az1rm3tOZwew2XY5OemE+fRNxYRqijQmT3OxmeStEpBRU4ZSCmjM276+CatWkGlSjIT2UABS+SEjV4hdPATkDI9TTVI6FQxpATZeb3Oc7AiyYcRjkraxAH7+uj4lCmJyMp1UxXwSRC0FKwDpjdgDnXhTmCb8xoySyn8/a3VGNBT6f5dgls9TIPKveZU7SDv2cs1Ll406bdzGg1AdRt5sSwYHONVpyJKxWOqfhcXPQ6cSxhk1aYWaIEnmrmD/PQVfA9loap60U8BrMcTpq12oRgq0a5BwlnyRkzXc55K2DzUzup4uTal74PrAK13uccZigYvcrjJ9PbGzsWu/igvl6APn75VIJDTodciClPPBJGIhMz5zDGaWRinVjkZqevQXdSupgoCjGr19QAp8PCbBY5YttYrHSJZXwT1q3sfI5YSezae+e8LAcjTTTvJHNWtrIfs7pO9qvhQEAXwrLYUL3FlMamseUS5MenMq/s/pOB4FKfV4ngM8YlHKDoRRp6CJE9YjQL1XEh7laEOaw/ZV8IiHDgMN0pwM7TQ/seUPg7sZnH6+b/pQeDZS+wdj44kalvMTH3PJcgrpLtExNNTmbIHEPuYT6SrhrOX2MfPxuQtx8+y+C9W694hnyp0xdhf6W29Vy1wTIgGvl2p3gxIlAjx+2oCYng+FY0KwAi0lrgsFU7UDrVCXxlrBYDFh4RNnulHjIGo1VjrqIGHMVEKWeQAeWMRjtepECY8YZrDmFOP0eOm7UCzz1//8VRB/pH16pz6lhzFba+VF70uI8SkPGs+u3+emQcI2ocu7ztHYuTLUfgaMEknBK1n0hbynyRnwRxW8ydeTYxsScJ8KhCTk9QPYUf0GX+QjC7ElY21sduYelCMpJ/bRLXIr+avSfUQuZEDrqI4TnxVm382V91v3YOrQ0LWqkoaHUsYV9l9F0DMuI95pY/yY6TEkqRLXXZDUGwoogSuB41yBoyBmW4vJzPSGLC2F5zWDOn7rRMJYmDVW+tI/qRXSxx0bMP/FQUE4EgT+tlt9drwIMWmovndGhiWZaJeh7pf+A5Lc8PYjkUrZEQWIKgxQ7bPAOG/BaXesJfoZeKcC8tQfiNIP28VUi2pcNrJLOYbVmPhYRyMnz9c8jiaC9tKeYBaxJz+JB//t7uSAEI5G0FYqfVvb813XxQZEGhtAJql0UMboFHQ2e4JyWlkjb0LPXSUxH9cMZEZdZj8Y2we4TGZJDxyx8gRKb1Dtu5KsCgZ0psUCjQ/NK6WTFs7e+aLKHjkcA5/1N+u3F4ChU4P2DQ7XE7tsiakoCuPqUjvoqXOeQkvnaas7U7wEug6wRye2lMd8BSK0ms93jpwEZETegUeV6YRnUUcSC35Nlq6m9Wb8IqFRzzZM2MIl3lKOh0X2Zvu3xf4NDKL/A1iKcGRF7SiKJ+QNByCIS+MYNbEBo+OPwtHn7qd9aID/zphwz9+Vs/Yo8ksnSgxyv6253A2dnawsLRdMJFKFdFzTNJH1d63eEEl9QujUlV76cw+zB5MARewKsENE6jViunTr4VqBXAMkbrYvgHYgmbmuhTz13dVXcinMeo3sKTo33JaUtJRYZTVeNwgpRowxd3XMsXdWoN1aTlsIf1aVpkZ0y2Mm+qGYsCoJK7VAt37gHgEQr8yuabKLqekPrxGYDUc0sgDf/s5RBN5qHn38qs3+nByCZylhGK76kjytwO1FSOPMCbHb/F9GhHVsZOGe3utu3vFgT0dGEZQ+xjEJsYBTMhsyQ0kbeeaFUl+Fkt6Xl9KSM/qLlABnPxXZiRNoUCxoMTwH1C2PrfPUqrhIt4B+8/TIJEnfWsOkIN2/wlRYeXZf2eaaVePi+QCTf3VQI0NQX8YVREYBc7EmNEn/G/I/2fsPxxzPqPBaTg5Oy4LTpYfJc+AvOndRSyRgSNXLRKIkps+rJaoly2gGKDJ17B6eFFnykaETUW55/j9waMP0eaWzft3N5ny8HPBc1BgHaRtP28s5eRdxOgFrAjUk21jT2TcbIZGuTzpu7TsV3GLh2WrdZBx3HrqDh4vL5PLntneKj8F8Wwx3eq9kxokuTX488Wh3riugl2sLoGFf9/MaBuHluIMTgN5n517AWwOzwmPLWeu4lzWtmWOPbR3zjeMbX4C2ZwjMnQ3wdk10d0xHI4Jxu/9M+uWej+PtuQaEnnzvtQ6mn6n1LphCMXXRGVQ1QYBB7+In9//XsSf3+YcZoXKQ39RG7EKgFW1u+Eq5i6oyFpu7DqKLxbM9EjnCNLEW/Awph1vus1W7CjttVXKL1U49P4nfdb2cSuSHClrOpSTJ73KDv16QUbqKf7CST5wOXvLvlCaWXvRqutFVp2vHH44BntQp75TIos+CPb5e3LvAnOaPt4fiVuXnasOyJdoo/+VMqncZzawffwslgQqfhxAhMSJxGYoxvmv8/0JQ/+MK6V9l9LJrYmo8CaxmlKXFGM0WQv6g+fywnzj421zUCrTPSzse12Fua5f8qAJIB2XOKllgvYvNIQM4cevM3SufGx+h/sSHZ0/OVMc1u0MqESwgQni19W+98xB4IxPyCVh+ugs+uw3vVnG6PeQM0oUklJMB9uXBP1xXLoWj+hetT/73jzKigIqMAVQLIzSk6anngyplO7g+KhCC6tfFnLxcAdaYwTCCLC1qb9WlSdgmrb/pJKTmxtLB2w45ju7OOL5rfNE6ZvO5n0QCr4I7tVJdXDQGJzUPxO/IFohFXJ8iA8qwIbC9/TmJ2cSA3FxdARJ/edHwQhEixuZOYdswLtxy0eBN0iAqQIgS3TPCItRT9TSPgkhAMHGBcEZAYe1taEFdDhBFSFgwqJcfZQmkNRJA3IjhZZPo4IMXZMIO8dw1GlJ000CrHBNRAsYsT0ccKaWF0e66XfManhvYH8xVL6r4wo9KVrTjV4GpVgG9KMYVV48p/SaWMxqO6Z33FTPVnduBCbO9/wxUx15V7eFu1eaFsWnNcFQR5DmF06Naulpzn6tpwYl2Yr0/hrFAmcZBuskRCGhdPCstBTfMRPPTxB6SgwxJMD4d/PswOljagP5VoRrV2kVeY57PjnmcjYGnHsr193+lAky47Vg108H+Zke9AxZBSmvofBTXACXJnvNrXV0e7TPcVLwRL9V/pCYpJ6rSo9Uwc1ugFM0l59U156KMzLeZw++DbGh1qZCEe6jZX/sDs5sNUsi7Gerk/kttxs0TeymAa8w9o8VLScNnAbl5Mk8R8ldm/7/g8R2oo3mJKEeol5AUv5k/c5qG5GJ5E3QaLhtxiWgSkWP3SIAajSex+UYrgA8VlUKwscnegmffjPhuZWTUid+gZaZ0VodJtcknTHuNT27vNdqK4oWUBDiUT20W+esif5m0/RCnIbky6A+SmfWTRBNq3KjMod2Dch0gFJVZrEN/tpRvvV+Ef9h0pEwpW1XDSasll0kYcxQh4Ow1j00koTNdjh7G+aPASYVehPD8WSRcI8r2+NdaMjCduHXKkifCg6pvxUwICMgcBLYgr6ox/Lke2cwaN8AD7nMd+kMQ5JYwg0p/H1/juSXmCowoxaVRSBwo/nNwjkpHhpY+R8baFpud3B9AzWBGGfu/cxqFLm6EvsMEknf/mdQdK2xbOUnMP/E8KKx/G3g3Cr3e1PYDFD03WdLOYmCfh68n1jMN/CwamaZzidH398A1Ql6A09X8BRRTHG+leyIyd1t9VCuBWxRvTR/OG6Wd0voR/Lh92YxTcrtnSmI5zbaYXBpwApfYNOlR/DcVU8+1pHYB1gkd+zagGtmpJGxbZnGpQwvgQ7Cza49JrL8bVWjnbBTKbsWfPHYaVstEG1F91DOnAx19m9XFEKMOrYrANtnlnHwdDKwJo0Kw6WKHrQVGkREYjIkOMrfy65FBPjpjnEjMEbzr9/PrCYnP02X88VfP0+07KY+e0ue+P3bYdRP+6tpwBhwOZrFUD7TPZlB/jSuDA+/8aKfOKDNkITBD8ZxKhwgJxYNMK9IiDf397b2+5Lu3gNH847RKT8PswV/xu8ti+D3NbakppWV0RyxUKGl6H6/aIHrbthVILWr7n3VXwIX4+IQPJ5TOe1PT0syJeYUXykoRaxX95s6t0iDEABz75u0IvlIv+2GewmPOWv1+9Fy273MwQGpogqkv4w0rArFWpuSZo8txWbjZKK9MBDn+dxcVZOGn0jPBENBgXUSOVlaHUiNgiZjypU1I5xvKYGRj3C8dMDELWajwAk69L7A7UndBVHvI1NiJ+q/hSRU6y8ld78eV9qg2zvdnwKjibEV7jnjMrXmtrWzhSugz21fnahcumLSa3/QBNQLoId8xlcrDvDvZBddHQx2VdUgnsXjd2n64FGgYUxRlOTWlwO0wgXDniYozsL5k76HmjqNIKu5pRtKuTw4I+7q5cSxlTWLqZFfPD/D8jKek5pbAwKSDu1W3ogJgjERURqT2J1R9jZwgliVZostH9BL5hoWNPoRlo5riSYNKfQz6RyXcA68gS7g99MZesB6vlnHZb5Nozbx0J4+8E4EbZ1HRPXmI9hQ9C0iNjpX+crd5bbPZ4cKV2Sg/LIQPcLttp4VKnC20RduqEjQTTYWRgUaMNDFYnFRJ/cBRwIJyGUQEYF7d7zf4TTEXv2EgQRnXCCB16tuny7SWtXwCzCgrR+tWQjyx8GKWO1zUlOLW29JpLxFl8QJQy4j58dzgYa6nik8bpYpnhLvbMDHaTPHg8JOd7k87BjuORaTC+4rkMUHWmYuVxy1l+tLK18Ja91dTVHpl6AiAusN5/IJ0JPQwhwlELsXSez8WOFDX8YxvtMotuC0mxvFBYdC2mSCeytQCSMGxlTyXfAJ6BZB/w8nvOcSDMDViKLlFxP2PT8O0mDfnMUVU0I5x/Q2hRlq5yXpVAoo6umofneWR/FUytGAtmwYwZOU21WhU63qBNy4fToRqRVtZfC57C4B+Cdpy1kkOO4wKsdLe0DJAMpIM3xfQ1D9WQ6deJLX5HDhquFdHwTBZkjGtL53Ndci/oY++AU7bIFRZtJ0te9p8OrITcdfTYt5Gb46LbSJePNnuoFNeai5nLbFuT3OXS3zGX737TPYZZ4PtChZX2+yQF9N/1F/Ms80tvtfZ9Cb2Wcnlyr1RFZq+ow769Pv/+MjJuBPLxSZU3MXHAFxWz3KVjr1lqZLLWdjYZ0n8qWlMmBitO/27sbElR1nTRYyVgSpH3wyb8e5BJahQZZkSlbLbIdyVIBYOSI8rjHdpK20oW4bC8Hd3RlkOl47qfgESKtKi7asOpwjVS3b+WhKJESxYN+QOTB0taw1kYROMxveQ1K9KRAQN+gBNWBL6BETd+5t8o5lUqZS4hY/CiwQwRkG6X3awXBjikYfELsEiueRXygxOJTi08znvyje7g4SMOLHSuk52Fu2BABw6WF/cjcQLIaVEUea4QEw3lQG2P/HlGZ4nmoa1w++07SF/ZxefO+wtfBfAEk1hcIc4/z3D7cuosdhy7NkQnaORKLDwTYk5ISPwq1y1afzx/fbZtbyGqNq3sSsTQSO513/2bXVEjGqyNK158vr/2rgUty35GoynU058Rfcru5NRz8C1aMMU/9fC8J0w6AIU8F7n9XL2WFxmvyxL81Q3SbJ7hVNDFuTIAFzRvowFWJ7R4oDa+uS/g+AjBkEiRPieU7shb/7LVAW8JJzdBfz3TTBTSNuIWBDENkPnjBsgc/vH3Dmt8+AV95ZNQU9f4wHcFFnx/v/X8OhPPt8+bDlAKM7WpJIDpnRlfsn8Og6k0IRPJB4kEb6dRaEAOaUqKbYLWmbk/XvP6/A0DDAxaULF07e8wEhnjxnhwUtI21NJ3o7x+Ri46fXxsGgDX8TmqRrO+Bs7ICqtCZ4I/2iCruztICY2aoMnGCrv0CwUV1NFRKTTWLZcnHMQYR0gzttjJpt7hRnOkeQnVA0aMfMkk/8rPKfE0pT4AP/n2LT+ckgHQFk/T2t9+S/U2wR1D6pmoaUwljsU21+rIeIEWsfg5BMLGbOn93kfW522+Hwff3v9Dad7VZfjQOjiFEfQxJrVlx7K3Pkd8MpNiMFAY4aAhRW7196a9LB/b5aLwQtDJZhpBd93G73tOlPRXQ8x8ry3oMNj97K7YJHPDkeHsVIkwaooKgQgddgnhN0oQqtT0ic1iexCWrZeNcTpyb6ROqHE9MSwyQy6h+FgEVLzDIbUc33NMCIjxK04NsNGfumIGcrBJhtbGGKqhSYIsIxxcedux1/qENGLskXBPyZ2IBmPfQ4ZkfkGS3q2CEXJoXIw0eY1h5uVt/8zjG7RcjSKxrlUpNGyUGAUyYNt7kr9M/g7GrgpCrRrloFIs7wa8z1HfAMvdkd1VbRbpOynhqrCGiuVGxEboVusMh9+LLa38MjKSnRls7Jpz/awOtcDUWqzn8VV908lnz6wikSgqQmW1kqZAQVkJDbKnAQC7bF66FG2DUWw3l2ue6iNBhdt+kewKIDhqxoH9pWKo3cUvetc9mc+NgxVNW//2IFf3bXdQxxv6At46uCpg26y4gHb7JCeFfSrQUboEanUjoPR6K96ojUPiwNhQg96TkEJ5MxH7A2LlSkqQ7xbLFqwCzSKz2pijFhp8bCMj7wGcRWlbc6lmPqpPTax7/VbUQp5O7oNef+gn4supEVvL9EU7aN4Nq1qyYDCpidNK/ny97staPkIVc7Hf12GYvmcLB2zDe8p/xoMyQfwt5acWB6X+lsTTRkwe8ogLnOZN95S8zcD3TkldEsbYDYGOtmAzGT/qNdzUkwv/1buhYPhq282ZlaNzz1MfSM2FmT+ETFZ43BygOz4g6AGYqdc3asSttxMnOk+o+rJy/m1NyDERb/R+urpV7Vgs1xWsEJ4Nv4eANC7FpcSZjlUuKJVzol7GY4CtHcc21Ged/sRIksa7fOnE39n0j4RMN2OIssMT73iJph8FNiy7hlkDaWWOW+4KlkDqTZdqd/V5SoNjYVVFCCFFLlDBUGAyHP1JU5yShoPtIt48czZ11LXBsg/j7+cxMH/jaY1RIzJijq54nqAS+RVbmRrrlNBNcJxR+2v4rgqqmJNpiL2QHVEZwCyA1Ifka0TXbGLZSIAIqf6AHB3hQYq2T+pKyPeKYwVAUIQuJtUVm6RXvjmAhNHLPQtCalMfPjuNCvj4xHo3FG1Z6B5djp6xLRCJFdOscEl9WzRv5ml57060l9U1ul14v26lPOoxtijcgx7Cw1nOF/uawYUquwBm21JprChjP9LO+BISNnyw2e4bsrF/9GIDxyiclcg+OxAThhUnaaTnHGwfXrUjWwOw4W6UOzuHg4mTtHPBMWyjmzbtYJaujHFJcxKNVB3IwkaxysdtkFcmOOR5dXR9EFYEvZLwEMKVEE7k67XW6oKt4IGbv102Fg3HN35LtqyGJuwJ7weYwX41xOoMb9cxGcQckUfo2soVQlFre7QnP1s5twft7q+gIOBo1pfmNXsJPJadWPdMoaRLgH4tA/cDcZSMzKg0QAj6Sl8vTH8FJRpXj//tmoxNWeVXUH2FMDiG/MDsx1QdLJPFffq1XO08jvPGVOgZ4jq/LaOp4FmTLcBnuO5thR9pIOUJ95GmDsXwbktvxJTmDlkkfcAzHsL5cY2qjLcYc+dBvn9Uz+8czdIBqJ3bzJPPYH9HblVTw3DtrVcLALd1ItRUgtEz1+KFkTWJiXKxHMzVFln1tNKN/D2/GoDxMWveb+hj+q0XUkoAeD6kRTXGzUQtU61SfZf7BkXezPrRupSNOsGFxy7XPqA009L22l6/fFhcUjKyPtKvLOMI2NmSBSbnLVF7CWLEI8XOE9JIhoXSZaTSZv4MEQKZcepeoeZiZsi3yRDflHVYTDNFz0h/EAOijStqxZ3jezSJoeK4ocBKTjcqgnFPSAQ8a5OPKg3/1L4fwqGUTlLl+CNPSs6CMBD45Dxtxq5spnaSu9qrO7Za977Mi06GjStR1a7QuUZbQYujEkILKDdBF8qkFmmDgazOmBAqdviOduHvc+3EnKxPiySP/wBqw5p5mRYj/YXmmbOPVhr2B2iTuk6lcOFxSzhP6lH+xW/xRYpDGmKJAhCGmYA17wcknNBEowOWUqQrUFep8HHqzDC0bVUFvArt/sJchNR/7QMCChZ1LRHuQZFQ81ld0feBvyXDnBLxLwzE1TZs9OBaAaugoNvsC/c0nMBu/O6MEQPbGG36q7Ay2a6VFVmPFS/XiJf5SFCN9I/+LJsyJLYQ3IaANEMuVpMjb65aiNr64BCyQklyRTu6AWQg6W/zHrDHQK5ivBFYVWMW7+KBKFPAnRaUucMN1zfQ66Rc/tbqrpfxlTaI+GsV81nKsVXHhUnEZq09ih8r3uM6r4ssL+a0YVfa9xYm7QpwZA+cpFDyZ8dcZowdXOCWSYOUEnjIhZnY12LVOe0CsMjXaHn659N+zzP4UyPJER9CzmOExGX/D1IA3XLcnN1YegklR03J9a7Dc8GK+WlF57mwEjT3ZGRnN3gCD+PucXqNsAHoR+ImE/XnEuK6IKWoQVfYh5HO7e1JYTg+j+cI1YIM8QME9gDgi4CfNrsWUp7MqfixJO61NKjSAdMhW/s0D9cSdW9jv3w05eHyyctEX3rkf51bJk8jT/ZOb0DDyxaw/8SOJLcWuApIu78GEIlTmfTTu2Cwy09jubn66bqBbt3QWlH+mESTMuam1v1zKw/17z18JnGksm+O3KQyjpGKEz/54D/n9h+wBI9vAkTKt0YeuXv6/Cn9l+ozx4q6UOv0FmkBdcswoGnLrsjwd4Dch4AYPqf5T3D2mPt5gT2RncKURPd5DSOgZYPki1vlwjhJKpc2eyM/brRRxfZ66muj+LWqsfUFSbS4SWfnd03j2OLsFBxeLQ6muMAvk9vuFLKUwfpmEnt1dy9RbZdzVSoXh/FqQnuKprUc9JH+USS2lxo6JjayoHVtfLu1tktGSIPpCe0JmLzCeBBIfYL6dzeYjXb0i5juciC3Y2F388ZgCkYnQ2tXuPFxge4/UvxUGN1KpPEcMseWgTttDNo2U8CG35DLj87pJ4DQuxzf2TyqmakwNfx4bNoig/q2ka4P8fRQZLqTUnI1jksHqzHMfJV9w7hpINV6OtuOAdPGePsA3Pn5OIXEtBgvSZ+JEBTL3+pF3gecFuS70ToCCx1z903//IjadC/W+ohKvzlopEvsAN1bPLz0IrWYBojORA+lNKzdQLuEDFz1ShhgbYVxgdwVJ4v9nu818a00aX2jf49B2yUccBQKhKa30wxKn6apIh2WK3UE2tXAXBHInC8sXbueocmhqSyX49G2Y/i5PYmZFJk/5HZIlz3qXW8EwozgX+NQO2wXPl6jh2xfQTsDSKv3d0WbREPBugghn8OR19RtySVAd2kQridid9YdT7x+FuJSFXSmBw33LkLSUqmB27hgz8Yrd/Av/SXGp43rYBlHnCcNDalroQuPOkrjmbJjNHK678/sxuo6DKGM2YJBTKyfldEXzLMnoXIStKmhy8gJdW3PlLnh25jTQJeat8L7qU7lh9UXoDKcWExDdd7Pzae4rNuaLzDy1NZJcJFdrohQtzgFChGnsbsjflzPtN2+nldOW7WmoLltLiOcxuryEVuS2vqio4hAS/0LD5rs041giwIZBFL+IG3iVggoX00G9f8n8d6S7oPWgJ2BoBNNzpH6HdNXQu00vFp7OrFAI/OGK/LMquFrjgLozHGvNth7aCd5KrFl7COVuL6aLwuBqZJfNeDAxF1W2boCsi5bZeFPOxXFYHpMB/qj9AUboJLxhazenPp9pp8Pi/2tKA64VcknzlqWstJGUkLZUxiH4wN00w2veF/yZHfQvUmdnUnZJ/vbcS3JDC9OYIahdb3VNeluTFHn5yydIKqEW2gXpbLbgz5lWPbvLvdng2a1UUWTe1mQBByLaF1mdIFPAv0Rh14RztnUybacCVQ7B9Z959H4eY8sOf4IDNIrNRmCNwCIHSEN2cUbR1m7iwQ4cKM0DmeBTwsFDcRpfmY872X/wcqb1cAyOJkxkP9
A12: U3VgYFRfrkBvC3g2zSnemZ0kmBPXGF6LvGn+sNQv1IW5liCOMrRSyRF9AIGoNdFeE923OuVPNWg3Kw0scsJ6dkBSWIYK+Qgl1i9GkqMefxQ4oo7Qvq+Ksf2S328DHDx0YEd4WVHPe4haHgd049XDEUD3xkMWk0Cq4HMQSmFSLUxT986YsTWrL9oInST72qKZXz/rBf2gphohOC337SX65JrVtvpA6zBJJGIDspdGVbrYdFbyprxORt3H7SDJZkaqv7bJ3xq5fUrnfhn0OAkerHQ0Tbd/Xn796cQ5GkR2Fnc2SPQiQJYN3vxsD5mVMYHrQU4n7emTaO9TcW2Xa2kTggrPTy7ZHFvxu/arutL9jjo5UJeFFrPlMSR/ILHHjXywNVmU2/QAe9J0fqPZE7WCJ8U14XHtCgOGr6V0KnvSr3fBEvD2nJjn1iWUSKS4clZ4jfaz+zNvicXJ+f90RYz8CrtHqX4FRqRjEzOF9OTnK1gIWazZaQpeqf//aQYioM8CqKrAyzhgCKAzob40OxGtCRa0LTamnAnL5sInENcSKYCnqT78pOWDStafRXlfDBQEE3RPMtlc88Pjv0vRMCEz4zZ4UzJR/iqu74KMGgRmvRzcW3Rq5BKuSi1WV45HDSb34egnz453A6nnL1RluD02GA+A/4DcfczZU6t+CYsne6r3VUc+DPEFRkN/jp+bTIDVyS4fDSnSa4i+nBGMt8knumeQN4OOK494CTtTzqrINka1QdKaGbY+StNphglauWfKJfulXaWqyb2U/tQrtxhEB8a2lbM3/0MkH7DB4PEoUZsxDg7lTnA7EjPkjx6X4/6+cjEgEYI8heky4H2oT/NT9ZtKsq2XrgtTTp6n9iFYDr1RwXR62V8Rvh/urF+KbTali2MQExvYY7VcZnI5mFOMS0pT0czLlj8cwF95aZmvLhPN4Fh4T50oX7Kq9SfbWMOJitz6q76vdls5mr7lgAsHJOgDd30K+SyQB3Z5YnKgdUxE4OB8rmGc7fCJl2YbibmFgA4P8RiYZr4sEcwvbfvd7WSuFCUIQFyfUHRhXidADOEQs+FTyRGa5UleQ5YDoj2CuZNol6qTFftmBisJPirlJ8l+kiTntZCu8rkaoqhbc0lHHRBbajO6tREPFRm2HLNr6rJ4HnL6N5WPsbyhUA0A33As4vaLknePb7T7DamypNRq7bfYk2EBTTMujlp0/QEbZTQcvvVZh48t9IOGl4jnxcoLoiKEhpzjcdiKzvkuKshSyMGykHqXvxGr0rS7ZXg06RiOkVpWXEX/NKiplVkCfy8GpLvPShGMY9VwC6BILR5o/zDBqmk9Wq6BtkUX0SEfUyqYvaR297hufqyW+LI/2qN3HnGsHDtCpHWuurK6Qs32rOo+2uvTFxPH+wd7Yq32n4x1WxZ65ELK+5/KytwMn1hhlvgqPtkF2eILONKx2Nl37oJJk1yq8ifymeWPXQOsef/BgK5+REqiCl69SX271jl3kCLeWs/0LPHzbO5tTLtRiXs8qbpq871y+pA5EoG+Inr0v2kfZBANwt3et8I85koBSarzH5pOdCBi3WD7Z6Q6eL/NMRoYZliTHVPFdbCKeGMy0HX0UActSjDyn+HkDBHqL/sSPAUH+nPx+GT/AShhILms7dFqZI2lYUcp1G9LddmKvwDSTxXZPJPd4Rv6+rREe4SfwKB/Pc09YNjEVqXsF68xtCDfurYyus0ymUDQEjX3rbxzpZX7eimgNcg3eq5I9KXHfeWnNAYdT5IFnSpu8uqkkt/MV3um/83TZEdtSYNm7DcyFtU6UjCxGGJ+JZv6e5V6J3Wka+0SC15munH4xxYgPTFeOp7mFu7e8bk0gLrdoZoO19LbbHg51qEAjWMY+/ysPnI8DLQcf3qFb8ehMqf3VPfO0jjnPxNEWyckWqlTyd9/QUci/u5pZo6oQXcKFjLIDlHbPJU+hgv+FfhPqzePbjOaG/sEAv59tdVjkjTbPCNv7586MSSZHG4hwqsrn70bpzcekxJ+AeZ+pjWOe2pQFzIA67XQKMsxB0IBPTajkoGqAAxj19FpCjmFCnCwxwYVvRLqlrxXpy6eQ27N2VRXhSUnBvYGzyeCkCGPVbLZJ0rBLuIsAfMcdd8iK3Yxp6wbjrwdj/1M3ba383PGsPx1VeouLsazO2aRnmQg5j0ToeJBbJ19S5B8AXausz+7LbfCwh/KauqAbXC2oTXWCkOS+KkQLeGpYpZDIXytKb193H1wgj+TL1g/e9Mo9AgRyBcdpZlFkgIHGGiaEORqj6+8NqTZxFHfgzxtPrrSPMDqxJ+poQNQcHwMWBKqHK3minFClvy9VphJmb1BFRmH1PAs0Xx6Ug+/vR0CjJl1cQdB1C7wPeqhAWdpz5GtFFYyRxVBTv4FtJy9lI4EZhaAmtnTi1ABW431SO1xEunckzJAeSenWq482MWrzltUvtO4peB5WhoZg+pt7xQd2dvu3QtgxbTNwDxNwnO5Ztve8/Ldfvsqba/NBEvugACWUVeoXEgIl8SElez2L89yTD2jJaucU43bBxn8AtvQPN/hlcUQrEI519wdw74jfEKra/uFY5H+23IhcMdb/A8dAj1SkOyGpnun3GsDkYjvxQkl6QEDW5ZUkvgMPwitP8uXh4HSmnxbe8yR1MVEjNoTAjtnQTj9htrI0v9xJgfiDf7oDI2KW8gHYOYI06PYpTIGIw5rx9Ip0/mjz9ASXXhl+8eoTH8wqO1pyRW+AdgILUoKzrg9QDD3lyG6l9tHO4Mvkx2Kr3n7m9CFvMejtFSW63Q87hLpcdSGGbcIE5pdTMo8Id8ogzmasmACCFbpgwyR7p+lNtk6bNCbdKFptTXaimj8jmdaWhoN9Rk5svY0q2XK5oQ/Bb0tFtZqRuLJ9gnKDKnXrmayy3uMc2YHfllSk/lBqjWdPOx5tSdcSyh7cgRJcsOr1ADL33Va/j+POKu7/dfMad6/R7PMbrFiu5t1Yvon2z4PKdb9yf0KDWE/K8PB6qW6GQ1Tk5RpabIeJYFAZtbuqEWTne+8CziQT7wCf6OJ0jV4DWuPPRNGh6rByxXunsBLAsIvElBogWvv3BTj6pvCRmUuLVPuJl6onwRQKNUdxh78X87vzwL4cWpZ0fYGDFTaRfzQgu1fzYYqWrOzXdiLbachn3h/6myZKNpI0kSWgdJp56vWultp8AORd1mb4GX6RVTeg3auzm20afq4eZneJUP0Q6T9DzIP0VQQzuhfXeta3yyb1S2mtKTVWBuZb0u9Vmper8glVaz3ICfnUcZutp+kdZ91WKTX4ckXwOiHKklp9jJ/BzMIjdBPS5eraNIpvVukYbOpVSGGj7188/oZ06Gu/Z8k9bKOqGpZTNSOUAOK4x4QvLArm/YQfWDr5EfBKM4TePzw2A9+GrAgBbDneueVEYb5/iubRjq/hoNlVVCr3Xe+OiCYhebWDehL5PRHa7+s+zvC+3c9dpmKw5mPCtJEpuYGshK4b7TMcf5Hyx9Kn8ntwrou0b9OFRMXSFnE0BKn/9GFthNsSdtebdUEJ10fh01mvrwifSkU4YU+ivyoY3wI2M2UdadEudtDPf97vtxb7IXxB/fOFctDkWOsz706wQ2chb+ORPkdGcoiIAKhIY4eqO9uM2VQvHxG8akBwKW/0iah/D69R+GzrUkQV1r4xvsifDafdt27uk/eNsoPpTX3MiKjf8e/H4/IO6JFdwk0KHJrffN88FzdxBCtBuwlfkz4+eoOoNTrFmwxWNQrlr6YYmY5AUYk99ojpWPDv0eQEwRm7q8AU2eQMM9eJSFIPsI6j1RecfW39jZYjLA1mnVhO1lmTlbigra93EGGEtJpBJLX87p7H0F2F4cjpN+0jl9jahCk4UpvQi1lMyf0DI0bbaHKvnH/ACgEbTkt3E4hWal2e74LhbqM0UqJyecwklgdQaPHlDodqL2qGZWANUSB7jmOh7z9YkrkDiD3fbpMsYBedAgEXKE95KbvFR2uqn9rC3eX8E+uyNU1cAhYTTAGbWvHB8/eDYqK3VO3aVdlubqHNmyHHTcrPiSiC+BfPTGoXXRVEOoTmGM0PxxqQJE+ssiWOyTos+dTdLsKrHROJB4LNUKokoyvoZvvalDu1Nou1/Ktw8KgJUW8knfwwe55izCe23QuQWSinz/yNHZ6GefxZe4TC76MyeeRz4+U/SwSGA0zuSWXMUxcRxXQ7qJtJZe2mmp0ltH/lKGuIgysMYsk1l2/C9eBEj2ebr6YKg14hUE8l8SsReBJwz334Rq6mh0W0hwzFYLehJPkv8b7fVs5ztq2OWe3RtDcbYLFQuDBmwD2BofT/+0jDHkBlUSvVdYQFLzJv63ToOJA+5J89GZHrHACV4ZUHBIq1opRth+t/Fo6O7AHgiev93hbl/Atu4g/ybNtyJq/wxot+bbCl8niEQAaNq44qEG/tu6zu0+S5fE4ZwOgoipJNIaxXrqyKNMIT5Ki1GaOlpbiJfke1Xn80RH83jweqB7kc1laUFCeIyWYUrYT4QwizUa5qs+Azw2sXvPgwuY649t479lslc8Bwulcgj2sG//1IuSzrXuiwJ6IwuHRATCkfim5hBhGGKZYmKzf9bOSyxaqQvYgZuOHrDMTJnX0YNZDVlL/Qc+Cq2tProQsBwwyZ56jmQc6GNNIaXpQw5/ia6Ow+x+tPkbD3mNocbS1/wihrhaeFkhVhUlzEVRoIPof/w0cACopvGGWi/bJweE+RNQS6Ujiegm+Dt4sf4JguvFD0kDBHnzQmZiF3qf0r2/dHhHMviyUMVqS2dq3MEVbjL9bSa7fKUa6ZxayhjLrrjSB/SunNkehbuoT+BIJJtnzRBjaWLobaiObLRIpVYswp2p7xOLWupEZTWG4c1E/H6a5UL58zC0bnjxVD0cZYqdGh4+1KsJqkfUtJcYQMw3Lhj2aFrRL94abAvpUuMe4eMn+CIt59qeSFIZzUnayicsNgOMoNEiNewgtTf1jiglNx5rIm/8K5Zk3KoKFmKA01R561Ow2TvzEUQktVLmPS3I+o7oEZ8gpFC7Ninfc3yHCjczcLb8UfBuu8Kf+u4FrVNyiXVW8jofY4/duD7UfcZOjcJ+g/UA0mLBNjpXqDDc7nYibVZddXHMDskcnee/TzRtLgOFnvs5Lj/2wn9SQP00oNDTSgcuCl9pf5xWmib7n1x+5CqZnxs9rCmt7NVbph3cA35dYqysPk2wshwOaY/Pz4q3YxK4nq+WtpZXoZkoSFE+4pQSRkVT437p0uV4g6eUzuGZvIYewslFeJ8MfW3TikZH7C1zV50aJrcnTAT0gJ2mIsBWh0CoNm0Mm/AOuYw51Qyp214JM1W0SyqLeIn7xSLc0TxsuwwFSWg0l8gTo6mbz+0v6BxTy1WvifEbpOhSQA8S+PeLCQk+myuRBFoFaGUEHGjbRr3Qz8LtFYnXyS2xZqJvZRsb5BxJW4b78zq+9z+EyHwlbAMrHtjbFzg5RQ6SsYRyF+ww7b50hwmSCNciqnprHNEGoPIT2djO2SNvKzgTDEY40AdoByDgN/CCmMd705+xuBBu/KC6Vlpxc3YQimQCqSpyBalfmFtKGiy28ho6YwJA7Tk/pS5CbX6/vfQZwpnXFJwmTO6ibh6h0E6E0bkNBiTpANvBgkmf5coFtZS1rA/ZBCqNLQkMsuwx9Voinm28Bp6ch/E/Hu7GYga+LdSFR4r1NnjntJBdbucaVNIeD8LzplHv9pVfrkd4rYfPgxtnv9DZxsolaQ9NGMI/aOZtXOnyJ75uYZq6J9fqlEq62LFIPXozoMjeXVEefjAWt8TNNbgWsa8B4kKB9Ag5RDFEMYenVL3ITcQQ/I7WWeRHTmHwbsrRm6izAZasbYFMRr/BZGQWrbbhaWqpcTeVtgUcs4YG12nSkk3/Y+vyex8m8Eh0aV8R55w0rRwJDbKMyKuCK106+aY3LZ13IHnaMQap8i2ZIGqmzGllZkdrpZ7L8zYiAYwVs8qy3gkuPdSVVYXl4Bnj+JyveNJSqqo4QPIkmHIjvWaggOeew8EFC+YchG2FH9z6SA5Ho95YuMAtK4AdIXd05KhRTB7UNhrRcFCHBoXg/h4osVHcN9/0A0CcVCPiEoN+mZRgtmrbCGPS3AM7jExU9IfB5ZBw8LzyPhhAA/65DYyEc4BJ/ZRdPXpoJjX01aqrqVO3BMH3/s+IOX+hHd1Y3kunYpHAuFZmgY32AG1jXUMkpilvRykU8mwrFTHFnO5oyL5diJEBAoS4xbacxS4NXrejkA89rPxC+1e/Ud0CM7snVdbwtfv1geRFkB3WBlmXTVPvUWXbtZUF3GtcGV+P4GCqn3PEVz+N/a79x1Xx7L086sstCDHez+MwRXI7q4tvQMiJTZv68cB3QR/KP9lCEaKSewF1Woz8n9O6BEcI4WmiZbcYDE7MWBl43LC8kf+WqzHYCooicVa3sCi/cY3s8TpUe4pA4gLfp5X+xSjUca9M+0qYLrh8y1lTZN0pVpIK8fOm50aS0NCYReHqfKA2Y7ab9PsbV1x7mur4oocH6u/VTsTyWep/8NJSwYQE+xC3oCU3VDzfISWCmzb87Sd/H1y7mBxjq2NgrnsxKZoGyXTlh1/FazjQRCFW0K7BVOhxX6sY0b0quVFz9415wwV3ysm7J6grhm+9sN9EBFnSRHw+yIlW5f3SYTPqpU/GLPaNy8/Q6vzFYVg5habm66itLjPVJmI+ol0taqk7Ie+vWzPiiwdZLLrKbpyXDh4Ea49WocHiczltRHgUyn9vK5MVtkJHx+RIJEMEljKJ2YEUdxz7N1KylKz/obaD99qa6eLD4Jf9tnhpnpGvAWpu6DpBaVZCXgMAZhzI3GxZNOVleNkvU8UhqShH7ESYjVF5H6qONrNzorWGO6GEAI0Z/4ZAIgixkPf/k81DEEtm68KWSzz2lPbSRiw7BW8vzMYx3/SxflA0DG4pwrCo6HUIlOoUaJZ0nasuRuK1zDpGx+/D+SOsq70MWtaxzKnCEfzWOLtYpAh8PICvwVPwglzvfRt0tVCouCJ6+1TFAySfwSxPL+ut1gVo4kScjNKtR+v1ruG7Am1eVPwwY0uR3Tjy23qf2pcToRURYNVwbzTNbutigrM6mn20rL9c39OXXyX8k5oYtqpYNGKCPuYUhnSW8phhCCBlWUJx9+kNCzLrkU47yqlHewwltWA3LVuFbZg8PbCQMfclGgLu2/kYqaX+WNZMK5q+Tsy48SuBDbEgwTMdBBabv8pLQ7ahfHi0z8sI1t9pE69w9scYf0ClLZgZApaA6HEgJnCAtSgn1+8sfpnJKetWZ0i8uQ5lOuAjH6YsmZJFxtd3WsjJrlV06mqwtuqmKDb3QQtNHmBAO8Nu4ilDcWRUjeeaKwn3bb5W4PREeLG4NAmI4Ay5vRhpidEk2jFwHIbn6gDbxJ89SV7fDXfQqwPIfGdlcCBAgUhBkCM+UkU78MdU3pMDSgYA83XKE9KvLVfgwPBej/N/BaShUPfLlRpbZDgfOi5OBPsq086hUeOxQMsQWDC7aV/Ot4L8ASs5u0qbZdOgTj1+k9kn34HyMUW66OD1TkwxH7aCAsWJxPRX5CkTsiDW2dm3wmCRROS7zxEkgV7lTj4vjRCvza5HmLMq6/QUDGdhA7DDIXh+TzjypqWCiu8Cq99BLFl03hnqhRr4fuB3CKlJ+MV/uZKh6H5uvGTpCCgpIbXjCz46ICYEl/tVpgowD5Td99cSZ73uvujDyXh67Kf+TSkQDdeFM0gQEUgLB+JOr0h8ExcnC6UPaFBzG2xWZxGltyxSuqWZKQY0uiyW69+cKURMDUtJ274w0Op4XF/nQKTgcRTUpDbJjOUGsoOthSyZXwVI9884P/kW2c3ZI80NDAqHb58CoydTz9eVbgBsjkBzUD/ePESpDb7olfVGYMATNf1AYA0Ym1r7V3ajDCyYgqyCzri79hjFIJtm8GepLjvUWuwy3bUiKzTpOIdPGnd5xaS0TbqtxK+KXXLwfrWsi08UUHmZZ27qWEOQCSSyTaSvtHfp9RAM5/gh9S7OooWI0NLGt2C+ZOwzaQe0mnV0AIKeOY0UctqK5gCH0mxOdxlz7LJnT6AVHfUYJK7L+3HrqdfsBDOIfN3FdA0qhJAkXiefBAoRRYOnXRBDewrx5nl/J/ksgZ1jo6WrAmiutdm2cbEB11MwQQngR0d3lZSApxFnW5wexKs7VrA/G7ioAxvRxVO7gbEdL6GJOHjek/fKN7HigDhJk9P85pGuorQu27GzjhZlKxiJHRbiLT3HLwB5VRIG3iX2QURiPQXjshxK6XnEdrTgtvm1vPETD6oI+TA3oNy/0PE0MkRfykFhEr0fMyOX20KAWCdgJ8ppEsCEna8o6xOtvSl6EIM1otOZ+iiHtU/hKRH4DnAUqELBHMxJT2qE5NLbQ/WYdhha+TNLUYJcfdD/FzB9ZdJpILoZ2dKGR9fj+T/C8rO82bW4APhz3hxl16DPDSOVNcSSLTlls2f7abjRFtiIkYWn55M88aRee/O+TKL1HrIVGS2tdXFP1BlYEmDGjQdSAXgMG0qowxXtV1a9sDgYmbvfVgsS0ufxVoUSlIjd8Z6ljxQS1GBKNvZ9zZIGtE2adl3lwLlv6HxrRSir84QFPi9QQAgCmadMIc2mEq7JgvWXurtPPxAK1sKh1ChIRlmtdUM26OlWzVBjYuFPPAPW6rLTEtWQRqlN0tb7k5ErXFRnkxE128+pwp8V+vPWJmrLSawXCTensM32wLcOLGxG2JwL4ewYhVO8kE3ojq5JL6QD7d+oji1OdM7FaJpFtO6wetK+sby11+dwVa8yjyDs0+u+Ns7bD+nxtMpyihx64PkclYIWFZ0mUfycINptALO3bilAhtRpVkK0w6B+PY+XzeMb/RyVvzJ54JPWWbOCXjMdrqFRBSjBaabLPZxubwNB48G5c9rME/ZCPxlCNWjdd/Xx4r1jE2zjH74gEibm6xp4s6BCG1ClmraN5akEEiVp4Oy8LJrRQzq8vk60diw+5OaiFvZrVkFjzIUQ63xRu8J6uZvOjRv5HbhZ9w0iRmROowZPL6ag7Jff0hvenkj/tOeesXdj+kPwzUwDWQUI/9SRopYB5AXmboZDCcNxo7i8/N0XNWTDV6ybxEUFriPZ7NC5GpJHnvLSk1EytcOexuLR/TFRpDeaXaxYjZew49YzcxH3aMT+vdNhdYOBAz0OnaUGT6UXLfq9KKIJMYKVJgObOzBntwLHhjGe/8wO0QNPKCpOzXH71urt592XJnBvb7KHIE+uw0gXPKjKPBaVa6Ak0bYTCoGFbkh+xE9J81SkORy86zCv7EOp6pVCfQ/4d8nI+nX1spGTvAjjaF/LvdFtadBV6wp6RQd0NfWgoqI1uU8jZb7ROLt6iWgY9MQpqZF7xeEEHQTm1fL/Bl5tlTpqYXq9OigbKclwk3uk1BRuS1TQJK2vtb4Svn0XccxY/P7uKnmlH7r4UXscttCStXx9T/1S30x2kD3LBrJnppLXFI6+51xryNB2vQ7I3/Cmo/aQcjpilmaBvsYNhUudlyWC1BoU9r8Yh83nSAzFi0mjxQWygCTLRWXVfsV8q+I5FclaqpucDy/cNeICkRXs/RjO2ydOAr5/KBTt789xC+8bb7lHJLIAZYZ10oA5zwfuq3duNkYZDf1g7gPyLsdfLTYCU/GB/w+qMeIlZ2EThp5YNEUXFMBEVX0H/cWnAjxjjGc1Bxz9LnSGC3SzJrhLYXLJVerdbrZoXsHz65fy83HirdG4Yl5xoFKRH/vS7valP4xwkkxuev6EcNzFpGN4iI0RXkXNjCoqJ3UYZ61qtO6WGT7lWotVlp3P7F7fu9LPYGDMklIKnCZfbC2drh02UciVmRoaHmIQfxMcwUBtwSIfeWQuz5ZKMLK90d6s9tpRJKkhKw4AloeMy6Bm2zqJSGOS5TUCgMh9uVBqvyCdh3Vs/Sxsq+nz9kVOxphOKuiq22GWajO9CV/M7bEOd5cfcwspDCYQ1o5ClC2KmoouEyHz+pfCECJN1Lr2aHdWvYJ7QOATAu3Og64QYCV7ceSH9evIrN5VistP/G/3E0WxcJlgm6uiEeg1M/HfNYKVsxkzKirPCQak9++nWsux5hziGeJ+8WkWdN+hZMt63GDEh+TYdzlFQak729rtRUNbTnL2yU8vvhrn2J2jlH8V3820cLxzEn0N3FTzqME/0QDQzzXZUu/lH3Y3da8SnlqmfPAEJLjHoZWSs9Pe9SrAEyV5msS+rtL/rSDhVlL0ZX8n8NRowS6UCFX+iz99TvUXNLOPvwOmdP/a1pIykOmeN2XB0OI7aEGN81xRhgROvHmlef7YhkmFSZAZPy1FQj1pGXI16xaxmHzWmGHrIuRmWQZPN+IQBBGBErcOnGO9EF+x+eiGY92jU3qaVbaH2DOBW6h3KbpzgikRiQZmEpDgIfyGKGTpccnJmUCQA9w2TxjTjZqTx4BvjJdk8hijgA9ZeiNqgv28ZngikZi//mJGTifu18picNgjl1gyJqwp1A7HLhni/aRW87xSRzhAuQAO5Rf6o/Vqaw4zLfUTgca407N1gdK5WHBUTEQTdVXOJeKIZm7e52EdHqscrpQvjxsnbuTMks3TY56dDwRR7mFxPwxXwJlTzkHdP8CpIe1gzea8FWsAKo83jQ4ZwdHZojx1xQnukJAtLDFTnm0bGXrNYi1aqiQohh2QEB31S3oiE7WvExzmoK8Vd7rPylmgpQRmODIxrgmvu5lfjNHlR9TsSYbRcEYmc1s1DZSypNXUYvEB8ZW6wemUA1DrMx3Ph+s88Mhu570wFu1A+RucAgRzycj8OFCJjap9G4UlGq3thkXsCo5k7qZfAvjyoqjqEzRYAmcJS/8yyGp8z8tzM6WXsC1YDWeFhpswJSTawZPQfiEScRVAGvvGink7x29oOurxEp9lBNDK6bt4i4uK2PYGJO2glCxaJQJtreDZyD3K9TIozmcs5y8j3AbearaW4BvvqB5TsdPFjuQTef4SDadCSShBl1zRVCn18mW5Fjuw01sjLOtsx0B+W5KsCc4J3iUiH1WDR2dJhjaVRTydDthZo5BsQyWdNUSr+HSsQgYTnxEzYA6jZ33NwqyP8nNngmQsrfaOYPpVgdxsPqKWWWvYCeoJhCNumhZH0Hv45CWB2AGd69JCloljYbUWkRm81sfQcyBwBOu/cnaqTui7jfpAJujbV56Afjc1ai3ckuXM1banofB+eLJZfDD/i7elkS4c00qf3Scwoj2K4H+cSL/5eTEfOkLJB98Ew5osnlUMrfCuEDWmDY0k1YqxSvgcFeGRe1GAznWWJllEgCxksGIc5JGScADrr4z/Fz2opG2YG8HG+BVn1Vpixz48FZZyDO5erNlTck+YATUGvM9go8s6L4eyewa1Tj6lzfsp1ENTo2W9uawUeyKs9R9s2reb+pgVs6fmXZBdDAvKBn5b9tN1xb99B3KsMihlOd18AHb0uis6p8cmRjwMgzrJE3HIRKh4eqBxjkvHiQcHZ95X7yYoMq8alLbtF0kZ91JcS6GlgripHxxfuZFfWtX1drnu9i9+L7YrENDQs4XHQTBlyAVD3mUZBaFfu4ojIJiQMUUqi7BWq93je+zmctxgMFbXo+q/tibc3I7202c5VjZfYwjH11iidHkNQZjHqN+irw5gVicqyovBJos6P31Ki8Z8N3EQ53ec+BXFOG5uVm942aapcQXTJLZ9ZIh8sjj2JEAYUCuS1iPADcCdRko0GgjVAaddc6h3cgvVeqRKv9N2HvMSgD0egOpZIyhF3eXVK5tb2QcDmhxGqf2ILf/1d3VkP58laPPTWEl8VmLTbcwPqR7u3difr/gKZrkgawxK9uEr9u2oiJXcCQeDH3gPCT+V04BTBu5lOHlC3OamVtoUDYlbUKKTvJKp0MIli4Q0T3DV276vYrV0ofXhgoXVS3jr+j+rHSO6v2nlBd3h8cjUWHWz9m4NE/17x7xQbNs2nxwLPWnR1L4YFYlmrgOewSuoj8zE6FfP+jL38CK9oYKXO8HeJcRil0loBIELQ+ywO9G89TJCU7ANeGklc4lIQp1QVvP3d3OYx4+F5cfnDUghuF7BrRHRJlvjAJLY8/w6OHFBRMwWCb63XnOHz0UGn7yf5Vj+1aP7+XXRra9UGs/MbnG0jG+y3vUN4RInlfQ9jdGAFxnqaDod83++17hxG5/Ge0Do4LcV2L/Q/kEiX7PLMF8ZWee0l3lw9F98j5Q1grGyHBoNtOu3+8MGC1tosWO5coM4pB+kiIKkHXyGx9TijJEfxNvGquUKv8MmXvoBBDewb9gLGVCbne4VDVib6rxAEqPLfWmLG4ef1ZRwjgRJuyTFTh6lMyly+LTA9gN3DGUHvXMF6efGv/9Hw8rCk0Ik4sJ0ptFimMeowc6cuObkteu8omES+jbC3Hl6MbUChv5ybq7dfNj85oi7sizZP54P0Dihucb0pTdn8AKkTBadLyMzLOmdXVFgIktjr7a0k0ejbXR5SGER1RQAqyseg+cFdNODspqBT+yOFfGFsJvL6SptpuK/+/zAy9/atzSBWW/v5Qi9eFPdyHCyj8oVkLpyrGgq9z+RPoMPhWbVz22Wv7sr2nLhYeObzil66M18GWxYxo+RC117skuf1XR4fZRZTfXuE+KjNCDvZbbzEwJWRvMg6Dhn04cJh41k1Dh4EMbmmQEYg57iT/9uZWtm+nLEDhD+B0x6fxMylSpKcqKeDo+Da0jVIxdIvGtcR2euN76Zwj9DqYjeC86t5suKHA+XYt6JpQolmvHXrm0Wvw4fpiDdBBtbtVCKFGs5vlG5P7K8pG6D04eKAimHWwtIiGhKjw+Z7s4qKf6WblRT/Eb9oISq1NC8Jgx015DWAGxnCuRGa62AAC91tYISkm07RdCsFa7aeYtITGt/CvqGUKj+kc8Ey+ASLQqt3dlmLTF0dXPGEe1wmzw7TkLkHM5uDcZLJFSEcO8FT/d+r3rRIXhoB73ULKOg7Z84132VuPcNRU0C0F1Gbk+oFgTOugaje8gWGU7+zJpr/ziNRuCv+khzCshN8U53lRwPWfZ8epSQ7XlPYQBTx4ng3NLnewNKS6xmfo8zeb0ydJ055rCqqjq9Xxz5eqWyC23lyc+K1+PAbQ5frZTtNoAS5wcmst+Rm6DvDgmDshI+1RZBPTID3/VF1Ri/tcteO3zsvZNsDI+ZHJ58adR43gszG2Piry/ySD8KY+83XHnRR/W/5UX3/trTd58rCtRr8LMQ6ZvrJsuzrTv0mOxveStaS10mxXDIdqHdX489YDSYW33D0QbtmPxxL0fmRKVn6yKMWaa8uLbel6pRcaDaHdmPV3qYaZrPKMlHa45fLQB3NDpNqu8dEHVRCBHpIIeQ/6jIAkWQAoTelBLLbFzqHohHgRWviow0awmzltt+QLV1/4mPxNuTym6CTQiEM1D9kx9ihAvBkwjKsLMdsPe2xy9hELe5796xXBVMAresxv1ChiGCIBYvvclVucU+eXh4VjZYatdOBoiyxDrhlKzZE70YbMt+oCzoOtMG+7h2EEdl03Y7ldXW+PxkkULj7kaWa80xUWO/LZ1dOyeSM1MhWnKegl2z7XFxoxJSqp+TjZnOzcgUOLJVPVyFcik6Mx3hof+6T1V/FXJl6l5e+rF9mYCl2XcZszVuTu1mvzVDOf9K72eksn0CDFRzy+Nhk/6U4t6Lj76WSmUXHmgtWITvEASMTOA2tYQg8Q1whi+YFFhfunDcCDRrWxzXUumntEr5PwNIVZU6g3uh29PfJg/hD0M0wAsyItESDN8eB8Lx8v0mXOj/BvNi7uv7fN5ehx5tQt80sExOQvd5FT0VLJrSsBCwbFxq06eZ8yNmJuP+C8Ut5HNsnvNa9yiUsMvcuJocNFfhMZ99VKdX9mfREmrG4BbBVPcj/QHHeW/nj1c5uNNf84gxIxoTFt9PVfM+kI1xeSjPrB4D1N9rp3qasP1t7q52GzeSZca1ePfidDw524p5jpm8qis4vhLJG0XAR3/Lfm8zQy/XFi1EOs+NAU+kbANV2u1OOIn+vo37pgAEUtXGY64IVgSU4WUbNDJGQWkLU7z32EcgsYPpQeMGcTPE4h6ua3suRCG31l3zheCA0CFAZSjstdAgVjhqwjlFgaJflP3cjyRjlqPMbWkfm35PH7+UrEgE/FQB1c6E8q0M9ERY2h2eVklS//T1Eojx/nWvu8iZBGRi6wfiBkyKf9n10efEf+N4NOBufGF1Xii9PbbCMm7BKhyrmR+jq88soLrD7ZtF6u6rHFEvAQqF9zNZOXeNCoppepQdEBF0a70c6xT11YJ5FPjhA5UZ5gG1y5P1whS6OcDUfoP2+kYBa9s45e+VtyVwzpECBfm/7DoOfgGzK1JxHw0F+UU6ueXp8ZNnGW9yeIxUb2qJzrbElC3M/nrEcgS4G3EERNK7/37jTsifHjPbTFHL02B5sCudqDrw7pE1cALbQMgkDOxEfRGl/e4drB5p5t4d81Y43sLSgTDvlFqRM3ujG7GO+8psQYWwAhhIrl4yZWX59SeYe1n4Wvkn4aI1n9oZJWbv7BvhUYW1CablZzbWL9TDSUHvCY72B/RAtennjlqvZ+i8G0e7N0Tn9hTHC8uz0E2OYwiToXF0CC9tGUac7358JLndKc3S9nBRbsOe6l435NYMT1X7DshseH7X5x3cd+hUm4UrbImkqER1TaT6L4OmI1G9pWJ3tzuOzr2tNzczEFvH5VVaBHZQBehgpeBo1r38EXoQivFuBVfybTT5+jyAda/hvIZCgOtOoMmAsgcyeF0Ew1PtQ75wnfAKMD6FwAl84jlUf/xEnBjZssdRvm+gNV82sbI2+N0zjpcnxDDKh0zB+FAXbFXm185pOXDVTOuObASp3DS86B2M8sNNlMhcwKM2yJ+IUaGouRGIsavKhuBOmb4io8ZFqIINXfvNFZ7/FRCdBZp0/iJdsabi+zb74nCCuUO3vrFGL6NgJGLAOLT7lJ37A2xlRgVAjwnqPZscLMh3J6X/kRWOxkF4RuCK6c9y9jiCrqwaBWjQXskfCcM1MzPrtxh/08sLT5LW0545w1pD64lJqC2TSM6HcOK/XhY95wXbOPc4/O1c8+0ITqw0mllvy9MPoLdiwEsDXkrCw36SfgbPv1eVMXoUoLmGk8eRJL4tpWzQOeFRkbVP/ubiX/z5DeFQ79P/NuUqrvH9ldFX25syN6/3WZ+l9L4NCrA+BOlAc5n79MSZSITBwbD8FGFDwwndv1ZuM57YOLGuhJRamqLg/G67I3c8F7i029uXnsi875tdwE1sPYWktcdGs6O2rtI4YxLwvriDMKbKdpP4zx4tfbSjuLuKJzLlqTSw77ZqoxwRTgILgJyUOtnWdya1nOWrCPAH16b69oq+OOLZptbgpfN/iVjTwcGK9aNy19ZTq3Jd0m1MsQU7hmduLE9j5tpPLKT1q0/jqc1k/9Ew5p/UQYUGvqSW+gkQ33xZXrLLkec/n3kdxNrAtNPDmEL83zobUFrBD+dXNAv8lEDvzxFVzkEDZYDJdMHj8NyCaLOkgI2jb/CTfP8CeXqY3BG7aePFmbS6wd+fzroXB8Rxicr6bn//2W4zUP/3wSE0SD0hDrMKM072HUCRGdKyNwmPbhg1Fk73Z2NSkzFD1W4H6gl0I2PTxgRso5D2J+ugs/ldPQPN50IbQVcuVbBKfR+RrCBMXXMUH7DmyPgovo01yKChddaPQRXfL1UodJD/oeWywLuqtUVP64+CvV5y91SKrOPnbuSMKXNctn+w/Zo0hxGgdZ8NUxU2EsacrHK5XVRZJu6I/5riI/RvmZoPID8NwUoIcg+pFOcWr0FY8NbIk/zqYf2uUjEuY2/HZNJHayGPU/8TZR/by3u3ETlVwE45xChCoqIzOHYq6rI63ryNL6CZHZt+sTwK93moAuQkCBMFGYpbBa8g6hDxy0nVTir04WEX1SXOJIw/zZcLLUxMsqSsoUdA3hc19CIrtj8d4OCMsZZlE+/MeE3YNdcbmqfrpNDHb0xJ8aUFaYbVVI0pfGV1dUUUUmoG5HDZJhjS/IlCUYJF3qEyQ6AiWuBFFDO/BZiyDOQ3teh86SQRXq3jOx/uW7WGe4RK91n2Jxnhx7Jf1soG00H1gIKj3OPjBrIQtV89Gs5G1vfABSq8coa0JWO6rW8StB3b/wkmAxtwqkGNRvZKgqR0v8qTWqXf9undLpko3VrSMx0SQ4nAFKs2uR8qMsSyZpLXDSNu+b+AApsx0W622oEBusBjUWiEvLESg+7rijWbQS3aBA9WWw3clEwalELUd4+5gPfi9k55FLHDOdLTlM9QjqN46wrdF+VxcBwv8DHlQ1tZWu2MYPFsZPVG8k7UWsl3/FNOBigjw9XVc2EMWj/Fl2IoHb5sFjpXD46EoYWqhLyky41c3z01TeNbxXUEmvDaX88+q4tGCEhWr7AlNTBey0v6HCCwLDVPMNi+uKiOFodxOlT1gOfxKJ9EiFWgyuKqevECdrD46rHY1CNejImo+aYv48XVGKo0CaKUedOCgajElzN2+1SRgN7cUp8l5KxwYtQZXWkjXUnG9VVJ8hsHfsp7r3CQ21Y/SHb1RmjwDgfSpLCNE9EGtLTzHJ1e0jg99Xy+FH/aN3VmFaiVn7AYLZemt5wC3i8xIIWHM+UYlDNvhNK552xBPPVm5tVa1A6lh8XALJx4LlRF87HsySBmt/m6Sk6IISNQ229masHbjJ47m8KLvWArvCMq5wVXeKvoOl9SDc0pL98MBJpUK57YNH2sJN2R5fmoxo/a6atcem/vgP0pP/O2PuD8j4S8sC5UAhH1aGP48IuuLiZjE7mdLROO1LCnpKi79fOCGmYTETTIZheAGEL7S8aQfqS6hQVMXhlt0HnBUWVRhckNhxeMnqsmFLTZd1BypWOHcIASWCIGTysN918Qy8eIs9bwbuJrZLVXG9LQFUbpiTi2Pt4j/rlo7B62nWwxSAtqCDB1ij8wqNPOt5ICdi6LUB3AzBc/m8U2Z5h5cbdHN+cTnP/3Lz6b0FlRZvwEmsXMIXlcdGD9WRvhW2QTWqRF94IxEh3ia9uYCJI+0+oPLrQ1DPKW/g6foI1dnZinKG3y56bAsBXS0MDs1n/DOzqGhc6fxfwBd0/CVS4XNwDiPBhdx9rHVfb8KmDQ1lXrefSNxC9JaZs5GzPVToH/jZTOu7eHdubIcXioecuaCKitc2wHdNRvmaAjUYCmC9Tdt6vaIoiPtpANXr4JdQMLqMOJXXyOp+RKs05G06eRsInzD7VLD9uGJkBZe33HEjcwL0ygR0z6xcjJoxEL1coslbLjB+6bjBoDWqQmMguXNAdEg1IDHF7DAAMhPifY76Y3sxlV5yi3k6MOz0NvRRza06qMC/QTawWeEGZop/SP50jMfIQWu6WrzFkAqeYqhGSPxDsHuSqgUm7XvRG1WbXdUhJYDFjy064u/NAtwuAvS2ZjFqPwTFuTW56QjgTMfZzklzPSmUeZBL2vn9aJqyQh1ND2NFqfxgQZa5KjnFIZimuf+z3U/mZfcCo4tSgd3p71GPqnxTk/CQNJy1JHfuMPl3xgegWu2yuSLqKxINoV7ZNvmVwbHvE5kP79crMR8vPW5uviD9ec4HC91YkPJKoOUV4UMfkfxzxXUtrjNdnOED1TFNKX5hSEDvlTl+s/fqOdkWNn1r0uAanst+YOBLNR/dFlzlCqwiD0RNh+Apq1c5A7zkCkYpP2NqXlvxmJObYh96cshDtgvbm4THQEgclzD2NIMU8SKgHtzsqEtWQeOD/qdHUW5TSVDJWYKqZA4GcHB+qAuM+iEw+i96KBqL7AZrYTznM1sWrW8UcttvH0nWvjzwBb72vobuMbNjk+osUKaD9tcZemOxoWgXSvanlAh2RAuq9PK218Y7GnnHBcGvWy8yC617ig9w+Kj3vs56XBgKGxuG4EWFl0hrlsS9kFSPunA+CspOBJzAsFxhnMBUsYVMj053XN+WV9nQVSYF9w+4E1JBXHRE8MdUGD/mBSWTbAxrLUjqT34PdVJLRwuwNhTEBvwS3ym8FtDgbvGm7bvbYf7w1RseDPt/MQV9LxB+33SNAI6m/91tlM2jMOC1CKMy/b/LLZXvOtT+pDNxkpck7dwze/O6lh7hmuDXs+w/NS7DmkaGo7ZpFWnBRiv8erWgZBSvzmCuA0zPMuQj5gtAxMtGImgFGnlYoqkldvQosd5Qypi+yU588PxyY1bxlZfU67ryGaI/8z+9fWqHT0/1wvJTEa8c/2I+gDSvg5aA+8Va4oqkWroTNqhgairWzhzWwhe/yOFRZ9F29hPXT6z+C5lJRLyM9H/uYmL4yC+El1GJj0w1G5sBjTn+T3Jfcv0JqNdeNyDYCw6ge8I9POjAlx+CaymuLgADmNf25i/OOi5OxLEVXR8UYuNLl4wVMtZx9rcmpg1/KLALlZ2KD9KBb5yFOrXZ8FFerQNY6I2HYjlKmSvGokZ/vtFErdmX9LqacJKlBThglshpgHYW1tPFV8AIlM2V5SfY01cBBI+aQqjVPuWbg3Sgsanvwl+habFXmR+BQXI3Hxpm/YR0Z1q846cHb4MBWNRt76t76u9/mkpafABMo4oXBgIWGsP1wPe3G8/kC9LfkTrNBHsO3J1Po9XoTSsO4bKNXVqwO6g/+mDhVZ64F0jonY7rPo0aaSXWkUJFklaV9fGdrTu+hzv+IS8YRCwhKw8O4iLM59F0rFf+w/h2yC00Yz7cO0Mt2SQegq5XDIzLngSSP9/W4/7+6Vgf4WTivw+aBC+4hLynVDhJnYEWLvR8JbaaGRzd2l235wRldjsHc8ji7jUEklSRiA63HXjl9u68MrhOoM6bovyhTxN1UtH0ejudWjEsR6N+hNNQoPsV5NmFe137zdVAWoB+9RTxuP0//7tHuKjvbChN5ynKWPjhG5fA/cVPFStbOTechQkjo3IX/OHTiWfOgo4kBv8izcnt7+WwFLtoTJbi0kMBRgy0ljmkGGi51Zh2jJwiWod0ypXIElCreu2vYFmauaRpKAoyMexZgPMikYlCkWhZK6V2R2mQaHoinA+AeQJa1NNWvqyIRBY5e+EPcP3+YvOokfNBPnI0KJnH4Fl0XurxKDYdR/r+Qxo8gVvyXKl+z9ApdtamRPLIKmwZsRMrPP1cPcBUNJAz9v0u3CJENaYB52d9j3dZgDqanFoBbzuH8SzBUYtQN1fqe2Tpoj2uWngiCFr5OMxvYbw7f8RVPKj886lWQc3qJXsgbcNW/9faIlFkBgKVQDs7xtTvYFUkIMGRuHyo4X9Q/VJ8z75eC7twtpurGH8xRITulkDgaeCk4iNz+kkr606rfGiudiZhDm/hrIud58/nwUTjwTnr2xT9wXvDJducCmONhgDPCErxYBb7jeQ2HWIOXPtd/QdbyyQ6uVc3U1EFLvIQpMeBm9y3ND+ngzO2YtTEjRr8gWART/0ZuWPLvV4ACJiYy1QN8TMTXKHgCJlpMrKVzg8v1Zovjt+wGgNmWUZXibROhSJi0HSE8ypBUo0LysGIeWpJVYeU+4L2K2IhYulYGKBqdbBiIa9ggw2eoB9AUOKw2aVrVJrOGI4xfbq5+6HmwnX7WjdLaGZFE82OdLWcg8CnlaxsR8EBAXiyxLp3WC42g6Ub3QslgswNBVVn6FO492YRO4YoSzjk4RlnkU7Gr8IsQNWIcn8BZ4l0xHtz2FwmxHIap5Ylbs0mpnl/dw6+rm5Vvi92RCn3vGSIRbqqY6c+fsHuXv5WQ2jsczZhT3SDibEc6QJEUiszRdEoXU7HMtt/ZptQ/NpUDmkFkbln4A2MCd7VlI9SL/XmOU7eyr4audYntuHg9XeX1OsSz/sNRTTkyqzL5RpLYsKWtaco/A2JOg7AHWaLNgLEE8gHWZpFOW5FtCRf1yjyRa9RjBTA4XqKzQr2Wr8pCS+VEfHbwEm4BRbeBrWnX/mZwK/Da8+oJd07ZWElnIjvoycMQ8ck4r1NW28o9T5efzXBO25YkGuIlcmnLIvp+Vm23Lgh3gnXZI+Wb1Gx12mWs2elOqZsx1pZA5TfQrPI2TUeZMoO9j5bduR4jjSeupTVDxhxMPrYLTqebKHV4ZEDD97VYQg8JroKb1OiYY7qZGOBOW7bT4rGX8/9ylas1Uy9+dktdMCeFSl9f0juC/LMP/L1XIiy/f02pm1OUvxhyb/vk1bv8PHLkZ/hEQancbERG/GbfMhM8wzJASxpIA8ghiKXG83PFtcl2tXUaI9n18SEPNYgHKHg1bqtgYLbmXL3RDXbxyK/kvSUyrUljFtm8vqa+1IL1eoghdS3LhLemdME0SI4UQrWZZGot4nb84ck5ZJ6KBHHPOhEJn71f6JUkNxo/KIaHPxG+AMfyKAhZNwA91ku0u+Py+2ESvMO5jKRsVAKj0gcX9ncREDp//3ZglYGccWIICYEBGjDvobDS7YSsUShj5P1PXCYNaW+4QgbL/IKqVbClmXrzoL+FRv7J0rvKObSgbaFYu8lol50090fxT9rKnZj16/W1csEw6IZ3AMpoyPfQHOZeA719tJhXVkhJtftuRkDi6GTbdW6TZuYEHrzVKU/8AUPNaCrxVfBhCIjtbSnnoPHxqLl7K11HILze8qP3AAUl0cQ0xPSFMWX6vKGB0mr0Ektg1dHBTXaT52rnlFBj6sm2PrPUNSBap1mRqEMpE1m+bdxKYYdTNT9umll0kzNfQyjhh+Vc7hpVTMxVvCRMWOuJIkL8IdIQ/i56DK/DBNXID0r0sT37oxS0VHw6VJiyxmJsjPk4/lREiOOgk0z7tB02UUMg70LLDBBrqVI940gBDYMqhW2Ad7Xp5dh1bVSElwv4UBrSrkC5H+6COohiDvILoQacQiJLfxkJ2+ODzSxynl6/ACgijdwxYqOyP8EP8xNbZ5stogF1TkJErkDQ4UqMTq4DvznL2l+c80FN30SQFI82KftGZmzhdOo1WU5A/xOCVLeatpc3lAMqXR1Hldv1tbbq3etSSZDGuqw2XfkJp83DYI7YSmwzm+ZdqRoqBHX23faqZWax2leMXDcfwvJgxQPMMF/Ke+9JDWe5FZFG9e45eM/6PL751zhmPHv9oJXEx7JrT2SLl+3yi6PFBuiwN3H2YBAHeBhz1DDIhrh+NuufoeQoM7cRtYoHjOm2C8iqmgeliRtmLRdZlbBXAHc0ni2ea2ANYMj+Lzgr5ZIMo+1UoGTMMkqXYxk+3v6QbOw5cerJIvX6pgO+zit2xGxeftd/nL9qpDoUcNMqRkiAdkSe1xMnzoAhhy2rfRvLNhg8+jszxWGiauEBQ8K1s5o/23zrJHUpr6MRUIEvUzBMg5gcJ5r5/6smvVmzWrAEgAl2m6//OGDwfKCSZoTQSFpq+cvUQ7OTE6EYmllpBHp38hdOzTq7mR7fobWUntWnwM5eTDQNdBycZ3plZg5VCnqGRrtfPRhwx4hrscFCAD0NoNfWum3vyvY39oUR6ZrUnlPiDSlja0giI+ETQLx/bHUGOV3J7YvL+UBuA51MjpBwaYz8I7DVVWVWil/kKNhk3Chcuq0Ud9t8BZe7BBC5X3LoQoLCbxGjkTZpKy7i1jleZiovgSe9xOx/9ERBWN8EoJzZ0qE3DjlwdJfha170Q7R0AkImB/XU0fvP8VkCINFYkdFhU+dDh1eqpshOfqAqblGGYC3XVBt7rh3En/6CpqsYdxNDsP5+sxIpcNCDMNgAMNwYgueIpoXYKFNO3e6sVSdxiK1GKuBJyBWci4prAI4hVTpCQoTtBl092nuBOAR6+9iJr3DnATBV+T2+4wM+DxZM7/a39OOAQMdXfZdwh3G1clzCSFiw3vVM4PTe7uGKqKcXUBrPUlO5Ts8HS3f2Vgw1yKo4PcUicP/xd6T3Y/NQNVYzSA3H6GmxN6OG3HRGh8lQj519wEh0EFo3ledaZZGn251KKjNnuzjYPm2TtP1PdNqBnFPF0PSJ+OnxeKbkfe0xq+lIhK/V7eAgxLRcj1t+SX5IO/R1qU9PmNeqIsCYXkHNDpJ9p7ItCasxIJrY8YXC3TOMxXZObSAKsAO3I0AbFljxxMhfySOSkPD4usl65Y3BHDKb49p1Bc1QplrEhDOaouEwPHyHOgQCjr0ckqrvmOyGvIepIZhCS5Lghrwe3Af1+q9QNW+HPJgkcDz2kagizUJB6D33X+GxIHvFayrUulxAmtNQz2m6aOCIjynbw15HMFXkqZ5G8Y4nMHIR/ngytQ3vpPcE88P5zA2U5gBuTPjTB04xmUf2CE7YxblPb1gKs3+bS6uKxFiwINDO+TEXftCx35VAx8ud9SuQu05FOEUXYRMBdfRkIdKDmNL9lxmYInX1J9XXnb5RCxT6uMsgvZK+MCuWuL59lVi6tYeemPjcLzjjAUSOxgZOYtP/PTRQxfO1y4Ivt3QdRNgXLpmIYatk/G04wNV6RvqQbk2xF5sL4wg0kOzPm5SaLG9UqeNDPkr0e7o3Agfex5Uqb+93nuoy6DZUAUm9ZJeN7vVaMXinXjO1uYIrTkT7cxgn0hYjaODVyPMbmK29AZ+WwKzz54QQo/AFe+wIw27lqSNJJsP1X+yWFFLJ6w9R0fYs3KFK0n4b2ttGzUhEyXrq85XpXptYbbq63LbgN/5og8Re4oCa4xIy+nv9gVYyuoEMhCiVmFAGlN8UW7dIrfElMo+t3FyXVbfUBRyOQN3WH3hy3V9LL48GS3t6B/5Pdm/tmSMbcfCDLoNZc20HHHltXfVBbsTgJX81NSmPPvd91y+TRh63TG2xoC9uKBtnpRIkYZuRLzvySnbd8syx2chhcBVgI1Vov+l/ePY2vUSVDEhVjB3pWIAUiiadfYDeZGeByUxtnnx5qgjwaqOj1sAMb5KO8kil270zSCHADq+cVctFZKI0IDkxBb6FGgHgD/4zx7yxwd4MVFklHFnkNRkm9H39XjJ3ZjglhZln646XeL0PVsD7JqZ4rgCfS/bHAfW9zrjQuCuJKsG5o0shPWI2reeMSsa3o5reQ1yYXA5HTfmgUpFYbvDxhWnJh+d1WHepUojMaxx0baLJelrAIMvpC0R2/RnZ2Uk952m6pfxx4s60uWbrQvdr+R+2iDArRbkTXQlhK2VJuNn1rCpnxcFZ4rHOMcCdF5SYJUa+iiBpslTgD5gFdCfjQaMi2r3aD8/oM5qOlvpVU8e58DBzQfWtHKZjjq3TAHuamr1X3EGf+d7C3PMMwh1sHGBGGbwqIeSCkSRNyyv6BCvpdAv3tLpPvDbkCKKaj9ryXYwPV7i57YFMEfVUqzjyplXGdz9w2CF1ixlpSrGA3XJf7hwflcVe98u6GDZfxteJM+tSUeWX3x9uwZL4eqS+ZEJpOgUVdMtqFJgIOPxuDHN05d3yQQ3UZrUWAdNSP5pPW/6YEnWw7ds/Uy9+MsrKKVGIkFiRQdnOxfUX7r99iHN/usrQfDZi6EJhljUM2SKEvHqZV+BNggmcGNUAhYK/4BBMHC+Ow298/rzOb+vm05WHnke/gDYCM0LRaYGZ4sL99AD6JsPey7AUQc8vfHTVdCjw+j7uIJMi6jNRnJJkZ2b90cYPvfSX9oMBVCnmkM9CrWOjSJLzLtYj1x2rP6DWNvDslpLcmc1LlTpyO8fe8ba5sgnEVopxr6craC9J9GNtc7gGSwHXdc6ozSvF1wNp6KRpTPeAj8YKd6k2d9UJl3YeMfdubFIoLj64LK0TvUntuG0rK0KjlCVe3V7i6jEH0PLPQVMSfY/e7QAVuFX7UiZgPC4s8v+LugqyHwV3wln4VRMteguNrhAOdHr0Nnm8/UHydiKkOxm1iqw9sgsePlKAdTg5n13zwd8hDYsOLp+0Ia/gktRoEgACR+W6EiatQBwsOf7fQHXB9peT6YMHV2aIff2LclaI1Z2/83creNPx/nzWL0awizo75+AZC47yOngx9uFvF51MMBopKV5CbzyQYHH0C9zvNEYnVSTb01NNJFYlxuFNniZXmv65CqogpnBpHhsVCWILHvPa8fqd/bhNEf+ll5Q6CcjO7ajGKa5tCRXq5ejMqotlGApWLBSwEfGVLsmsXRXtoV0SjnZAbycPiTwo4HpnjePrtFe2otNQ3oLdV1rLm7vI0dR6rvoZLbwqLwNUONBAnEdp6c9WJI0FRox+FW27dzBYjwaB3AZ0cWY1hxqIqB73NXDJKaZZ3tyX4581eHiWcXsRQOkbxR9WYQd1ht6PG8BtXVcbWx7Zw+Iu9uL5IpS1EtlItt3cSWPIkaU5BeTqK+d+C4ti2Lls4RJU8m1qUiD1Yxz5hAnYmXrFo3asWhBHbqUsB6iu2fs5/dUWeiZTyFK2Hc9aDqC47ZEQ+YVGvdznn+kfDGbpoL5cG8mVELGj3bu2EbY+HE5NYY0p/5z7Wt3U+S7CLXT1PHIc6vToyLCU/3NjHYSnHMLMsDFjTotXv0daoSUxCNLmB9sRkvhiCdZ5pmvQ0E5keUAA9cOajQ9vs1ODXJ/W1Xf3sMPPwJHAQPZ4qzDMr60hSZG9IdfzVi6bbsKpxMKGIZ3PI8gtBLmcyIWznjVKit3aZl/cHUXIvNMPtFqJHnqZyyer+Tm/3d2qRYW3kcrxrDz7V9UMG3G1UCMhRt9ibDLruD5aqPwWvucmGVTwSplYspgYvNSGyspA9RcaD/FoMBxVksZND8/eKA7Z0DQCi3NDaY1RPf/PRQwiD0dvFLUgWIB2AdrlLOK6uYDjw1xRti8ppEhWSlJrfTxs/cO4u5lpjxyfwkXWSm9KFp/mvy46ycM16q0215nVi6H1wyBpT8ck9R/nrRIYKrvT+ZwOMYmIkzgmuwmnobnDU3ip89qqD0KEfxS9QaSHWBH8K32qrsEm2OZQi/wWHTCwAP8sGwq4B8+OCHO9gHJs1G374rSnzoi+PV0yhSIHY0HGSxWI8OpSFujQPAVw9a7ClNcppiAwHnWocX8MOLrw1HHUYl1zlTsHUtGvbXEfa7cnsqdBFEndFsD5udbSMSGumnyeWR+DrpiqlG9ak8U5l3LErYUP18h9AEQZB3prZx/Y/9t0epLBS3PS3zUvd0DyBpQdFSPW5gIkHh+XtRXXRimRFI8ew7xN4e/MUidol55YHFKTgkMp5KugkjB4g+Vjy62oHSj2/6BHHhF/B66KAElDeDp114cOYjw09pdyvp85It7msRSJzk4S5hsoXIBo6NNi+G+bJ0gsK2RhtZXi6hM1MbN3UokusUG2qR898CLe29M4PZWi0lZzaOln26m5Y1gf0g7FMEj2pX3eYrQWhd95KhzcpI844oGVlIYRBGTBJlXkFFc4B1BMdlmK37B1WRGPWymj6M2stTFnVF/aWtDadyyNZAEsWb088N38EmiXKmsRtACP318wLin5+aZHEZll14MpI2XTnzIVT8eWBMPBcU+n8Sx1m6hRtGL3MzLBHZAUcRghBSBlCjvFlvHVh2uG7/AiQ4eAZZgMH18eoIjpUJH8bJA2ijjVEF5aUv8BtdMeVlm18USwi41ugfVd4OaXTorO0mlF4YPubUz6kGxCbmk/YvAkMbl/V5LupEJlw8rg5WZaxomwaD+q9LSgv8mXZIYkPib8A0gSq5dEzU3Xe3dEDK1l1df28PoZHPCs1vnuH0cWmhWOAPFcIZMS7v01jpyWgcf5XQAICCx7IuQnuOqySbjPEOD6rOPIFBu2b3IsUpN820ZaNU8nJXv89OKUhmQI/O6L3MnTC3w3Y3hkAjzbg8fI69dRlRHlatNiTnzEzFpHpV0q/0Y3fr4Ktn3u6IV9DSHWtFleP1ZgJ9Eym7N1Z7gpESrZSU5GBYznxw84HvlHznzWNjvXFDm8FeVlNDX3wCbVnWPzlhM1CyWMTFaaThrKM9hq2n1soCcQtzxLWShAV5Q2eX0aOlRzTGTEM/EfMKwFabNW1sLc9I9XnGpDHDRmkvw0OTfags5iYXZTId1+Fguyv4neBysyV6Nd30zkn/TfB12W/+1qS0xz4Fc9qcuWqJGCouY4MWMmx0gRuu1S1rCcoG6G+1u9+RPEfdPCotuMi4aM/93i+tFEiFID2TjX7KkjCKIkj4d+75tINf3EDawMPGVWyqJu3gPx790La+OWEoIDhnKTnlCDQ04dIt0aiv9+Hifl8oVRPOLmmBY9lqDQHJdfhn11bYefiqzXD3Ryb6BpBVr9hTW4/C/edZM15ZGHrwGCsxBa8z99OaGrScN9sXqK/yjlHMAyrMTUfaQCQMtwOYtbRQ+FxOJxNHmc7kEt3pRmBrfUn3kzvdgL8BKRlDaQJn1h08zOO3mltwW6n+QyNO6jWQ6rEWzFlF9DsDLHnCnIS4R25mVONuy2txssu8p2NJoigYhcEZ+bfWAjnonSeOi4GS0BMuThKaL3sbW/ns23bzWkd26nsBr7UzSQM45EaK4SRWNkGjZT2N0Ti2liP8J8SkaGlJj5spz+qkomqRTDvibiJfIHW9tFquupBsDNefRAQCuv1X8r/KyUXOE5gH95oD2VDEmnmH0lx5nDUEXWR1ZuIpb24+jzT4sv5DXM3plAPUVbRW4HsU/4n2TCgH6NZWKAZLB4iV3CnFOKiPxxnI/UKCuyp6xcQkwSJc50okuDakTNq9F+w8LgaTMdQCylGFsVKM3gv/QPaL47a4w7VlHAEqt8Vg/4Re3zFx9niDaOwdG9RQ9QT/NS4BthMCvankrLnmStryYZmD/9GyBPd4dQVp1A09ZN8cZjxR2+xUkPSlO4MaguxorRQq0s6qcpnJrRBklc8sdiPiJRNjBF+DbYds3eUeqoQtGp9owMTINnI2nfLGcWIrL+aiE+TQl5pMicBFWeFm8BbOXB0A+aEMT92K0y8KGkQ9KE7k5pgXtyMey1tnLftIFBD+kG9m0IOAmPjQWXsAZAvh6X5itrv7V6Xwtd28EAq5MPNIjeAg9CA5mGZQYelkLb6OVMt1chof+bpbKegMoxKHZ1osAUYQcGTBK8oPtC6S3GLv/jIqWfljKSdvWC1e7Fsh1SHy0iz+ldPCuvEmkAvNp3g1kqAjaOWjLMvjKWtk02QhyvhjSM57fpXgPGBgIORe1HN9LiRFRNkNXpSFGmDjrnsgglMNT5mw8NcAQ5637kAmvfnLOC3166W/QR+0DZ8AtIl+xVZlB7zBT3WGHJWIMgFKOcURvCqNd9jw6EDrhtQJGYxKeXedwYCwDXLXkNqp8d8Qw+WUYfyRg2rJmivlKvrjURUVR6qPL0i3u8h3NPyDZM/ImWdLDRmjy/xiDs+wPRMqhKYm96u1U58nQQdXXNMRBMl1xcvvxuaL4P0IYGLWYuUhrk8yCedjgHbv5vLwdZAxf4SYcHEXcZAIFyLdPCKhrqmfSmEvZ1ZCZ90TSzuggI2MSjT7B9orhT8cLOIhBez4o0Czx6RMwHdX3FjFiuL+giDHgpIQF3CEwXlxafADVqhiOiV81y0Loi028/V+1IskR4Xt/Bxe2NwxsX5dvnKq//5rL5ScpChC6QN8Qxn9zi/oBXD8hLowd7R1tbZ5Q22Pyvt3AIbmzTT9uexbo6q8oBywx678s7mcDo7J5TV9n8YyIktngc07Bgc/8MaFboJgoITJk8Bb5/fkKATUtohyJLVAg9mAKN/FXdrcfCmzYawpGdgvMBW7DRnqSIlGDnFT/GLenlmlk09GyeLAYB8F9aGUq1+GuTdllnowkCMQVU+TTjGDUA71RqZruTxGwqdZ6RPMXQKFJD1CLrChOPAb79eB2IWfUFJI2yLVjf5npHSgwJv9a/lbrIkOawAwdmfkpzKfzv+TqcpJzczpCJycJVmTk53EVm6nuFeyegFvGMpNoRSMow/1ggMlzgZ/yoI6SXe4eYShJM3BYmO6D3DOUgAfqdMJHqm/bxXY9zzb3MDtKVVNlNsxKeaY4fCiw6AzAhr/juS+UcTBoD/sq4+iOwKGzn6GjjW3cPagEltm/eQ1AFJ9hzH/yBcH8waJlZJOu777aNLnKButCWXt04x5P2dxFpWMp8B7TTxSd4dwLrk56U0O5mGkBDJMw8fn61JGAGZHa+qC8ztwHmoCe0NWLnXpLU17MK2Ddq9XoFFv3q3W5q3OP/uKIlYT3ZUjulXBcOj1J4F+1alo25j2NN72g/1g2EeuBBFN3rJ7boyfKQFidzPKn1XDkxDQW6BP5m2bbMI5LTVH8tj8TkPe+ptgDpzMAyII0wgy3UO4Na6/7bon8flNLow1K73lekW9UM00x8Joe5K8yqWW/MlNVGQiYSxbPE9aHk43XNwDTxw8sI4Oby3R4Qo/fuArXEmBOIYqlpG31B2+OiAlB5aJo8UI1D/x+DnEhsBYgeMYQVm/q27sdB53XCxnJ+QfwYySkcqkWecPt2A/DM952NOhkt1xMqHXrM+Wmmn78LN15SBLtlTIP7PdsUVuCDinn0/taLVHHtjL44pQ8WUxspDyo2Ls4xzH9bccMiwhvcnt02QOOmwImP2SSvHb2SARqKDxddF0Fk9WStoT1rQD3NDSmnBTN9SF10kbSrzNcjvXnmTsppE6QqG3QhO/O9CQpu/yY0O0qdjCUMChbEyqFvf0hxpOk+NJsrOGMvXEIOONW7o6VVVrNxsj7MsM+QK6dGj6fR5/4euPy2EzeNu/GbWxFv2rRleIVku3yEeH2hiDiLFVOUtibtC+n3c4E8dDKpUwfr+4fVXuBmw5AFYSiyfMGJ7ZR/YOL3NW6/9t6/z7Ayo3vhuTJrUYkVgHT0GX6+E/sTib6gPY63DjHpYTkQWpU14c6iFttVKXXviEdt4NhHCcJw73VYvh3hT8pUe0Z8Hichax45ALQzUPL8cVmYx9HamYxwmjwkc2X0HlyCnXzBAFPO6O1R/Tufrz12zXLYzY1bRAZHXai1+7vhZ2v63DrlU0x/+QXjQu2YGTaUUMo8dlfHdu2L6uA1/zltPkVz4PYyVFUTfjUdNRyI9wKIgUh8QiYjvs97g7LYbofwEue4xY4/xEX2lqTZyHSQ2VI711b5IAQXcSislv/ZWSz1OvWndP0PirN5l/w8T0NXyGnBDiLpxPGXn84/FPF6ir6e/oAr4vQ0Fse4gaj1dwkRrgLIEtJ/TTqGTmMqfkv8/hImxaSbflNmR3/MB+zXG153chTAl+ERKCD48xWtfoXMYTBPAG0yZfAvw2fqqyezyPFQcIUvkLHdWmIO3799yMxgvXDqaIMPbVWAsHm6+d3KAbgARvz0XKM/d9gCK6IGNRCMT3oA/lZoA0siupDJH9r5UNQw6XdeP6LCHID2z6led8Fro8lVxWUgeidR09mSuJ1RU7bkBIHoOBVp1ok1DowLXHsMs4R0BdSDO7OaoiA5jLOv3a+5/OzcGsD+nECMwxtgj2XcGd3bYV81L5bz+76+NcedF++M2xx8T2rjIzx0BlwBlYm9Gf5KXhgh8hqct08IWZ7zbk+WwYaQmTMurSIaO33RyAx71eQCv/Jd31o/Ts4WgvxCbINDgbLK8cUs4nxDHsYV83Utbxabgv2Rsb467CAgLqljvUh+T31mt/5RNv0fyP7Bv9ZZOl1B1pg0VtKnxNT/TzW8No9OTxdPi2COr4bYSiiDz1r8/QK9L4HsGHqMD6JRyxFjV/QIvrn14UAoqCv0OpQxmbGlKZxkRrjTu4K6ivjTAVLI8Iv2w3seOWdlBZa4aITezbbY5JLDVR2C7UdgSGLpM2CaIeXkOKWDLnxwf+W0yG+he3nYJOshppT0o5xoWmM453LOiPz1V0JArdTTQmBYa0yjRSKT6l6a//3Dh3e28wy0hwQnBPhH2rkLfg0zJJ4SF853GVIxwuqsuagJMqm7xJFjZBAulDQy30NBfwffku9vaDvH62Ynrsz01DKPjAsdk4jDmdKj/yfGDHfbHlFadhZMX7skVw6qVDOpD+tei5qQyiWA3I/jXHehf72wDLJzqsyBoVSBnZMO3qNjjkz1UWYrVwk9LoOn8hoUx1RBfRM9o1ZS9E2t70QAPdgvfP2hWwwe3gM0tmc6Z07rhrCxyZQflTW4n9yJjEfCRcL7X+5xIOa9N6b/U9Wn+I0FsPeBTdhH/W0ayhSUz06kycN4JLESuzqPJ/YrTBgUbKLdkO9L9+RtbMePaTpP/KUzGJbQN81ZlOdS9ZUqvt5A8opnf30XQe8mDeYGCRi/87xCR0WUqbl7JcHNa1uWgRtOY/fD4SBxVsRi9sOSPk//raS27b8A8qx24Z89BpPGnMaQzfxgSVxC2ckt2Ggvj/xwIlvlxQRyKTO9M8EqB8bb+aVMKwRT67JUk9x/7JEBUYYHXOvnIjF7GlazqkLUejGxOqWbg1f7p9NZuy3+k7vznjSmXSSx86HJktGLIpZ2D++S3+a/p8GHhW3fYEvbnYb19q3/Wl7H2aK8CYDBTTRBY6xpoLLyvw1AvcSaQ6NPloqCh/+GbC842hIuHiv3Y8QXob1/0MZ3JBI/42L54QbpFNi0xjjk5d99Y9rrlZnH5NyGs3aRezcWMRPmMLltzS/I2DfCHgG4dm4+udZbh/3/SDEw2+8V9deGKix/OKNK+lJnwEaHyc0E79X4V5zsHgU+8yr7GDJvSCEriITQ7Ey1RxY32nqKrPXU6i4fhOQxv0UZ5A4p6+R7dLsBbufJdz3I1Gpn5vO9humBLG/dBagm/9btC2UJbX/X8/LJtwijFSAqnNu1Dt7IOrNoHgr2h/e8AKCirGVUq8S08i4YadRgxUwTwICMOqcge453aSP1BWcvfDXvABTPmSpEvY+zGbgAV2negsRlpXit5i61C7Z5k03fEbUj52vpGMzNfmaTKXcmtjEHj8IxAJNMygavcjI5apkLCVp7yqA1dftvaPKhmVeAZDrWtqu0Zs4ksSAVnN0Iu/ASBuuiVcBiFmbluYm92hnkRsqE2dKxFbEOY3/LD6XvSb+pgivLO/LZdl440q+NYmug8Ic5sbKsV+pzsknSc6lonCfNJ3oAOXPum/O5h6tHZ6tfpzQE0gyEiF6XE/0yid+xMvgaZWBKC9/6pRaYS4LLLBF/LY8BrFTPNTiH9Xg0mzxkSF/Ke8SOTGnqAowtJHU5agA+69ymv0reBvSMThtEGtT92Un3peRTCUNJK1ojT0HNdmShjy9MCZxzcsL4Wez0L2uwtRSYkbeSDghD2wUBWWwOsSGI9qSl1Zk7W7C6OPSXhCI6keRIxBwdQKmGzWVN9qZ6T/WGKShO7APFm3vXE9nS6+BHpeOCm+n+BPCKDerfTZ0l+FifFCQ2Ws783c6AVpt7VIyKmEF9LAToS6ShDIYDi8pcQWf88kCitjzx9pJ0QC6FRrmvCT6sPdgEdyIOhnWu/QYQhxeHUHhB7Lbx8H73AKJtbW9ZjaUua6yB7pyQ+XHQLD++SDP3SqxKTdlbuAKiD+2iJughaz0PHHaADoSuvYZnbGMwi9WoGopTAO8wqrHWG3N6lkpYdFpki8NEiACIVRCeD5deW/EEJI+ogQto1YTS95Aq+qeR3vQtspaWpvext39GueRdXxdV5Qse27tCyRDEqtpNHCADgLDg2woaExWi+Q7W2xyoAIsZiVQzCCmwrRuepkvlIf8BV/7U9ewBRJuSUhyUsdxNbeVXqkm3hev74teMnne2ezeeYloiFbinCGaom8qBCI1Ki/Gy1/fm2E3tYUbH2X5SmYfTolBkbZ4lSu4ojs147aAD6UeYXszmzd53GMYcac0SVLowmNy5KSQ3dTrzXT6EvTEC53GttgAHbob1F2BxPH4DDMOQVnCWVWC2njom3rbrw9JRKc3oc+y1rBO+Oh+9X4bNYK8yEJYPEArZJM6l9JoimpsOznPTVdzssoAIfMEbtyQjB2EtgAa177PuGQ+4EsoCtChKjEc6R6hK/YZ1r1mHw4mVABb64hhN5VEHIttsMZaBbdHVd+ppL6D/Y3EIQEosgdoVgeo1YI7TkNNoWYGsq04EuaFga0b8yftz8Z++1z+ZKDBbLYa23s90rvJyPY+O4A2NZtwmXJJ678Y3xLAs/dIaSNyHOq4tnw
A13: 5Ivwt8JxbKP1vSSNN9Ut9FuUIpQMDo1mBhJ33GXPz46qUaa6C0ehB+/D79GqTVdkFfbXCGydbKjyoNWblb36zn8smda6IfCcLIS14tIHFv37tf92N1FK0kk7GIbYN44iHMMwQWQGpeKib2sK5tHpNZctSeJaViWsllE9gT42TnAgClxgMjNxMtrU3jtth7xm383l/nK6mwDUsPsaRQ8KdyaFKDOrF5ss6hNTdYNnn98ZTM6elhkDCJK7EzaEiDVlqNHvTxEh37/NhClkak3dcE93476q5kl8uJHNqbIKmoC42fzEnimE9AQAU/mz7KB3vqAwxp26NRPT9ZydmsbycDmsJ4WlfNOxRnLJNfa6uDZN6kYSDpo1vkP3ZnvA9vIAk5RcgyVm0oDi0n8vVc6z3pjK3xs450E3UaxwNRMcltaWVfpOHQtT8AE0IoBC2+LUQ7NwdIQRP5eFdhg+NIep2Xh9FRZSCUDn4UoE9OdiqHIeKtOGJdGlf6Ke6KVaXH1+WVsn7DNwbHzXpR7RkfPd9u0pFtuTJj+a/2wZxtlnZTyKg0C8MhebeuRhHnIu0bzAdukHVq/042ba5dgurnvb9i6TPOfA9G7k43J4YHEfUNKXpEtp9VVhbCez7LpclQxdL1Rm3+dp+rlDxMkXoiDn94M7wg3hg3bfGRcHwMI4ik2BZebzRI6t9zhRH8YVdUsAp7sAgbeuYPUX5jiz8kJVFGn2tLomVHeNUVt0HZ8uiiS8uZm0R/8EtZS5e2VOdM9V9AhyQ9oipDk5HzAOw6euGWEOqZcTeK89ipm/D0Uv3+H4ehj7jRnvAESpz75gi6/bbndXQhOj1Ib4PeO/3N7zD2OFy61B6LnSu4csuHtDc1CHbyzPrmss9nRcXq0qtaAOlE67A4tgm7KW/AWYs+86+jzP0y4HAU8PjqNXpqwVKnrTf4O8zr6EoQR/erf1krEQVyPwXyz3h0Fd84tbRqfCKq8SPcVpDMf45s+QYrwWeefCNj23bD4XBoOXWNKYvpVMED5QS6Jh6Uq8qhyNvSqDKAugVx/coZ/ANJQaFDAXjScosGz9lqiZqcxccTyT2xA4S4bfmkEYGfNr1FZFbav/61eNILOe/5CrUCjrnu16RO/NkJJIX1ORlOFKp1Yk6/t6UGQ6b82DwqNZuFeWhusCoS4AESMyPIdarpJN9DSaY3ZdmSQHagTiBmSBYOLDdQG0AH3J+R/qDpI9hcMG/DXvmqhvgJkyV8enFCSNJiNYyGTtCb/wHMhoNIPuOqp+Ua+ht+n6iJkpcxy38lwfJMK0hDTwvb2THQImfhIE1+YCfEGjk4ZrXr6IamxCJqatNZ2DQNlLfsiS89jZ6IUbwXv+Fz6vqvrfzvQ9++zrDmjmfIs+4LEO0s6iB09xLHLX84EgKoOiGifQY1P5xhdewunaQXhIqRkzcd7EyI1WCQQXWSrL1iSxLSlIHPpGBVMP93k3MxHECImmm75ueu2vb863Hy3p0TIBaw4rQbEq1dNvPyom4IT8ZphrGQZPGjuaFyduDX1nXApYAQ7q/xuMLFmJ4vdepi0N/srifmzUW+dZ5iz+cboW4o2npR5E8F/PiGZFXTDqJZ2sYorRxcRSmCYCSZk2nddrjV8yhKdX5kv8tVBifsDPiw7l3m8lZv67/HH2tX3vH+BBOzp83g3SwTpKQBqUagm72xi4jdr0XmvLlU3GEHfZ7EX/gDbMnibXsVtKz2RiuM+CX9Nz+oN7u0C9yaQeUwFiOeB5x/qfpih8QfEi2y7++HeahGi+OYOuUT3JvJNOmHAMRi3c9OCvxIyzmH4+sfnwcRK1PcLL+sEEt5/kN5dE6XT5mnZAEXUaEOiC/EsXarudIkU5b/pjLjq54UNXvsy7/Yf+4lEJ6JBSM8WjnNXLqeG0V3MiyhaASb8RrEhes3qsXLPUHc7AON+FfCn4M/apqULtEhMSIy5wuq5cHmpBWqKKCL5E1lxCDpBC3w5zZXgxLN+Gb/DdSgkPPMRfy9n5tWsaqJXwbwObem9WJZNGM00xVL3OZ7vCRCuHnI78JqUcYz5kmBQsm55GVv0LP2FhURrDHMbVWhOcg3cmGbxIGOjFOJX7d6fNTiIA77v+aCFxTMQ8FujywH6D830gIXfiFNMtWVCjLAQs+o9KhE8ihb7aN8jF70H0unc1yQBveAa+tWiXMmM5NWc+u5Rwnq3t18mSkKxVrjbTYCEQTn8W+AQxqS/q4JW9q1WKW2lvRqF6fxUzrhTjFl8xGLdUDbqzsZRzh6J/Wf9LMLNmR3aaxObNBAOL+pA7azgeqE63ZRdc/6wbhXi+hf9lwqJw3pJD5FVt4gHc0Q/TunDaDfkd/0VQPo1VDtjOuhWeH096E21CJFnv91IY1Wzzju3q99IubgQ5r/sKvaRTF2BTufhbpM/s6AAi5T8BYf8o9GnGF7stPursLOmI8DC6lyPqsfe0xo7Db7P3sUnNJ5UpIAzlZeQFHvVaBHGSNoim8WaNI6jPQQwjbaLSgcosBOJhQFR5j1+OLWJZVCJFaOyS1uuer/PYdmw3GlHDMYECT3pAh7ePDvkL799ss8U2xr1/BrxIpbVt/Aqp/y/Zn3GMKFrdB1TvWSO5ml1yzviXqbvK7eSrF0zXYBcjKAsVp0n2GtD5iUneV/V89K6RvUXUK+ks3b4rFNC4KCRGcSDcxq0GQks6qTwJ+vsBlpNDZcbmuSwT/x/oLna9imEXbO6u+OL0R7DrjS6DEnGENRTu3HCXtlQxraSPwkFVnBYf9Fy+G+tR45aBA93msza2+gFxOqVS9x/+XvXcFShcPyjMp8QG0ZvJ9Vc9ibwSRC6H4kBHxS6Kdfso6vDcUGEffRUj3t3FxrbuwNOf4rzIBeR5RZu15s/aM/Smol9Mj9Qm9F+WzvxDhuSdL2SCwcQVLALLAx+8xaILq/aELHT2PIvjg1T4suq2b1XC2k+UYgbUmuVoEkFsnVZR/GrTNv+/T3FyX4EnVdNFU0PNFVo5ycBFYyvorY7ncwBMzJrjib2Tyt2o4Eu97PmG3p9epKhLNVPQ80BUYvfZcnIYiHZyFd6tuPUJYZdsjlAGfEEHoAFKrgZFbQkms5FX12l1lGjbP3RDyPxXKPIXMuMqU4zALMhc/n9pBzMxYkHnJCdlMCgrgxVNxMei/olrBH4/S8TwmpXTarnlsL3Uk9AJvUdI8oljvoFFVFn1ncw3s6iZCvZjkRcgnE6lQW7vPyX2UBVWhfZTgdDc1DFlzfGHekS4ThCslsNf6Iikcnbl5F9IXrE80YBSAcp8Z1Pn2W7keRr/8aBlVB8NUZ07RGW+Ec1uEM6SoVE5yzedDg+kPZVLkQy23eSuiXRI05zM38PTA6HMSpNP07vueFssyZVe8Z1yew591/hUyuxDKFsBqiGabckXSIVm8wfizTnEjsMbaxMrh4O7vyQEP24J/XU5IHp3NBH1BqwO69v4XwlWA4YhSqFesTk9JUAFJREfzrlC8MBHahdZGHxK8OkaMZrX7XPF2hlShrNN3EqOTy/TxQO4j2BtEIkKqD9ysjO9r8k+EOaqiwB0n45qQZe08UQEN25uDnJUpUleHE1eAsnBuSvH+USkAWKkXuqXmi4E4XeSngLc42v91JGtNl9Llmh28VpFyW62NNmTQOnNugo9RAQ8uDpYD7VDxtG8y4ir4IJ5Q5szcwKZMj4pKDURE1hHzlY2kvGTqkv+5nM4XEWrtqPAhSH25APuTdiJXUfn2xg6/u4LB3kjXu/gR/4xYyEHCjU7jpKdtLRSd3kkxcZ0acuNIynO07MIyFJv2AY9GMq+OfFMbyW45I8lq+mRspH3veaMvArPSAIgkUxAMXWTIP1k95LiK8PPVohLnBPFziX7AB4Uger8ifbpMAh017gHR4qWTvPTSfwnJdWzbIVa1owAv7jTBgpOWXaDYy3FU+Ee0hx8pn1YlQAipupLcRdAxd/zt1ixlRNki8VI/I581wSNxJTt4ZQBGbADVBE3kIivH2pOrXD5EyHBEN8Rf92PaQbk6MUw5EqGOfMMjHFbf+ukEiag0n9RgMvBp7/zUUrn1M1vOC/NXxNypebqSqLNa8mgPlHDrKHapYXg3PwTyU01s2fVpHn9A/x5h9EeC+QESKGVc3lhJmfnTCFuxp3mZZEDD4Vz/FBfkiDNz9us+zcl44g1zIQ3Ax7VE3Jkuk8uNbgFW9m/iGlgEwWJj9HJcp53CN/MrkWBM5KGG4U+jHg+PSHvpJGJGArgplMqzmgccYd/xktFZ0D2ozZezeLAFcNmVI6umkA/f1SYwqLHeRWkz+BWksvFAXpeiJ9HIBEjD+Yzb8mkkHkbG4XNKimWwNwiVUfBFiL3h4wEH8yXktv5+pJY9J/abhrD34x+xrhKsoI3tANSImkiY+6quKaFVhYxUIuEjAoSxkZh65HvWizTJrVEzSXwcrpDRf/+x4JNf5Yu3sx6p/sAGfyXl23oylcAfCJ64qhWdYh4YIcPwb1pRORYAnFhuhFp4WYA7bHcoYxiRuh7J06hzahezBx09lx5RWmJRLymaFmzsiH11e84KZGLH1WnJkN3Cvr+ngha6K0KhV5WP087Y80OqBWP7t6DuWwsJYFo26EYkVepAb0arXZUKjhsEGq+u2lqVhaFDarsI5D2pSsFwdljaww1NJAPTOmdQtMDSfQvxNbTIdcuDugNO0O8/gYTEMJFUBpoW1moCcqHuLFe71/q3Ap5A+QrBkwM+BDUuvOOMgmip1T5sm2iwLYN5Wa/yowIDhMP1DFZNd/GqUpRKN1JeGpeeLiaB2afnjxMMWHBMq1/VzDYNfuw82BpA/t6Wp3KDuk2FRuRYgSL5pPD7rzbUzRDqb+fFSOCk0ro/+14pOOPsUp5TsV00mFFtY2crMrxQLdI03LOCt5xiO4NDAyzKuqjW1a++fddCkuHiIwfSPQ5NPtcbFCu+QsO0uQxqqjBTNrNYvPnu8+1gmb/lq2HVkWUhjv2RgGVdceW0vWNcsDfUIo5gkrjrWDUX73fxdqtMrjOtfkTEZfqJOK434lQ18yuLClz+Ou9O3rpsX0OUl7r3vocie6jc3xeFVZdFniygiYzkbbRmyUTkMeaukrCdAlMFA+Vf93FCvfeOeomQ3cs8nia2qmwTzSHpl8B7axqDLhz6Xrx0wctrmNZy2f3BlYMzvSE0IPiVGbxK2TcGnCsVGpraQ3QAjXpT4OCJG7UmoG1evITLe5euHCNbbdZgMXNGBS3YOW2/+nozJ53o6vETdZNSgJR27wwQ6iz+mKxKUhvLkrPg7hP2LPW88vzLTDKyRmmbIoJsOE5LSvQP7w6J8oAMtkjEmd5JP2x/bOEPPLtaPF4j1j96+uGy6VEabLzjTAWDAdPPJMUdMzNQdN6wWpPULCSb47P8DsQcSoc3vgplniV/KsKqfQ0tiiad8AZi+3QbQMItqSDgKCABmR9+LA2kMy4rgysvmynVHJ+G0Jq0W2FNaoiK4YkOz50Dd5f0fbMOKuGlDo77ojxoKjFIWfkuzt0YOW+HYzyl0USf2tY60ltiwd6qR5mK8BakvW6Ib1UMWmgDfYbv5B2T0fntjQ3xaWy+YVYTsTCP6b8jct936gnVC2yBy+dNh/vCJnSuhrJzPIigfIapjpoqOE3Q3iKpa8Dj1F97znvogjBI/kJK/ZWvx+9/QyIucF+1ScKvDa6D/tnmMVo1QZTmT2oIMVPhtZJKpljoeKge5/i9wRzzYpYLxJBA8qXNwQ/vR06EpUZgPiq+aIYezu5hSSJMViU4nYiEnhaxNAMvyg1yePQvbyjVsgXrNTX9Acm9CPkBKLDB1pw6Iza4jFALg1n9auwNxsgLllbZsjK0lgSue1jqqprHBWoLB5hfzTlvBn7o1mG4TaMyPwuLPqLyFcgXJ50AbxnVNq+NR/ttj8TJf737BbumU57K6gXmUdDtj4kGenNxXvjckTwpanl0AkKNAPPacvICasFkxYBQAi9Pg9xfDratU9w4AVI067eb6NIihblHHf/w3nXwftYlU7GrAeWccXZ0G4MHax3n4lRbjId/WYz0/CtJTMy6w7pOELm5QsAD/zSn0xLiav49NIaNi77xKG8ljHitsGp1w9+2fQbF3OqBLqYHS6Z4pKpUXqOD9dlxn1WPFrz8Jn5WrJkrnw4WU4UR9dgmkY4qdFbm5qkDWrYlmMcZH0hhLGTiSEas4TUjkLgNlqSqgjS7LsOExiEmfMC0YwlfEmgnuWEpVf4g/ndEULdga6z0uvor1cso9U7PspsVrEKf2WGmuqUxtWDvqUbtQ0rCV8gjSJPhi9oy+Rk+OZXF1nKBKZaK3SF/D7oICaBNjPOEV6J+WJpuPnuNUkmmgvkOJlbcXysXpiI+SiGb7JfhyD0UTgawaetbrG/lHYX5I1Fe/828ZbOHuacYw9EPLVJCniBCdg0cJm/s0GhC+yvjrYnXePJFLiQsxKxlWzg6p6guEGiq0jxXU5KT++M/rBb0zJ3pT7kNNQMG0rBHBUoS5uPW1jAn7XD+v52k9bLmM2vSSVstoSqr1yPPWg/Xdh2HSCghg5vEPAeFzO+N28BmP1/RMooHvclhO6bicXd9JLjeQIYiyqwNRJXtVLFXCQMI2Q7//0UlfyqejTe667XsXJXfDdcu6V7J7ghjeFH50aS/TDG0DNSG8H0qYlu7K53NVZ98PMEa8/6YrUPLi7yRRrx+nXc3p7x5pC+j3Tgv6H4C+r7Em1sbygQmpV0vNsdo56oP1OR8+c+BPfkIfzdwkEomj5Ec7rPEIWgvXvKq8/sY00bMbBFyn6lAtgpe3jhFwtyvxYA+Q7KLVJ/znb9vDpgdQVYBsyHRcAInaTecsCWkYx5dlR1zMlCPWEWuZtLKYyEH49UuJwkFfdHGrctk5+XOob/JTd0nAmmV6HmV4Ep1/M3U5HfYW08VlIMRnjJms+hBqNZ4yP4Dg46nuGXsp1Vc1HCmm1zk6ATV9ZaiXeVSvjMFfJLqRIgqEsaahXmagbvkIzpUXtRyNcw+4MWs+3/+mf+6CBepoPcM6zxzdPeQME83WJK7cHl5tDBhU33sLUEKG4hDu8uwo430+ogbJZbjQ0PvfEFQldyhIFKEPFw0UD8RBqwAyF6AD3aOkZxOm1cLSwF4bCNB0FEFZAHhuNmjqC6QalSSNtQJRnjfBVsi5vRHAliumJfD1hX7McaGZmzrVIhqSVC3eXLfpYGwkV7dw1dvG1g/F/U9ZVO77DMnT9BFH6NTI6WCWv9GP+s/VlAYl1xyx4jukgag9J7nGYulkJa1Wu8tlzzIGUmK8kxn3+PAs0FGzwlGdboWOrH8e1DSRlHJplZo1ypLJJkvtDQoRHSFlQDcTWfHGE7u593kE5qaVT5e6TE98u77VNjDF4ZzHax66EUUY6PiHzhaX1bYauTywc7MHTGuIwf3b29cPaluFLEpW0WHMYBLFti/lAA4OaLMMLpi8fB7Q+N1pnGNjr0v8dcYdpYg07eI2swmn8ylcm0l9YQDsCEFGyaB2zoNIDLUjCATsVkiCMeKrowVE2q3xPUMsSI0B3jz+Ptb9JOPxP9AzwrPASXtu7udkP59u5kbhLF1NKQ6qORArfenf9mlQJLfO24A5v9Zz4QltFok77R7ft2RRuiBCfZLelVPHM5i6yph4scaG+RUdfh8Zv67ua3cSU+1RXKuY1IsL7DYt7XjB78SK/XZdsT1B+UY6RG10kMgsos4VW7jT1GY2h9rBilVYRVT1DGkzrUI5gnIGSYEm79wIP2nX3FkD1Yl9gn5DggCT0DOR0ogQO9PDHp3mrJIlavrIFE8dYZm5BUOktMaO7FInz4/jIYi4167K96qOHFJDOwMszt7s7IyD/hY+HLtEEdFn6ZEUYaSmk9AC849zDGm1dHfioTAxAWICZ4C9JNRcxKturr830oq+vWksgEzUHuLSZqX059B8u3udOphzBG5GGzY3oMWuW6raZUufa21eZpFjUp8x3LmocTAsN3/s0bemv1bzoewuT46xY3IXQFaRCTpI9Hd2oYLU9grRMiGYV/1cbTQXMf5VwFF5BXtEQZ9jFvkznFF+Ou7daislqGdLtNbzYaCjmJX87WNbC3IiWP9JJaaWB+IJetz5mVHFK/2HdbPgRxoSX2WaB0ua2qYP3/eEsG+aDXAFpkv+pG3uTy8Nx+OHWAk0o2a+/s2tXzR/T4/f4rd4M7NSYsEBM+ZyUlhYlgZv6t+ojR7E6vmKDy6VyNREQd+8nWY5KS2EA1MjCwjtU6/uqvGcebYs0llM9uM9EXc1nY+Usni18/bWvrXMU5rmziNNs4kZT+bqMxqk5VTh+qtl3PWZJoEb/pj18Mu7Mx4L2D74ca6UN/BKrHfLMayDj5FZ0/NT5x1dqFxddgczc+VZ4x6n+PtA6yBBmIZGOLQFm9zvuQ39FvixEDYEaGhCbZeBDDlfIfbTDOpWVwdHCSv6j1CiLXwr3uVHJ6P6hI+E20uQMD2+60TU675+0zngQopl83P91I3ScCCJ24+aHibnN94Th1U4plYW23xGGUZVtcd0ZYi3PaQaoZ+dPUlQwdItn65z7yVK9Rm4xgpQv+Ur85uDu0mMCh5UYXAo5M/PietxTetp4ZoEJVQs8I6yBxun4rp0zdLjODrqNeKOqSdAS69AtH6ab/TbNkQTwGbv5sfXMm6d/1/+E1gyxkaDhrsrc6HytBoszi+mXst/0IYY0jBj4mLfALuv3nJBAGnbpj6NnEAqmQG/pkt+HlZfWXClzIVEH22zA/wFRJ23aIpqOLmmhhVxDhiQXAESFtnjtkYPPhdwJp2kmZmywIaNmaHUk+G94fNCfIAQPs/XpCbd50q3DORjc5ZvLlQNskVtN7cNgC6SPiRJgRLuYslw7FzCx0QxD5gmDCXvHLy/FMKbXrq5X/GYBly3GSPUX8C9wuW4eM7apY+J6wV5FhD5eRarMVQ7Wl+4LOM0DDmUadK3Z71ufnTlPmHEu2niaMDxaxJup6ym4XGdwSpApyb2e6BdMse7k1TcRz6GVq4EKm5cnIvhfoDFeLvHh6WnhB5K4Gx9UPGSZYW2w8FgbaX3r+/DTEErSCmdZthKtZb6RzxvD8Grgg9apLbJeiTn7BgX9c1HNfMDBdeQqxQMPS1oOciUUL+W5pszmkwuPnFdp+Y3uGY9SQaAfVZLt5Ug7bN+9SICL8aW/yOabumFILX6ksNqf18KPxBgiQU5U/k0T6GKigZM31TUJlS36hfVSMZ0kEHUZDa+kHKMnhpdFj/Vv1QdoqOSco7jjGNdTp62WUvy682DJQ9KLKgxVtpaLcByHs1QtOiJaU8KSHYSoFv4uW+5Ip2InU2k6HSwymM4ZTQPOPhO5duuhhPnkW0ZssWptrrBaI2GT3rdXXzDeRssqLadTwGMqR0oPkrILDp3O0sKW8bzXlqdiaDA17vSVLXWcTw48c77RxB43qFuT85lXkbRhAaeJUrN4j2Y0xzV23JK5GnT5PXtQxh80ydyHqc0ahV954yxuFkihQwGrNBKQF3d/Q17Aj1A7Y5hzA/VKkAvQxMJQFIfsewzCdDoyvl6ooyqsTzv0GGVvG9pY1qs6Gx2pMa7JDEj9uxXaldb7+bBiq+dqAKu6tn2OrdAFhUEfGk7OWjQ9vpHhwoOv6g+p6y5OnqgY0MycSasHp0JFnNDU2weevOeNwsLzUuBniCOp8p0TQO0aHIFq8q66k9pexiBBUcnj9HvKyxnsKtlY8a22E/LqqP1nQIV15Xzed8zSjyeWPXRo45zJnSlAHDFYpRq2fba+j7XAeV7v2dicmCTa+sN/bx5BnG47SaFZAoki/uyfh01TXUCwCaUduqJSDxFyZ+j4zwxoZcMnc5dGPLYxauBpKXt6/PgAasSfcNnkD+EpnnpNkHSv+i8PiUM1awnCl2dd+F06JjsS12b5HK4bqgP2MNudt9SYkU2KUr9tGgtC03wJVm41r7YoUJDz2hovMlpyNkbD5jqgQkLtnTgnucL5nK4z47rwlpi43s3wWRPjzFjM1NVVyrkekmoviKBbNYvuWHpnULxsD35NiDVKAwJvj8FteZfdNrl5jbidN/c1bRNFpo8yUsb/AXb5fQO8XUm3bzqeAcyaAVwJp1dGLVIqSSL7DyqsdNFexec2LhRF0NsY5t5tmPLLbwVQYebBOKXwjzn5Wd5jHuaqwFwljoBl9avqKTork1aKzlINi0yVJnf6uwUKhR6FbLUcw2ZvnBXiNWogO3ZImytf0dCqcuGa5bwH2tzCeBOgx4Alz7RDtzMI3xQsLDDfFZRTtTCvp4OsfDxQrid8pYdJeyX1vAoaVgbsd7xN9CIOAI+1tt6NxctYpMutjM+A2ocoETKspwaO7upp7KSZ7APkRDB1kRxwbPBIt/f6KqMyNGyPXsFCbjZ1l6n+aiQ9ak9R19GLnnAn4gGO6BnvVwgh4otsC2OOUS9E8OAI6i0r9XpQad/ibrt57ILTuANw70AgG8KWMOhp0+a3/iaPpPR2x8LvvOqIIMTyhDBrsCyHxHz1NavNwLCS8LC3BNnMznENNw/2DsveGPb0fa01y7XVa6pnik2xpEMJuDgHFozcCYuVpOPyZCThzy79CChLrTNF0HsEx2xRXvyBI1wxjEjyR1OPSGWiGpxfhgZAGNaKhsgqtyc8xK4Zt6qn7xxttuJ8bPr/rpBO4mUIEQzM9WkkrBa5fXv64UI5uAF/JefEQPpA8uOhkqVj41v3kLcTHsNiDIHIEqNBg93IDt4R2i57i8Sha+jAgyzz9peDPBsEThQ/1t48We44I62KPLhXkv2YtpNPM/TOyFINl1PZW/Y4PG7KNgbkpZLZG8fbqwfGxltc7OxTRLuRZ4Uur5b51zP6UEVBJMJErwueU7g9Vryqno8JD4+nBHVb6B/UpED58UmTXS7uzWV5vJwgpOkXHSweZ/0/6awjWADQnndaioztgPcUhj0BEQbtJtCQf0X8KROAFw4qUDxrRmMWds5Zdh7w2uukSghU46QAsSEw84ftLnKoEtlW8139V8GGwhcI5/AGF5HfHD+GsWVdvl9JJH0vMchgKIC/qvA9GQPWHtDEW9patU2Z1T1JQIGyT4tiQC+DBHo9wwHSIwkU19QngIp4Ty0KEkqwrPwZRa56wWc/IKbFKET+LpjhFlZQP8QJJTYiBj9CpQeVywNYNw3pl4eKNSjhzxBUN1E3AiTRTSRIomcPrewHi68xl1wvvTEU70pdcj2b7EJkt660EWwlY0FgZcxH0r6ex2j9atmSbDj0t8TBts2/KiUBZxnYzePJpKfhntmi9F88K56XZGuit5/LkQ8/wKF2X2nFtCt8Yw2z79mT63c7UxSjyoC2N9FgNmSF54t2IibRDakeiT3PFop9BIGuSQmpdaEuyf/EjobhbAy4hPHAjFy3NS/vL/oF2QWIMHVBuMQy3N4Xf9+tAzG5ZGnOWZypm4yHb4kB6Yu7oXAI9EIGFgfpiboQ/g46M/cuWU4wQKHvx0rILf+KnGs0Hty6XM82CpOql25JVU8YxCe8x6lznI35q3M7HnOBpZy4pXrM0lGL1P4hWYT1pGRpfkcqYsfoD3n4Pxa1jG9Kza8Ac7af0UYiKNCrq5FvjMEzWumBw2Elm8ZZJI3XkLhY78wFyjVcOmBJZ4So3VXaPxw9+kL1sBNTq5ooT777ywGgd8tp0Fb8ui9gl46MFFaLtohAkcgVYZ0vEMljl7YghfdFVvAZfUAFARbC3bERTMMkfAqDcUchLChH4Qu6JA5va8wtEieqn13e5Zc5hvieOrYIfKB3Lw8gg+tgMpTdMYi4zGl9BQF3cvYLxznZOxH9zwt9CKSx4bUfb39a90BirF5R2pbRYzQpGbtGAqKUI/G/m17T6ClcZNewZUQZfpCbg4qunDnY6iHkA6UKqSajsxCwwPJMMGylLyP52VJjSJfeEUAG+RrkaxFGUuJztYsNc7ci5Sf8lJ/6BHl0u2pvAzV6igSNT3fjJPqUjF1cMZBgR3KR8wnjEr1G9/iRgMTo24O8q4CLSTLi7lg0PXg4w+3xGWYAuLDHRvjCI2l8xKH8EQ4OPi3pATQ+xwfIzW55p3+MHGEYhMY4yncTtMw9r5voOkY/IzQOSPGnXpHaKz5GSdRQ3egas43lQCRX/lCtxr5uKjdjzZJ0Pj9sBDTFBTr4MsA9fY28p1/knUuyRu027s68xkGNfd2N8NV3K0FeVkXpM1kCAcfN6aEheyOKskSc39uMlE2Tq7o50ZykcmXe9OPaEKdPn9ZB3gQlNzyJuCPdMtm4Glhg2wAcRsOzdbzl5j9yLNde+4rB797pbpW0imEGcX0MfX6OPg1uhuy2ZwfbxoPccexoZGtUWlQEyTLSO7e22bRXJ5hGYPOw284kWwv2jZ0FT7UWy7svkuIUsgjvE7vBtvaoTkl1H1RFxKtQl8JE+78hLFyqn45urG3qQubgzY4ZGTYjGXLuGdszKEA5o9auxuuwIp1rL9EKFkyiB/kYISpwBMGxmqi4IBWEJZczhop+qKmvj7l6g8CiF9opzdMZIliWZqOkRXmOltPla17FLOE59auuETQA0HYl2U2r1bXDtc2pAXFxK/QsCsZIeCihyQNhMlQg+8p9hqBLKbQZm7XX5waPwjoxncTlpxJIKifs9Mu5agBrHb2ec+VH7Jx1Er4PwFK2EPCTUIC4L1RW5vhYWgpmPF0u2ystkrr0OHB9XxIS5OFK2x2DGu1k0l5cmWutHJhwnmR+7Ctp+iqNMKmWV94R/pZxXOI+JHe0ZONlpuRLcG0yRnZKQVMVuu/YDgJfwKIlJ++z8Pb5mzt9voVv0r+VtxneSVQ4rtp0jk6dBKXtfvZKKv5mZVNiszLY+1MwrUhsMbkdK2HMSJZz9Vi+z+JL0FSMfD4iqTWUNgxNpoEllyVzx7yn5seaLMzAfhMnVVOzNzfxE2PLU6Rd4JrN0u7e6f0xn9nMkRUbth68bhfJ3QOHgnihGUlkmq5/rDUMWVLmsRGRhbi+BayjiZq9P91jDQmqX0+Wc+Zs4gPjpxTXNqmN+DMahoK66xdxGbnKl77DNUEFjYrT/FP+Vh7/DDvAsW9/OqnLq07Qq/cVaVvlkwnaROiUbgBDk/pxpguII5skwIChubO2tLUOfm7q+HX+pwPAw1O8CGgtoNRqyR+YCGKyZEGBHLwt2rq4XTtGC8wr/7PSsZaYPI+A2DWnLkWEUWToW+e7a6k8GGwuz6dkDuJcAfaSah67HNeXjmcw/Xzhp5i3JwwsWe7Lxnu9pGXxYIfBS334dBFHfvM3igwE6qOZER2/58n9By3CfvXVkQvdtghgG6gQyEsG9M2LUWlLgL4eEevEa2cXSkpBA6fxtIGwFo6dT+/wl+22sJ2jwYnNK+76cACYLdUuswwdtgZ6QWtU7Zaww+7Hmz32Gwpc0jCULTFQxSkuYmEr4ObZcJzprs6mi1KJAdSgoAWKauC7uPtfRoTxaMwd0OtICyBMdu5vnetqDd5NPREfit5ErBpDVgo8h24D3NUpSyKWGRdfnQ7KJpPFQZ9hsCx2enkCyl00U4HTyR3V00UjSQ1GzbVKr3h2qwQJ2Ak95lqBKtsXGQCP40mqEwQOMH9O3PqTu4J2lMUeCKOhKXWB/IMegt8ntI/sSN0eX8ddqM9FHttScxsZYyd2dKTpE4Y7Z/SPOLTksK2GpsRCwsZ8W/xK0j1AHUA66Z2a5PiFFidITWViwSFXmW73VirXOi8pP7gVhuH8cUQPoslQ7Oomy5J0z0ClN//DSO46RGJ3HhddG0yBLed6WytIxinVnUKmv1qOFtTnwnF4qBfp/X7VL6ycNRINKjHqKu5yYiG/lc4lYfcnD+ZrFs38CYmT1EBqjDhDq7P3o1PuCJF7xOZJeIycSOdNvdiFoP2kSskg6ct2ex25xCQYdxsYKusTTKh4l23zOsKXfzIrIJE+RlXGn/TlZZMyB5JrnGjb51tYHNa15PWcXMea131MRNy5zjjs8Hl0puhtRVrK4Lela+ZbNjq9LzPdjUjLG5TOKiSft3yT6Es+EBIVEi5aRDmXtNqpBBJvpGF8c5K6khane49duo5gyMZsKtUXbLRIHVB9cd9xa05X68+EJpr0wo555e3JW+cLvkbdwdZlbKNaRxwKNWJVfzYhTuhm3K6T6R01s6fn45sxXDIAQgVwBNQYJL9GmXkETzGXtRA6tecsABVoRj6VL4tY6/w1wQuG97SX50KqGNWXEMzTTXPEt1ueoCOQuIWcajI54yb0EJuXgewys02r4Bn1Wjvdu0Q1v7lafgwllMfAOpLDAsGIF/+/o9w3vlqoZn8kr2BcQ1i8KUHfkr7yitYPM1LnkMZIekl5JdRZi1xdr6+SVauHI5XOyqLURuB+EEfeN+YsafmnG8J106vYbexZ0wGSgKgSdADMcDWSutKJ2IDCQj5fnaKLpkGu76UCZwlcCZecMoIQs1+xjvuzR0rW6OX/sBAWl2AxTruhf2oVSTnzfu9Wwf9jc33a7o27mjzsjF9H2FE+eMuE4mmRf13fqBUBlhJClibSU3nQaWPTwD70sK2ioXYoX1ovMawztDkkNIY+5dJq7UWQhdr/Hlp3O84Rex1bfzzUHQyHYXg5ytTJilgu2FfgZL8icbOjCAMT5DBw/9PrO+K5layDl8cQ078/dQIw14P4ItHhvmEBkTdaUJa37ziwd71vw2k81dBGlRJugegQ3vk9xc1t1uSxmhoLL1EwoeljzrJW8sLt4xKN18yJKFj3OSI22R/tZJJ+hTCmkXBxg/dlTIQWqJ2EWyMRnndsVMnGkKrwtHbtEqxMvLuELckUfrgsz4AvoVVaqA0OjaGyNrkcaEl4DdVb9s1xArTxZkGkCfJzk6FgViuuBC/QI0ddtBo+HryncOhgHniqvX16bUdODBlGhdpIk3Vc6sT+D0mUTMz0Czv4FxW23J++2FmOeW+31JcKVBPMsn1IsnA7g4YoJv3DHERMQz0wSM6jIPe4jttKyKnNvSN0mR/FGhwBwNDoVnyO3MKG19Lo602VxqOF8tF/gaJwR5TqRqZVb39ja1+0JhlqJvss8pMKRA/Q0pweDWZBmDZzgo9KA0Sx6IEq1379BdDGDdQCsIb2wiWnZFQhnjSbEK2kG/cB7Ol5Sg0Jd3+jCCuimlODZUSMtRhPLR3cHdc0aZxHIH54rK5AilxtIAQ/uJXv4go0glX6fOL4SCGX7pOwr9MTRXtdlxSTfyaITQyhmpuXer2/crFko/stmiX5s/r+ZEfAaTJkh3PIbGlcHzkroap39b+Gkwu/skBUGhm3tdqV5r0b6fomL5qP/DD2TLKXm4YPB5mVUBwJwJVCsZ1Q5C2rmVWR1+eCp7/dMC3c3NzdYmV+8J/L6TvWLSlhG4t/LIkXVNcT+vvyDToEHJag7wGZr6HU3stjprHy5IA8umPmpH86NDwJCeFEG3qHDPWQlXSw1zHD97/x1U7Ps6JlC0hQcxnFDKbai/u5OYMfh4ezq0dwgpLqmqnSqNF1nN/vJyzsF5Or7tU6RqCHODf0Kad2xhMIqcd3FXeGxuqQcDDRIuaJTyyLtnT8/KoAY6n713aPR5rS++0vhtbRz7Bz2JK1lobT1vPWYlQtuDRQsBKEmhVvVqktu01AmI82ntk3fV9ep6+6pkpkbU5bom14uEMxEBRfwhcZb7dIc3B8fhUAkwYa4h1/C8f0nd3UWPtNsFRAUSZkzl1XJHovDYyimIf4gFz39kSYWecPCpurBv17CnB/1oxpaP0PHUPDS6n7nvfKkZrSUgGHJ56HM4uePLXIbkc6b9hhXez4N+GUt2ETOpaoBXwzpmXwrBiKVBgggqzBP/vbHbpPiMIKEyRe6Yvu4kTo7wVrxa90JKJKfDnsWDO2dqGplUpxfAaRnz3kqZAGwxvHjgswVMtpQ1OHW48vR4gqeaLUgJe1RTBAU8xxJN0w7UOu4u5bMovgv0vIdqX9DWmzlOXkLC+96T1AVeyMtEO2ON+1QJ+LqWgM9IHoyIoY2LHcRvLnaJJwyscpzQfWYRKUg6mJ85MxBdOkT4LfRuebqYhUHdymiQC1R9Rl+EgCG3aBUtGctV6V/IUs7PIs+00VZcRbVdMF0rKBOYAjVIysjL4Rf03wkfZ5pIOfttHbDtci0OT+DEGX81BxScpVC3pP19r4PMfaRLcvIbeAGQnZGZIW/YxRCYY4pEvy9N8BrdtwxTcqLdud9LwdiojiAoE90Tfr/k7fKGSHvRcDbQQWMlyiZ7zK0ZUG5gamTJuL4gBC8z2XnbdPCLwyK1vLFswwoKn1djVimK7GhFPqT2h4XRrh36egXzYhGAPyUAZKVb+HzS0hgBDxttK/l6W5jIcB8Qbm4mlgWZT4p0fDlbcTMLZxOsilPAK2EthI9lbnVct80LrQ+kELh78KiqFr/fMD4qo2LvIWVW6OTqYMhRpp4AUSG5irK91hdrvz+9Ege1lwHM1jhe9rdrVWXwLLKx0cwzZbJUVViCSde1raYsMWLUkS5Mj/nHS/WVoLJQU9J4Tum75lbNTMXdSP/2oV+E9cLGGzOt5c24N5ppZMnBTCcidarxua3j0Rj18fVDQSpCexn+vVTNQDnvWKx95TiPdrzEFFwM4MOArFyavkDRirHpsqBs+TstW8iDcV6zG/0ymk6HeLfkc4fbrDqATguooCO1YVtWxRUB6g0dlCyU5O97ojo1t0gPd6tHHxOTl1QK3Ravm8JBKRi7IGeyhXsg+bMK3JPTeHoUURg/mmpQfQvU6BFLU+Lo/LqZGeNt1iejjcWryoSuVk0xZN4pJnyy60dRz3T5EVKNdkeEvfSMhoItuqY5PXfoZsIwum2GuAljX/8f8IopPKwMPvYOI1oSkcsW/+h+OKs/HXPIyDY5t94dgxRnK2GYmpwJnr73i94SQygP6As7pLUZialYhP7zcDYgyBy+fVEbQmJ4Oxp5mZv18MlK6bzF1ABfVh9Tz5JTTXWv0MA65FlY2Qi0yl95L8GzPoHK4TUvRT0EFgyAPPYEG5yZ+VytF7uwRjr/xBSjSKJr9Tp4cDLC1mWuKZcJbmPvey7cROlo9vX2vN4tlPLllX87ZDJ8Ei3aLo9PpQyxGHUDJpHwyfjon0hDzx4zzfU5uRm+o5/HPdn69Y69qPS3FFxd4prAxbcQPvqGAOXZusvmsiGfU0FhNK4LUa8Fizz+BrNBl2aoYFSmCqNrpeYzNaJQEo0/3otv7pTWmZY/Xm0nzEcrxNs9IVdVwLk1qtLorc23ZUKclWPDj73x7eQmyVmEMxPjxzxmfy7jaIwF9aUIndgzoNTUFWkK8yIBin7PjdES5meVFznPg7tZLZywC5tWuwGFxNSK+3FtTenqY6Jw80vsfappgJIai00/fsqnbDTjySQM84efu/PKVbmzKdYvdsr/qYshk43oe74vZFdrMw6e5rkZM812/7KUZ/kwgRgI4CB1Qeiu1RkRkD3WH76DAwErSAMdE1q1Owt+qZ59pV2sVN2Cw2IE6lIHetbG4YQpdf7Q0eP0g5/6FmvM6SxVukHP0YgyFLmhncdYotkwE3DdKhHj3XXjwUP1foQ5+u5Vsv5bzbrHClMWHRXVQ7UcqOyaAJurhtorS9DTegQ8l8c7OShBX7s6gJV2OCuNfi0JT4wnyjX50OzOWIFqhdEMkavxmKFYBV7xlqLPbBN5+TZai/DBreskVP+1zJrT44GnCjpBZEAWDv1DR7kd9xItiLCKweGCIThTvpluEr7Ynp1iRguRp6o3+QuWubi0jquYyQoqLsAhS1GeQgeX3oD+kmoFVJtrtna5CbHqVwgDIhc9E3M9NqAtIzENz3w5DGF+DGWn2459MEEccmjqkcgnWOD3hRSFKTwqCJzdk9Qf1XJ0C3ATacE/uA84PwCmj/eat7v8LTRfzrml9tC2FvUYRFWTFcFpizL3ZYqkJOeCZjeQfjpCBmS717bSmdXFlB9OyD2KiDrL2hJduiO+FOsmhQxQipd0i32oc7e8zoEhLnz1OOshya/lcCkSEj6ehiAJnqfV05wOGbf6o5UdXlD2Mz+Oe3V2QTNaiUrG41hX2MI5o/OlG4zVcB417C4mgdU5+gGIVJLav+tgwMfrnQFKCRaN2SmNQlC5FClz4+6j9p5HDeoKw9W5BHOnLE+jtb8xiG41X0jcDbT+/aUmV0kGOnTPqllCfdkegH5Z1U1i5J9iO0EPr3pZC95p9C5tpDq04VGcwlwyryp6zh79THNnhSLzAAwboiOQgyt/mFtuf/RLaM9VBzhjzSXrjwNY5GPM/TtNxlWE27LrvFcoz44a9CX1ACi0dpRTTVKIaSkMPZTP8aIoXF/qZ0CZD/v2p6gavgmodYiTR4kJ7+GoZ7j2CO2JhNgTSoynwzD7sI6dle+g8Yq6jC5BrMoA/ZUOwte1Wo3LdZ2xlb4bO33DHdOpnBikjj1WmDMqd2M5yIfym0hONaurVUR3KnMcPdR6pJsSJzUhYJwIDGiGTi3Frd66aafcNzQUKydpHbmTkCpJpxGvkve9vs275fZFi5ACIIFrp4dIhSwIHleK4jQoDhGQK64SdN3VwVXZxZwY3d4kUHBSdVWpD69ZAZ2eZTRQoyL4TfbdrBpa3BYvblpbcqjhRMpiUPlXi7dI+98eEUeIouey1noFEJBL07jE6hY8DBoDE8tc6eM6txOoW8sXjL6iibBRSNElBrOmhMzt8RPBNzlVOaVtHaQfetBnMr0WEEXAji/w/kh7qHx4rgbpwyqY22lkioeXFqZNopeOzBVyFPfT0adk3xd/E5NLH+lBhZPqkRrUsUt0SjGP+b+CdVwcUQycc4PTmzXrx5TgXYIBSqmA/tidagib++R0oMvfNxWvLD9cuytGEwnaNLwDiSo5sAysbIwtt32y2GSlCeENR7Fh0a6EYO34A+9IK5MwdNcuh5s7fJT7skhiYZojfWp9HMJY2EpPBxGPhr+OuAeV92XKT0bv0S9Bn/qM6d43iL9LGn/8/kO5XVnnAptzFSJE7BlBdeY3LNNMh9qiVXeTTmUlYNgp304wxlJ7JqWJ0pHTqhsxNiVayS87QwnSC5qtph0LpJ0rkZIQi8nOJly+voXey1PZP2boj3rN5ic/b24XTjrjjCQ+rDPoRhQX/gidMiwX+U0Wds0Oem/jUkqjBwWmOfAFdhINWGub2NSCc1Qbszei7EikNrPsR0wGN2bZrNw/10Em/D9PFZjV5J0qRdPpwPzPv5xIm/FHiQ6FI19YlWN7iWmq3YPh+oxQK3SVdM5eVzTsWwayPZk/cTe+V5cUAj1OTMmfExwqm/p0UFoYQT7cC7LNoX0nGLwidxgnrA9wUP11Olcx9ecB+AkhlB+gaVo5Bn6peSgvGC/1Mn+zKNEiJLiTpQFHilapIAmOGQJJVDjMsbZ6hR8dOsCePhzog+afBqxTbmdguHTWQMSZy92ALWJfexGQWaJK2xUV9xDopjixT63UoZ1Yu+8i9qBCyyVAfjEznQ+ptu0+Hk/wNXgcqpS91vX4mENShFIM2tMl0ixwQRILa7nouy5orAFekY1xFCabAnT2ORmlE1+6i2C0arYQ6lc8QHyCOs8Owsf8dfoQF3mBlAmu4y+ALRfkSuqRX/5EbrfQkRWOf1bRUYjKIa2nJ80uMwJYGykDEkanWY7Q3HlQwqXOhzLaM+zO9jCQizmCuE9/bn/W2pekrF97gZFzabBfwNTLaxh2fqZOJW3ePz07LaOTIGl3BQJAa47cIjljqGoLF+cxvUWSHJ/5mCPsi8CjycG5zfg/7LbsTZlTDbRAwJD6aOwf87bi6FxGWzXOSoJxga/RuSm3wCMMpjUoGfSu5EBP/CezTUNPcDmHvXCrDSYNkvLw+7Qke3Jfog6rjNda33mXLzJHQwoJ5xcFzBvroTrzDpTpXETkBxS8oJp/NFQWJh/6A0WDERr+PsZbEITVMFfCFYSfeUidToPfQOYWvqyNNtbMbHh/kfjrVdV54RWDDYCOsMEKlAd3aWjNKktNGZESIqEpDOsfzhv5PsYDqVT5pgSKacksKBqmYM4erwILbHPwty86qzYOiO0A/j2B1kbmN0kyxqG+Sy16KaL7zaTACzu68UT4odTU5Upqc+Og80Rz3nb5njBjw4/syvc4HA4TMvk7cKo2UaFIfEg2cGMwrUnyu8tJzJHahkQerk8Gkc/kMi3enzxbOdEyWEWY66xkFmAVI4bu8/0pOA1ozkmjrTmZr9jwFvmff5QVrJj5/FAI1yg1ncfNY4XLQl6ULBqMF7xw/DiXnW2Z3IirpHZVXD0e562nq/q7v8oY2T80V3sMiS2sG7iV2DZEr58AA2srAPIVSm09El0ZGCPhR3VpeotJyTv9+Nt7oC6xP7Bk8ouqwFHshl5lFWQmRSfqRYXPcuKBW3DJhb7yA0Ys7o2W7PmbJL3yBVLmeKzTcduTTfj131vIW8h7ou495n1wBexxU+f/fRpylAhb2p6mevVSXo3QHDZUxJ4HhQBuQSerNzGtt54v9dfYExJSxI2bykVWdLWCv9oyIpGRH0LeuSoV6wVLmwNJY7z5gTEkDVU0NvgJim6msSkkV6uAstZK8/DT7QtarUjDNP1MTMA/2CkN6rcO0+u703YCMRxt2vGsO7nzbQtXtH78dTwB3VvGy0/oarvQYMbYkrJaS9tnL0T1QZgdGOSqlfaiiNElXmj6pyfl2BFE2RTv8w0KwH7YJ+Lw2l1JdHqucVv/NBW94wK9/8g7Gkl01QV5jEARBA5BaIOv4oJ8CGRwyD6481+UgGWsnvayTXYu6gumltn7KTIyK84p2VBxOUlIjRIIlFDG6e6du6D45TDLmsknybsh87V09x9+LB9R3TrGGey9pWTQHDY70HeYoyXkwYWmpvJ55Jmp6u4PukFOh3ymNnvqG+zAH9vOAJyHeVwweA82R3ksaUzikE7yyMcaIg29nXR6engV/cGpBGwPhIO5sqJjlkytQ7LeK8x+JMjAQhcybRLEYlo3G74vJITIQK/Xz5khTs5R+sZkaUXaS0Yd8rpWDE0bB9osIptMPeMxPZRMvzQilZ/Q8YUXTh9KgDv8yNNylTH+lLO3MRVoqH34Ns3wGvjt3ZQcK4qsk90fNlELMKfO4TTfoJs6zynyxJnjnS1tg766mVXh5EC7cud6M48INDYf4U6CaSf2ZYe3ItDH+WPFcFFmbuvAxo7q4e5cS5fosbTkIcxWwAWjbvoVn2pY9BVS5dg7V8J08gj0HKX96ZIjyoOK6IgPpsucJNmYbQPJw/y5ObHIPJLtdKKTgjtZn3bwpjmlsgNIJWdWxiK524expaY0Ennj2vQsewtJZys3WU0K2spSs1kZzjCVEvs2OKs747IuGoGI8wot/TWdfu+HsyeLavTu0GCVTAPtqtrHr8I9DFx8yXZaSvDf555MlNDu1kNXw/5deNuLkFe/Zs/sjGizZ+fMQ5LN3Te+LeH/KgM8cbKhxeDw1LOMonndjLU9dGblAzRls1i2q4EkWch0gEopEsRLZ5M1sZzHG7OoewtmOmViG8+NdFlBVOSVpbAgMLpcQvPAcDgCkXoWkueypuNFgv1neNecKX0IUrpOVctxBLIJ37cHCR8BChW1dI2ZJeK8v5DNMEQCIQsUnU13kqYw+BZzgx7xquTRZW7/b7519SJbttvNJwUEzHjizpgF3KNRQeoWYqe286vp60TSME58R01bD2wGMBJgDazUhoqMhLAQ4c1SzVbAjzdEP/aHAfpehpiJfbKKB/qf3SaHx2tTbokxxI8GQ+4shJGJYoAdxHtIjyN4eevjr+vz/5QXoe2dJUjM+Rr4FRr8gMcGbbjMv854EqKuO3iXPvLlKbM4S68Bn3bCuhrrCSRStbnu4Pf9oURjKj4HJeO5xYidcWypkw/uLws+/D3yq74Sa8RkgwrVFZvMl06b71gQs5JUIDtV5H7MIqgrMDq+jtHW2KFBf3KILL0yeUkSYZJQ/FZvDMgVz4VMOGrpjtFUDqdgnnpO9BTcNZBYC7/BwG7xzGiq4/Kpyw7vZFmS5wu6BbM8fIr640UG1LZ9VkKsYDORsE9k7PPUbU6bP/hqfTjb8/iSaKiNxhQ2QiRIxT14fnQ9MrtaSFdt+ihqMtDiwDCkWHrm6pniuairpNspr8/tojgrj5P5b8KskhriXp5yt3U3CG4NPuXeHJlYt/hrd084NrniZz6Z5uKYIl+aBLHdXtmm+7IC9lB9WQlnxBdpJNqBDbj9QH2/iU7szplyQgSztyrVrS3qE37xgLN4j4Pi12/eIwKZJA9fSvvMe87+NIrRq/K4qgy90OabmTeFAFXcsRYOC6r8frlfM4fFJEys0PG53ZeaBMRdbQ5qgEzQ5j7TeTDha+YEDw7+P9Qc/7XPi7jWWUD+sZ3PMl33vYgne+O+PB1iYwtIOQ3S+XjYud19WGl+5OZOHI0nQAKTCfouq+Qpcy79A2uzsTObPn7spBD+v2Jzmoibwgrfm8efd71h1C0OvGUT706JUfoen1bBjiRMH7XQGhaa9d/wRIoycyJaTEKyyjzoncDmzvV+/SoeIs1l3iTn3h/t3z7apgkqEskliUv+P2MEgPVhKn0037LQYjWSiBoMNZTnQZT9YyJkKFIht4ZG2bB/+fx5TJde+IfLlPS6qtDj7jZ+tOUChtaC9CTY1Uc0Gl8Ah7lROseUrjXoEB/RDNIQpZi3zBZ7lKAqPrLgY63OM/v0pKoN6HJdU+pS8UomVd2klRHej0vsyLPcNMQmqgZQ4pfYf168IoYE4UANU0uMduUuPR81wTNC/GeNNKOrkN8hQrWdYkzT7u0iN/1+e8pEkDvUdqau+RKggKz3WNilCpMFNIRJqCZwCuPkJaTsFvcWAkayuTltold45y5ADIRFhrn6E8aaFGYN0zHG8UG959eWi+xesuMg+ATmbRJDWjJMTAN1PDW0AMYt9xYJshHnDNTl7NIIAZ+qppLmXEah/hDiohy7eQYyDuPnV3DamNCxNZYnpwPsxizhqi6WjPe02YGbti//27fHUSLXipmHRFtRLs8MCfsUfpDYdi7wQHSbm923QpGn+Gk43/quIFWy/vXRk+pUNHbcB+WIfYTBt5XoQ5lxOWHHpvXgRsNfRGwqVX19CV13A5hY6JtHvxepJ9fdS3edS4HuiE1XjFLETdzUYprG5JRdn0QbEO/W7DHST/1s8T2+wOukt1dMvsEq7C4jee4qKIKwKu6a1F3ZAQ3X4lV+oCTURMJ7LJYAmq3p+uDK9eYYfEGtjzCIr0GHMjyIw7ZkJoFL0FuKqTQReEp8PhtkkTPrHIHOrIzFIOtN0bfrEeFpvhDaMKgbPlh/1EJlcHQlXoies2QsExLXS4uEIIqjfa13PPvykNZmCvgrOrCKk9FHUyO2/XjkcTuESepWqldGDaj2LyilUffBDzDrJcvTOplOzB9rQ6rAdB6Rq15wY42tUc1k59KojeeOiivpOebt6xz4v0dxaXSdpy4fy74lCl6FSdnWudvrFjTZlQwuLy6jHdlRU72hOPOlQkf4OYCJtVwyGzzCvqC1mrYoo3IDzD3Li6wOVhfyyzku3hmMys+y2bbZrBA3+x725IuTWQNF4oDRYYnjcaki7UWBuhkoiHky8aqyYh+Ph80q0UsrIBgMohHAyrmFVsB5QF+0UuyjPKGUhxRQxbMNt3QEB5SAiETumSV8mzMH6iHyU6YIlkcQbt4xdfXuyTAV2ZsX31g1X4gNiNqyHq8OLvc8h7zmxQV9cSi2EuQABI/xxiI23ZVcfH18otzA3wA1WSh/zrv377y+NfgmL5ApgZk4XfuEdxEW5HPDssf8VlwQt4KdH5gI/qe59mAYsNzBztTm8BnCRlKNJ7jv2TdxszCtlBweBfV5rxpsfKpuSB5jH1Eh1989Cz0aVHdqmVbZxwC06eVUGsI6pa/1E6m+9RcJjYt2pEnxrd3CDdWJQAeV5iK6+kLkSqGQ9cmv0V8dRrvMpvapYnDIw3bY0HwarE084VdQ1g7U280/HntFWE+vBcMm3mhHXNdwEP/KzGc4K53CRLvz2Y0c5zVkWgtVWe39i5xmZtrudOhLioOmU9sFR2l++lBZsaG5EyVJtaEabNcNYz2Ka2T4EJc+/QYaaEh17TACOuvnC8Zg+Vjz3SFfNPSZwCzgPsMgRikbTRQjUYrmSOCGWE4siC1meMQTSfmB5fPU4jJww7eARnz4w7gcVIhXGUojhZfMiyuLAboFA5To1YsmnT3ADCwVhnhEvRm9emiKqhiv7Ew9rgKupLOICnw2JjDegG9ElBIYZJpdWLSTN/9/YMS3ZbNvQJa/gC9LxxIW96QfyR000xSYoL4Qt6GEQVby095pBpl8SQC4rM2EfrZLntlIHh/pwhlPCDktBbd2MXDIVSO4ooMQDVb+THbro6Tt8izJcW1NEMI6z0WgCWGqU62gTRHwMbhleUo71TdcIu/ivwYRV+iordXoIJhOc1hIhhbmHd6aVRNFp9mMNb9gtzM2uQae5/T4mdS5n0bvckN0URtZ2OYrF2qVnrqTcCAQ/94tD4F6J/V+sfCqttHQ6vkD8HlAy1NBu5vHp93hHQj4l0pH+nYKsu35OmHcEYwAEnrL5glrKF09BrjA0Oi2RCvo6z3XQl0VZWIoUDOAYE5xjiYR698wP7R1rGL1LnDnpr9JGe2ksWaVHRWk9FkTUG/0zhoDbxSFD1dWbyN3NsoR4tWsSB31Ztl3t5ih9VWmFGmf/UsxxYMzQNuBoX8fJHYPjLXSS/Kw/iyYkrwNLVZaCODDSXgZUgiRlobkm/62B2Q2D6neM4hGnQOYy6X0PBxjROkK8EMPgQTMGDZ/xkaBPfpMaw7zwliqwiA2Zo6t3nb4Veekw0nvZ5QVUhB69Sy0L4AdJDIc6ZyLM2M/JEU0x4mftWcadRd3JFa2j8wiuuJcyHEvqNQLuzOPBui27sRBAbECfVqUJoQZ9sfg4jtLRvyF14rK5E3BjXu9/mb4/45Jtc5/U2MwQgzCGAqIHy0am21qLaFkTjt51WaHXSM8rtYYYkUaxgmXyexUMsP6QXtOsBun21DKDuaYl3z9AIuvIX5+43LiAIZzvmtZJuf41KFfiEVj9CmcGNNt7fJhgzf0TSmz/hU9oZ1F1xESorI2ZtC0HjDjp6IiRy7Wl5x2mL8GJSE941LiMB4JIB45OMEvWTm88UJ89717vA85fMmZyNoDDckQC70xAxOSaBxZMwBy0l4s0fcRxufLInoqMSCvsHyV3oHKDtS3QUNlMn3MSHicK2oxKW830vS4iiArW96w0xvzpbKE1SgBvmZK6KjOuTYwfibHlNhmuVl7d+hOTtmE5sx3auw2kzHrllRHscw+Gy9JWxlnjugL8abjeOOYVR/GrqZmDcPSllyWGwUA2mKZae0YWKEM/RK50NRkN7EgKYdmykTgm1DZ2zXDc4hLwy4ozgok/bOZXXiI+9fnDZukO/xDhbhyLvQPjXN5G5mndETiPLGjGbv87scDLhg+bphpXByDmer7UgWpEEtsDSH8OrQGc6rORKDIpTeLXNEinscZvbiaVH9LdYvATIkpqqOtcozWAaw50mjaLH9WAFDZdxfzGvkjcZquCDCId1I+39LvQ3YleDWBRavIfPcbLjqrrVP1+WV0EFPhGFTJIHCSXELb5kcU0LHKh4qx0IW6LMNkgDsxKd7eO+3LxhlHyByPc6K22CYE/mCGCPkkCr+p9+1a5ykiQeXacR9nUWwo8vnkCTvcM8yKVRwOvJO3CjtYbKhHVCE+ut8Gh+fxKqD/cb0Wbd5eD28O9tHncn23j+xk27HtekbcrzK+q9CNgqQbCMXrE3Sd+NZJ4NZ3jIowxMuBs+F3PQoal4qeRIR/uwRyvNCdl3jLQVzbQkJ9Bms/lNtDbWL5mH5bUK1tvmt915vMOITysthk2rYjn+ItEiNmo0VJJn0Ey2s4oiKg8IcY51yF1g2Otjda+Y4P3gJfz9MwakoErbkL235ftWTnoWcn51KpXRUCOo9dY77Xj0Nc1uMPeeCQrllG2HUjl5i9DbA4Ab2MPTVJH1Wh7qz2GHj6sEqIdXcj7bI33RNyZMF1v5938Zsc2J0w89I/zL80JJDKN0LkE5d9hMmScT5cHJ+IpI+X6tLHuxLg/60aB0Nh/hQOWASv4BJO3ODTJVPH4bdOjCZ6Uqz0vDXtoGxh9krXlfDZ1012Wxb7qU4joh4hhatTbD0iRQemUPZ1f8XYgWxBKObcp0U41FuR55tXuV09eODlgbZFxafp9r4vo3IIvQvynTE6i4DS8lVWuPXeifJqg9kAeZwEStq+irnJJiWw8h7c968HDSh7cgtq0SURhHPZ/lM++KZzaVdVKm/2MXccRXzVWaTggC8dbFyDp6+EFco43/dqMd6Bljh1zneGp3JZYv5BCzdq2YwBVg1j9zDnZuKREbKmIAVz8YeyNQT0dQNHHbp9MJNDhjGLA4KTim6d7b9jYHE7W+Vk7fBCfS4QkgY94Px4a4mUFG6aXbk/uaBhgu0afKRHMY/mA4DCau02rc/nJled4dTTmnkqQ1fu35I9sguIL7fi4ydLGPEH1CJT5Wairbvrx1uS5ioFknZDJTO+VNZ/r28PAkM+Di+V8l58z1o7GTj3T+37LBKTEqyoh8e83aX9c4lgWdeFST/4VMQdxtvJCJAbyv4eY/+/MvJueYrI5Jpgr4ZRv/XrgAVE+FU0qaqpKlaABdQNY3F/i5zMZTjg+X8dsUqXQhbJW5zgthEQvmhvGuEw+FdFYZzJp5C0vkSVIpTcRlRpNXd/d8uQYc1/Q8O6GogoX7doSrgzAlIMVBJjdoF4WSdz2+EVNsduXnlvFcb1sOb5264ekAxAbwcMKGpXOhgzR/C7ZIXDjYUYowvH2WSqtd1w10MBzQcA/Gfk4Kks7lu/0YTMoPndpGpWBEohpSD5EfxIWIpBrIvDkOSEChQaF7lKR3K46kIYR4Xuk1FXdXTHGkSeVantXXs6t/YvWaYFqKrfaebKOD9Jo2nwS54zHXqtJC3Nm+UIsBNCOIOxVGVfq3r47mGprUwa96FXRdFdLwfwcXibOrozZDvZrvxEGuS+9OZ6+TEFAW1FGddmQ1UgB1ei3fIu+of2FRdth5WiUabpE9TwaoC9Xuu0mwTAfhj3rYvOVuC0Uby+ehmMG6j2meXHpmcIQ0P1+sZL5gcCFSXiktgsrRc8veuhHKCvvOTer5Kdu7ATPdwMYzYkOxo2jUKOXOszMuG7OEfnaDSrcK+4EJ1Ij81ZCgGNv6B3/3D7sdErwn2lc2xYH/O6VKpspij80V5TPz9mwwB6YH57USIfLuKdLjuAx2/Z1XH6DenxjbMUXf/SYh0qn/u0vz2eyyCVa4+Y+ZStZkYPq8CEmJSMMAXxjsaZWb58fA6C/MRGTfqIlkpGAJCIqfDuYaxMXcTJBHsEm4fEc5qtz9eHE1um/zrkUe4q8rINBFnpK4Jw0qcWNPzk4/lkplyhYRYy+wNzWeQaUdIdKswdMJwPc2AhFzkXBqI+Au1Z8J1FYxjr1MCzHhpvOogU+XNM6KOubQj7CEQUa4t0bulf4WZq2APSofww5+MTTACpY5qpjlIDbTJQuVlivzoVDQ3ErTQGTO52sTsZO0MhTOAgfM5fU0RpXdcW3+NsXfoYyvmhHbbHaEFjcT+3mcyv7ZXm4+Fe+6rIt5lgWJkmdmoXo8xgc8bguvOiVtCNUZoT/6wG7FTRJqtYvbmPVQiSQvspBMgLmR1tlJ/lXZSCnpx5sMqVHYjqT9fFO4HGWGWBwYbazDt/fE6dTifekGqhXRS/JcoS9QWZUTSckHSmMBsmNf/7o1RpBDpq+kbm713RkYhe3jNF6cDfKz++FZef98/lN4C7ImvYhnEGIZlwyhQgtvat/z9x8cFgcsyc6YshgCMEAErH0V4ijVP/XDlNrFuEp0XiQHG4uHlPEx4c7MEW6fKdWV1AlgPgioQGpEs1ANfq/w+DJGMgypDdWVj69bI+a53MOWp3AdF56GFuxiMLJDWDcGmDNSdNWKz9FTFMiQ8m+EAoWg8q1q0fs109W+TFlpe+A7KQ+8rxQPx92CdCMXaquF2InvYuN9DzO0y9Q+uve9I+uEN9s2gQOUeQHR9xg6RHoeWMEqTaWmzd/2X9MBHYFt1SYvvqOhTBsDD/xi1AkAyeUWXH3BRz7VlIZk+TPa6hYJSP85gsz7pUoJVSkt0wMYKQFU7UJiYPkLCbi+Kcw30yXUGxIQsBGj3a1x3SRHl90GagOG+r/MzRS9ha1/E5ETbazko80J9Hr6IoAgPtx8WGTEN0cXwvkTRBXZJpUAV2Qn412CUT36a8+Q8t60JRTp25AIlfIDCOacX3x6Qgmdv+U5aZuLBhdAZ74uNc0O7inT6uceNGS5ES0uDHb3i5Vpo3akbEch7srcA0TUudLH/AJL8/mTGGnVJ0Po6CmDRWT2XktxaQbyumxWk5OqjL8ra/lgeP84TM2gp4XgJpFIwT7WFSeeoMcwTjze8aYpKdjzXjBlffc0RLCelhUYCId3IuHr3wYQgLwoqGtbbycRj+/C450Sayhm83BO5zZPWFfG/up0VIvf/BESXZYAaHr9C4FgMud6fqupz1cC1VBCWVSsEYCPth9SRIu3mwNyUzbcZU+1+jNhnWyv36pNY8PIeaJjtqoBbej2tnjJcCV6Lou75M8cAa5ekFR6BplSSJFwMl8U+ygkJXyt5oWyIoiMoN+CYG9B+Ayb/Dqpkrh4D5Q32rfZ9m6hdnc9G8Wm1g2uboILwh9C1LCZBwbtpqIlsM4oMIdRDS7b+KrtHw7jedVopvQe9ZXGTS3eamAv+SeX/E9Zyj6pTrJJQ8x22zPv3afMQdYWeXNG4qaGoz5czKJHCSP2z07hFH9e8wYy6HPpuxSUS0sEP6yPlXMtynN8xLykr2PR9gKUB5AIDmsoHJOhTazXrRa61JW6LERFq0Gq4jHd8JDL11J0GBsbrVYUtvcmi0eIv/k5hik3GO3PMcfDf2rRY09EHa28+bQhIij+FdLrJjNdeKKLPtmbynWw8IB3ZYr93s9WKNx7f70XRno2igIZ5PyaiydFfTiz8Cc1KxXv7rW8sXXIRXTPIUDr8CKDUZFBs8hC4Tu58dPfOy1Ajh8MLHUtssopwBn8Dh5xBjqNz8DKolbx7Mvezmbj8llPBoxrUjrYzUWT+aRMrN87lXdtk2YHYNFzTp7e+s+Sfo9ICwPTcqXB2ycHuGD5q4fVfr6CO6yvXD0p/Ys9WcYkm92cg//Lh3zCUwo3QKDoa0nD1Im+Fqh3VgTlaALvoO7Z43yFlMA52EEUQDFSowNBYRDc0YNNBCp/wqw4pnAZ/hefo1LQESGonTuAGB9d/1GRzpGBD9/VcG2/Ews2H2uXzGWGZny6uGvRQH8Kiyeo/6AW2A6GTK44Jvf7HDpk22voH1LU0Enitwbcra0+qMUZnSuRJdIhKCBQLfnIkYRjvVKPys3IbRZ8qnSgqA3Z9tCtBK5VFTZVpA0kyeFU0WcQ2Y/s3wjgZs/9iyB41VDKXCOVoE//DPlFGk0jvYFnGLFPwMXAJNPRzeSDqiuNt4aUqBVLoQ4hLI8KYvJw9DSICRK1ZFjt78o/KL5sud47gRCNxU5LgcWp6bVg/6JI2lwt9409Y5hF8aeDYChta+/2RGBJLKSl4K8bGfnwec/cHwJdXTr/mSa0o8meC8kAnzZTy7GHfPJiIVmxPcRklsZ0pWcmFSS5Dkf6IJ+5fQm+aguU6Zv67T/C+DqMwdqbfdt63DoM+FRFB1GSIu8aU123getzr/WwDaQS3NfGMjz8CZrHwVed+9pcFNjXoXgteN9jyNWFgv6DSciv0g2Hj6Kfj3VweAdypKrSP5KG9TEOKwSN8ce61F7MKD9SmcSOAn988sYdcnq9hR2mbew6Kwnt0RHEEZ8gBYfEzJIFdTk50A6yRP4uYQMpwuHmfq73eqoIMMZhJuKqRN6SxQjg/mjMG4kTajNWDrqQ6P3mwgg3m8Qli+thGeF21i427wCGqdwbvOWQY7L+48RAV3ocedlRSyZUi+vVLUgXGxxPBioviVF+yEruQQW6Og5jUseABpA1/fJD90XbWw5thphD6eG96o8IdUvquHGOhD6I8MQUlJKQH9MyVUEJI3IrzIq83rwzbhLSbaZiU0AWJdY6xeR0LJJVOvFjYp8OtkHQZswdCZbBdTjvqkXBmQfMzrVFrky87FsyeKqemTbszgw2Z3IQw3dVZfnMxnePhhsYQ8d9YrqkJ9RAOEvqpyoLJ+bm2FTSoyEb78OkprnMKms2B8uzyc2JRT+zLc+eMxdAO+0Kq5h5BoMpNls/OKXeayMdoTWSY7whFCE8WXKlqDZXwgNpuSyG1p9sheOLS/W8t9Hj4A/87jtGFi443jJXiwytmcLgv06f80pN8oLCWE6bVpYkUZfgURwDbaI3pyiTmDYdalUwxrvH3S4XTGVCD/HKoXI0wk0bUiT4ylEJbOSE1Rjy3VFwHwxDfmvMydXhCN6KQKVSYaF3j2RaSOgOsWi0vk2Ny/AymWh9UugAGF569mSAE/p58XaIwJajjVT//w3jIu/i53IUYM0KRNYJ4SQBDyTGKmKffiA5gz+NI83TbXn7oH5Nccs4BqYOlSWudjCBSBK0HaiBfbYAyP9No051+VS2YN4pEXbf2qDUC8VOo8QsNlFl3Uei1x7EASJienGIbwe41aABsxY615o8pzZcCnmAI/42CHso+OOSAPIp7hJ8NBO4+FzGqt+hKwxDfjC8mYDYG3Tq/pEQT8sLpNjl0haqBgaVmY2cdGYOSZsAoXPQ6SjM+M3LVt5FMRqEX92eLZ6M5mQsRRE53wMDSaQZGZLkcmnwnV2SYqhyNRNqea3DjRfmQVcmIiBprDwh/e+mEHTAT5FnBBiclsVkrHIHxis9F6le/AfJmcuKNoL1kQyUlMtWmUkzq0homvQFO+KYs6fbDN0RDSuZDx1p8OVC55OQylTo0jG0G5kWRSxnwo0kSMjZJZrOeh7xB2PTLR+V1GBQorC5Qx5fPmH9xON1M5ogzpz7+DGvogD5TEi1wWV0qrIrTtEs6OMRblo9n3Ky6dt/d0brFzu3IE+QLvl0ESHMHR/S0Ocmz7fvOKNNOCPHBAKnwofAVUNjIZPD7nwIrM5ewWGSh10mARSElQqcZgmZa8Vx/iEnrUAdVSzsc+GAaez3AUJ8E6j8igG37SiFlcxU/EkK6YqAKOMhLhUh9Yn0y9j6mUT4znoeQkMFTMfYbKBORrbr2C4HZ3Q81a05iJn8cIPOg/+OeX+N6X1dbYahhhE8IaSmuJnWkRBnzjcPtcocXP6p1xzQljPA1INQgwT2wZTXMtpP+HbeKPSnpbo/VRzqGTMH1M/N7MmTXQPpDhqvR5GKdIBY/cnzdjB2Gv0smWSoM2DRxkcMWu9Elpfj2/FCB7kkeSNYvkbHtlljQrIqbSjYxHYTzS9QYilp6uChbCfqyCo2oKGUc1ztTQ1F3t74QAWggjjTRV2kmC0bes5P+fsestI2TCSwmRDm55hk5y1ogfKZSEXJB6whCb2pftR+eRM4ANas+P0jslK+md5o0K9+AbVuMq4CiYTYQOLDaoBLnk7/9lESKlA6UgKmdqEi6S0bc6qXqBy8GgMsk4loRL0pw4gizgjvlSsUbiyK501qhh0GipIluJD1vu8lOZa+26LkLZdZxuBh+mE/YOrCU6mcvaJriespoQ/2j42mri+/faHiEgoaE+1E5z0j3nveI7A60RDbmC1HMq/7djEsXR6aWGVwT6N+TcVGN/2ueTw47TyPf27I05VjrO7iEgZtp6p+vpe2w+imonMxwn2qGSbEqWmq4cGYGjxXg/UnKgemMsfRwNGoChQiLQlBADM89a2XEwnJSiCW+ZEATqqcrgp1IQjS3ulFCVdym+mAmsg1uwgOFLtu/S40b0M0i3fpocNctXcI4ox6W8ZHzsmLZxHd/OBfLxOZzzKv36NZLTzyiULr1Wa4juwhi
