Workbook

Sheet 049
A1: Projektname | B1: =IF(Projektinfo!B1="","",Projektinfo!B1) -> 049
A2: MwSt.
A3: Typ | B3: Ordnungszahl | C3: Kurztext | D3: Langtext | E3: Menge | F3: Einheit | G3: Einheitspreis | H3: Gesamtpreis | I3: Nachlass | J3: Preis nach Nachlass | K3: MwSt.
A4: Leistungsbeschreibung | C4: Trockenbau
A5: Hinweistext | C5: DECKBLATT | D5: Leistungsverzeichnis Anliegend übersenden wir Ihnen ein Leistungsverzeichnis mit der Bitte um ein Angebot ____________________________________________________________________ Bauvorhaben Umbau und Sanierung Jugendzentrum STEP Stepgesstraße 20 41061 Mönchengladbach Gewerk Trockenbau Auftraggeber Stadt Mönchengladbach, Der Oberbürgermeister GMMG Gebäudemanagement 41050 Mönchengladbach ____________________________________________________________________ Einzeltermine nach Bauzeitenplan 05.12.2025 | K5: ="" | M5: 958eedbb-a44d-4be5-896c-310f2905bf09
A6: Hinweistext | C6: Inhaltsverzeichnis | D6: Inhaltsverzeichnis A. 0 = Abkürzungsverzeichnis A. 1 = Baubeschreibung A. 2 = Vorbemerkungen zum Leistungsverzeichnis A. 3 = Allgemeine Technische Vorbemerkungen (ATV) A. 4 = Zusätzliche Technische Vertragsbedingungen (ZTV) A. 5 = Bauschild A. 6 = Allgemeine Hinweise zur Preisbildung A. 7 = Ausführungsunterlagen A. 8 = ZTV SiGeKo A. 9 = Materialökologie A. 10 = Zusätzliche allgemeine Technische Vorbemerkungen A. 11 = zusätzliche Technische Vorbemerkung A. 12 = Aufstellung beigelegter Anlagen A. 13 = ATV für Bauleistungen A. 14 = Hinweis Positionsbeschreibung Titel 00 = Technische Vorbemerkungen Titel 01 = Planung, Prüfung und Bemusterung Titel 02 = Baustelleneinrichtung Titel 03 = Kellergeschoss Titel 04 = Sockelgeschoss Titel 05 = Erdgeschoss Titel 06 = Obergeschoss Titel 07 = Dachgeschoss Titel 08 = Zusätzliche Ausführungen Titel 09 = Dokumentation Titel 10 = Stundenlohnarbeiten | K6: ="" | M6: c5d114a5-c90e-49de-af02-bba1d607bff8
A7: Hinweistext | C7: A.0 Abkürzungsverzeichnis | D7: A.0 Abkürzungsverzeichnis AG = Auftraggeber AN = Auftragnehmer ARC = Architekt ATV = Allgemeine Technische Vertragsbedingungen BE = Baustelleneinrichtung BG Bau = Berufsgenossenschaft der Bauwirtschaft DepV = Deponieverordnung DIN = Deutsche Industrienorm EfbV = Entsorgungsfachbetriebeverordn ung EG = Erdgeschoss ELT = Elektroinstallation HLS = Heizung-Lüftung-Sanitär LAGA = Länderarbeitsgemeinschaft Abfall LOG = Logistiker LV = Leistungsverzeichnis OÜ = Objektüberwachung des AG RTP = Rahmenterminplan SiGeKo = Sicherheits- und Gesundheitskoordinator TGA = Technische Gebäudeausstattung üNN = über Normal-Null (in m) UVV = Unfallverhütungsvorschriften VOB = Verdingungsordnung für Bauleistungen ZTV = Zusätzliche technische Vertragsbedingungen ZVB = Zusätzliche Vertragsbedingungen | K7: ="" | M7: 73580009-9348-4c39-88d6-fdbd27793e84
A8: Hinweistext | C8: A.1 Baubeschreibung | D8: A.1 Baubeschreibung Bauherr und Aufgabenstellung Das Gebäudemanagement der Stadtverwaltung Mönchengladbach - kurz gmmg - hat nach einem vorangegangenen VGV-Verfahren Planungsleistungen der Phasen 3 bis 9 auf der Grundlage der Vorplanung und der Machbarkeitsstudie beauftragt. Neben den baurechtlichen und technischen Anforderungen sind folgende Maßnahmen vorgesehen: Kellergeschoss Einrichtung des Jugend-Partizipations-Cafés im ehemaligen Lagerraum mit Küche, Theke, Lager, Bühne, W-LAN-Ecke, Garderobe und Schließfächern Abtrennung einer Werkstatt für den Hausmeister Sanierung und Erweiterung der WC-Anlagen inkl. Behinderten-WC neuer Entrée-Bereich mit Sauberlaufzone überdachter Treffpunkt mit Spiel und Sitzgelegenheiten Lagerfläche für Spielmobil Sockelgeschoss Neugestaltung des offenen Bereiches und Einbau von Prallschutzwandbelägen Hebelift für Rollstuhl und Umbau der Treppenpodest-Situation Sanierung der WCs (auch in der Hausmeisterwohnung) und Einbau eines Behinderten-WCs Sanierung der Kassettendecken Schachtwand für TGA Überdachung des Innenhofes (Spielbereich) Wiederherstellung der ursprünglich vorhandenen Treppenanlage (gespiegelt) Errichtung eines Außenaufzuges für die barrierefreie Erschließung des gesamten Gebäudes Montage einer Zaunanlage mit Zugangstüre Abbruch Betonquader und Gestaltung der Freiflächen mit Bodendecker und Hecken Erdgeschoss Erweiterung der Foyer-Fläche zum Aktionsraum, neue Eingangssituation mit Sauberlaufzone vorgelagerter Grünstreifen Einrichtung eines Kunst- und Aktionsraumes Hebelift für Rollstuhl und Umbau der Treppenpodest-Situation zur barrierefreien Erschließung der Bühnenfläche Errichtung des 2. Rettungsweges für UG und EG durch Erweiterung des Treppenraumes Sanierung (vollständiger Rückbau) der WCs und Einbau eines Behinderten-WCs mit Wickeltisch Ausbau und Vergrößerung der Küche (vollständiger Rückbau) Umstrukturierung des Cafés mit Theke unter Mitnutzung des Balkons Schachtwand für TGA Einbau einer neuen Türanlage zum Treppenhaus Sanierung der Kassettendecken Obergeschoss barrierefreie Erschließung der Etage über Aufzug Montage einer Boulder-Wand mit Prallschutz Sanierung von WCs und Umkleide, Einrichtung eines Behinderten-WCs Einbau einer neuen Türanlage zum Treppenhaus Schachtwand für TGA Reihenbestuhlung für Veranstaltungen Dachgeschoss Sanierung des WC-Bereiches Sanierung des Medienraumes einschl. Brandschutzverglasung zum Luftraum Einbau Aufenthaltsraum auf der Empore mit Balkon zum Luftraum Schachtwand für TGA Die Herrichtung eines neuen Aktions- und Kunstraumes sowie von Ausstellungsflächen im EG sollen zu einer einladenden Eingangssituation im Erdgeschoss führen und die Offenheit und Neuausrichtung der Einrichtung nach außen darstellen. Äußerlich werden Teile der Betonflächen und Klinkerfugen, Pflasterflächen und ein Balkon instandgesetzt. Ferner wird die Außentreppe ergänzt und ein Aufzug errichtet. Interim Für die Dauer der Umbau- und Sanierungsmaßnahmen wird die Einrichtung komplett freigezogen, das Leiter- und Schulungsbüro im EG soll als Lagermöglichkeit dienen. Haustechnische Maßnahmen dort wären vorzuziehen oder zuletzt auszuführen. Die Interimsräume befinden sich im Vitus-Center (ca. 613 m² im ebenerdigen EG). Die Flächen eignen sich aufgrund des bereits umfangreich ausgestatteten Zustandes gut für eine temporäre Nutzung. Raumteilungen sind nur im geringen Umfang erforderlich und sollen in Tischlerarbeit erfolgen. Eine Vorabstimmung mit der Bauaufsichtsbehörde hat bereits stattgefunden. Ein Antrag auf Nutzugsänderung ist rechtzeitig zu stellen. Inklusion Die Anforderungen an eine barrierefreie öffentliche Einrichtung sind im Bestand oft nur schwer normgerecht umzusetzen, da die baulichen Gegebenheiten aus der Entstehungszeit des Gebäudes allein schon den geometrischen Vorgaben nicht entsprechen können. Von Seiten der Inklusionsbeauftragten wurden folgende Anpassungen gefordert: Die Erschließung des Obergeschosses ist derzeit nicht barrierefrei möglich. Somit ist die Erstellung eines Aufzuges im Sockelgeschoss neben der ebenfalls wieder hergerichteten Außentreppe vorgesehen. Dieser bedient das Erd- und Obergeschoss. Das Keller- und Sockelgeschoss kann von Straßenniveau aus erreicht werden. Aufgrund der verschachtelten Geometrie und der Höhenversätze auch innerhalb der Geschosse sind bereits Rampen vorhanden, die eine Barrierefreiheit gewährleisten sollen. Die nachträglich installierte Rampe im Jugendcafé entspricht dabei nicht den maximalen Steigungsregeln und wird durch einen Hubaufzug ersetzt werden. Zur Überwindung der Höhenunterschiede an der Treppenanlage im Sockelgeschoss (offener Bereich) ist dies ebenfalls eine einwandfreie Lösung zur Herstellung der Barrierefreiheit. Der Zugang zur Bühne wird ebenfalls barrierefrei hergestellt. Die zur Deckenkonstruktion gehörenden Rampen aus der Errichtungszeit vor dem Eingang zum Sockelgeschoss und innerhalb des Erdgeschosses sind ebenfalls etwas zu steil. Eine bauliche Anpassung an heutige Normen ist wirtschaftlich nicht darstellbar. In jedem Geschoss ist nun die Einrichtung eines Behinderten-WCs vorgesehen, dabei kann im Obergeschoss die normgerechte Ausgestaltung der Bewegungsflächen und sonstigen Maßregeln aufgrund der erforderlichen Eingriffe in den Bestand (statische Belange) nicht hundertprozentig erfolgen. Die Umsetzung weiterer Maßnahmen zur Herstellung der Barrierefreiheit wie zum Beispiel die Installation taktiler Leitsysteme, Schaffung von Kontrasten, Ertüchtigungsmaßnahmen für leichtgängige Türen usw. müssen im Zuge der weiteren Planung konkretisiert werden. Dafür empfiehlt sich die Beauftragung eines entsprechenden Sachverständigen, der auch das erforderliche Barrierefrei-Konzept erstellen muss. Nach ausführlicher Planungs-Besprechung mit der Inklusionsbeauftragten werden generell die Möglichkeiten von Erleichterungen akzeptiert, um die Wirtschaftlichkeit der Maßnahmen nicht zu gefährden. Die Situation der Barrierefreiheit wird sich durch die geplanten Eingriffe deutlich verbessern. Architektur / Innenarchitektur Ausgangssituation (Bestand) Der 5-geschossige Gebäudekomplex wurde als Jugendzentrum bauaufsichtlich genehmigt und 1981 fertiggestellt. Durch die Hanglage wird der Klinkerbau auf unterschiedlichen Ebenen erschlossen. Das Kellergeschoss ist von der Stepgesstraße über den Parkplatz erreichbar, während das Erdgeschoss derzeit nur über den Fußweg im Hans- Jonas-Park erschlossen wird. Die ehemalige Treppenanlage an der Stepgesstraße wurde vor unbestimmter Zeit abgebrochen. Das Gebäude ist mit seiner verwinkelten Geometrie ein zeittypischer Kommunalbau, der vor allem durch seine innenräumliche Ausgestaltung überzeugt. Die Materialität und die Formensprache sind dabei Innen wie Außen konsequent identisch. Eingriffe / Urheberrechte Bezogen auf die Anforderungen, die derzeit an öffentliche Gebäude gestellt werden, besteht ein enormer Anpassungsbedarf. Mit den geplanten Eingriffen wird schonend und respektvoll mit der Substanz und dem Erhalt der Gesamterscheinung umgegangen. Notwendige Eingriffe werden als solche erkennbar sein und nicht dem Versuch unterliegen, das Gebäude unter heutigen Gesichtspunkten "fertig zu bauen". Einziger Schwerpunkt der Außengestaltung ist die geplante neue Erschließungstreppe inklusive des Aufzugsschachtes. Unter Einbeziehung der zu sanierenden Klinkerflächen an den Fluchtbalkonen soll ein der Umgebung farblich angepasster "Erschließungsknoten" entstehen, der den Besucher zukünftig mit seiner äußerst einladenden Geste in das Gebäude lenken soll, Orientierung bietet und charakteristisches Merkmal der Einrichtung werden kann. Atmosphären Die bisherige Nutzung des Gebäudes hat ihre Spuren hinterlassen. Es ist sehr schön zu erkennen, wie sich Nutzer und Besucher über die Jahre mit dem Bestand arrangierten und dabei fast liebevoll mit kreativem Reichtum und in Teilen vielleicht ungewollt einfallsreich improvisiert das Ihre zur Funktion beigetragen haben. Es ist erstrebenswert, die gewachsene Atmosphäre möglichst weitreichend zu erhalten und erforderliche Maßnahmen behutsam durchzuführen. Farben und Materialien Das Gebäude besteht aus den Farben des verwendeten Materials wie Klinker und Beton. Geplante Eingriffe sind in der Studie farbig dargestellt, um dem Anspruch einer klaren Abgrenzung von Alt und Neu gerecht zu werden. Dies bedeutet aber keineswegs eine Festlegung auf konkrete Töne und dient lediglich als Platzhalter. Innenausbau / Einrichtung Die Einrichtungsplanung (Qualitäten und Quantitäten) ist mit dem Nutzer abgestimmt und wurde in den wesentlichen Bereichen visualisiert. Holz- und Metallflächen sollen dominieren, das Jugendpartizipationscafé erhält einen industriellen Charakter mit robusten Materialien und Oberflächen. Brandschutz Der zweite Rettungsweg für das geplante Partizipationscafé im Kellergeschoss kann über die vorhandene Treppe ins Erdgeschoss geführt werden, wenn wie dargestellt der Treppenraum dort bis zur Fassade erweitert und mindestens feuerhemmend ausgebildet wird. Türen im Verlauf sind ebenfalls mindestens feuerhemmend sowie rauchdicht und selbstschließend nach DIN EN 13501-2 auszuführen. Der Medienraum im Obergeschoss kann mangels zweitem Rettungsweg nicht als Aufenthaltsraum genutzt werden. Die Verglasung zum Luftraum ist feuerhemmend nach DIN EN 13501-2 (E 30) zu verschließen. Für den geplanten Besprechungsraum auf der Empore ist ein zweiter Rettungsweg über das Fenster (mind. 0,90 x 1,20 m im Lichten) erforderlich und möglich. Da die Brüstungshöhe bezogen auf die darunterliegende Geländehöhe mehr als 8 m beträgt, muss mit dem Hubleiterwagen der Feuerwehr angeleitert werden. Es wird davon ausgegangen, dass entsprechende Aufstellflächen im öffentlichen Straßenbereich nachgewiesen werden können. Energieberatung / energetische Maßnahmen Künftig wird Wärme zu 75 % über Luft-Wasser-Wärmepumpen erzeugt, die restlichen 25 % über ein wasserstofffähiges Gasbrennwertgerät. Der nach Gebäudeenergiegesetz erforderliche Mindestanteil an erneuerbarer Energie (65 %) wird somit eingehalten. Eine Photovoltaik-Anlage mit rund 90 Modulen mit einer Leistung von etwa 40 kW peak wird auf dem bestehenden Dach installiert. Die Amortisation der Anlage wird mit rund achteinhalb Jahren angegeben. Die Autarkiequote soll bei rund 38 % liegen. Durch die Stromerzeugung wird eine CO²-Reduktion in Höhe von rund 12,4 Tonnen p.a. erwartet. Die gmmg hat eine CO²-Bilanzierung als Voraussetzung für eine IHEK-Förderung in Auftrag gegeben. Der Bericht der Energieberatung stellt die Energiebilanz im Ist-Zustand und nach geplanter Installation von Wärmepumpen und einer Photovoltaik-Anlage dar. Demnach können durch die geplanten Maßnahmen rechnerisch 31 % der Energie eingespart werden. Es ist geplant, möglichst zertifizierte Baustoffe zu verwenden, zum Beispiel Holz aus nachhaltiger Forstwirtschaft. Je nach Marktverfügbarkeit und Preislage werden auch recycelte Materialien wie zum Beispiel Fliesen verbaut. Zudem sollen recyclingfähige Materialien bevorzugt werden. Die Einrichtung soll in Teilen als Upcycling entstehen. So ist unter Beteiligung der Jugendlichen angedacht, ein Upcycling-Projekt für definierte Wandteilflächen auszuloben, für die unter Verwendung von nicht mehr benötigten Materialien eine gebrauchsfähige Funktionsfläche konstruiert werden soll. So kann zum Beispiel aus alten Holz- Weinkisten ein Wandregal entstehen, verzinkte Regalböden werden zur Pin- und Magnetwand und leere Flaschen erstrahlen als Leuchtkörper. Raumteiler aus Gabionen können als "Wechselausstellung" befüllt werden mit Sammlerstücken. Heizung Lüftung Sanitär MSR Heizung Die maroden Heizungsleitungen und Fußbodenheizungsverteiler werden saniert und die einzelnen Räume mit funkgesteuerten Raumthermostaten versehen. Durch den Einbau der Hebeliftanlagen und Aufstellen neuer Wände (evtl. in Klebetechnik) ist partiell ein Anpassen der Fußbodenheizung erforderlich. Im Erdgeschoss wird der gesamte Sanitär- und Küchenbereich entkernt und mitsamt Fußbodenheizung neu aufgebaut. Im Kellergeschoss frei unter der Decke verlegte Leitungen werden von der KMF-belasteten Wärmedämmung befreit und optisch ansprechend neu gedämmt. Lüftung / MSR Defekte und marode Lüftungsanlagen werden einschließlich der abgängigen Steuerung saniert und hocheffiziente Motoren eingebaut. Schadstoffhaltige Brandschutzklappen werden ausgetauscht. Die Anlagen zur Wärmerückgewinnung werden saniert und optimiert. Einzelne Anlagen in Verbindung mit der zukünftigen Nutzung des Jugendpartizipationscafés werden erneuert bzw. angepasst. Eine bedarfsgerechte Luftführung entsprechend der tatsächlichen Luftqualitäten wird hergestellt. Sanitär Aus hygienischen Gründen wird die gesamte Trinkwasserversorgung erneuert. Dabei wird auch die KMF-belastete Wärmedämmung ausgetauscht. Alle sanitären Einrichtungen werden erneuert. Erforderliche Installationen für die neu gestalteten Küchenbereiche werden nach Vorgabe des separaten Fachplaners ausgeführt. Die Ausstattung mit Geräten ist mit dem Nutzer abgestimmt. Ein rollstuhlgerechtes WC wird mit einem Wickeltisch ausgestattet. Elektrotechnik Aufbau einer PV-Anlage auf dem Dach mit einer Leistung von ca. 40 kW peak. Installation einer aufgeschalteten flächendeckenden Brandmeldeanlage gemäß Brandschutzkonzept. Herstellen einer Sicherheitsbeleuchtung und Kennzeichnung der Flucht- und Rettungswege gemäß Brandschutzkonzept. Erneuerung der gesamten Grund-Beleuchtung mittels LED-Lampen zum Teil als Lichtschienensystem für eine nutzerfreundliche da flexible Gestaltung der Ausleuchtungs-Szenerien. Zusätzlich atmosphärische Beleuchtung mittels Spots mit Direkt / Indirekt-Anteil und Pendelleuchten sowie LED-Stripes. Im Innenhof, im Treppenbereich und auf dem Balkon im Erd- und Obergeschoss sind Leuchten mit entsprechender Schutzart vorgesehen. Diese kommen auch im "offenen Umgang mit Kunst" zum Einsatz. Erneuerung der nicht mehr zulässigen Haupt- und Unterverteilungen sowie der Verkabelung mittels halogenfreier Leitungen. Aufbau einer strukturierten Verkabelung für ein flächendeckendes öffentliches WLAN-Netz im Gebäude. Aufbau der erforderlichen Installationen nach Angabe des Küchenplaners. Rückbau des kostenintensiven Notstromaggregates. Einbau einer Aufzugsanlage und Hebelifte für Rollstuhlfahrer zur Überwindung der "Split-Levels". Der vorhandene Lastenaufzug wird zurückgebaut. Für die erforderliche Veranstaltungstechnik im Jugendpartizipationscafé (KG) und im Veranstaltungssaal (EG) hat ein externer Fachplaner in Abstimmung mit dem Nutzer die Bedarfe geplant. Freianlagen Parallel zur Erstellung der Machbarkeitsstudie wurden die projektübergreifenden Planungen der Planergruppe Oberhausen hinsichtlich der Neugestaltung des Hans-Jonas-Parks fertig gestellt. Die formulierten Nutzungsanforderungen hinsichtlich der Ausgestaltung einer "Stadtoase" (Freiflächengestaltung und Spielgerät auf dem Grundstück des STEP) wurden dort planerisch wie auch kostenmäßig separat erfasst. Durch die vorliegende Planung ist der Freiraum neben der neuen Treppen- und Aufzugsanlage so gestaltet, dass keine unerwünschten und unkontrollierten Räume entstehen. Dies wird erreicht durch die Abtrennung des Bereiches zur Kontrolle des Zutritts und durch die unzugängliche Freiflächengestaltung mittels Bodendeckern und Hecken. Schadstoffe Eine orientierende Schadstoffuntersuchung hinsichtlich von Verdachtsfällen auf Asbest insbesondere im Subbereich von Putzen und Spachtelmassen, PCB, PAK und KMF hat mittels einer sachkundigen Begehung stattgefunden. Dabei wurden von verdächtigen Bausubstanzen Materialproben entnommen und im Labor auf den jeweiligen Schadstoffverdacht analysiert. Asbest - Bei der orientierenden Schadstoffuntersuchung wurde bei allen entnommenen Proben kein Asbest nachgewiesen. Asbestfundstellen sind die visuell eingestuften Dichtungsflansche und die Brandschutzklappen. Alle Arbeiten an asbesthaltigen Baustoffen müssen unter Berücksichtigung der Vorgaben aus der TRGS519 durchgeführt werden. Die Schutzmaßnahmen richten sich nach den durchzuführenden Arbeiten. Die Arbeiten an den asbesthaltigen Bauteilen dürfen nur durch fach- und sachkundige Firmen durchgeführt werden. Die personenbezogenen und die technischen Schutzmaßnahmen sind zwingend einzuhalten. KMF - Alle im Gebäude verbauten Mineralfasern werden als alte KMF eingestuft. Alle in Punkt 5 "Erkenntnisse zum Ortstermin" beschriebenen KMF-Fundstellen und alle nicht angesprochenen Fundstellen sind bei Eingriffen wie in Punkt 9 erläutert einzuordnen und zu behandeln. PCB - Bei der orientierenden Gebäudeuntersuchung wurden keine PCB-haltigen Materialien vorgefunden. PAK - Bei der orientierenden Gebäudeuntersuchung wurden keine PAK-haltigen Materialien vorgefunden. Caveat - Eventuell unerkannt vorliegende Altlasten Die mit dem Bericht beschriebenen Untersuchungen wurden sorgfältig und nach bestem Wissen und Gewissen durchgeführt. Naturgemäß können bei derartigen Begehungen aufgrund zum Teil mangelnder Demontage- und Zugangsmöglichkeit nicht immer alle schadstoffhaltigen Materialien erkannt werden. Treten bei ASI- Arbeiten bzw. bei Demontagen Zweifel an der Unbedenklichkeit bei zu demontierenden Teilen bzw. von Baustoffen auf, so sind die Arbeiten sofort einzustellen und die infrage stehenden Teile sachverständig nachträglich weiterführend zu begutachten. Im Gebäude sind zum Teil (SG und EG) Kassettendecken aus Stahlbeton vorhanden, deren quadratische Hohlräume ursprünglich vermutlich zur optischen Erhöhung der Räume dienten und teilweise Lampenauslässe enthalten. Teilweise sind nach Fertigstellung des Gebäudes Hohlräume mit eingelegten Heraklith-Platten und aufgelegter KMF eingebaut worden. Da sämtliche Elektroinstallationen erneuert werden müssen, Abhangdecken aber aufgrund der Reduktion der Raumhöhen ebenso wie eine auf-Putz-Installation nicht in Frage kommen, werden die Decken in den Ursprungszustand versetzt und mit abgehängten Lichtschienensystemen versehen. Ein Rückbau- und Entsorgungskonzept wird zur Ausführungsplanung durch einen Schadstoff-Sachverständigen erstellt. Arbeitsschutz Derzeit befindet sich im Kellergeschoss ein Wasch- und Putzraum sowie ein Aufenthaltsraum für das Reinigungspersonal (ca. 2 Personen). Ein Pausenraum ist gemäß den Arbeitsstättenrichtlinien erst ab 10 Beschäftigten erforderlich. Daher wurde in der Studie auf einen entsprechenden Nachweis verzichtet. Alle weiteren Mitarbeiter der Einrichtung werden in den Büros oder sonstigen Räumlichkeiten wie Café etc. pausieren. Zwecks Festlegung von erforderlichen Rettungswegbreiten und der Anwendbarkeit der Versammlungsstättenverordnung sowie zur Festlegung der Anzahl von erforderlichen Sanitäranlagen ist die geplante Anzahl von Personen in den jeweiligen Bereichen nach Absprache zwischen Bauherrin und Nutzer abgestimmt worden. Im weiteren Verlauf der Planung sind diese Annahmen laufend zu verifizieren. Die Möblierung und Ausstattung des STEP wird für die Baumaßnahme vollständig aus den zu bearbeitenden Räumen entfernt und eingelagert oder im Interim verwendet. Möglich ist die Einlagerung in Räumen der Einrichtung, die in der Vorplanung nicht farbig bzw. nicht grau hinterlegt sind. Unter Berücksichtigung eventueller Verkehrs- und Transportwege für die ausführenden Handwerker eignen sich dabei die an der Außenwand angeordneten Räume (v.a. KG 1.06 Übungsraum, SG 1.04 Werkraum, SG 1.03 Betreuung, SG 1.27-29 Spielgruppe und SG 1.31 Spielraum). Sollte in diesen Räumen aufgrund von Arbeiten an den Ver- und Entsorgungssträngen Maßnahmen erforderlich sein, können diese vor der Einlagerung zeitlich vorgezogen werden. Bezeichnung des Vorhabens: Umbau und Sanierung Jugendzentrum STEP, teilweise Errichtung und Nutzungsänderung Im Wesentlichen handelt es sich bei der eingereichten Genehmigungsplanung um folgende Maßnahmen: Untergeschoss Nutzungsänderung / Umbau: 01-KG-G0010 (derzeit ohne Nutzung) ist geplant als überdachter Treffpunkt mit Spiel und Sitzgelegenheiten 01-KG-00010 ist geplant als Jugendpartizipationscafé mit Küche (01-KG-00030), Theke, Lager (01-KG-00040), Bühne, Computerecke, Garderobe und Schließfächern (alle Räume derzeit Lagerraum) 01-KG-00050 (derzeit Lager) ist geplant als Hausmeister-Werkstatt 01-KG-00060 (derzeit Raum für Notstromaggregat) ist geplant als Raum für Elektrotechnik 01-KG-00080 (derzeit Instrumentenraum) ist geplant als Technikraum für die Lüftungsanlage und als Batteriespeicherraum für die neu geplante Photovoltaikanlage auf der Dachfläche Errichtung: 01-KG-F0010 (derzeit überdachter Außenraum) ist geplant als neuer Entrée-Bereich mit Sauberlaufzone 01-KG-00200, 01-KG-F0030, 01-KG-00160, 01-KG-00170, 01-KG-180, 01-KG-00190 sind geplant als Behinderten-WC, Flur, Waschräume und Toilettenräume (alle Räume derzeit überdachter Außenbereich) 01-KG-00230 (derzeit überdachter Außenbereich) ist geplant als Lager für das Spielmobil Sockelgeschoss Umbau: Neugestaltung des offenen Bereiches und Einbau von Prallschutzwandbelägen 01-SG-00060 Einbau eines Behinderten-WCs Installation Hebelift für Rollstuhl und Umbau der Treppenpodest-Situation 01-SG-00010 Einbau einer Schachtwand für TGA 01-SG-00150 (derzeit Abstellraum) ist geplant für Einbau der BMZ als neuer Standort (derzeit 01- EG-00010) Errichtung: Überdachung der Außenterrasse als Wetterschutz Wiederherstellung der ursprünglich vorhandenen Treppenanlage in das EG (gespiegelt) Errichtung eines Außenaufzuges für die barrierefreie Erschließung von SG bis OG Montage einer Zaunanlage mit Zugangstüre an der Treppenanlage Abbruch Betonquader und Gestaltung der Freiflächen mit Bodendecker und Hecken Sanierung: Sanierung der Sanitärräume (auch in der Hausmeisterwohnung) Sanierung der Kassettendecken nach Rückbau- und Entsorgungskonzept Erdgeschoss Umbau / Sanierung: 01-EG-00010 Vergrößerung der Aktions- und Kunstraumes Installation Hebelift für Rollstuhl und Umbau der Treppenpodeste zur barrierefreien Erschließung der Bühnenfläche Errichtung des 2. Rettungsweges für UG und EG durch Erweiterung des Treppenraumes Sanierung (vollständiger Rückbau) der WCs und Einbau eines Behinderten-WCs mit Wickeltisch Ausbau und Vergrößerung der Küche (vollständiger Rückbau) Umstrukturierung des Cafés mit Theke unter Mitnutzung des Balkons Einbau von Schachtwänden für die TGA Sanierung der Kassettendecken nach Rückbau- und Entsorgungskonzept 01-EG-TF010 Einbau einer neuen Türanlage zum Treppenhaus Errichtung: 01-EG-F0010 (derzeit überdachter Außenraum) ist geplant als Ausstellungs- und Foyer-Fläche Obergeschoss Umbau / Sanierung: 01-1O-00030 barrierefreie Erschließung der Etage über Aufzug 01-1O-00030 Montage einer Boulder-Wand mit Prallschutz Sanierung von WCs und Umkleide, Einrichtung eines Behinderten-WCs 01-1O-TF010 Einbau einer neuen Türanlage zum Treppenhaus Einbau von Schachtwand für TGA 01-1O-00030 Reihenbestuhlung für Veranstaltungen gemäß Bestuhlungspläne Dachgeschoss Nutzungsänderung / Errichtung: 01-EM-00040 (derzeit Balkon) ist geplant als abgetrennter Besprechungsraum mit Balkon Umbau / Sanierung: Sanierung des WC-Bereiches 01-EM-00010 Sanierung des Medienraumes einschl. Brandschutzverglasung zum Luftraum Einbau von Schachtwand für TGA Darüber hinaus sind im Wesentlichen die folgenden Maßnahmen geplant: Errichtung einer Photovoltaik-Anlage auf dem Dach der Einrichtung Aufstellung von Wärmepumpen im Außenbereich Erneuerung des Gasbrennwert-Heizkessels Erneuerung / Sanierung der elektrischen Anlagen über alle Geschosse Erneuerung der BMA und BMZ Erneuerung / Sanierung der Trinkwasserleitungen und Sanitärobjekte in allen Etagen Brandschutztechnische Sanierung gemäß Brandschutzkonzept über alle Geschosse Erneuerung bzw. Instandsetzung der RLT-Anlagen Stilllegung des Getränkeaufzuges von SG bis EG Leistungsumfang dieser Ausschreibung: Die GBA Gesellschaft für Bioanalytik mbH aus Mönchengladbach und die Z² Umwelttechnik GmbH aus Viersen haben Gebäudesubstanzuntersuchungen durchgeführt. Die folgenden Unterlagen liegen dieser Leistungsbeschreibung bei und sind gleichermaßen Vertragsbestandteil: Ausführungsplanung: Umbau und Sanierung STEP Mönchengladbach, M. = 1 : 50, Baumschlager Eberle Pagelhenn GmbH, Stand 14.11.2024. Gebäudeuntersuchung auf Schadstoffe, Objekt: Jugendzentrum Step, Stepgesstr. 20, Mönchengladbach, Bericht Nr. 20900282A. GBA Gesellschaft für Bioanalytik mbH, 23.03.2020. Schadstoffkataster, Stellungnahme zu den durchgeführten Gebäudesubstanzuntersuchungen. BVH: Mönchengladbach, Stepgesstraße - Jugendzentrum STEP. Projektnummer 2024-144.0, Z² Umwelttechnik GmbH, 28.02.2025. Wesentliche Aspekte der vorgesehenen Sanierungsmaßnahmen sind: Demontage einer asbesthaltigen Brandschutzklappe Demontage einer asbesthaltigen Abdichtung unterhalb des Estrichs im Bereich des Kellergeschosses Demontage von Asbestzementplatten an der Unterseite der Sitzbänke in der Kaminecke im Bereich des Erdgeschosses Demontage der KMF-Dämmung oberhalb der Heraklith-Deckenelemente, welche im gesamten Gebäude weit verbreitet sind. Diese sowie weitere, kleinere Demontage- und Teilabbruch-Maßnahmen sind unten sowie in den Planungsunterlagen der Baumschlager Eberle Pagelhenn GmbH detailliert aufgeführt. Alle Abfälle aus der Schadstoffsanierung und den Demontage- bzw. Teilrückbauarbeiten sind einer externen Verwertung / Beseitigung zuzuführen. Die Bereitstellung zur Entsorgung, Transportkosten, Kippgebühren und sonstige Neben- & Verwaltungskosten der Entsorgung sind in die u.g. Positionen einzupreisen. | K8: ="" | M8: 178c4929-6d08-41ba-b931-135f3f96162b
A9: Hinweistext | C9: A.2 Vorbemerkungen zum Leistungsverzeichniss | D9: A.2 Vorbemerkungen zum Leistungsverzeichniss Zusätzliche technische Vertragsbedingungen zur VOB, Teil C zu § 7 Abs. (1) - (3) VOB/A und Anhang TS gemäß Abs. 1 des Abschnitts 0 der ATV DIN 18299: Die folgenden Regelungen sind bei allen Titeln des Leistungsverzeichnisses zu beachten. Im Weiteren wird explizit auf die Ausführungen in der Leistungsbeschreibung hingewiesen. Soweit in der Leistungsbeschreibung auf technische Spezifikationen (z. B. nationale Normen, mit denen europäische Normen umgesetzt werden, europäische technische Zulassungen, gemeinsame technische Spezifikationen, internationale Normen) Bezug genommen wird, werden auch ohne den ausdrücklichen Zusatz: "oder gleichwertig", immer gleichwertige Technische Spezifikationen in Bezug genommen. | K9: ="" | M9: 3c728cc0-6051-42f1-a00d-81f43397fe14
A10: Hinweistext | C10: A.3 Allgemeine Technische Vorbemerkungen | D10: A.3 ATV Die laufende Nummerierung der nachfolgenden Punkte bezieht sich auf die Vorgaben der VOB/Teil C,DIN 18299. Nachstehend sind die Angaben für alle Gewerke aufgeführt Für die ausgeschriebenen Leistungen gelten die jeweils relevanten Aussagen A3.1Angaben zur Baustelle A3.1.1Lage der Baustelle, Umgebungsbedingungen, Zufahrtsmöglichkeiten und Beschaffenheit der Zufahrt sowie etwaige Einschränkungen bei ihrer Benutzung. wie Baustelleneinrichtungsplan (des AN) A3.1.2Besondere Belastungen aus Immissionen sowie besondere klimatische oder betrieblicheBedingungen. Keine A3.1.3Art und Lage der baulichen Anlagen, z. B. auch Anzahl und Höhe der Geschosse. siehe Baubeschreibung A3.1.4Verkehrsverhältnisse auf der Baustelle, insbesondere Verkehrsbeschränkungen. keine wesentlichen Einschränkungen A3.1.5Für den Verkehr freizuhaltende Flächen. PKW-Stellplätze können genutzt werden A3.1.6Art, Lage , Maße und Nutzbarkeit von Transporteinrichtungen und Transportwegen, z. B. Montageöffnungen. wie Baustelleneinrichtungsplan (des AN) A3.1.7Lage, Art, Anschlusswert und Bedingungen für das Überlassen von Anschlüssen für Wasser, Energie und Abwasser. wie Baustelleneinrichtungsplan (des AN) A3.1.8Lage und Ausmaß der dem Auftragnehmer für die Ausführung seiner Leistungen zur Benutzung oder Mitbenutzung überlassenen Flächen, Räume. wie Baustelleneinrichtungsplan (des AN) Im Bereich der Baustelle stehen Flächen zur Verfügung Die Zuweisung der Fläche erfolgt durch die AG-Bauleitung A3.1.9Bodenverhältnisse, Baugrund und seine Tragfähigkeit. Ergebnisse von Bodenuntersuchungen. nicht Bestandteil dieser Ausschreibung A3.1.10Hydrologische Werte von Grundwasser und Gewässern. Art, Lage, Abfluss, Abflussvermögen und Hochwasserverhältnisse von Vorflutern. Ergebnisse von Wasseranalysen. nicht Bestandteil dieser Ausschreibung A3.1.11Besondere umweltrechtliche Vorschriften. allgemeine und gesetzliche Anforderungen wie z.B. Lärmschutz sind einzuhalten A3.1.12Besondere Vorgaben für die Entsorgung, z. B. besondere Beschränkungen für die Beseitigung von Abwasser und Abfall. allgemeine und gesetzliche Anforderungen sind einzuhalten A3.1.13Schutzgebiete oder Schutzzeiten im Bereich der Baustelle, z. B. wegen Forderungen des Gewässer-, Boden-, Natur-, Landschafts- oder Immissionsschutzes; vorliegende Fachgutachten oder dergleichen. allgemeine und gesetzliche Anforderungen sind einzuhalten A3.1.14Art und Umfang des Schutzes von Bäumen, Pflanzenbeständen, Vegetationsflächen, Verkehrsflächen, Bauteilen, Bauwerken, Grenzsteinen und dergleichen im Bereich der Baustelle. Vegetationsflächen werden bauseits für den Baustellenbetrieb freigehalten (Vorbereitet) andere Vegetations-Bereiche sind nach BE-Plan des AN zu schützen A3.1.15Im Bereich der Baustelle vorhandene Anlagen, insbesondere Abwasser- und Versorgungsleitungen. Siehe Lageplan zum Bestand im Rahmen der Baustelleneinrichtungsplanung des AN A3.1.16Bekannte oder vermutete Hindernisse im Bereich der Baustelle, z. B. Leitungen, Kabel, Dräne, Kanäle, Bauwerksreste und, soweit bekannt, deren Eigentümer. siehe Ausführungsplanung Bestand TGA A3.1.17Bestätigung, dass die im jeweiligen Bundesland geltenden Anforderungen zu Erkundungs- und gegebenenfalls Räumungsmaßnahmen hinsichtlich Kampfmitteln erfüllt wurden. nicht Bestandteil dieser Ausschreibung A3.1.18Ggf. gemäß der Baustellenverordnung getroffene Maßnahmen. keine A3.1.19Besondere Anordnungen, Vorschriften und Maßnahmen der Eigentümer (oder der anderen Weisungsberechtigten) von Leitungen, Kabeln, Dränen, Kanälen, Straßen, Wegen, Gewässern, Gleisen, Zäunen und dergleichen im Bereich der Baustelle. keine A3.1.20Art und Umfang von Schadstoffbelastungen, z. B. des Bodens, der Gewässer, der Luft, der Stoffe und Bauteile; vorliegende Fachgutachten oder dergleichen. nicht Bestandteil dieser Ausschreibung A3.1.21 Art und Zeit der vom Auftraggeber veranlassten Vorarbeiten. keine A3.1.22 Arbeiten anderer Unternehmer auf der Baustelle. Gewerk TGA (ELT, Klima und Lüftung) Gewerk Rohbau A3.2 Angaben zur Ausführung A3.2.1 Vorgesehene Arbeitsabschnitte, Arbeitsunterbrechungen und Arbeitsbeschränkungen nach Art, Ort und Zeit sowie Abhängigkeit von Leistungen anderer. siehe Leistungsbeschreibung A3.2.2Besondere Erschwernisse während der Ausführung, z.B. Arbeiten in Räumen, in denen derBetrieb weiterläuft, Arbeiten im Bereich von Verkehrswegen, oder bei außergewöhnlichenäußeren Einflüssen. s. Leistungsbeschreibungen A3.2.3Besondere Anforderungen für Arbeiten für Arbeiten in kontaminierten Bereichen, ggf.besondere Anordnungen für Schutz- und Sicherheitsmaßnahmen. s. Leistungsbeschreibungen A3.2.4Besondere Anforderungen an die Baustelleneinrichtung und Entsorgungseinrichtungen,z.B. Behälter für die getrennte Erfassung. s. Leistungsbeschreibungen A3.2.5Besonderheiten der Regelung und Sicherung des Verkehrs, ggf. auch, wieweit der Auftraggeber die Durchführung der erforderlichen Maßnahmen übernimmt. im Rahmen der Baustelleneinrichtung A3.2.6Besondere Anforderungen an das Auf- und Abbauen sowie Vorhalten von Gerüsten. s. Leistungsbeschreibungen A3.2.7Mitbenutzung fremder Gerüste, Hebezeuge, Aufzüge, Aufenthalts- und Lagerräume, Einrichtungen und dergleichen durch den Auftragnehmer. s. Leistungsbeschreibungen A3.2.8Wie lange, für welche Arbeiten und ggf. für welche Beanspruchung der Auftragnehmer Gerüste, Hebezeuge, Aufzüge, Aufenthalts- und Lagerräume, Einrichtungen und dgl. für andere Unternehmer vorzuhalten hat. s. Leistungsbeschreibungen A3.2.9Verwendung oder Mitverwendung von wiederaufbereiteten (Recycling-) Stoffen. Siehe Leistungspositionen A3.2.10Anforderungen an wiederaufbereitete (Recycling-)Stoffe und an nicht genormte Stoffe und Bauteile. Siehe Leistungspositionen A3.2.11Besondere Anforderungen an Art, Güte und Umweltverträglichkeit der Stoffe und Bauteile, auch z. B. an die schnelle biologische Abbaubarkeit von Hilfsstoffen. Siehe Leistungspositionen A3.2.12Art und Umfang der vom Auftraggeber verlangten Eignungs- und Gütenachweise. Siehe Leistungspositionen A3.2.13Unter welchen Bedingungen auf der Baustelle gewonnene Baustoffe verwendet werden dürfen oder müssen oder einer anderen Verwertung zuzuführen sind. nicht Bestandteil dieser Ausschreibung A3.2.14Art, Zusammensetzung und Menge der aus dem Bereich des Auftraggebers zu entsorgenden Böden, Stoffe und Bauteile; Art der Verwertung bzw. bei Abfall die Entsorgungsanlage; Anforderungen an die Nachweise über Transporte, Entsorgung und die vom Auftraggeber zu tragenden Entsorgungskosten. nicht Bestandteil dieser Ausschreibung A3.2.15Art, Anzahl, Menge oder Masse der Stoffe und Bauteile, die vom Auftraggeber beigestellt werden sowie Art, genaue Bezeichnung des Ortes und Zeit ihrer Übergabe. nicht Bestandteil dieser Ausschreibung A3.2.16In welchen Umfang der Auftraggeber Abladen, Lagern und Transport von Stoffen und Bauteilen übernimmt oder dafür dem Auftragnehmer Geräte oder Arbeitskräfte zur Verfügung stellt. Auftrag und Aufgabe des AN der AG übernimmt keine Transporte A3.2.17Leistungen für andere Unternehmer. Siehe Leistungspositionen A3.2.18Mitwirken beim Einstellen von Anlageteilen und bei der Inbetriebnahme von Anlagen im Zusammenwirken mit anderen Beteiligten, z.B. mit dem Auftragnehmer für die Gebäudeautomation. Siehe Leistungspositionen A3.2.19Benutzung von Teilen der Leistung vor der Abnahme. Siehe Leistungspositionen A3.2.20Übertragung der Wartung während der Dauer der Verjährungsfrist für die Mängelbeseitgungsansprüche für maschinelle und elektrotechnische / elektronische Anlagen oder Teile davon, bei denen die Wartung Einfluss auf die Sicherheit und die Funktionsfähigkeit hat (vergleiche § 13 Nr. 4 Abs. 2 VOB/B), durch einen besonderen Wartungsvertrag. Siehe Leistungspositionen A3.2.21Abrechnung nach bestimmten Zeichnungen oder Tabellen. gemäß VOB Teil C DIN 18299 Kapitel 5 | K10: ="" | M10: 749b552c-951e-434e-80fe-876f6b3741c7
A11: Hinweistext | C11: A.4 Zusätzliche Technische Vertragsbedingungen | D11: A.4 Zusätzliche Technische Vertragsbedingungen Zusätzliche Technische Vertragsbedingungen unter Berücksichtigung projektspezifischer Anforderungen 1. Allgemeine Hinweise: Für nachfolgend beschriebene Leistungen gelten die Verarbeitungsvorgaben und Einbauanweisungen der Hersteller für die eingesetzten Baustoffe, -elemente und -produkte, die Publikationen der im jeweiligen Fachbereich allgemein anerkannten Verbände und der sonstigen Herausgeber von Richtlinien, Merkblättern, Empfehlungen etc. in der zum Zeitpunkt der Ausführung gültigen Fassung als vereinbart. Im Fall von Widersprüchen gilt die weiterreichende bzw. qualitativ höherwertige Anforderung als vereinbart. Alle für ein Bauteil oder Bauelement erforderlichen Bestandteile sind aus dem System eines Materialherstellers zu beziehen und als durchgängige Produktlinien anzubieten. Alle Bauteile ähnlicher Art und Lage müssen aufeinander abgestimmte Oberflächen, Farbtöne, Falzgeometrien, Kantenausbildungen, Beschläge etc. aufweisen, um eine gestalterische Durchgängigkeit zu gewährleisten. 2 Baustelleneinrichtung 2.1 Lager- und Arbeitsflächen, Aufenthaltscontainer In diesem konkretisierten Baustelleneinrichtungsplan sind die Stellflächen für die AN-seitig gestellten Container und sonstigen Baustelleneinrichtungsteile eingetragen. Das Anlegen oder der Rückbau weiterer im Zuge der Bauausführung für den AN notwendigen befestigten Flächen für Krane, Stellplätze und Anderes, sind nach Rücksprache mit der Bauüberwachung des AG auszuführen. Nach Beendigung der Baumaßnahme hat der Auftragnehmer dem Auftraggeber diese Flächen im Urzustand wieder herzustellen und in einem ordnungsgemäßen Zustand zu übergeben, außer das LV sieht eine diesbezüglich beschriebene Bearbeitung der Flächen vor. Etwaige verbliebene Verunreinigungen werden unter den Voraussetzungen der VOB/B und des BGB gegen Inkostenstellung gegenüber dem Auftragnehmer durch den Auftraggeber beseitigt. Die abschließende Zuweisung der Stellflächen erfolgt nach Anmeldung des Platzbedarfs durch die örtliche Bauleitung des AN in Abstimmung mit dem AG und der Bauüberwachung des AG. Dies gilt auch für die Nutzung von Lagerflächen. Der AG behält sich vor, diese Flächen auch durch andere Gewerke bis zur Erstellung der Außenanlagen zu nutzen. Die Baustelle darf nur für Waren-, Baustoff- und Bauteiltransporte mit Lieferfahrzeugen befahren werden. Das Befahren der Baustelle darf nur über die hierfür gekennzeichneten Zufahrten erfolgen, die anderen Straßen sind vom Baustellenverkehr weitestgehend freizuhalten. Das Ab-, Auf- und Umladen von Waren, Baustoffen und Bauteilen muss an den hierfür vorgesehenen Positionen auf der Baustelle erfolgen. Verkehrs- und Rettungswege auf der Baustelle sind freizuhalten. Die im Baustelleneinrichtungsplan als Feuerwehrzufahrten markierten Flächen zu den Bestandsgebäuden müssen auch während der Bauphase freigehalten werden. Das unmittelbare Baufeld besitzt während der Bauphase keine Flächen für Stellplätze, LKW sind sofort zu entladen und zeitnah aus dem Baufeld abzufahren. 2.2 Zusätzlicher Flächenbedarf für die Baustelleneinrichtung Nicht erforderlich. 2.3 Wiederherstellung Baustelleneinrichtungsfläche Der AN hat nach Beräumung die Baustelleneinrichtungsfläche wieder in den vorgefundenen Zustand zu versetzen. Leitungen, Materialien, Transporthilfen, Abfall und Fundamente des AN sind zu entfernen. 2.4 Anschlüsse für die Baustelleneinrichtung Der AG stellt dem AN bereits am Baugrundstück vorhandene Anschlüsse kostenfrei zur Verfügung. Sind keine Anschlüsse vorhanden oder reichen deren Kapazitäten für den Baustellenbetrieb des AN nicht aus, so versorgt sich der AN im Rahmen seiner Leistungen eigenständig mit allen erforderlichen Medien, Anschlüssen und Verteilungen. Die Anschlüsse für Medien (Strom- und Wasserversorgung, Abwasserentsorgung) sind bauseits vorhanden und können für die Baustelleneinrichtung und für den Bauablauf genutzt werden. Die Dimensionen dieser Anschlüsse sind für reguläre Nutzungen ausreichend. 2.5 Erscheinungsbild Der AG legt großen Wert auf ein sauberes und geordnetes Erscheinungsbild der Baustelle und der Baustelleneinrichtung. Alle großflächigen oder -formatigen Bestandteile der Baustelleneinrichtung des AN sind in sauberem, ordentlichem, neuwertigem Zustand an der Baustelle aufzubauen. Dies betrifft insbesondere Container, Gerüste und Bauzäune. Fahrzeuge des AN dürfen nur zu Anliefungszwecken kurzzeitig im Baufeld stehen. Das Parken im Baufeld oder dem Schulgelände ist ausdrücklich verboten. 2.6 Feuerwehrzufahrten/Fluchtwege Die Feuerwehrzufahrts- und erforderlichenfalls Umfahrmöglichkeit ist vom AN über die gesamte Dauer der Bauzeit zu gewährleisten. Ebenfalls freizuhalten sind alle Flucht-/Rettungswege im und aus dem Gebäude. 2.7 Arbeitsgeräte und -gerüste Die Wahl der zum Einsatz kommenden Geräte obliegt dem AN. Er hat sich jedoch an die geltenden Richtlinien und Bestimmungen zu halten. Hilfskonstruktionen und Abstützungen sind, soweit sie nicht ausdrücklich ausgewiesen sind, in die EP einzukalkulieren. 2.8 Sicherungs- und Schutzmaßnahmen Der AN schützt die übrigen Bauausführenden vor allen aus seinen Tätigkeiten herrührenden Gefahren durch (Absturz-)Sicherungen, Abschrankungen, Markierungen etc. Die vom AN diesbezüglich auszuführenden Leistungen verstehen sich einschließlich Aufbau, Vorhaltung, Unterhalt, regelmäßiger Kontrolle und Instandsetzung sowie Rückbau nach Beseitigung der Gefahr bzw. nach Aufforderung durch den AG. Die Absturzsicherungen sind durch die Gewerke im Bauablauf nach montagebedingten Demontagen unverzüglich wieder herzustellen. 2.9 Bauzwischen- und Montagezustände Alle für den AN zum Angebotsabgabezeitpunkt erkennbaren Leistungen für Provisorien, Bauzwischenzustände und Montagezustande, die er zur Erbringung seiner Leistungen benötigt, sind Bestandteil der Leistungen des AN. Hierzu zählen neben Hilfsmitteln und -gerüsten auch Verstärkungen und Dimensionierungen von Bauteilen für Belastungen während des Transports oder der Montage. 3. Vorleistungen des AG Der AN erhält zur Ausführung seiner Leistungen Pläne gem. Anlagenverzeichnis als Download im PDF-Format. Papierausgaben werden nicht zur Verfügung gestellt. Dem AN obliegt jegliche über die den Vergabeunterlagen beigefügten Planungen und Berechnungen hinausgehende Leistung in nachfolgend beschriebenem Umfang. Mögliche produktionstechnische Änderungen sind vom Auftragnehmer zu planen und mit dem Auftraggeber abzustimmen. Der AN fertigt vor Ausführung seiner Arbeiten zunächst eine Planlieferliste und einen Planungsablaufplan und sodann mittels CAD eine prüfbare Werkstatt- und Montageplanung/ Zeichnungen an, die die zu erbringenden Leistungen insbesondere in Bezug auf folgende Inhalte umfänglich darstellen: Baustelleneinrichtungsplan Rückbaukonzept Terminplan (mit Fortschreibungen) Für die Gerüstbauarbeiten erstellt der AN eine prüffähige Ausführungsstatik und einen Ankerplan (Befestigungen in der Fassade) sowie ein Konzept für das Verschließen von Öffnungen der Anker (nach Demontage). Die Werk- und Montageplanung der tragenden Bauteile ist abschnittsweise dem Prüfingenieur zur Prüfung und dem Tragwerksplaner zur Sichtung vorzulegen. Entsprechende Vorlauffristen zur Produktion sind einzukalkulieren. Der AN ist für die korrekte Dimensionierung der Bauteile allein verantwortlich. Eventuell vom AG in den Ausschreibungsunterlagen oder Plänen getätigte Bemessungen oder Querschnittsangaben verstehen sich nur als Kalkulationshilfe und sind vom AN alleinverantwortlich zu verifizieren. Die Anfertigungen werden im Format PDF an den AG durch Upload in den Internet-Projektraum zur Sichtung übergeben. Mit den Dokumenten sind dem AG die bauaufsichtlichen Prüfzeugnisse und -zulassungen aller Produkte, die solche Zulassungen benötigen, zu übergeben. Nach Abschluss der Arbeiten sind die Revisionsunterlagen, Revisionspläne bzw. -zeichnungen/Skizzen im PDF-Format an den AG zu übergeben. Der AN erstellt örtliche Aufmaße als Grundlage seiner Planungen, Bestellungen, Fertigungen und Montagen. Der AG behält sich vor, jegliche vom AN erstellte Planung innerhalb von 10 Werktagen nach Zugang zu sichten und Prüfanmerkungen in der Planung des AN zu tätigen. Der AN ist verpflichtet, die Prüfanmerkungen des AG innerhalb von 5 Werktagen in seine Planung einzuarbeiten. Der AN erstellt seine Planung daher so frühzeitig, dass er eventuelle Prüfanmerkungen des AG rechtzeitig vor Materialdisposition und Ausführungsbeginn noch in seine Planungen einarbeiten kann. Soweit der AN der Auffassung ist, dass die Umsetzung der Prüfanmerkungen des AG nicht seinem vertraglich geschuldeten Leistungssoll entspricht oder Bedenken gegen den Planungswillen des AG sprechen, zeigt der AN dem AG dies innerhalb von 5 Werktagen nach Zugang der Prüfanmerkungen schriftlich an. Eine freigegebene Planung (Konzept etc.) entbindet den AN aber nicht von seiner eigenen Prüfungs- und Hinweispflicht und von seiner Verantwortung. Diese bleibt unberührt. 4 Prüfungen, Abnahmen, Gebühren 4.1 Prüfungen und Abnahmen Der AN veranlasst und koordiniert sämtliche noch nicht erfolgten bzw. noch ausstehenden behördlich oder öffentlich-rechtlich geforderten Nachweise, Prüfungen und Abnahmen für die von ihm erbrachten Bauleistungen. Alle hierbei entstehenden Aufwendungen für Prüfgebühren, Prüfkörper, Laborversuche etc. sind vom AN zu tragen. Der AN ist für die Rechtzeitigkeit der Veranlassung der Prüfungen verantwortlich. 4.2 Zustimmungen im Einzelfall (ZiE) Der AN verwendet ausschließlich bauaufsichtlich zugelassene (ABZ) oder bauaufsichtlich geprüfte (ABP) Baustoffe und -elemente oder solche mit CE-Konformitätserklärung des Herstellers. Sind solche Baustoffe oder -elemente in Ausnahmefällen nicht verfügbar, so ist der AN für den Nachweis der Rechtmäßigkeit der Ausführung verantwortlich. Soweit hierfür eine Zustimmung im Einzelfall (ZiE) erforderlich ist, besorgt der AN diese. In diesem Fall ist es Sache des AN, die ZiE terminlich zu koordinieren und alle entstehenden Kosten und Gebühren für Versuche, Berechnungen, Gutachten, Prüfungen/Versuche und Genehmigungen zu tragen. 5 Dokumentation Der AN erstellt als Fortschreibung der Planung in Bezug auf alle vom AN tatsächlich ausgeführten Leistungen eine Dokumentation. Der AN übergibt unaufgefordert vor Montagebeginn Quellennachweise der eingebauten Produkte (Lieferscheine, Produktdatenblätter etc.) an den AG, gegliedert nach Verwendungszweck bzw. -ort, Fabrikat, Hersteller und Chargennummer wegen eventueller Nachbestellungen. Die Herkunft (z. B. von Steinen, Ziegeln etc.) ist auf Verlangen nachzuweisen. Der AN übergibt dem AG unaufgefordert vor Inbetriebnahme seiner Werkleistung (z. B. Mauerwerke, Betonbauteile etc.). Der AN übergibt dem AG im Rahmen der Dokumentation alle erforderlichen Übereinstimmungsnachweise für Bauprodukte und Bauarten. 6 Sauberhaltung, Reinigung Der AN hat für Ordnung und Sauberkeit auf der Baustelle und im Gebäude zu sorgen und seine Arbeitskräfte in diesem Sinne besonders zu ermahnen. Er richtet seine Arbeiten so ein, dass keine Verschmutzung eintritt, die die im Rahmen der Leistungserbringung für gewöhnlich zu erwartende Verschmutzung übersteigt, und die Leistungen anderer nicht beschädigt oder zerstört werden. Er kalkuliert alle Aufwendungen in seine Preise ein, die für die regelmäßige und ausreichende Reinigung sowie fachgerechte Abfallbeseitigung (Entsorgung) aus seinen Leistungen, wie z. B. Beseitigung von Verpackungsgut, Sondermüll usw. entstehen. Der im gesamten Baustellenbereich vom AN verursachte Schutt und Abfall ist sortenrein zu sammeln und umgehend (arbeitstäglich) abzufahren. Der AN wird am Ende jedes Arbeitstages seinen Arbeitsbereich in besenreinen Zustand versetzen. Bau- und Hilfsmaterialien wie z.B. Schalung, Rohre und dergl. sind jederzeit in sauber gestapelten Gebinden auf der Baustelle zu lagern und unverzüglich nach Ende des Einsatzes wieder abzufahren. Das Baufeld ist jederzeit von ungenutzt herumliegenden Baumaterialien und Schmutz freizuhalten. Verschmutzungen auf Zufahrtstraßen und Wegen sind durch den AN unverzüglich, bei Schlämmen etc. mindestens werktäglich zu entfernen. Alle evtl. erstellten Bauhilfsmaßnahmen für die Baustelleneinrichtung müssen am Ende der Bauzeit, nach Rücksprache mit dem AG zu Beginn der Arbeiten an den Außenanlagen beseitigt werden. Materialabfälle, Schutt u. Ä. dürfen in keinem Fall in die Kanalisation gelangen oder im Erdreich verbleiben. Zur Einlagerung von Materialien, die noch zum Einbau vorgesehen sind, werden ggf. auch innerhalb der Gebäudefläche den Gewerken Flächen zugewiesen. 7 Bauausführung/Leistungsumfang 7.1 Schnittstellen Jegliche Bauleistungen, -stoffe und -elemente des AN, die als Vorleistung oder Einbausituation für Leistungen anderer (Nach-) Unternehmer dienen, sind rechtzeitig vor Ausführung in Bezug auf die Herstellung der zugelassenen Einbaubedingungen vom AN zu prüfen. Soweit der AN Leistungen erbringt, an die erkennbar Leistungen anderer (Nach-) Unternehmer angearbeitet werden sollen und die hierfür nicht geeignet sind, trägt der AN unter den Voraussetzungen der VOB/B und des BGB die Aufwendungen zur - auch nachträglichen - Herstellung der zulassungskonformen Einbaubedingungen. 7.2 Vorleistungen Soweit Vorleistungen zur beschriebenen Leistung angegeben sind, gelten diese als bauseitige Schnittstelle zur zu erbringenden Leistung des AN. 7.3 Anpassungen Der AN erbringt sämtliche Anpassungen für Schräganschnitte, schiefwinklige Ausführungen, nicht rechtwinklige Konstruktionen usw. als Bestandteil seiner Leistung, soweit diese aus den Ausschreibungsunterlagen erkennbar sind oder solche Leistungen in der Beschreibung erwähnt werden. Gleichfalls sind sämtliche Bestandskonstruktionen, auch solche mit unregelmäßigem Verlauf, anzuarbeiten. 7.4 Aufmaß und Maßabweichungen Grundsatz der Aufmaßerstellung und der Aufmaßprüfung ist, dass die Aufmaße - auch von nicht mit dem Projekt befassten Dritten - einwandfrei nachvollzogen werden können. Auf den Aufmaßblättern ist jeweils das Gewerk, die Beschreibung der Leistung (Kurztext), der Einbauort (Raum, Anlage, ggf. Betriebsmittelkennzeichnung oder AKZ-Nr.) und die dort eingebaute Stückzahl aufzuführen; spätestens mit Übergabe des Aufmaßes zur Rechnung ist die LV-/ bzw. Nachtragsposition aufzuführen. Bei Massenpositionen (z. B. kg, lfdm, m²) sind die Einzelbauteile / Einzelelemente / Einzelstrecken aufzuführen. Bei Luftkanälen sind die EDV-Oberflächenberechnungen auf Basis DIN 18 379 mit den Kanalpositionen und Aufmaß(Montage)-zeichnungen mit ebendiesen Kanalpositionen beizufügen; Kanaldämmungen sind den Kanalpositionen entsprechend zuzuordnen. Längen (z. B. Kabel, Rohre, Umfang-Brandschotts, Dämmungen) sind als Einzellänge ab/bis zur nächsten Richtungsänderung aufzulisten. Bei Aufmaß nach Gewicht (z. B. Schlitzschienensystem, Profilstahl) sind die Gewichtstabellen mitzuliefern. Alle Aufmaßblätter sind über die gesamte Ausführungsphase hinweg fortlaufend durchzunummerieren; keine doppelten Aufmaßblattnummern! Dem AG sind spätestens mit der jeweiligen Rechnung (auch für Teil-/Abschlagsrechnungen) alle zugehörigen Aufmaßunterlagen im Original zu übergeben. Allen Rechnungen müssen kumulierte Aufmaßzusammenstellungen mit Angabe von mindestens der Positionsnummer, dem Positionskurztext, der Einzel- und Gesamtmassen je Aufmaßblatt und der aufgemessenen Gesamtmasse beiliegen. Das Aufmaß wird von dem AN angefertigt. Die Kosten des Aufmaßes sind durch den AN zu tragen. Alle Aufmaßunterlagen (Listen, Berechnungen, Zusammenstellungen, Skizzen, Zeichnungen etc.) müssen einzeln vom Auftragnehmer mit Firmenstempel, Datum und Unterschrift versehen sein. Diese Unterlagen werden vom AG oder der Bauüberwachung des AG im Zuge der Rechnungsprüfung gegengezeichnet. Zusätzlich zur Unterschrift muss der Name des jeweils Unterschreibenden in Druckschrift ergänzt werden. 7.5 Demontagen/Erneuerung Sind Leistungen als Demontageleistung oder als Erneuerung bereits bestehender Bauteile oder -leistungen beschrieben, so ist der Aufwand für eine geordnete, weitestgehend zerstörungsfreie Demontage und Entsorgung Bestandteil der Leistungen des AN. 8 Bautagesbericht Der AN hat täglich Bautagesberichte zu führen und dem AG wöchentlich abgestimmt zu übergeben (z. B. VHB Formblatt 411) . Sie müssen alle Angaben enthalten, die für die Ausführung, die Abrechnung und die terminlichen Auswirkungen des Auftrages von Bedeutung sein können. Über besondere Vorkommnisse ist der AG zusätzlich täglich zu informieren. 9 Stundenlohnarbeiten 9.1 Abforderung von Stundenlohnarbeiten Stundenlohnarbeiten sind nur auf Anweisung des AG auszuführen. Sollten Stundenlohnarbeiten erforderlich sein, sind diese vom AN vor Ausführung schriftlich durch Vorlage eines Stundenzettels mit Beschreibung der Maßnahmen und Schätzung des Umfangs dem AG zur Freigabe vorzulegen. Spätestens am folgenden Arbeitstag nach Ausführung sind die vollständigen Stundenzettel 2-fach, unter Angabe des Namens und Berufsbezeichnung des Arbeiters, der ausgeführten Arbeiten und Materialaufstellung, der Bauleitung vorzulegen. Die Nachweise über Stundenlohnarbeiten müssen enthalten: Name, Beruf und tägliche Stundenleistung der im Tagelohn beschäftigten Personen, Aufstellung über die Verwendung der besonders zu vergütenden Materialien und Baustoffe, Aufstellung und Beschreibung der ausgeführten Leistungen. Die Stundenlohnleistungen sind im Bautagebuch einzutragen. Eine Abzeichnung des Bautagebuches bedeutet keine Anerkennung der Stunden. Nicht fristgemäß vorgelegte Stundenzettel werden nicht anerkannt. Die Originale der Stundenlohnzettel behält der Auftraggeber, die bescheinigten Durchschriften erhält der Auftragnehmer. 9.2 Später verdeckte oder untergegangene Leistungen Werden Leistungen in Form von Stundenlohnarbeiten erbracht, die später nicht mehr nachvollziehbar sind (Abbruchleistungen, später überdeckte Leistungen), so sind vom AN geeignete Maßnahmen zur Dokumentation der erbrachten Leistung zu ergreifen, beispielsweise eine Fotodokumentation mit Handykamera. 9.3 Vergütung von Stundenlohnaufwendungen Nicht vergütet werden minus; Aufsichtsstunden (Bauleiter, Polier o. ä.), minus; Überstundenzuschläge, minus; Anmarsch, Materialbesorgung, minus; Materialtransport, Gerätetransport (sofern Bestandteil der Hauptleistung), minus; sonstige Vorbereitungsarbeiten, wie Werkzeuge herrichten u. ä. Vergütet werden die tatsächlich am Arbeitsplatz anfallende Arbeitszeit, verwendetes Material für diese Leistungen (nach LV oder nachrangig Tagespreis des Baustoffhandels). Der Verrechnungssatz für die jeweilige Arbeitskraft umfasst sämtliche Aufwendungen, insbesondere den tatsächlichen Lohn einschließlich: Lohn- und Gehaltskosten, alle Sozialkosten, Erschwernis- und sonstige Zuschläge, Lohnnebenkosten (Auslösungen, Wegegelder, Unterkunfts- und Übernachtungsgelder usw.), Wagnis und Gewinn. Eine Einrechnung der Stundenlohnarbeiten in die LV-Summe (Angebot bzw. Auftrag) berechtigt nicht zur Ausführung dieser Arbeiten. 10. Baufristenplan Der Auftragnehmer hat einen detaillierten Baufristenplan als Balkenplan über seine vertraglichen Leistungen zu erstellen, anhand dessen die Einhaltung der Vertragsfristen nachgewiesen und überwacht werden kann. Die Vertragsfristen ergeben sich aus den "Besonderen Vertragsbedingungen". Die Festlegungen des Auftraggebers, z.B. zur baufachlichen oder terminlichen Koordinierung mit den übrigen Leistungsbereichen, sind zu berücksichtigen. Bei Änderungen der Vertragsfristen oder bei erheblichen Abweichungen von sonstigen Festlegungen ist der Plan durch den Auftragnehmer unverzüglich zu überarbeiten. Der Plan ist dem Auftraggeber 15 Werktage nach Auftragserteilung, bei Überarbeitungen unverzüglich jeweils in 1-facher Papier-Ausfertigung, in .pdf-Datei und als offener Datensatz zu übergeben. 11. Lärm-und Staubschutz Es ist der Lärm-, Staub- und Vibrationseintrag zu begrenzen und hierzu mit dem AG rechtzeitig vorab abzustimmen. Die Ausführung ist erschütterungsarm gem. DIN 4150, lärmarm gem. Bundes- und Landes-Immissionsschutzgesetzen und AVV Baulärm und staubarm gem. TRGS 559 durchzuführen. Besonders Immissionsintensive Arbeiten sind dem AG mind. 3 Werktage vorab anzukündigen und schriftlich zu begründen. 12. Fachbauleiter Der Auftragnehmer (AN) hat spätestens 10 Kalendertage nach Auftragserteilung und vor Leistungsbeginn einen verantwortlichen Fachbauleiter unter Angabe seiner fachlichen Qualifikation zu benennen. Dieser muss während der gesamten Bauzeit erreichbar, auf Anforderung zur Verfügung des Auftraggebers bzw. der Bauüberwachung des AG stehen und deutschsprachig sein. 13. Einweisung und Koordination Vor Beginn der Arbeiten vor Ort wird vom AG eine Unterweisung des verantwortlichen Personals des AN (Gewerk-Kick-Off) durchgeführt. Der AN ist verpflichtet das seinerseits für das Bauvorhaben vorgesehene Personal sowie eigene Nachunternehmer entsprechend einzuweisen. Weitere Koordinationsgespräche und Baubegehungen finden nach Erfordernis und auf Anordnung des AG statt. 14. Baustellenbesprechungen Regelmäßige Besprechungen und Baustellenbegehungen finden jeweils 1x wöchentlich, in Abstimmung mit dem AG, ohne besondere Einladung statt. Der Auftragnehmer ist verpflichtet, an diesen vom Auftraggeber festgesetzten Besprechungen durch einen geeigneten, bevollmächtigten Vertreter teilzunehmen, der zu rechtsverbindlichen Vereinbarungen bevollmächtigt ist. 15. Auftraggeberaufgaben nach Baustellenverordnung Für die Baustelle gilt die Verordnung über Sicherheit und Gesundheitsschutz auf Baustellen (Baustellenverordnung). Die Anweisungen des vom Auftraggeber beauftragten Sicherheits- und Gesundheitsschutzkoordinators (SiGeKo) sind zu befolgen und unverzüglich umzusetzen, der SiGePlan ist einzuhalten. Der Auftragnehmer hat dem SiGeKo vor Beginn seiner Leistungen eine Gefährdungsbeurteilung für seinen Leistungsbereich vorzulegen. 15.1 Zusammenfassende Angaben für die Erarbeitung des Sicherheits- und Gesundheitsschutzplanes (SiGe-Plan) Die für die Aufstellung des Sicherheits- und Gesundheitsschutzplanes nach der Baustellenverordnung (BaustellV) erforderlichen Gefährdungsbeurteilungen (§ 6 des Arbeitsschutzgesetztes) und Ablaufpläne (ohne Anfangs- und Endtermin) für die Arbeiten aller beteiligten Unternehmen sind vor Beginn der jeweiligen Teilleistung dem Koordinator vorzulegen. Die Aufnahme von Arbeiten, die nicht in diesen Unterlagen erfasst sind, wird grundsätzlich nicht zugelassen. Verzögerungen, die sich aus nicht termingerechter Übergabe der Gefährdungsbeurteilungen und Ablaufplänen ergeben, können nicht geltend gemacht werden. Die Maßnahme unterliegt der Baustellenverordnung (BaustellV) vom 10. Juni 1998, BGBl. I 1998, S. 1283. Der Auftraggeber bestellt für die Baustelle einen Sicherheits- und Gesundheitskoordinator (SiGe-Koordinator) im Sinne der Baustellenverordnung (BaustellV) . Der AN verpflichtet sich zur Zusammenarbeit mit dem SiGe-Koordinator des AG. Werden vom SiGe-Koordinator darüber hinaus Unterlagen angefordert, sind diese zur Verfügung zu stellen. Die Kosten hierfür werden nicht gesondert vergütet. 15.2 Bestandsaufnahme zum Bauvorhaben Die Bestandsdaten wurden vorab ermittelt und daraufhin die Planung abgestimmt. Die zu erbringenden notwendigen sicherheits- und gesundheitsschutzrelevanten Leistungen wurden vom SiGe-Koordinator analysiert und in den Ausschreibungsunterlagen berücksichtigt. 15.3 Erfassen aller Tätigkeiten entsprechend dem Bauablauf Der SiGe-Koordinator stellt den SiGe-Plan auf und passt ihn bei erheblichen Änderungen an die Bauausführung an. Für die Anpassung des SiGe-Planes hat der AN dem AG zusammen mit dem Bauzeitenplan ggf. auch ein Baustelleneinrichtungsplan mit Erläuterungen des Bauablaufes zu übergeben. Der AG leitet die Unterlagen an den SiGe-Koordinator weiter. Die Vorankündigung wird an das zuständige Gewerbeaufsichtsamt durch den vom AG beauftragten Koordinator fristgerecht versendet. Eine ggf. erforderliche Anpassung der Vorankündigung wird durch den Koordinator veranlasst. Nach Auftragsvergabe hat der AN unverzüglich den SiGe-Fragebogen auszufüllen, die Ersthelfer zu benennen, die Gefährdungsbeurteilung sowie eventuelle Demontage- und Montageanweisungen zu erstellen und an den SiGe-Koordinator zu übergeben. Diese Leistungen werden nicht gesondert vergütet. Verzögerungen oder Forderungen anderer Art, die sich aus der Zusammenarbeit mit dem SiGe-Koordinator ergeben, können nicht geltend gemacht werden. Eine gesonderte Vergütung für die Zusammenarbeit des AN mit dem SiGe-Koordinator zur Umsetzung der Baustellenverordnung erfolgt nicht. 15.4 Maßnahmen für "besonders gefährliche Arbeiten" Beim Umgang mit gefährlichen Substanzen sind die entsprechenden Betriebsanweisungen zu beachten. Der Umgang mit solchen Substanzen darf nur mit geschulten oder entsprechend eingewiesenem Personal durchgeführt werden. 15.5 Gegenseitige Gefährdungen Gegenseitige Gefährdungen können in allen gemeinsam genutzten Einrichtungen stattfinden. Insbesondere bei den Zuwegungen, Lagerflächen und Baustelleneinrichtungsflächen. Erhöhte Aufmerksamkeit ist besonders beim Maschinenan- und -abtransport sowie beim Einsatz von Baumaschinen geboten. Rückwärtsfahrten sind nur mit Einweiser erlaubt. Bei Tätigkeiten mit Emissionen sind entsprechende PSA anzulegen und ausreichende Sicherheitsabstände einzuhalten. 15.6 Festlegungen baustellenspezifischer Maßnahmen Der AN erhält vom SiGe-Koordinator die Baustellenverordnung mit Alarm- und Notrufplan sowie den SiGe-Plan. Jede Kolonne muss über eine Kopie des Alarm- und Notrufplans verfügen sowie über ein Funktelefon. Die Ersthelfer sind dem SiGe-Koordinator vor Baubeginn zu benennen. Wechsel der Ersthelfer sind rechtzeitig vom AG anzuzeigen. 15.7 Gemeinsam genutzte Einrichtungen Werden Einrichtungen gemeinsam genutzt wie z.B. Lagerflächen, Baustelleneinrichtungsflächen, Zuwegungen, Treppen, Stege, Gerüste, Sozialräume oder dgl., so sind diese entsprechend den gültigen Vorschriften herzustellen. Die regelmäßige Wartung und Unterhaltung obliegt dem AN oder einer vom AN bestellten 3. Person. Die Einrichtungen sind auf die örtlichen Gegebenheiten und Bedürfnisse entsprechend den zuständigen Bestimmungen und Verordnungen abzustimmen und auszulegen. 15.8 Anzuwendende Arbeitsschutzbestimmungen Es werden folgende Bestimmungen zugrunde gelegt: 95 / 57 / EWG Sicherheit- und Gesundheitsschutz auf Baustellen Baustellenverordnung BaustellV Arbeitsstättenverordnung ArbStättV Gefahrstoffverordnung GefstoffV alle gültigen UVV´en, Technische Regeln und DIN-Normen | K11: ="" | M11: b4dfbb48-e429-4b9b-923e-aee4ebad50ca
A12: Hinweistext | C12: A.5 Bauschild | D12: A.5 Bauschild Ein separates Bauschild mit Werbetafeln der Auftragnehmer ist nicht vorgesehen. Stattdessen wird auf der straßenseitigen Fassade bauseits ein Projektschild angebracht, das Informationen über den Auftraggeber sowie die Projektbeteiligten enthält. Dieses Schild bleibt für die Dauer der Baumaßnahme befestigt. | K12: ="" | M12: fac04996-cab4-4fdb-a661-a245163d9235
A13: Hinweistext | C13: A.6 Allgemeine Hinweise zur Preisbildung | D13: A.6 Allgemeine Hinweise zur Preisbildung Bei der Preisbildung der Einheitspreise ist davon auszugehen, dass es sich bei den LV Massen in jeder Position um Gesamtmassen handelt, die sich aus mehreren Einzelflächen bzw. -Massen, verteilt über den jeweiligen Abrechnungs - abschnitt zusammensetzen. Vor Bestellung von Baustoffen und Hilfsmaterialien hat der AN die tatsächlich erforderlichen Mengen verbindlich zu ermitteln. Soweit in den einzelnen LV Positionen nicht gesondert angegeben ist, dass der AG einzelne Stoffe liefert, hat der AN bei allen Positionen sämtliche Baustoffe zu liefern, auch wenn dies nicht ausdrücklich angegeben ist. In einzelnen Positionslangtexten enthaltener Wortlaut "nach Unterlagen des AG" bezieht sich immer nur auf die Planunterlagen des AG, welche der Ausschreibung für die Einheitspreisbildung beigefügt sind. Die exakten örtlichen Bedingungen und der Leistungsumfang sind jeweils vor Beginn der einzelnen Arbeitstätigkeiten gemeinsam mit örtlicher Bauüberwachung und dem AG vor Ort festzulegen. Einrichten, Vorhalten und Räumen der Baustelleneinrichtung sind nach VOB Teil C, DIN 18299, Punkt 4.1 Nebenleistungen, die in die Einheitspreise einzurechnen sind. Sich aus den o.g. Angaben ergebende Mehrkosten sind in die jeweiligen Einheitspreise einzurechnen und werden nicht gesondert vergütet. | K13: ="" | M13: 902aff23-3b4b-44f0-bfc8-632400b6364d
A14: Hinweistext | C14: A.7 Ausführungsunterlagen | D14: A.7 Ausführungsunterlagen A.10.1 Vom AG zur Verfügung gestellte Ausführungsunterlagen Alle Ausführungsunterlagen sind aus dem Anlagenverzeichnis (Teil B) ersichtlich. A.10.2 Vom AN zu erstellende/zu beschaffende Ausführungsunterlagen Der AN hat alle entsprechend den Dokumentationsrichtlinien des AG erforderlichen Unterlagen zu erbringen. Der AN hat Bautagesberichte zu führen und dem AG täglich zu übergeben. Sie müssen alle Angaben enthalten, die für die Ausführung und Abrechnung des Auftrages von Bedeutung sind. Für sämtliche statisch relevanten Elemente sind vom AN entsprechende statische Berechnungen zu erstellen. Für die Erstellung von Ausführungsunterlagen bzw. Werkstattzeichnungen durch den AN bzw. bei Änderungen gegenüber der vom Prüfingenieur freigegebenen Planung sind die entsprechenden Zeit-Vorläufe für die baustatische Prüfung zu kalkulieren. Kosten für Zusatzaufwand des Prüfingenieurs aufgrund Änderungen der freigegebenen Planung durch den AN sind Seitens des AN zu tragen. | K14: ="" | M14: 7f6261e5-efc7-40a5-9a88-a46ddffbff06
A15: Hinweistext | C15: A.8 ZTV SiGeKo | D15: A. 8 ZTV SiGeKo Zusätzliche Technische Vertragsbedingungen zur VOB/C. Sicherheit und Gesundheitsschutz auf Baustellen A.8.1 Der Auftragnehmer verpflichtet sich, die zur Regelung des Arbeitsschutzes auf der Baustelle geltenden Gesetze, Verordnungen sowie die Berufsgenossenschaftlichen Vorschriften und Regeln zu beachten. A.8.2 Der Auftragnehmer hat vor Beginn der Arbeiten eine Gefährdungsbeurteilung und deren Dokumentation (§§ 5,6 Arbeitsschutzgesetz) dem Bauherrn vorzulegen. Weiterhin hat der Auftragnehmer den von ihm bestellten Betriebsarzt und die Fachkraft für Arbeitssicherheit bzw. den mit diesen Leistungen beauftragten externen Dienst dem Auftraggeber schriftlich mitzuteilen. A.8.3 Entsprechend der Verordnung über Sicherheit und Gesundheitsschutz auf Baustellen (BauStellV vom 10.06.98) ist für die Planung der Ausführung und die Ausführungsphase vom Bauherrn ein Koordinator bestellt. Dieser erstellt den gemäß BauStellV für o.g. Bauvorhaben erforderlichen Sicherheits- und Gesundheitsschutzplan, koordiniert dessen Umsetzung während der Ausführung und veranlaßt die ordnungsgemäße Anwendung der Arbeitsverfahren. Den Anweisungen des Koordinators zu Sicherheits- und Gesundheitsschutzmaßnahmen ist Folge zu leisten. A.8.4 Jedem Auftragnehmer wird die Baustellensicherheitsordnung ausgehändigt. Diese enthält u.a. allgemeine Hinweise zur Arbeitssicherheit, Ersten Hilfe Leistungen, Brandschutz und zusätzlichen Maßnahmen. Jeder Hauptauftragnehmer wird vor Beginn der Arbeiten durch den SiGeKo in den Sicherheits- und Gesundheitsschutzplan und die Baustellensicherheitsordnung eingewiesen und verpflichtet sich durch Unterschrift, die in diesen Richtlinien aufgeführten Regelungen und Hinweise während der gesamten Baumaßnahme konsequent zu beachten. Weiter haben die Hauptauftragnehmer o.g. Leistungen für Ihre ggf. eingesetzten Nachunternehmer sicherzustellen. A.8.5 Widersprüche gegen die aus dem Sicherheits- und Gesundheitsschutzplan und die Baustellensicherheitsordnung ergebenden Maßnahmen sind unverzüglich (schriftlich formlos) unter Darstellung einer gleichwertigen Sicherheit gewährleistenden Ersatzmaßnahme anzuzeigen. A.8.6 Unabhängig von Pkt. 1 4 hat jeder Auftragnehmer das Vorschriften und Regelwerk der für ihn zuständigen Berufsgenossenschaft zu berücksichtigen. A.8.7 Vom Auftragnehmer ist ein für den Arbeitschutz in seinem Bereich verantwortlicher Bauleiter zu benennen. Dieser ist für die Einhaltung der Arbeitschutzvorschriften durch die ihm unterstellten Arbeitskräfte (einschließlich der Arbeitskräfte seiner Nachunternehmer) zuständig. Er steht weiterhin dem Koordinator (nach BauStellV) als Ansprechpartner zur Verfügung, setzt dessen Forderungen nach Verbesserung von Sicherheit und Gesundheit der Beschäftigten um und nimmt an den vom Koordinator einberufenen Sicherheitsbesprechungen teil. Für den Verhinderungsfall muß ein Vertreter benannt werden. | K15: ="" | M15: 84c5a1ae-423c-4497-8d72-5fc4e4ece69b
A16: Hinweistext | C16: A.9 Materialökologie | D16: A.9 Materialökologie Es wird eindringlich auf die Einhaltung aller nachfolgenden städtischen und gesetzlichen Vorgaben zur Materialökologie hingewiesen. Sollten Verstöße festgestellt werden, sind alle vertragswidrig verbauten Stoffe und Materialien oder verwendete Reinigungsmittel auf Kosten des AN zu entfernen und mit zugelassenen Produkten zu ersetzen. Kontrollen erfolgen durch den AG und dessen Erfüllungsgehilfen, die Bauleitungen vor Ort und den SiGeKo. Allgemeine Anforderungen (gilt grundsätzlich für alle materialökologischen Anforderungen): Nachweise: Die geforderte Qualität der Baustoffe und Bauprodukte ist rechtzeitig vor Ausführung bzw. Bestellung durch Sicherheitsdatenblätter, Prüfzeugnisse oder sonstige geeignete Nachweise zu belegen. Die Verantwortung der Produkteinhaltung liegt allein beim AN. Aktualität der Nachweise: Nachweise wie Sicherheitsdatenblätter, Umweltzeichen - Zertifikate, Datenblätter oder Emissionsprüfberichte müssen aktuell sein. Bei Umweltzeichen gilt die jeweils aktuellste Version. Ist die Gültigkeitsfrist z.B. einer zugrundeliegenden "Blauer Engel"- Version abgelaufen, werden die Zertifikate nicht akzeptiert. Im Fall der Überschneidung von zwei Versionen (Übergangsfrist) ist möglichst die aktuellste Version vorzulegen. Produktänderungen: Notwendige Produktänderungen während der Ausführung sind unverzüglich mit dem AG abzustimmen, es sind alle vorgenannten Nachweise neu vorzulegen und neu vom AG freizugeben. Originalgebinde auf der Baustelle: Es sind alle Produkte auf der Baustelle im Originalgebinde zu verwenden, eine Anlieferung bereits vorgemischter Produkte in Fremd- oder Neutralgebinden ist untersagt. Feinstaub/ Gesundheitsgefährlicher Staub Die Staubentwicklung ist, soweit technisch möglich, zu vermeiden. Beim Maschineneinsatz sind staubarme, abgestimmte Bearbeitungssysteme (Maschine und Mobilentstauber) zu verwenden, die den allgemeinen Staubgrenzwert von 1,25 mg/m³ für die alveolengängige (A-) Fraktion sowie 10 mg/m³ für die einatembare (E-) Fraktion einhalten. Die BG BAU führt Positivlisten staubarmer Bearbeitungssysteme und staubarmer Produkte. Werden gesundheitsgefährliche mineralische Stäube oder andere Gefahrstoffe freigesetzt, sind die notwendigen Maßnahmen entsprechend der jeweiligen Technischen Regel Gefahrstoffe (TRGS 505, 519, 521, 559, 900 u.a.) und der Gefahrstoffverordnung zu ergreifen. Beim Bearbeiten von Bestandsbauteilen mit bleiweißhaltigen Anstrichen sind die Handlungsanleitungen der BG BAU zu beachten. Stoffe mit besonders besorgniserregenden Eigenschaften Alle verwendeten Bauprodukte dürfen keine Stoffe mit folgenden Eigenschaften als konstitutionelle Bestandteile (d.h. Stoffe, die im Endprodukt verbleiben und in diesem eine Funktion erfüllen) enthalten: Stoffe, die unter der Chemikalienverordnung REACH als besonders besorgniserregend identifiziert und in die gemäß REACH Artikel 59 Absatz 1 erstellte Liste (sogenannte "Kandidatenliste") aufgenommen wurden (SVHC). Es gilt die jeweils aktuelle Fassung der Kandidatenliste. Stoffe, die in ihrem Sicherheitsdatenblatt mit Eigenschaften gekennzeichnet sind, die zur Aufnahme in die Kandidatenliste führen können (REACH Art. 57). Dies umfasst folgende Stoffe: -erwiesenermaßen krebserzeugende, erbgutverändernde oder fortpflanzungsgefährdende Stoffe ("KMR-Stoffe" der Kat. 1A und 1B) und Stoffe, die gemäß den Kriterien der EG-Verordnung 1272/2008 (oder der Richtlinie 67/548/EWG) mit den im Folgenden genannten H-Sätzen bzw. RSätzen eingestuft sind als: - karzinogen (krebserzeugend) der Kategorie Carc. 1A / Carc. 1B H350: Kann Krebs erzeugen. H350i: Kann bei Einatmen Krebs erzeugen.- keimzellmutagen (erbgutverändernd) der Kategorie Muta. 1A / Muta. 1B H340: Kann genetische Defekte verursachen.- reproduktionstoxisch (fortpflanzungsgefährdend) der Kategorie Repr. 1A, Repr. 1B H360F, R60: Kann die Fruchtbarkeit beeinträchtigen. H360D, R61: Kann das Kind im Mutterleib schädigen. H360FD, R60/61: Kann die Fruchtbarkeit beeinträchtigen. Kann das Kind im Mutterleib schädigen. H360Fd, R60/63: Kann die Fruchtbarkeit beeinträchtigen. Kann vermutlich das Kind im Mutterleib schädigen. H360Df, R61/62: Kann das Kind im Mutterleib schädigen. Kann vermutlich die Fruchtbarkeit beeinträchtigen. Stoffe mit PBT- (persistent, bioakkumulierend und toxisch) oder vPvB- (sehr persistent und sehr bioakkumulierend) Eigenschaften. Für bestimmte Stoffe (z.B. Formaldehyd) gelten besondere Regeln. Diese sind über die Anforderungen des Blauen Engels bzw. über die in den nachfolgenden Absätzen explizit aufgeführten Anforderungen geregelt. Biozide Der Einsatz von Bioziden gemäß Biozidverordnung ist nicht zulässig. Hiervon ausgenommen sind Biozide, die allein zur Topfkonservierung in wässrigen Beschichtungsstoffen und Leimen eingesetzt werden. Hier gelten ggf. Einschränkungen und Vorgaben der Umweltzeichen (z.B. "Blauer Engel"), die in den jeweiligen produktgruppenspezifischen Anforderungen genannt sind. Ebenfalls ausgenommen sind ggf. erforderliche Durchwurzelungshemmer in der Dachabdichtungsbahn bei Dachbegrünungen. Polyvinylchlorid (PVC) / Chlorchemische Produkte Der Einsatz von chlorchemischen Produkten ist ausgeschlossen (z.B. bei Fußbodenbelägen, Sanitärleitungen, Elektroinstallation, Abdeck-/ Trennfolien, Dichtungsbahnen). Ausnahmen sind zulässig für Anwendungsbereiche ohne vertretbare Alternativen (Fenster, Türen). Spritz- und Montageschäume Die Verwendung von Montageschäumen und sonstigen Ortschäumen ist ausgeschlossen. Dies gilt nicht für die Verwendung bei Wärmedämmverbundsystemen zum Schließen von Fugen zwischen Dämmstoffplatten gemäß den Hersteller-Verarbeitungsrichtlinien. Dichtungen und Abdichtungen Zur Vermeidung der Innenraumluftbelastung sind bei den Kleb- und Dichtstoffen in Innenräumen amin- oder oximvernetzende bzw. -haltige Produkte ausgeschlossen. Es dürfen nur Produkte mit den Umweltzeichen "Emicode" EC1plus oder RAL-UZ 123 (Blauer Engel) verwendet werden. Abweichungen, z.B. "Emicode" EC1, sind in (technisch) begründeten Ausnahmefällen bzw. in Bereichen mit sicherheitsrelevanten bauaufsichtlichen Anforderungen in Abstimmung mit dem AG möglich. Kann auf lösemittelhaltige Produkte an der Baustelle nicht verzichtet werden, muss bis zum Abklingen der VOC-Emissionen eine ausreichende Ablüftung (ggf. mit mechanischer Lüftung) durch den AN gesichert sein. Für Flüssigabdichtungen in Innenräumen dürfen nur Produkte mit dem "Emicode" EC1 oder EC1plus verwendet werden. Als kalt verarbeitete Bitumenbeschichtungen/ bituminöse Voranstriche dürfen nur Produkte mit "Giscode" BBP 10 verwendet werden. Dichtungs-/ Dachbahnen und Dampfsperren aus PVC sind ausgeschlossen. Holz, Holzwerkstoffe Der Einsatz von Tropenholz bei Bau und Ausstattung ist ausgeschlossen. Terpenhaltige Holzarten sind zur Minimierung von bicyclischen Terpenen zu vermeiden. In Aufenthaltsräumen sind harzarme Holzarten zu verwenden. Stark harzhaltige Nadelhölzer - insbesondere Kiefernholz- (z.B. verarbeitet als Fensterprofile, "Seekiefer"-, OSB- u.ä. Platten) dürfen nicht verwendet werden. Formaldehydhaltige Verleimungen und Beschichtungen Holzwerkstoffe müssen mindestens den Anforderungen des Umweltzeichens RAL UZ 76 (Blauer Engel, Ausgabe Februar 2016 oder neuer) oder des "natureplus"-Umweltgütesiegels der Gruppe RL0200 (mit etwas anderen Prüfbedingungen) entsprechen. Liegt kein Nachweis vor, muss vom Hersteller ein Prüfbericht (z.B. für Boulder- oder Prallwände aus Phenol-Formaldehydharz (PF) verleimten Multiplexplatten) vorgelegt werden (s.u.). Bei akustisch wirksamen (gelochten) Platten ist für das fertige Endprodukt (gelochte Platte mit oder ohne Beschichtung) vom AN ein Prüfbericht einer Prüfkammer-Messung vorzulegen (s.u.). Bei konstruktiven Holzbauteilen (z.B. Brettschichtholz) sind ausschließlich formaldehydfrei verleimte Produkte erlaubt oder es ist auf alternative Bauarten oder Baustoffe auszuweichen. Produkte mit formaldehydhaltigen Beschichtungen sind ausgeschlossen. Hinweis: Bei großflächigem Einbau von Holzwerkstoffen in Wand, Boden und/oder Decke ist das Auftreten von Formaldehyd-Emissionen besonders sensibel zu betrachten. Als großflächig gilt bereits eine Wandfläche, eine Bodenfläche oder eine Deckenfläche. Prüfkammer-Messung: Holzwerkstoffplatten dürfen bei der Messung in der Prüfkammer in Anlehnung an die vom Ausschuss zur gesundheitlichen Bewertung von Bauprodukten (AgBB) erarbeitete "Vorgehensweise bei der gesundheitlichen Bewertung der Emissionen von flüchtigen organischen Verbindungen (VOC und SVOC) aus Bauprodukten" folgende Emissionswerte nicht überschreiten. Die Messung der Emissionen erfolgt gemäß CEN/TS 16516.15. Die Beladung der Prüfkammer beträgt einheitlich 1,4m²/m³: Summe flüchtiger organischer Verbindungen, Retentionsbereich C6 - C16 (TVOC): maximal 1 mg/ m³ nach 3 Tagen maximal 0,8 mg/ m³ nach 28 Tagen Summe schwer flüchtiger organischer Verbindungen, Retentionsbereich > C16 - C26 (TSVOC): maximal 0,1 mg/ m³ nach 28 Tagen krebserzeugende Stoffe (K1 und 2 nach Richtlinie 67/548/EWG bzw. Klassen 1A und 1B nach CLPVerordnung 1272/2008): maximal 0,01 mg/ m³ nach 3 Tagen, maximal 0,001 mg/ m³ nach 28 Tagen Summe aller VOC ohne NIK: maximal 0,1 mg/ m³ nach 28 Tagen R-Wert: maximal 1 nach 28 Tagen Formaldehyd: maximal 0,08 mg/ m³ nach 28 Tagen Formaldehyd darf auch weiterhin nach der EN 717-1 gemessen werden. Wird nach der EN 717-1 gemessen, ist ein Wert von 0,03 ppm (0,0375 mg/ m³) einzuhalten (in Anlehnung an das WKIRechenmodell für Formaldehyd). Holzschutz Im Holzbau sind Konstruktionen zu wählen, bei denen nach DIN 68 800 chemischer Holzschutz entbehrlich ist. In Aufenthaltsräumen dürfen keine chemischen Holzschutzmittel eingesetzt werden. Sofern chemischer Holzschutz produktionsbedingt (z.B. bei Holzfenstern) erforderlich ist, dürfen nur Produkte mit BAuA-Zulassung verwendet werden. Gemäß BiozidVO sind die verwendeten bioziden Wirkstoffe zu deklarieren und zu dokumentieren. Es muss - bei gleicher Eignung - das jeweils umweltverträglichste Produkt und Verfahren verwendet werden. Dabei ist die Einstufung entsprechend dem Produkt-Code der Bauberufsgenossenschaft zu Grunde zu legen. Holzschutzmittel für nichttragende Bauteile müssen das RAL-Prüfzeichen RAL-GZ 830 der Gütegemeinschaft Holzschutzmittel e.V., für tragende Bauteile das Prüfzeichen des Deutschen Instituts für Bautechnik aufweisen. Behandlungen mit Holzschutzmitteln sind im Produktionsbetrieb des AN vorzunehmen. Auf der Baustelle sind sie nur im Ausnahmefall nach vorheriger Zustimmung des Auftraggebers erlaubt. Beschichtungen von Holzoberflächen - siehe Oberflächenbeschichtungen Kleb- und Verlegewerkstoffe Grundsätzlich dürfen nur lösemittelfreie Verlegewerkstoffe (Voranstriche, Leime, Kleber, Spachtel etc.) gemäß Giscode-Einstufung der Bauberufsgenossenschaft und den Technischen Regeln für Gefahrstoffe TRGS 610 verwendet werden. Ausnahmen sind nur nach vorheriger Zustimmung des AG erlaubt. Zur Vermeidung der Innenraumluftbelastung sind amin- oder oximvernetzende bzw. -haltige Klebund Dichtstoffe (Verfugungen, punkt- und linienförmige Verklebungen) ausgeschlossen. Es dürfen nur Produkte mit den Umweltzeichen "Emicode" EC1plus oder RAL-UZ 123 (Blauer Engel) verwendet werden. Als Verlegewerkstoffe für Boden- und Wandbeläge dürfen nur Produkte entsprechend der Umweltzeichen RAL-UZ 113 (Blauer Engel) oder "Emicode" EC1plus verwendet werden. Für Fliesen und Platten sind mineralische Fliesenkleber zu verwenden. Trennmittel Es dürfen nur Trennmittel verwendet werden, die biologisch schnell abbaubar sind und dem Umweltzeichen RAL-UZ 178 entsprechen. Auf technisch notwendige Ausnahmen ist die Bauleitung hinzuweisen. Recyclingprodukte zum Bauteilschutz Bei Maßnahmen zum Schutz von Bauteilen oder der Ausstattung sind Produkte aus Recyclingmaterial (Altpapier, Alttextilien, PE-Regenerat) zu verwenden. | K16: ="" | M16: 9a253783-fb44-4426-9f61-9522c0cda9d8
... A21: Hinweistext | C21: A.14 Hinweis Positionsbeschreibung | D21: A.14 Hinweis Positionsbeschreibung Stoffe und Bauteile der Baustelleneinrichtung, die der AN vorzuhalten hat, können gebraucht sein. Für die Ausführung der Leistungen gilt der vom AN aufzustellende und vom AG genehmigte Baustelleneinrichtungsplan. Der Baustelleneinrichtungsplan wird nicht gesondert vergütet. Eine Koordinierung der nachfolgend beschriebenen Leistungen mit anderen Gewerken ist erforderlich. Hinweis Positionsbeschreibung Alle in den Leistungspositionen für Herstellung und/oder Einbau vorgesehenen Materialien verstehen sich jeweils einschließlich Lieferung frei Baustelle, Einbau und ggfs. der Vorhaltung der Bauhilfsmaterialien. In den Leistungspositionen der Vorhaltung ist mit der Vorhaltung neben der Bereitstellung der Leistung auch die regelmäßige Kontrolle und ggf. Mängelbeseitigung entsprechend den Eigenarten der Leistung, den Vorschriften, Festlegungen der Planung und des Vertrages durchzuführen. Erhält der AN von dem AG oder Dritten die Mitteilung, dass Vorhalteleistungen nicht im ordnungsgemäßen Zustand sind, ist er verpflichtet diese umgehend nachzubessern. Dies gilt insbesondere für sicherheitsrelevante Einrichtungen. Die in dem Leistungsverzeichnis dargestellten Merkmale hinsichtlich Qualität, konstruktivem Aufbau und Werkstoffen werden zwingend gefordert. Die Angaben in diesem Leistungsverzeichnis dienen ausschließlich der Orientierung für die Werkplanung des AN. Festlegungen der Ausführungen nur nach Bemusterung und Freigabe durch den AG bzw. durch die AG-Bauleitung. Die Vorgaben und Vorbemerkungen des Auftraggebers zu Verträgen, Rechnungsstellung etc. haben Vorrang vor den Vorbemerkungen dieser Ausschreibung. Hinweis Allgemeines Alle Ausführungen im mehrschichtigen Bauablauf (alle Ausführungen und alle Bereiche) Die Arbeitszeit ist wie üblich von 07.00 - 17:00 Uhr, oder individuell nach Rücksprache mit der AG-Bauleitung. Es besteht ein striktes Alkoholverbot. Das Rauchen im Gebäude und im Gelände ist ebenfalls verboten. Türen zu dem Gelände sind immer geschlossen zu halten Leiteraufgänge der Rüstung sind zu sichern und gegen die Nutzung von Unbefugten zu sichern. Entstehende Baureststoffe sind, wenn nicht anders beschrieben zu entfernen und fachgerecht zu entsorgen. Nach Auftragserteilung erhält der AN über die Bauüberwachung (BÜ) einen Zugang zur Plattform Capmo - einem digitalen Tool für kollaboratives Bauprojektmanagement. Capmo verknüpft Daten, Werkzeuge und Prozesse nahtlos miteinander. Durch die intelligente Integration von Terminplänen, Aufgaben, Nachträgen und Mängelmanagement werden Abläufe effizienter gestaltet und die Projektdokumentation zentral gebündelt. COPYRIGHT: Die in diesen Unterlagen gezeigten Inhalte unterliegen dem deutschen Urheber- und Leistungsschutzrecht. Jede vom deutschen Urheber und Leistungsschutzrecht nicht zugelassene Verwertung bedarf der vorherigen schriftlichen Zustimmung durch den Verfasser. Dies gilt insbesondere für Vervielfältigungen, Bearbeitung, Einspeicherung, Verarbeitung bzw. Wiedergabe von Inhalten in Datenbanken oder anderen elektronischen Medien und Systemen. Auftraggeber dürfen die Unterlagen einschließlich der EDV-Unterlagen nurfür das nach dem Vertrag vereinbarte Bauvorhaben verwenden. Im Übrigen verbleiben die Nutzungs- und Urheberrechte bei dem Verfasser. | K21: ="" | M21: 9b52ab61-51ea-4f62-94cb-1fcf5d4e6e2e
A22: Gruppe | B22: 00. | C22: Technische Vorbemerkungen | K22: =""
A23: Hinweistext | C23: ATV | D23: ALLGEMEINE TECHNISCHE VORBEMERKUNGEN Die neuesten Richtlinien, Regeln, VOB, DIN-Vorschriften sowie das aktuelle GeG (Gebäude Energie Gesetz) sind einzuhalten bzw. zu beachten. Die jeweiligen Herstellervorschriften der im LV beschriebenen, bzw. angebotenen Materialien und Produkte sowie die dazugehörigen technischen Merkblätter und Sicherheitsdatenblätter sind zu beachten. Die Einzelpositionen verstehen sich inklusive Lieferung, Materialkosten und Einbau, soweit nichts anderes beschrieben. Für Befestigungsmittel, die der Witterung ausgesetzt sind, müssen korrosionsbeständige Werkstoffe verwendet werden. Für Bauteile bzw. Gegenstände die vom rechten Winkel abweichen ( z.B. Schrägschnitte ) gibt es nur Zuschläge, wenn diese in den Positionen ausdrücklich erwähnt sind - ansonsten ist eine solche Zulage in die Pos. einzukalkulieren - oder vom AN ergänzend aufzuführen. Maßkontrollen am Bau sind durchzuführen. Auf evtl. Differenzen oder planerische Abweichungen ist der Auftraggeber sofort aufmerksam zu machen. Massenänderungen und voraussichtliche Mehrkosten sind der Bauleitung umgehend vor Ausführung schriftlich per Mail oder Fax anzuzeigen. Der Auftragnehmer hat arbeitstäglich Bautagesberichte (nach dem Vordruck CertiForm KEV 320 Bautagberichte) mit folgenden Angaben zu führen (siehe auch CertiForm KEV 116.1, Punkt 1.3): Zahl der am Tag anwesenden Mitarbeiter ( Berufsbezeichnung und Namen z.B. Facharbeiter Müller). am Tag ausgeführte Arbeiten am Tag eingebautes/ verwendetes Material Angaben zum Terminplan Angaben zum Wetter ( z.B. Regen, Frost etc.) Die Berichte sind der Bauleitung arbeitstäglich spätestens wöchentlich zu übergeben. Bei Nichteinhaltung werden strittige Punkte zu Gunsten des AG entschieden. Stundenlohnarbeiten, siehe besondere Hinweise am Ende der LVs. Stundenlohnarbeiten sind im Vorfeld anzumelden, ansonsten erfolgt keine Vergütung. Der Auftragnehmer hat die Durchführung seiner Arbeiten nach Terminplan so vorzunehmen, dass ein reibungsloser Ablauf der Arbeiten gewährleistet ist. Abweichungen vom Terminplan sind der Bauleitung sofort schriftlich mitzuteilen. Anmelden von Bedenken: Der Auftragnehmer hat vor Beginn seiner Arbeiten zu prüfen, ob die vorgesehene Ausführung sich für die Durchführung seiner Leistung eignet. In diesem Zuge ist auch die Eignung des Bestandes bzw. die Leistung der Vorgewerke zu prüfen. Bedenken sind dem Auftragnehmer unverzüglich schriftlich mitzuteilen. Der Auftragnehmer hat dafür Sorge zu tragen, dass während der Ausführung seiner Leistungen immer mindestens ein fließend deutsch sprechender Mitarbeiter seiner Firma pro Gewerk auf der Baustelle anwesend ist. Zu den auf der Baustelle vorzuhaltenden Ausführungsunterlagen zählt neben den Ausführungsplänen auch eine Ausfertigung dieser Leistungsbeschreibung. Die vom Auftragnehmer verwendeten Ausführungsunterlagen müssen den Freigabevermerk des Auftraggebers oder des Architekten tragen. Durch Übergabe neuer Unterlagen ungültig gewordene Unterlagen sind vom Auftragnehmer entsprechend zu kennzeichnen und aufzubewahren. Nicht freigegebene Unterlagen dürfen nicht verwendet werden. HINWEIS zur Beachtung für alle Gewerke: Sämtliche Positionen, die nicht im Nachhinein nachvollzogen, oder nicht den vorliegenden Planunterlagen entnommen werden können, müssen vor Ausführung mit dem Bauleiter aufgemessen werden. Ansonsten erfolgt keine Vergütung. | K23: ="" | M23: 98f9e017-c5af-4af4-a788-f5455c0e126a
A24: Hinweistext | C24: ZTV Trockenbau | D24: TECHNISCHE VORBEMERKUNGEN TROCKENBAUARBEITEN Mitgeltende Normen und Regeln Allgemeines Es gelten jeweils die Normen und Regeln in der zum Vertragsschluss gültigen Fassung einschließlich der Änderungen, Berichtigungen und Beiblätter. Soweit in der Leistungsbeschreibung auf Technische Spezifikationen, z. B. nationale Normen, mit denen Europäische Normen umgesetzt werden, europäische technische Zulassungen, gemeinsame technische Spezifikationen, internationale Normen, Bezug genommen wird, werden auch ohne den ausdrücklichen Zusatz: "oder gleichwertig", immer gleichwertige Technische Spezifikationen in Bezug genommen. (Erläuterung: "Gilt nur für öffentliche Bauvorhaben: Dieser Hinweis soll gemäß ATV DIN 18299 grundsätzlich in die Vorbemerkungen aufgenommen werden, sobald in der Leistungsbeschreibung auf technische Spezifikationen Bezug genommen wird.") DIN 18100 Türen; Wandöffnungen für Türen; Maße entsprechend DIN 4172 DIN 55634 Beschichtungsstoffe und Überzüge - Korrosionsschutz von tragenden dünnwandigen Bauteilen aus Stahl DIN EN 13170 Wärmedämmstoffe für Gebäude - Werkmäßig hergestellte Produkte aus expandiertem Kork (ICB) - Spezifikation VDI 3762 Schalldämmung von Doppel- und Hohlraumböden AGI-A20 Doppelbodensysteme: Anforderungen, Ausführungsgrundsätze Herausgeber: Arbeitsgemeinschaft Industriebau e.V. (AGI) BG Bau Fachinfo Prävention Umgang mit Mineralwolle-Dämmstoffen IVD-Merkblatt Nr. 16 Anschlussfugen im Trockenbau Herausgeber: Industrieverband Dichtstoffe e.V. (IVD) IVD-Merkblatt Nr. 19-2 Abdichtungen von Fugen und Anschlüssen im Dachbereich - Teil 2 Luftdichte Ebene Herausgeber: Industrieverband Dichtstoffe e.V. (IVD) IVD-Merkblatt Nr. 20 Fugenabdichtung an Holzbauteilen und Holzwerkstoffen Herausgeber: Industrieverband Dichtstoffe e.V. (IVD) Merkblatt Nr. 1 Baustellenbedingungen für Trockenbauarbeiten mit Gipsplatten-Systemen Herausgeber: Bundesverband der Gipsindustrie e.V., Industriegruppe Gipsplatten Merkblatt Nr. 3 Gipsplattenkonstruktionen - Fugen und Anschlüsse Herausgeber: Bundesverband der Gipsindustrie e.V., Industriegruppe Gipsplatten Merkblatt Nr. 4 Regeldetails zum Wärmeschutz gemäß EnEV 2009 Modernisierung mit Trockenbausystemen Herausgeber: Bundesverband der Gipsindustrie e.V., Industriegruppe Gipsplatten Merkblatt Nr. 4 Anhang Regeldetails zum Wärmeschutz gemäß EnEV 2009 Modernisierung mit Trockenbausystemen Herausgeber: Bundesverband der Gipsindustrie e.V., Industriegruppe Gipsplatten Merkblatt Nr. 5 Bäder und Feuchträume im Holzbau und Trockenbau Herausgeber: Bundesverband der Gipsindustrie e.V., Industriegruppe Gipsplatten Merkblatt Nr. 6 Vorbehandlung von Trockenbauflächen aus Gipsplatten zur weitergehenden Oberflächenbeschichtung bzw. -bekleidung Herausgeber: Bundesverband der Gipsindustrie e.V., Industriegruppe Gipsplatten Merkblatt Nr. 8 Wandhöhen leichter Trennwände Herausgeber: Bundesverband der Gipsindustrie e.V., Industriegruppe Gipsplatten RAL-GZ 531 Trockenbau - Gütesicherung Richtlinie Anwendungsrichtlinie zur DIN EN 12825 Doppelböden Herausgeber: Bundesverband Systemböden e.V. Richtlinie Anwendungsrichtlinie zur DIN EN 13213 Hohlböden Herausgeber: Bundesverband Systemböden e.V. Angaben zu Stoffen und Bauteilen Bei brandschutztechnischen Anforderungen sind die amtlichen Nachweise (Prüfzeugnis oder Prüfbescheid oder allgemeine bauaufsichtliche Zulassung) der Bauleitung zu übergeben. Bei nicht genormten Stoffen und Bauteilen sind, soweit erforderlich, die bauaufsichtlichen Zulassungen der Bauleitung zu übergeben. Bei brandschutztechnischen Anforderungen an Doppel- und Hohlböden sind die betreffenden Allgemeinen Bauaufsichtlichen Prüfzeugnisse (ABP), die zugehörigen Übereinstimmungserklärungen der Hersteller und der Nachweis über den Einbau schwerentflammbarer Dichtungen rechtzeitig zur Abnahme vorzulegen. Klebstoffe müssen so beschaffen sein, dass durch sie eine feste und dauerhafte Verbindung erreicht wird. Sie dürfen die zu klebenden Materialien nicht negativ beeinflussen und nach der Verarbeitung keine Belästigung durch Geruch hervorrufen. Angaben zur Ausführung Allgemeines Vor Ausführungsbeginn hat der Auftragnehmer mit dem Auftraggeber festzulegen, wo das zu verwendende Material auf der Baustelle gelagert werden kann, um gegenseitige Störungen der am Bau beteiligten Handwerker während der Bauausführung zu vermeiden. Vor der Durchführung von Stemm-, Bohr- und Einsetzarbeiten an Estrichen sowie geputzten Wänden und Decken sind Leitungen mit einem Suchgerät zu orten. Späne vom Bohren und Fräsen sowie Reste von Schleifstaub sind sofort von den bearbeiteten Teilen zu entfernen. Der Auftragnehmer hat sich beim Befestigen von Bauteilen an Vorsatzschalen zu vergewissern, dass durch die Befestigungsmittel keine Beschädigungen nicht sichtbarer Leitungen und Rohre entstehen. Säulen von Schwenkarmaufzügen dürfen nicht zwischen Balkonen oder Kragplatten eingespannt werden; beim Einspannen in Mauerwerksöffnungen sind diese vor Beschädigungen zu schützen, nach Möglichkeit sind Fensterwinkel zu verwenden. Alle Maße sind vor der Ausführung am Bau zu überprüfen, sofern keine Detailzeichnungen mit verbindlichen Maßangaben vorliegen. Vor Beginn der Arbeiten sind die tatsächlichen Einbauhöhen bezogen auf das gesamte Ausbausystem mit der Bauleitung abzustimmen, wenn unzulässige Toleranzen oder Änderungen des geplanten Fußbodenaufbaus festgestellt oder vermutet werden. Bei Schleifarbeiten im Trockenverfahren sind Absauggeräte zu verwenden. Beschädigungen an Dampfsperr- oder Dampfbremsschichten oder an luftdichten Schichten sind, wenn diese Schichten zum Leistungsumfang des Auftragnehmers zählen, vor dem Abdecken mit nachfolgenden Bauteilen dauerhaft und materialgerecht zu schließen. Beschädigungen an Dampfsperr- oder Dampfbremsschichten oder an luftdichten Schichten sind, wenn diese Schichten zum Leistungsumfang des Auftragnehmers zählen, vor dem Abdecken mit nachfolgenden Bauteilen dauerhaft und materialgerecht zu schließen. Wenn diese Schichten zum Leistungsumfang eines anderen Auftragnehmers zählen, ist mit der Bauleitung zu klären, wer die Schäden beseitigen soll. In beiden Fällen ist vor dem Abdecken mit nachfolgenden Bauteilen der Bauleitung die Überprüfung der Schadensbehebung zu ermöglichen. Bei brandschutztechnischen Anforderungen an Wände und Decken ist die Muster-Richtlinie über brandschutztechnische Anforderungen an Leitungsanlagen (Muster-Leitungsanlagen-Richtlinie - MLAR) zu beachten. Die Verarbeitungsvorschriften und -richtlinien der Hersteller der Trockenbausysteme sind zu beachten. Dem Auftraggeber ist auf Verlangen Einsicht in diese zu gewähren. Das gilt besonders für Anzahl und Anordnung der Befestigungspunkte sowie die Fugenausbildung. Die nach ATV DIN 18340 Abschnitt 3.7.2 erforderlichen Maßnahmen bei Türöffnungen sind in die Leistungen für das Anlegen der Türöffnungen einzurechnen. Offen bleibende Schnittkanten imprägnierter Platten, z.B. an Außenecken, sind nachzuimprägnieren. Die Verarbeitungsvorschriften und -richtlinien der Hersteller der Trockenbausysteme sind zu beachten. Dem Auftraggeber ist auf Verlangen Einsicht in diese zu gewähren. Das gilt besonders für Anzahl und Anordnung der Befestigungspunkte sowie die Fugenausbildung. Die nach ATV DIN 18340 Abschnitt 3.7.2 erforderlichen Maßnahmen bei Türöffnungen sind in die Leistungen für das Anlegen der Türöffnungen einzurechnen. Offen bleibende Schnittkanten imprägnierter Platten, z.B. an Außenecken, sind nachzuimprägnieren. Brandschutzkleber oder Brandschutzspachtelmassen sind so zu verarbeiten, dass überstehendes Material abgestrichen wird; ein großflächiges Verspachteln ist zu vermeiden. Dämmungen Bei der Ausführung von Bauteilen und Anschlüssen, die der Herstellung der Luftdichtheit des Gebäudes dienen, ist davon auszugehen, dass vor oder bei der Abnahme der Leistungen durch den Auftraggeber oder eine von ihm beauftragte Fachkraft eine Prüfung der Luftdichtheit durch einen Blowerdoor-Test durchgeführt wird. Trockenbauoberflächen Sofern bei der Beschreibung der Leistung nichts anderes angegeben ist, sind die Oberflächen von Innenputzen in der Qualitätsstufe Q2, laut der Regelausführung nach ATV DIN 18340, auszuführen. | K24: ="" | M24: 8f270fb6-cd3e-4ee8-aa0f-f64c9967067a
A25: Hinweistext | C25: TV | D25: Technische Vorbemerkung Für die vom Bieter anzubietenden Materialien, Ausführungen und Leistungen gelten die nachfolgend genannten Normen verbindlich: DIN-EN 13964 "Unterdecken - Anforderungen und Prüfverfahren". EN 13168 "Wärmedämmstoffe für Gebäude - Werksmäßig hergestellte Produkte aus Holzwolle (WW) - Spezifikation" Die Montagerichtlinien der Herstellerfirmen der verwendeten Materialien sind zu beachten. Nachweis der Gleichwertigkeit von Produkten Sollte von Seite des Anbieters ein alternatives, bzw. gleichwertiges Produkt angeboten werden, so sind die Produktkennwerte durch ein aktuelles Prüfzeugnis zu belegen, bzw. die Gleichwertigkeit über die im EC-Konformitätszertifikat deklarierten Werte nachzuweisen, insbesondere die Produkttoleranzen und Brennbarkeitsklasse. Als Nachweis dafür, dass das Produkt baubiologisch gleichwertig und einwandfrei ist, gilt das Zertifikat "Der Blaue Engel". Alle erforderlichen Nachweise für die Gleichwertigkeit bzw. Eignung der Produkte sind durch den Auftragnehmer (AN) zu erbringen. Der Korrosionsschutz aller Metallteile muss auf die am Einbauort herrschenden Bedingungen abgestimmt werden. Sichtbare Kanten, nachträglich hergestellte Fasen und Plattenschnittkanten, sowie Schraubenköpfe, Faserausbrüche etc. müssen farbig mit der vom Hersteller auf Anfrage mitgelieferten oder einer gleichwertigen Farbe nachbehandelt werden. Doppeleinfärbungen im Bereich der Schraubenköpfe sind zu vermeiden. | K25: ="" | M25: 65d6fb9c-fc61-4580-a5ed-75d597d0854b
A26: Hinweistext | C26: Anforderungen | D26: Befestigungen an Böden, Wände und an Decken 1. Untergründe / Materialien: Böden aus Betonwerkstoff Spannbetonhohlplattendecken (Betonwerkstoff) oder Kassettendecken (Fertigbetonelemente) Stahlbetonverbundträger (Unterzüge) Wände aus Beton mit Armierung (Stahlbeton) oder Mauerwerk 2. Böden: teilweise Fußbodenheizung! Bohrung nur nach Wärmebildüberprüfungvor Außerbetriebnahme der Heizungsanlage! Befestigungen im Bodenbereich durch Abdichtung: Abdichtung der Schrauben mit Flüssigkunststoff (Ausführung nur, wenn Befestigungen durch die Abdichtung eingebaut werden müssen) 3. Wände: konventionelle Dübelbefestigungen möglich 4. Decken: Befestigung allgemein (Boden und Decke) ober- u. unterseitig in Hohlkammerspannbetondielen mit Setzbolzen mit seitlichem Abstand mind. 5 cm zu Spannlitze unterseitig Teilbereiche unter StB-Verbundträger Befestigung an der Decke (Einteilung nach Zeichnung und Details) starrer Deckenanschluss an Hohlkammerspannbetondielen Kurzstrecken unterhalb StB-Verbundträger starrer Deckenanschluss an Hohlkammerspannbetondielen Kurzstrecken unterhalb StB-Verbundträger mit Brandschutzanforderung starrer Deckenanschluss an StB-Verbundträger (werksseitig vorgerüstet) starrer Deckenanschluss an StB-Verbundträger (werksseitig vorgerüstet) mit Brandschutzanforderung in Ortbetondecken konventionelle Dübelbefestigungen ober- u. unterseitig in Hohlkammerspannbetondielen mit Setzbolzen mit seitlichem Abstand mind. 5 cm zu Spannlitze unterseitig Teilbereiche unter StB-Verbundträger wenn nicht anders in den Leistungsbeschreibungen erwähnt, sind die Trennwände bis an die Rohdecke zu führen 5. Anforderungen Befestigungen: Befestigung mit bauaufsichtlich zugelassenen Befestigungsmitteln 6. Anforderungen Fugen und Anschlüsse: starrer angespachtelter Anschluss: in Verbindung mit Trennstreifen an Massivbauteile geringe Verformung der Anschlussteile (z.B. Durchbiegung) zulässig; "kontrollierte" gerade Haarfuge im Nutzungszustand mit Trennstreifen (nach ATV DIN 18340) "kontrollierte" gerade Haarfuge im Nutzungszustand mit Trennstreifen mit / ohne Profilhinterlegung; Tragprofil im Anschlussprofil aufliegend (bei Brandschutzanforderungen mit Profilhinterlegung ausführen) Hinweis: Deckentragprofile bei tragenden Anschlussprofilen mindestens 25 mm auflegen mit Trennstreifen ohne Profilhinterlegung bei freien Gipsplattenenden von circa 100 mm angeputzter Anschluss starrer angespachtelter / stumpfer Anschluss zwischen Trockenbaukonstruktionen: spezielle Anschlüsse für Trockenbaukonstruktionen untereinander mit stumpf gestoßenem Bewehrungsstreifen am Anschlussbauteil alternativ ohne Bewehrungsstreifen mit geeignetem Fugenspachtel möglich mit eingespachteltem Papierfugen-Bewehrungsstreifen über Eck (nur für Gipsplatten) Bei Gipsplatten und Gipsfaserplatten mit Stumpf gestoßenem Bewehrungsstreifen an Anschlussbauteil bzw. ohne Bewehrungsstreifen mit geeignetem Fugenspachtel möglich bei Gipsplatten alternativ mit über Eck eingespachtelten Papierfugen- Bewehrungsstreifen möglich Insbesondere bei Brandschutzanforderungen, sonst alternativ ohne Verschraubung der Platten zulässig Stumpf angearbeiteter Anschluss zwischen Trockenbaukonstruktionen stumpf gestoßene Gipsplatte/ Gipsfaserplatte Gipsplatte stumpf anarbeiten ohne anspachteln nach ATV DIN 18340 Nr. 3.1.8 eventuell zusätzliche Anforderungen an Schall- und Brandschutz sind zu berücksichtigen Anschlussfuge mit Dichtstoff Aufnahme von Schwindverformungen lediglich von 0,1 - 1 mm (ca. 10 - 15% der Fugenbreite) Dieser Anschluss ist nur geeignet bei Beschichtungen mit Putz einer Körnung = 2 mm in Anstrichen, Tapeten u. a. können Risse und Falten auftreten hinterlegter Trennstreifen zur Vermeidung von Dreiflankenhaftung des Dichtstoffes Dichtstoff sollte regelmäßig gewartet werden, (vgl. IVD Merkblatt 16) offene Anschlussfuge (Schattenfuge) (Schattenfuge) mögliche Rissbildungen werden optisch verdeckt mit hinterlegtem Plattenstreifen mit versetzter 2. Plattenlage eventuell zusätzliche Anforderungen an Schall- und Brandschutz sind zu berücksichtigen offene Feldfuge (Fuge in der Bekleidung der Konstruktion) offene Feldfuge Trennung der Beplankung zu dekorativen Zwecken und zur Reduzierung von Spannungen für Untergliederung von Flächen und Einschnürungen mit sichtbarer Unterkonstruktion offene Feldfuge Trennung der Beplankung: zur Reduzierung von Spannungen und zu dekorativen Zwecken auch für Flächengliederung und Vermeidung von Einschnürungen mit hinterlegtem Plattenstreifen gleitende Feldfuge (Bewegungsfuge; konstruktive Trennung) Trennung der gesamten Konstruktion geeignet als Dehnfuge nach DIN 18 183 Anordnung bei Überbrückung von konstruktiven Fugen des Baukörpers bzw. wenn die Wandlänge eine Unterteilung in Abschnitte erfordert. mit Fugenprofil eventuell zusätzliche Anforderungen an Schall- und Brandschutz sind zu berücksichtigen Dehnungsfuge in Montagewänden nach DIN 18183 mit Plattenhinterlegung bei Wänden mit Brandschutzanforderung Die Hinweise aus dem Merkblatt 3 (Fugen und Anschlüsse bei Gipsplatten- und Gipsfaserplattenkonstruktionen) von dem Bundesverband der Gipsplattenindustrie e.V. sind zu beachten. wenn nicht anders in den Leistungsbeschreibungen erwähnt, sind die Fugen und Anschlüsse nach den vorstehenden Hinweisen auszuführen Die Grundrisse, Schnitte und Details sind zwingend zu beachten. | K26: ="" | M26: 69e91a59-2ed2-4cc1-bb7f-0c9333d2fc92
A27: Summe Gruppe | B27: 00. | C27: Technische Vorbemerkungen | H27: =SUMIF(L:L,"65ff528d-fd75-41e8-8799-c493e17362ef",J:J) -> 0 | J27: =H27*(1-I27) -> 0 | L27: 6dc70e31-e96c-4610-bf73-f2ab9e6f1e90 | M27: 65ff528d-fd75-41e8-8799-c493e17362ef
A28: Gruppe | B28: 01. | C28: Planung, Prüfung und Bemusterung | K28: =""
A29: Position | B29: 01.010. | C29: Bauablaufplan | D29: Bauablaufplan fachgerecht erstellen. Umfang: Projektablaufplan auf Grundlage der Architektenplanung fachgerecht erstellen Bauablaufplan nur für die eigenen Leistungen (nicht für andere Gewerke) einschließlich Fortschreibung jede zweite Woche Anforderungen: Bauzeitenplan (Projektablaufplan) muss mindestens enthalten: Detaillierungsgrad als Koordinations- und Steuerungsplan Darstellung der Zeitskala in Wochen Darstellung von Verknüpfungen der Einzelgewerke Darstellung von Meilensteinen, z. B. Vertragsfristen Schnittstellentermin zu anderen Baumaßnahmen Darstellung der Mannmonatskurve Darstellung des kritischen Weges Darstellung der Pufferzeiten Darstellung von Sperrzeiten für Straßen- und Betriebsflächen Darstellungsart Balkendiagramm (Gantt chart) - Excelformat Bevorzugt: digital erstellt mit MS Project oder gleichwertig einschließlich regelmäßiges Fortschreiben (jede zweite Woche) der Dokumentation (Terminplanung/Bauzeitenplan) für die Gesamtdauer der eigenen Leistungen (Ausführungen), inklusive mit Übergabe (unaufgefordert) an die AG-Bauleitung | E29: 1 | F29: psch | G29: =SUMPRODUCT((Kalkulation!A2:A50000=B29)*Kalkulation!D2:D50000) -> 0 | H29: =G29*E29 -> 0 | J29: =H29*(1-I29) -> 0 | K29: =B2 -> 0 | L29: bc507428-c757-4ddf-97ea-138662557598 | M29: 7ccdf301-9e8c-42ee-a19e-ff46167299d2
A30: Position | B30: 01.020. | C30: Materialmuster | D30: Bemusterung der zu liefernden und einzubauenden Materialien durchführen. Umfang: Bemusterung der zu liefernden und einzubauenden Materialien müssen spätestens vier Wochen nach der Beauftragung (Bauvertrag) mit dem AG, der AG-Bauleitung und den Architekten durchgeführt werden Materialmuster für alle einzubauenden Materialien (Bauelemente), zur Abstimmung und Festlegungen der Detailausführungen von Farben, Oberflächen, Materialbeschaffungen u.a. liefern, vorlegen und vorhalten Handmuster Profilabschnitte mindestens 30 cm lang Muster der Unterkonstruktionen und Plattenbeläge Befestigungs- und Verbindungstypen Abdichtungen Vorlage der technischen Datenblätter zur Bemusterung ausreichend Aufstellung nicht abschließend Originalbauteile, die vom AN hergestellt und auf der Baustelle montiert werden, müssen uneingeschränkt den vom AN vorgelegten und vom AG genehmigten Handmustern entsprechen. Sämtliche Muster sind durch den AN bis zur Abnahme vorzuhalten und dauerhaft mit Angaben zum Bauvorhaben und allen wesentlichen Eigenschaften eindeutig zu kennzeichnen. Wenn im LV nicht anders beschrieben, sind die Muster nach erfolgter Abnahme der gesamten Bauleistung durch den AN zu entsorgen. Die Probenahmen für Eignungs- und Kontrollprüfungen sind grundsätzlich im Beisein eines verantwortlichen Vertreters des AG durchzuführen. Sämtliche Materialien sind vor ihrer Verwendung rechtzeitig der Bauleitung zur Genehmigung vorzulegen (Bemusterung). Werden nicht genehmigte Materialien, Geräte oder Bauteile eingebaut, gehen alle dadurch entstehenden Kosten zu Lasten des AN. Verspätete Bemusterungsvorlagen durch den AN, die zu Terminverzögerungen führen, hat der AN zu verantworten. Kommen Materialien oder Einbaugeräte zur Anwendung, für die amtliche oder bauaufsichtliche Zulassungen erforderlich sind, so sind diese Zulassungsbescheide mit Prüfberichten der Bemusterung beizufügen. | E30: 1 | F30: psch | G30: =SUMPRODUCT((Kalkulation!A2:A50000=B30)*Kalkulation!D2:D50000) -> 0 | H30: =G30*E30 -> 0 | J30: =H30*(1-I30) -> 0 | K30: =B2 -> 0 | L30: bc507428-c757-4ddf-97ea-138662557598 | M30: 945cb808-0199-4af7-b122-3856e8760f8b
A31: Summe Gruppe | B31: 01. | C31: Planung, Prüfung und Bemusterung | H31: =SUMIF(L:L,"bc507428-c757-4ddf-97ea-138662557598",J:J) -> 0 | J31: =H31*(1-I31) -> 0 | L31: 6dc70e31-e96c-4610-bf73-f2ab9e6f1e90 | M31: bc507428-c757-4ddf-97ea-138662557598
A32: Gruppe | B32: 02. | C32: Baustelleneinrichtung | K32: =""
A33: Position | B33: 02.010. | C33: Mobiles Arbeitsgerüst H= 4,00 m | D33: Mobiles Arbeitsgerüst (Rollrüstung) liefern, aufbauen und für die Dauer von vier Wochen vorhalten. Umfang: mobiles Arbeitsgerüst Anforderungen: Abmessung circa 2,00*2,00*6,00 m (L*B*H) Belastbarkeit gemäß Lastklasse 3 beträgt 200 kg/m² fahrbares Gerüst DIN 4420-3 Systemgerüst DIN EN 12810-1 entsprechend der Gerüstordnung DIN 4420 sowie den Vorschriften der Bauberufsgenossenschaft und den Bestimmungen der Bauaufsichtsbehörde, einschließlich An- und Abtransport und aller Nebenarbeiten als Modulgerüst Höhenabstand der Gerüstlagen 2,00 m zwei genutzte Gerüstlagen Höhe der obersten Gerüstlage circa 6 m im Gebäude bzw. Innen und Außen Gerüstlagen mit allseitigem Seitenschutz Um- und Abbaukosten der Rollrüstung sind in den Einheitspreis mit einzurechnen Mit dem Einheitspreis ist die Gebrauchsüberlassung der Rollrüstung für die Dauer von vier Wochen abgegolten | E33: 1 | F33: St | G33: =SUMPRODUCT((Kalkulation!A2:A50000=B33)*Kalkulation!D2:D50000) -> 0 | H33: =G33*E33 -> 0 | J33: =H33*(1-I33) -> 0 | K33: =B2 -> 0 | L33: dfe80876-8bad-418f-a63f-44afb52d5adf | M33: adefa4e9-16c8-4d34-bdf8-c2734fb5652f
A34: Position | B34: 02.020. | C34: mobile Rollrüstung H= 6,00 m vorhalten | D34: Verlängerte Vorhaltung mobile Rollrüstung (Vorposition). Umfang: Verlängerte Vorhaltung mobile Rollrüstung (Vorposition) über die vereinbarte Leistungszeit (Grundhaltezeit) hinaus vorhalten. Einschließlich Instandhaltung, Wartung und ggf. ersetzten bei Beschädigungen für die Dauer der vertraglichen Leistung des Auftragnehmers. Anforderungen: Vorhaltemenge 1 Stück Vorhaltungsdauer 6 Wochen Abrechnung: Stück*Woche | E34: 6 | F34: StWo | G34: =SUMPRODUCT((Kalkulation!A2:A50000=B34)*Kalkulation!D2:D50000) -> 0 | H34: =G34*E34 -> 0 | J34: =H34*(1-I34) -> 0 | K34: =B2 -> 0 | L34: dfe80876-8bad-418f-a63f-44afb52d5adf | M34: 0c4be034-a50b-47c6-a7bc-2d6a908ec285
A35: Summe Gruppe | B35: 02. | C35: Baustelleneinrichtung | H35: =SUMIF(L:L,"dfe80876-8bad-418f-a63f-44afb52d5adf",J:J) -> 0 | J35: =H35*(1-I35) -> 0 | L35: 6dc70e31-e96c-4610-bf73-f2ab9e6f1e90 | M35: dfe80876-8bad-418f-a63f-44afb52d5adf
A36: Gruppe | B36: 03. | C36: Kellergeschoss | K36: =""
A37: Gruppe | B37: 03.001. | C37: Wände | K37: =""
A38: Position | B38: 03.001.010. | C38: Aktionsbereich A | D38: Trockenbauwand liefern und fachgerecht einbauen. Umfang: Trockenbauwand aus Ständerwerk mit beidseitiger doppelter Beplankung beidseitig Wasserschutzklasse W1 Oberflächen ohne Fliesenbelag Ausführung nach Zeichnungen und Details (u.a. W112.de) Anforderungen: Nichttragende innere Trennwand nach DIN 4103-1 Bewertetes Schalldämm-Maß Rw = 58,4 dB Wandhöhe bis circa 3,10 m (OKRB/OKRD bis UKRD) Umlaufende Anschlüsse starr Anforderungen an Befestigungen in den Hinweisen (Vorbemerkungen) Befestigungsuntergründe: Wand: Mauerwerk / Stahlbeton/ Metallständer Decke: Spannbetonhohlplattendecken (Betonwerkstoff) und oder Kassettendecken (Fertigbetonelemente) Schallentkopplung mittels Dämmstreifen Bauteilabtrennung durch Spezialpapierstreifen Breite 2 x 65 mm Ausführung mit Unterkonstruktion aus verzinkten Stahlblechprofilen DIN 18182-1 Wanddicke 150 mm beidseitige Beplankung nach DIN 18180 jeweils zweilagig Plattendicke 2*12,5 mm pro Seite Metallständer CW 100 Ständerachsabstand ≤ 625 mm Boden und Deckenanschlüsse mit Randprofilen UW 100/40/06 Befestigung mit bauaufsichtlich zugelassenen Befestigungsmitteln Dämmschicht aus Mineralwolle nach DIN EN 13162: Dämmschicht aus Mineralwolle nach DIN EN 13162 Baustoffklasse A1, nichtbrennbar nach DIN 4102 und EN 13501-1 Dämmschicht Dicke mindestens 100 mm Wärmeleitfähigkeit λ ≤ 0,040 W/(mK) längenbezogener Strömungswiderstand nach DIN EN 29053: r ≥ 5 kPa·s/m² Rw = 58,4 dB Dämmschicht einlagig, dicht stoßen, abrutschsicher verlegen beidseitige zweilagige Beplankung mit GKBI-H2 DIN 18180 bzw. Typ H2 EN 520: 1. Seite: Beplankung aus Gipsplatten GKBI DIN 18180 bzw. Typ H2 EN 520 zweilagig Plattendicke 2*12,5 mm 2. Seite: Beplankung aus Gipsplatten GKBI DIN 18180 bzw. Typ H2 EN 520 zweilagig Plattendicke 2*12,5 mm Abmessungen: in circa (L*H) A=(3,21+3,59+1,48)*2,55 m A= 22 m² Verschraubung mit Schraubentyp XTN Verarbeitung gemäß DIN 18181 Verspachtelung der Gipsplatten gemäß Merkblatt Nr. 2 des Bundesverbandes der Gipsindustrie e.V. Qualitätsstufe Q3 bei Oberflächen ohne Fliesen Ausführung erfolgt unter Verwendung von DIN EN 13963, Spachtelmaterial Typ 4B oder alternativ Fügenfüller Typ 3B (muss für GKBI geeignet sein) einschließlich sämtlicher Nebenleistungen (Behelfe, Aufstiegshilfen, Befestigungen, Trennstreifen, Versiegelungen etc.) Abrechnung nach vollständiger Leistung nach Aufmaß in [m²] Ausführungsort: Aktionsbereich A (Kellergeschoss) | E38: 22 | F38: m² | G38: =SUMPRODUCT((Kalkulation!A2:A50000=B38)*Kalkulation!D2:D50000) -> 0 | H38: =G38*E38 -> 0 | J38: =H38*(1-I38) -> 0 | K38: =B2 -> 0 | L38: cdefce3d-812d-44a1-b101-3ab0820f44aa | M38: 10ec5a3f-f376-4ad9-a6de-a333f9b43eb2
A39: Position | B39: 03.001.020. | C39: Aktionsbereich B | D39: Trockenbauwand liefern und fachgerecht einbauen. Umfang: Ausführung wie Vorposition, jedoch 1. Seite Wasserschutzklasse W1 2. Seite Wasserschutzklasse W0 Ausführung nach Zeichnungen und Details (u.a. W112.de) Anforderungen: Dämmschicht aus Mineralwolle nach DIN EN 13162: Dämmschicht Dicke mindestens 100 mm Dämmschicht einlagig, dicht stoßen, abrutschsicher verlegen beidseitige zweilagige Beplankung: 1. Seite: Beplankung aus Gipsplatten GKBI DIN 18180 bzw. Typ H2 EN 520 zweilagig Plattendicke 2*12,5 mm 2. Seite: Beplankung aus Gipsplatten GKB-A DIN 18180 bzw. Typ A EN 520 zweilagig Plattendicke 2*12,5 mm Abmessungen: in circa (L*H) A=(2,82+3,79)*3,10 m A= 20,49 m² Verschraubung mit Schraubentyp XTN Verarbeitung gemäß DIN 18181 Verspachtelung der Gipsplatten gemäß Merkblatt Nr. 2 des Bundesverbandes der Gipsindustrie e.V. Qualitätsstufe Q3 bei Oberflächen ohne Fliesen Ausführung erfolgt unter Verwendung von DIN EN 13963, Spachtelmaterial Typ 4B oder alternativ Fügenfüller Typ 3B (muss für GKBI geeignet sein) einschließlich sämtlicher Nebenleistungen (Behelfe, Aufstiegshilfen, Befestigungen, Trennstreifen, Versiegelungen etc.) Abrechnung nach vollständiger Leistung nach Aufmaß in [m²] Ausführungsort: Aktionsbereich B (Kellergeschoss) | E39: 20.5 | F39: m² | G39: =SUMPRODUCT((Kalkulation!A2:A50000=B39)*Kalkulation!D2:D50000) -> 0 | H39: =G39*E39 -> 0 | J39: =H39*(1-I39) -> 0 | K39: =B2 -> 0 | L39: cdefce3d-812d-44a1-b101-3ab0820f44aa | M39: 84200507-b6b2-4f9d-8914-9a6f0bdf1b97
A40: Position | B40: 03.001.030. | C40: Aktionsbereich C | D40: Trockenbauwand liefern und fachgerecht einbauen. Umfang: Ausführung wie Vorposition, jedoch 1. Seite Wasserschutzklasse W1 2. Seite Wasserschutzklasse W0 Ausführung nach Zeichnungen und Details (u.a. W112.de) Anforderungen: Wanddicke 100 mm Metallständer CW 50 Ständerachsabstand ≤ 625 mm Boden und Deckenanschlüsse mit Randprofilen UW 50/40/06 Dämmschicht aus Mineralwolle nach DIN EN 13162: Dämmschicht Dicke mindestens 50 mm Dämmschicht einlagig, dicht stoßen, abrutschsicher verlegen beidseitige zweilagige Beplankung mit GKBI-H2 DIN 18180 bzw. Typ H2 EN 520: 1. Seite: Beplankung aus Gipsplatten GKBI DIN 18180 bzw. Typ H2 EN 520 zweilagig Plattendicke 2*12,5 mm 2. Seite: Beplankung aus Gipsplatten GKBI DIN 18180 bzw. Typ H2 EN 520 zweilagig Plattendicke 2*12,5 mm Abmessungen: in circa (L*H) A=3,06*3,10 m A= 9,49 m² Verschraubung mit Schraubentyp XTN Verarbeitung gemäß DIN 18181 Verspachtelung der Gipsplatten gemäß Merkblatt Nr. 2 des Bundesverbandes der Gipsindustrie e.V. Qualitätsstufe Q3 bei Oberflächen ohne Fliesen Ausführung erfolgt unter Verwendung von DIN EN 13963, Spachtelmaterial Typ 4B oder alternativ Fügenfüller Typ 3B (muss für GKBI geeignet sein) einschließlich sämtlicher Nebenleistungen (Behelfe, Aufstiegshilfen, Befestigungen, Trennstreifen, Versiegelungen etc.) Abrechnung nach vollständiger Leistung nach Aufmaß in [m²] Ausführungsort: Aktionsbereich C (Kellergeschoss) | E40: 10 | F40: m² | G40: =SUMPRODUCT((Kalkulation!A2:A50000=B40)*Kalkulation!D2:D50000) -> 0 | H40: =G40*E40 -> 0 | J40: =H40*(1-I40) -> 0 | K40: =B2 -> 0 | L40: cdefce3d-812d-44a1-b101-3ab0820f44aa | M40: bd8fb39a-1de0-4300-986b-b7074cdd7971
A41: Position | B41: 03.001.040. | C41: Aktionsbereich C1 | D41: Trockenbauwand liefern und fachgerecht einbauen. Umfang: Ausführung wie Vorposition, jedoch Wasserschutzklasse W1 einseitig einfach beplankt Ausführung nach Zeichnungen und Details (u.a. W112.de) Anforderungen: Wanddicke 100 mm Metallständer CW 75 Ständerachsabstand ≤ 625 mm Boden und Deckenanschlüsse mit Randprofilen UW 50/40/06 Dämmschicht aus Mineralwolle nach DIN EN 13162: Dämmschicht Dicke mindestens 60 mm Dämmschicht einlagig, dicht stoßen, abrutschsicher verlegen einseitige einfache Beplankung nach DIN 18180: Seite: Beplankung aus Gipsplatten GKBI DIN 18180 bzw. Typ H2 EN 520 einlagig Plattendicke 1*12,5 mm Abmessungen: in circa (L*H) A=2,30*3,10 m A= 7,13 m² Verschraubung mit Schraubentyp XTN Verarbeitung gemäß DIN 18181 Verspachtelung der Gipsplatten gemäß Merkblatt Nr. 2 des Bundesverbandes der Gipsindustrie e.V. Qualitätsstufe Q3 bei Oberflächen ohne Fliesen Ausführung erfolgt unter Verwendung von DIN EN 13963, Spachtelmaterial Typ 4B oder alternativ Fügenfüller Typ 3B (muss für GKBI geeignet sein) einschließlich sämtlicher Nebenleistungen (Behelfe, Aufstiegshilfen, Befestigungen, Trennstreifen, Versiegelungen etc.) Abrechnung nach vollständiger Leistung nach Aufmaß in [m²] Ausführungsort: Aktionsbereich C1 (Kellergeschoss) | E41: 7.5 | F41: m² | G41: =SUMPRODUCT((Kalkulation!A2:A50000=B41)*Kalkulation!D2:D50000) -> 0 | H41: =G41*E41 -> 0 | J41: =H41*(1-I41) -> 0 | K41: =B2 -> 0 | L41: cdefce3d-812d-44a1-b101-3ab0820f44aa | M41: e596475c-cf3f-4b69-9cd7-8f69cf8ea219
A42: Position | B42: 03.001.050. | C42: Aktionsbereich D | D42: Trockenbauwand liefern und fachgerecht einbauen. Umfang: Im Bereich der geplanten neuen Trennwände ist der vorhandene Estrichboden mit Trennlagen und Trittschalldämmung fachgerecht zu öffnen. Die Estrichkonstruktion ist entlang der geplanten Wandachsen zu schlitzen und aufzunehmen. Dabei sind sämtliche Schichten (Estrich, Trennlage, Trittschalldämmung) bis zur Rohdecke zu entfernen. Rückbau Estrich mit Unterbauten bis OK Betonrohboden. Abbruchstoffe fachgerecht als Bauabfall entsorgen Trockenbauwand aus Ständerwerk mit beidseitiger doppelter Beplankung Küchenseitig Wasserschutzklasse W3 Cafeseitig Wasserschutzklasse W0 Ausführung nach Zeichnungen und Details (u.a. W112.de bzw. K913.de) Anforderungen: Ausführungshinweise Rückbau Estrich, Trennlagen und Trittschalldämmung: Die Schnittführung erfolgt gemäß den Ausführungsplänen der neuen Trennwände Die Arbeiten sind staubarm und erschütterungsfrei durchzuführen, um angrenzende Bauteile nicht zu beeinträchtigen Die aufgenommenen Materialien sind sortenrein zu trennen und gemäß den geltenden Vorschriften als Bauabfälle zu entsorgen Nach dem Rückbau ist die Fläche für die Montage der Trennwände vorzubereiten (z. B. Reinigung, ggf. Grundierung) Besondere Anforderungen: Berücksichtigung von Schallschutzmaßnahmen: Die Trittschalldämmung darf nicht unkontrolliert unterbrochen werden. Trockenbauwand: Nichttragende innere Trennwand nach DIN 4103-1 Bewertetes Schalldämm-Maß Rw = 58,4 dB Wandhöhe bis circa 3,10 m (OKRB/OKRD bis UKRD) Umlaufende Anschlüsse starr Anforderungen an Befestigungen in den Hinweisen (Vorbemerkungen) Befestigungsuntergründe: Wand: Mauerwerk / Stahlbeton/ Metallständer Decke: Spannbetonhohlplattendecken (Betonwerkstoff) und oder Kassettendecken (Fertigbetonelemente) Schallentkopplung mittels Dämmstreifen Bauteilabtrennung durch Spezialpapierstreifen Breite 2 x 65 mm Ausführung mit Unterkonstruktion aus verzinkten Stahlblechprofilen DIN 18182-1 Wanddicke 125 mm beidseitige Beplankung nach DIN 18180 jeweils zweilagig Plattendicke 2*12,5 mm pro Seite Metallständer CW 75 C3 Ständerachsabstand ≤ 625 mm Boden und Deckenanschlüsse mit Randprofilen UW 75/40/06 Befestigung mit bauaufsichtlich zugelassenen Befestigungsmitteln Dämmschicht aus Mineralwolle nach DIN EN 13162: Dämmschicht aus Mineralwolle nach DIN EN 13162 Baustoffklasse A1, nichtbrennbar nach DIN 4102 und EN 13501-1 Dämmschicht Dicke mindestens 60 mm Wärmeleitfähigkeit λ ≤ 0,040 W/(mK) längenbezogener Strömungswiderstand nach DIN EN 29053: r ≥ 5 kPa·s/m² Rw = 58,4 dB Dämmschicht einlagig, dicht stoßen, abrutschsicher verlegen beidseitige zweilagige Beplankung nach DIN 18180: 1. Seite: Beplankung aus Gipsplatten GKB-A DIN 18180 bzw. Typ A EN 520 zweilagig Plattendicke 2*12,5 mm 2. Seite: Beplankung aus Zementbauplatten DIN EN 12467 bzw. Indoor 12,5 LEF DE zweilagig Plattendicke 2*12,5 mm Abmessungen: in circa (L*H) A=5,81*3,10 m A= 18,01 m² Verschraubung mit Schraubentyp XTN Verarbeitung gemäß DIN 18181 Verspachtelung der Gipsplatten gemäß Merkblatt Nr. 2 des Bundesverbandes der Gipsindustrie e.V. Qualitätsstufe Q3 bei Oberflächen ohne Fliesen Ausführung erfolgt unter Verwendung von DIN EN 13963, Spachtelmaterial Typ 4B oder alternativ Fügenfüller Typ 3B (muss für GKBI geeignet sein) einschließlich sämtlicher Nebenleistungen (Behelfe, Aufstiegshilfen, Befestigungen, Trennstreifen, Versiegelungen etc.) Abrechnung nach vollständiger Leistung nach Aufmaß in [m²] Ausführungsort: Aktionsbereich D (Kellergeschoss) | E42: 18.5 | F42: m² | G42: =SUMPRODUCT((Kalkulation!A2:A50000=B42)*Kalkulation!D2:D50000) -> 0 | H42: =G42*E42 -> 0 | J42: =H42*(1-I42) -> 0 | K42: =B2 -> 0 | L42: cdefce3d-812d-44a1-b101-3ab0820f44aa | M42: c205085d-32b9-4f1c-bb7b-de2f5ee04af0
A43: Position | B43: 03.001.060. | C43: Aktionsbereich E | D43: Trockenbauwand liefern und fachgerecht einbauen. Umfang: Im Bereich der geplanten neuen Trennwände ist der vorhandene Estrichboden mit Trennlagen und Trittschalldämmung fachgerecht zu öffnen. Die Estrichkonstruktion ist entlang der geplanten Wandachsen zu schlitzen und aufzunehmen. Dabei sind sämtliche Schichten (Estrich, Trennlage, Trittschalldämmung) bis zur Rohdecke zu entfernen. Rückbau Estrich mit Unterbauten bis OK Betonrohboden. Abbruchstoffe fachgerecht als Bauabfall entsorgen Trockenbauwand aus Ständerwerk mit einseitiger doppelter Beplankung Wasserschutzklasse W0 Ausführung nach Zeichnungen und Details (u.a. W112.de) Anforderungen: Nichttragende innere Trennwand nach DIN 4103-1 Bewertetes Schalldämm-Maß Rw = 58,4 dB Wandhöhe bis circa 3,10 m (OKRB/OKRD bis UKRD) Umlaufende Anschlüsse starr Anforderungen an Befestigungen in den Hinweisen (Vorbemerkungen) Befestigungsuntergründe: Wand: Mauerwerk / Stahlbeton/ Metallständer Decke: Spannbetonhohlplattendecken (Betonwerkstoff) und oder Kassettendecken (Fertigbetonelemente) Schallentkopplung mittels Dämmstreifen Bauteilabtrennung durch Spezialpapierstreifen Breite 2 x 65 mm Ausführung mit Unterkonstruktion aus verzinkten Stahlblechprofilen DIN 18182-1 Wanddicke 100 mm einseitige Beplankung nach DIN 18180 zweilagig Plattendicke 2*12,5 mm Metallständer CW 50 Ständerachsabstand ≤ 625 mm Boden und Deckenanschlüsse mit Randprofilen UW 50/40/06 Befestigung mit bauaufsichtlich zugelassenen Befestigungsmitteln Dämmschicht aus Mineralwolle nach DIN EN 13162: Dämmschicht aus Mineralwolle nach DIN EN 13162 Baustoffklasse A1, nichtbrennbar nach DIN 4102 und EN 13501-1 Dämmschicht Dicke mindestens 50 mm Wärmeleitfähigkeit λ ≤ 0,040 W/(mK) längenbezogener Strömungswiderstand nach DIN EN 29053: r ≥ 5 kPa·s/m² Rw = 58,4 dB Dämmschicht einlagig, dicht stoßen, abrutschsicher verlegen einseitige zweilagige Beplankung nachDIN 18180: Seite: Beplankung aus Gipsplatten GKB-A DIN 18180 bzw. Typ A EN 520 zweilagig Plattendicke 2*12,5 mm Abmessungen: in circa (L*H) A=1,80*3,10 m A= 5,58 m² Verschraubung mit Schraubentyp XTN Verarbeitung gemäß DIN 18181 Verspachtelung der Gipsplatten gemäß Merkblatt Nr. 2 des Bundesverbandes der Gipsindustrie e.V. Qualitätsstufe Q3 bei Oberflächen ohne Fliesen Ausführung erfolgt unter Verwendung von DIN EN 13963, Spachtelmaterial Typ 4B oder alternativ Fügenfüller Typ 3B (muss für GKBI geeignet sein) einschließlich sämtlicher Nebenleistungen (Behelfe, Aufstiegshilfen, Befestigungen, Trennstreifen, Versiegelungen etc.) Abrechnung nach vollständiger Leistung nach Aufmaß in [m²] Ausführungsort: Aktionsbereich E (Kellergeschoss) | E43: 6 | F43: m² | G43: =SUMPRODUCT((Kalkulation!A2:A50000=B43)*Kalkulation!D2:D50000) -> 0 | H43: =G43*E43 -> 0 | J43: =H43*(1-I43) -> 0 | K43: =B2 -> 0 | L43: cdefce3d-812d-44a1-b101-3ab0820f44aa | M43: 9956e1be-1b5c-427d-a468-32d860756c1d
A44: Position | B44: 03.001.070. | C44: Aktionsbereich F | D44: Trockenbauwand liefern und fachgerecht einbauen. Umfang: Im Bereich der geplanten neuen Trennwände ist der vorhandene Estrichboden mit Trennlagen und Trittschalldämmung fachgerecht zu öffnen. Die Estrichkonstruktion ist entlang der geplanten Wandachsen zu schlitzen und aufzunehmen. Dabei sind sämtliche Schichten (Estrich, Trennlage, Trittschalldämmung) bis zur Rohdecke zu entfernen. Rückbau Estrich mit Unterbauten bis OK Betonrohboden. Abbruchstoffe fachgerecht als Bauabfall entsorgen Trockenbauwand aus Ständerwerk mit beidseitiger doppelter Beplankung beidseitig Wasserschutzklasse W0 Oberflächen ohne Fliesenbelag Ausführung nach Zeichnungen und Details (u.a. W112.de) Anforderungen: Ausführungshinweise Rückbau Estrich, Trennlagen und Trittschalldämmung: Die Schnittführung erfolgt gemäß den Ausführungsplänen der neuen Trennwände Die Arbeiten sind staubarm und erschütterungsfrei durchzuführen, um angrenzende Bauteile nicht zu beeinträchtigen Die aufgenommenen Materialien sind sortenrein zu trennen und gemäß den geltenden Vorschriften als Bauabfälle zu entsorgen Nach dem Rückbau ist die Fläche für die Montage der Trennwände vorzubereiten (z. B. Reinigung, ggf. Grundierung) Besondere Anforderungen: Berücksichtigung von Schallschutzmaßnahmen: Die Trittschalldämmung darf nicht unkontrolliert unterbrochen werden. Trockenbauwand: Nichttragende innere Trennwand nach DIN 4103-1 Bewertetes Schalldämm-Maß Rw = 58,4 dB Wandhöhe bis circa 3,10 m (OKRB/OKRD bis UKRD) Umlaufende Anschlüsse starr Anforderungen an Befestigungen in den Hinweisen (Vorbemerkungen) Befestigungsuntergründe: Wand: Mauerwerk / Stahlbeton/ Metallständer Decke: Spannbetonhohlplattendecken (Betonwerkstoff) und oder Kassettendecken (Fertigbetonelemente) Schallentkopplung mittels Dämmstreifen Bauteilabtrennung durch Spezialpapierstreifen Breite 2 x 65 mm Ausführung mit Unterkonstruktion aus verzinkten Stahlblechprofilen DIN 18182-1 Wanddicke 150 mm beidseitige Beplankung nach DIN 18180 jeweils zweilagig Plattendicke 2*12,5 mm pro Seite Metallständer CW 100 Ständerachsabstand ≤ 625 mm Boden und Deckenanschlüsse mit Randprofilen UW 100/40/06 Befestigung mit bauaufsichtlich zugelassenen Befestigungsmitteln Dämmschicht aus Mineralwolle nach DIN EN 13162: Dämmschicht aus Mineralwolle nach DIN EN 13162 Baustoffklasse A1, nichtbrennbar nach DIN 4102 und EN 13501-1 Dämmschicht Dicke mindestens 100 mm Wärmeleitfähigkeit λ ≤ 0,040 W/(mK) längenbezogener Strömungswiderstand nach DIN EN 29053: r ≥ 5 kPa·s/m² Rw = 58,4 dB Dämmschicht einlagig, dicht stoßen, abrutschsicher verlegen beidseitige zweilagige Beplankung nach DIN 18180: 1. Seite: Beplankung aus Gipsplatten GKB-A DIN 18180 bzw. Typ A EN 520 zweilagig Plattendicke 2*12,5 mm 2. Seite: Beplankung aus Gipsplatten GKB-A DIN 18180 bzw. Typ A EN 520 zweilagig Plattendicke 2*12,5 mm Abmessungen: in circa (L*H) A=3,42*3,10 m A= 10,60 m² Verschraubung mit Schraubentyp XTN Verarbeitung gemäß DIN 18181 Verspachtelung der Gipsplatten gemäß Merkblatt Nr. 2 des Bundesverbandes der Gipsindustrie e.V. Qualitätsstufe Q3 bei Oberflächen ohne Fliesen Ausführung erfolgt unter Verwendung von DIN EN 13963, Spachtelmaterial Typ 4B oder alternativ Fügenfüller Typ 3B (muss für GKBI geeignet sein) einschließlich sämtlicher Nebenleistungen (Behelfe, Aufstiegshilfen, Befestigungen, Trennstreifen, Versiegelungen etc.) Abrechnung nach vollständiger Leistung nach Aufmaß in [m²] Ausführungsort: Aktionsbereich F (Kellergeschoss) | E44: 11 | F44: m² | G44: =SUMPRODUCT((Kalkulation!A2:A50000=B44)*Kalkulation!D2:D50000) -> 0 | H44: =G44*E44 -> 0 | J44: =H44*(1-I44) -> 0 | K44: =B2 -> 0 | L44: cdefce3d-812d-44a1-b101-3ab0820f44aa | M44: a10204d4-4a88-4c32-9963-e04579e48a01
A45: Position | B45: 03.001.080. | C45: Aktionsbereich G | D45: Trennwand aus GK-Fireboardplatten fachgerecht herstellen. Umfang: Im Bereich der geplanten neuen Trennwände ist der vorhandene Estrichboden mit Trennlagen und Trittschalldämmung fachgerecht zu öffnen. Die Estrichkonstruktion ist entlang der geplanten Wandachsen zu schlitzen und aufzunehmen. Dabei sind sämtliche Schichten (Estrich, Trennlage, Trittschalldämmung) bis zur Rohdecke zu entfernen. Rückbau Estrich mit Unterbauten bis OK Betonrohboden. Abbruchstoffe fachgerecht als Bauabfall entsorgen Trennwand aus mit GK-Fireboardplatten beplanktem Metallständerwerk einschließlich integrierter Dämmung, fachgerecht herstellen und einbauen. beidseitig dreifache Beplankung mit Einlage Ausführung nach den Vorbemerkungen, Zeichnung und Details (u.a. W133.de) Anforderungen: Ausführungshinweise Rückbau Estrich, Trennlagen und Trittschalldämmung: Die Schnittführung erfolgt gemäß den Ausführungsplänen der neuen Trennwände Die Arbeiten sind staubarm und erschütterungsfrei durchzuführen, um angrenzende Bauteile nicht zu beeinträchtigen Die aufgenommenen Materialien sind sortenrein zu trennen und gemäß den geltenden Vorschriften als Bauabfälle zu entsorgen Nach dem Rückbau ist die Fläche für die Montage der Trennwände vorzubereiten (z. B. Reinigung, ggf. Grundierung) Besondere Anforderungen: Berücksichtigung von Schallschutzmaßnahmen: Die Trittschalldämmung darf nicht unkontrolliert unterbrochen werden. Trockenbauwand: Nichttragende innere Trennwand nach DIN 4103-1 Brandschutztechnische Anforderungen an die Bekleidung Feuerwiderstandsklasse 90 Minuten nach DIN 4102-2 Bewertetes Schalldämm-Maß Rw = 71,6 dB Wandhöhe bis circa 3,10 m (OKRB/OKRD bis UKRD) Umlaufende Anschlüsse starr Anforderungen an Befestigungen in den Hinweisen (Vorbemerkungen) Befestigungsuntergründe: Wand: Mauerwerk / Stahlbeton/ Metallständer Decke: Spannbetonhohlplattendecken (Betonwerkstoff) und oder Kassettendecken (Fertigbetonelemente) Schallentkopplung mittels Dämmstreifen Bauteilabtrennung durch Spezialpapierstreifen Breite 2 x 65 mm Ausführung mit Unterkonstruktion aus verzinkten Stahlblechprofilen DIN 18182-1 Wanddicke 100 mm beidseitige Beplankung nach DIN 18180 jeweils zweilagig Plattendicke 2*12,5 mm pro Seite Metallständer CW 50 Ständerachsabstand ≤ 312,5 mm Boden und Deckenanschlüsse mit Randprofilen UW 50/40/06 Befestigung mit bauaufsichtlich zugelassenen Befestigungsmitteln Dämmschicht aus Mineralwolle nach DIN EN 13162: Dämmschicht aus Mineralwolle nach DIN EN 13162 Baustoffklasse A1, nichtbrennbar nach DIN 4102 und EN 13501-1 Dämmschicht Dicke mindestens 50 mm Wärmeleitfähigkeit λ ≤ 0,040 W/(mK) längenbezogener Strömungswiderstand nach DIN EN 29053: r ≥ 5 kPa·s/m² R´w,R = 50,7 dB = erf. R´w = Rw = 71,6 dB Dämmschicht einlagig, dicht stoßen, abrutschsicher verlegen Beplankung beidseitig, zweilagig nach DIN 18180: 1. Seite: Beplankung aus GKBF DIN 18180 bzw. Typ DFH2IR EN 520 zweilagig Plattendicke 2*12,5 mm 2. Seite: Beplankung aus GKBF DIN 18180 bzw. Typ DFH2IR EN 520 zweilagig Plattendicke 2*12,5 mm Abmessungen: in circa (L*H) A=1,47*3,10 m A= 4,56 m² Verschraubung mit Schraubentyp XTN Verarbeitung gemäß DIN 18181 Verspachtelung der Gipsplatten gemäß Merkblatt Nr. 2 des Bundesverbandes der Gipsindustrie e.V. Qualitätsstufe Q3 bei Oberflächen ohne Fliesen Ausführung erfolgt unter Verwendung von DIN EN 13963, Spachtelmaterial Typ 4B oder alternativ Fügenfüller Typ 3B einschließlich sämtlicher Nebenleistungen (Behelfe, Aufstiegshilfen, Befestigungen, Trennstreifen, Versiegelungen etc.) Abrechnung nach vollständiger Leistung nach Aufmaß in [m²] Hinweis: Die Ausführung ist eine Erweiterung zum Verwendbarkeitsnachweis Brandschutz Ausführungsort: Aktionsbereich G (Kellergeschoss - vgl. Lageplan/Grundriss) | E45: 5 | F45: m² | G45: =SUMPRODUCT((Kalkulation!A2:A50000=B45)*Kalkulation!D2:D50000) -> 0 | H45: =G45*E45 -> 0 | J45: =H45*(1-I45) -> 0 | K45: =B2 -> 0 | L45: cdefce3d-812d-44a1-b101-3ab0820f44aa | M45: 60636e53-7d28-4d41-9caa-5957fa8041a6
A46: Position | B46: 03.001.090. | C46: Aktionsbereich H | D46: Schachtwand liefern und fachgerecht einbauen. Umfang: Schachtwand als Trockenbauwand Trockenbauwand aus Ständerwerk Raumhoch mit einseitiger doppelter Beplankung Wasserschutzklasse W0 Ausführung nach Zeichnungen und Details (u.a. W628B) Anforderungen: Nichttragende innere Schachtwand nach DIN 4103-1 Bewertetes Schalldämm-Maß Rw = 58,4 dB Wandhöhe bis circa 3,10 m (OKRB/OKRD bis UKRD) Umlaufende Anschlüsse starr Anforderungen an Befestigungen in den Hinweisen (Vorbemerkungen) Befestigungsuntergründe: Wand: Mauerwerk / Stahlbeton/ Metallständer Decke: Spannbetonhohlplattendecken (Betonwerkstoff) und oder Kassettendecken (Fertigbetonelemente) Schallentkopplung mittels Dämmstreifen Bauteilabtrennung durch Spezialpapierstreifen Breite 2 x 65 mm Ausführung mit Unterkonstruktion aus verzinkten Stahlblechprofilen DIN 18182-1 Wanddicke 75 mm einseitige Beplankung nach DIN 18180 zweilagig Plattendicke 2*12,5 mm Metallständer CW 50 Ständerachsabstand ≤ 625 mm Boden und Deckenanschlüsse mit Randprofilen UW 50/40/06 Befestigung mit bauaufsichtlich zugelassenen Befestigungsmitteln Dämmschicht aus Mineralwolle nach DIN EN 13162: Dämmschicht aus Mineralwolle nach DIN EN 13162 Baustoffklasse A1, nichtbrennbar nach DIN 4102 und EN 13501-1 Dämmschicht Dicke mindestens 50 mm Wärmeleitfähigkeit λ ≤ 0,040 W/(mK) längenbezogener Strömungswiderstand nach DIN EN 29053: r ≥ 5 kPa·s/m² Rw = 58,4 dB Dämmschicht einlagig, dicht stoßen, abrutschsicher verlegen einseitige zweilagige Beplankung nach DIN 18180: Seite: Beplankung aus Gipsplatten GKB-A DIN 18180 bzw. Typ A EN 520 zweilagig Plattendicke 2*12,5 mm Abmessungen: Schachtwand/Abkofferung Raumhoch in circa (L+B*H) A=((0,61+1,51)*3,10)+((0,35+0,34+0,35)*3,10)+((0,18+0,35+0,18)*3,10) A= 12 m² Verschraubung mit Schraubentyp XTN Verarbeitung gemäß DIN 18181 Verspachtelung der Gipsplatten gemäß Merkblatt Nr. 2 des Bundesverbandes der Gipsindustrie e.V. Qualitätsstufe Q3 Ausführung erfolgt unter Verwendung von DIN EN 13963, Spachtelmaterial Typ 4B oder alternativ Fügenfüller Typ 3B (muss für GKBI geeignet sein) einschließlich sämtlicher Nebenleistungen (Behelfe, Aufstiegshilfen, Befestigungen, Trennstreifen, Versiegelungen etc.) Abrechnung nach vollständiger Leistung nach Aufmaß in [m²] Ausführungsort: Aktionsbereich H (Kellergeschoss) | E46: 12 | F46: m² | G46: =SUMPRODUCT((Kalkulation!A2:A50000=B46)*Kalkulation!D2:D50000) -> 0 | H46: =G46*E46 -> 0 | J46: =H46*(1-I46) -> 0 | K46: =B2 -> 0 | L46: cdefce3d-812d-44a1-b101-3ab0820f44aa | M46: d497bd42-f8ef-44b6-b477-df0e20aad0ed
A47: Summe Gruppe | B47: 03.001. | C47: Wände | H47: =SUMIF(L:L,"cdefce3d-812d-44a1-b101-3ab0820f44aa",J:J) -> 0 | J47: =H47*(1-I47) -> 0 | L47: 569847cc-caa6-419e-a984-b7ebaa522b0b | M47: cdefce3d-812d-44a1-b101-3ab0820f44aa
A48: Gruppe | B48: 03.002. | C48: Böden | K48: =""
A49: Position | B49: 03.002.010. | C49: Untergründe reinigen | D49: Untergrund aus Beton für weitere Maßnahmen fachgerecht reinigen. Umfang: Oberflächen Betonböden fachgerecht reinigen. Anforderungen: Reinigen des Untergrundes von haftungsmindernden Stoffen nach TRGS 559 ist trockenes Kehren von mineralischen Untergründen nicht zulässig gründliches Absaugen der Untergründe mit einem Industriestaubsauger lose Materialien aufnehmen und entsorgen Abfallstoffe und abgetragendes Gut fachgerecht als Bauschutt entsorgen Abfall ist nicht gefährlich und nicht schadstoffbelastet Abgerechnet nach vollständiger Ausführung und nach Aufmaß in [m²] Ausführungsort: Kellergeschoss 01-KG-00200 Kellergeschoss 01-KG-00170 Kellergeschoss 01-KG-00160 Kellergeschoss 01-KG-F0030 Kellergeschoss 01-KG-00190 Kellergeschoss 01-KG-00180 Kellergeschoss 01-KG-00230 | E49: 48.5 | F49: m² | G49: =SUMPRODUCT((Kalkulation!A2:A50000=B49)*Kalkulation!D2:D50000) -> 0 | H49: =G49*E49 -> 0 | J49: =H49*(1-I49) -> 0 | K49: =B2 -> 0 | L49: 2bebe10b-a0bc-4d8a-ba3b-b747a44fe147 | M49: 371e100f-4c16-45f3-9720-1478b296e1a9
A50: Position | B50: 03.002.020. | C50: DAE-EPS 20 mm | D50: Ausgleichschicht liefern und fachgerecht einbauen. Umfang: Ausgleichschicht aus EPS liefern und vollflächig auslegen nicht unterbrochene Lage unter schwimmenden Estrich einlagig einbauen Ausführung nach Zeichnung und Detail Anforderungen: Dämmplatten als Ausgleichsdämmung aus Polystyrol-Hartschaum Expandiertes Polystyrol (EPS) gemäß DIN 18560 verlegen und einbauen Wasserdampfdiffusion /μ-Wert (DIN EN 13163) 20/40 druckbelastbare Polystyrol-Hartschaum-Dämmplatte nach EN 13163 Dämmplatten EPS 040 DEO dh für Nutzlasten bis 5,0 KPa Anwendungstyp nach DIN 4108-10: DEO dh Druckfestigkeit 200 kPa bei 10% Stauchung Druckspannung bei 10% Stauchung > 200 kPa Druckspannung bei 2% Stauchung > 60 kPa dynamische Steifigkeit ≤ 10 MN/m³ (dickenabhängig) Brandverhalten Euroklasse: RtF - E CP-Wert 2 g emissionsgeprüfte EPS Wärme-Dämmplatte nach AgBB-Richtlinie Dämmstoffdicke 20 mm Einbauort: Kellergeschoss 01-KG-00200 Kellergeschoss 01-KG-00170 Kellergeschoss 01-KG-00160 Kellergeschoss 01-KG-F0030 Kellergeschoss 01-KG-00190 Kellergeschoss 01-KG-00180 Kellergeschoss 01-KG-00230 | E50: 48.5 | F50: m² | G50: =SUMPRODUCT((Kalkulation!A2:A50000=B50)*Kalkulation!D2:D50000) -> 0 | H50: =G50*E50 -> 0 | J50: =H50*(1-I50) -> 0 | K50: =B2 -> 0 | L50: 2bebe10b-a0bc-4d8a-ba3b-b747a44fe147 | M50: 6493fa65-1f70-400e-8ff2-f038ae98ac7f
A51: Position | B51: 03.002.030. | C51: TSD-EPS 30 mm | D51: Trittschalldämmung liefern und fachgerecht einbauen. Umfang: Trittschalldämmung vollflächig auslegen nicht unterbrochene Lage unter schwimmenden Estrich einlagig einbauen Ausführung nach Zeichnung und Detail Anforderungen: Dämmplatten als Ausgleichsdämmung und als Trittschalldämmung aus Polystyrol-Hartschaum Expandiertes Polystyrol (EPS) gemäß DIN 18560 verlegen und einbauen Wasserdampfdiffusion /μ-Wert (DIN EN 13163) 20/40 druckbelastbare Polystyrol-Hartschaum-Dämmplatte nach EN 13163 Dämmplatten EPS 045 DES sg 20 - 2 für Nutzlasten bis 5,0 KPa Anwendungstyp nach DIN 4108-10: DES sg Druckfestigkeit 200 kPa bei 10% Stauchung Druckspannung bei 10% Stauchung > 200 kPa Druckspannung bei 2% Stauchung > 60 kPa dynamische Steifigkeit ≤ 10 MN/m³ (dickenabhängig) Brandverhalten Euroklasse: RtF - E CP-Wert 2 g emissionsgeprüfte EPS Wärme-Dämmplatte nach AgBB-Richtlinie Dämmstoffdicke 30 mm Einbauort: Kellergeschoss 01-KG-00200 Kellergeschoss 01-KG-00170 Kellergeschoss 01-KG-00160 Kellergeschoss 01-KG-F0030 Kellergeschoss 01-KG-00190 Kellergeschoss 01-KG-00180 Kellergeschoss 01-KG-00230 | E51: 48.5 | F51: m² | G51: =SUMPRODUCT((Kalkulation!A2:A50000=B51)*Kalkulation!D2:D50000) -> 0 | H51: =G51*E51 -> 0 | J51: =H51*(1-I51) -> 0 | K51: =B2 -> 0 | L51: 2bebe10b-a0bc-4d8a-ba3b-b747a44fe147 | M51: bbc99fae-e8a9-4682-85c2-e335422894a1
A52: Position | B52: 03.002.040. | C52: Zementestrich CT-C35-F5-S65 | D52: Zementestrich liefern und fachgerecht einbauen. Umfang: Liefern und Einbau von Zementestrich als schwimmender Estrich auf Trennlage mit Dämmschicht zur Aufnahme von Belägen und oder Beschichtungen Oberfläche zur Aufnahme von Bodenbelag sauber verreiben Anforderungen: Estrich aus Werktrockenmörtel gemäß DIN 18560 der Festigkeitsklasse CT-C35-F5-S65 Estrichdicke 65 mm schwund- und spannungsarm Emissionsarm EMICODE EC 1 Plus aus ternärem Werktrockenmörtel gemäß den Technischen Richtlinien des Herstellers sorgfältig und homogen verdichten in richtiger Höhenlage ebenflächig nach den Anforderungen gemäß DIN 18202 Tab. 3, Zeile 3 Inklusive Oberfläche abreiben und glätten (egalisieren) einschließlich sämtlicher Nebenleistungen Ausführung nach Zeichnung und Detail Hinweis: Estrichmaterial muss außerhalb der Aktionsbereiche angemischt werden (im Bereich der Baustelleneinrichtung) Estrichmaterial muss händisch (Eimer etc.) in den Aktionsbereich eingebracht und eingebaut werden Einsatz von Estrichpumpen ist nicht vorgesehen Transportwege sind für den Transport der Baumaterialien temporär zu schützen (Nebenleistungen) Bodenbeläge in angrenzenden Bereichen dürfen nicht beschädigt und oder verschmutzt werden. Ausführungsort: Kellergeschoss 01-KG-00200 Kellergeschoss 01-KG-00170 Kellergeschoss 01-KG-00160 Kellergeschoss 01-KG-F0030 Kellergeschoss 01-KG-00190 Kellergeschoss 01-KG-00180 Kellergeschoss 01-KG-00230 | E52: 48.5 | F52: m² | G52: =SUMPRODUCT((Kalkulation!A2:A50000=B52)*Kalkulation!D2:D50000) -> 0 | H52: =G52*E52 -> 0 | J52: =H52*(1-I52) -> 0 | K52: =B2 -> 0 | L52: 2bebe10b-a0bc-4d8a-ba3b-b747a44fe147 | M52: 6e4c59c1-03e5-477a-a20a-e0755363495a
A53: Position | B53: 03.002.050. | C53: Estrichzusatzmittel | D53: Estrichzusatzmittel liefern und als Schnellhärter zu Zementestrich beigeben. Umfang: Estrichzusatzmittel als Schnellhärter Anforderungen: Vergütung zur Reduzierung Anmachwasserbedarf für Verbesserung der Verarbeitbarkeit, Verdichtungswilligkeit, Homogenität und Wärmedurchgang bei Warmwasserfußbodenheizungen Reduktion der Lunkerbildung, Spannungen im ausgehärteten Estrich und Rissbildung plastifizierende Wirkung für früher Begehbarkeit und früher Anfangsfestigkeit auf Dämmschicht, auf Trennschicht und im Verbund und Heizestrich nach ca. 24 Stunden verlegereif für Fliesen, Naturwerkstein und Betonwerksteinplatten nach ca. 3 Tagen verlegereif für elastische und textile Beläge Erfüllt die Anforderungen der DIN 18560 und EN 13813 (Festigkeitsklasse CT-C35-F5) Ausführungsort: Kellergeschoss 01-KG-00200 Kellergeschoss 01-KG-00170 Kellergeschoss 01-KG-00160 Kellergeschoss 01-KG-F0030 Kellergeschoss 01-KG-00190 Kellergeschoss 01-KG-00180 Kellergeschoss 01-KG-00230 | E53: 48.5 | F53: m² | G53: =SUMPRODUCT((Kalkulation!A2:A50000=B53)*Kalkulation!D2:D50000) -> 0 | H53: =G53*E53 -> 0 | J53: =H53*(1-I53) -> 0 | K53: =B2 -> 0 | L53: 2bebe10b-a0bc-4d8a-ba3b-b747a44fe147 | M53: 647c62e9-eead-478d-9e72-8c171bd17838
A54: Position | B54: 03.002.060. | C54: Trennlage | D54: Trennlage liefern und fachgerecht einbauen. Umfang: Abdeckung von Dämmungen unter Estrich (Trennlage) Anfordernungen: PE-Folie Regenerat-Folie aus Niederdruck-Polyethylen (LDPE) dampfdiffusionsoffen Dichte ca. 0,92 g/cm³ Zugfestigkeit ca. 10-25 N/mm² E-Modul ca. 150-250 N/mm² Diffusionsäquivalente Luft- 0,10 mm Dicke = > 50 m schichtdicke (SD-Wert): 0,15 mm Dicke = > 75 m 0,20 mm Dicke = > 100 m Schmelzpunkt ca. 110°C Temperaturbeständigkeit ca. -40°C - +80°C Ausführungsort: Kellergeschoss 01-KG-00200 Kellergeschoss 01-KG-00170 Kellergeschoss 01-KG-00160 Kellergeschoss 01-KG-F0030 Kellergeschoss 01-KG-00190 Kellergeschoss 01-KG-00180 Kellergeschoss 01-KG-00230 | E54: 50 | F54: m² | G54: =SUMPRODUCT((Kalkulation!A2:A50000=B54)*Kalkulation!D2:D50000) -> 0 | H54: =G54*E54 -> 0 | J54: =H54*(1-I54) -> 0 | K54: =B2 -> 0 | L54: 2bebe10b-a0bc-4d8a-ba3b-b747a44fe147 | M54: 42008c5c-f24b-464f-a0fe-11f0e4490527
A55: Position | B55: 03.002.070. | C55: Randdämmstreifen | D55: Randdämmstreifen liefern und fachgerecht einbauen. Umfang: Randdämmstreifen liefern und entlang aller aufgehenden Bauteile zur Ausbildung ordnungsgemäßer Randfugen und zur Vermeidung von Schallbrücken, fachgerecht einbauen. Randdämmstreifen zur Schallentkopplung an aufgehenden Bauteilen wie z. B. Wänden, Säulen Anforderungen: selbstklebenden PE Randstreifen (mit angeklebter Folie) nach Herstellerangaben sach- und fachgerecht verlegen die Technischen Richtlinien des Herstellers sind zu beachten standfest mit kaschiertem Folienstreifen für einen dichten Anschluss der Trennschicht ohne Hohlkehle Randdämmstreifen FE 10/180 befestigung aufsteigenden Bauteilen Randstreifen über die Estrichoberkante lückenlose Verlegung Stoßstellen im Randdämmstreifen müssen abgeklebt werden, um keine Mörtelbrücken zu erzeugen (Schallbrücke!) Ausführungsort: Kellergeschoss 01-KG-00200 Kellergeschoss 01-KG-00170 Kellergeschoss 01-KG-00160 Kellergeschoss 01-KG-F0030 Kellergeschoss 01-KG-00190 Kellergeschoss 01-KG-00180 Kellergeschoss 01-KG-00230 | E55: 62 | F55: m | G55: =SUMPRODUCT((Kalkulation!A2:A50000=B55)*Kalkulation!D2:D50000) -> 0 | H55: =G55*E55 -> 0 | J55: =H55*(1-I55) -> 0 | K55: =B2 -> 0 | L55: 2bebe10b-a0bc-4d8a-ba3b-b747a44fe147 | M55: a39a6e3b-adf0-497a-b067-759ee0bd62a9
A56: Position | B56: 03.002.080. | C56: Bewegungsfuge 10/65 | D56: Bewegungsfugenband liefern und fachgerecht in Estrich einbauen. Umfang: Fugenband für Bewegungsfugen in Estrichen aus Einzelteilen liefern und einbauen Bewegungsfugenband zur Erstellung einer Bewegungsfuge aus Einzelteilen. Bewegungsfugen einbauen, um Bewegungen und Verformungen durch Schwinden und Temperatureinwirkung aufzunehmen, um Höhenunterschiede im Estrich auszugleichen und um Bauwerksfugen aus dem Untergrund zu übernehmen. Ausführung nach Zeichnung und Detail Ausführungsort: Kellergeschoss 01-KG-00200 Kellergeschoss 01-KG-00170 Kellergeschoss 01-KG-00160 Kellergeschoss 01-KG-F0030 Kellergeschoss 01-KG-00190 Kellergeschoss 01-KG-00180 Kellergeschoss 01-KG-00230 | E56: 8 | F56: m | G56: =SUMPRODUCT((Kalkulation!A2:A50000=B56)*Kalkulation!D2:D50000) -> 0 | H56: =G56*E56 -> 0 | J56: =H56*(1-I56) -> 0 | K56: =B2 -> 0 | L56: 2bebe10b-a0bc-4d8a-ba3b-b747a44fe147 | M56: 9ef56687-dcfe-4c97-9aaa-a21d42482ff1
A57: Position | B57: 03.002.090. | C57: Scheinfugen | D57: Scheinfugen fachgerecht einbauen. Umfang: Scheinfungen (Sollreißfugen) als Sollbruchstelle in den Estrichböden einbauen Kellenschnitte an Einschnürungen Anforderungen: Scheinfugen (Sollbruchstellen) herstellen, die eine kontrollierte Rissbildung beim Verkürzen des Bauteils infolge des Schwindens einleiten. Tiefe bis zur Hälfte des Estrichdicke einschließlich dem kraftschlüssigen Verschluss der Scheinfungen nach Austrocknung bis zur Belegreife mit einem Reaktionsharz. Ausführungsort: Kellergeschoss 01-KG-00200 Kellergeschoss 01-KG-00170 Kellergeschoss 01-KG-00160 Kellergeschoss 01-KG-F0030 Kellergeschoss 01-KG-00190 Kellergeschoss 01-KG-00180 Kellergeschoss 01-KG-00230 | E57: 10 | F57: m | G57: =SUMPRODUCT((Kalkulation!A2:A50000=B57)*Kalkulation!D2:D50000) -> 0 | H57: =G57*E57 -> 0 | J57: =H57*(1-I57) -> 0 | K57: =B2 -> 0 | L57: 2bebe10b-a0bc-4d8a-ba3b-b747a44fe147 | M57: e5d8450d-c588-4d43-926e-2c7c06e8e467
A58: Position | B58: 03.002.100. | C58: Estrich abstellen | D58: Estrich fachgerecht abstellen. Umfang: Estrichboden z.B. für den Einbau von Duschelementen und für den Einbau von Ablaufrinnen abstellen Anforderungen: Abstellung im Estrichboden herstellen und einbauen einschließlich Schalungs- und Befestigungsmaterialien sowie sämtlichen Nebenleistungen Abstellung muss vor der Ausführung mit der AG-Bauleitung und der TGA abgestimmt werden in Schichtstärken Estrichboden bis 70 mm 2 Ausführung nach Zeichnung und Detail Abrechnung nach Aufmaß in [m] Ausführungsort: Kellergeschoss 01-KG-00200 Kellergeschoss 01-KG-00170 Kellergeschoss 01-KG-00160 Kellergeschoss 01-KG-F0030 Kellergeschoss 01-KG-00190 Kellergeschoss 01-KG-00180 Kellergeschoss 01-KG-00230 | E58: 6 | F58: m | G58: =SUMPRODUCT((Kalkulation!A2:A50000=B58)*Kalkulation!D2:D50000) -> 0 | H58: =G58*E58 -> 0 | J58: =H58*(1-I58) -> 0 | K58: =B2 -> 0 | L58: 2bebe10b-a0bc-4d8a-ba3b-b747a44fe147 | M58: 17afce97-f366-4c5a-be60-505b5aa2813a
A59: Position | B59: 03.002.110. | C59: Bodenöffnungen schließen (Estrichboden entfernen - | D59: Bodenöffnungen schließen (aus Leistungspositionen Estrichboden für den Einbau der Trennwände entfernen) Umfang: Untergründe reinigen (saugen) Trennlagen und Trittschalldämmungen ergänzen Randdämmstreifen liefern und einbauen inklusive Scheinfugen (sofern erforderlich - nur in Abstimmung mit der AG-Bauleitung) Estrich einbauen und am Bestand anpassen (angleichen) Oberfläche abreiben und glätten (egalisieren) Anforderungen: Reinigung in den Arbeitsbereichen nur saugen Trennlagen PE-Folie Regenerat-Folie aus Niederdruck-Polyethylen (LDPE) dampfdiffusionsoffen Diffusionsäquivalente Luft- 0,10 mm Dicke = > 50 m schichtdicke (SD-Wert): 0,15 mm Dicke = > 75 m 0,20 mm Dicke = > 100 m Dämmplatten als Ausgleichsdämmung aus Polystyrol-Hartschaum Expandiertes Polystyrol (EPS) Dämmplatten EPS 040 DEO dh Druckfestigkeit 200 kPa bei 10% Stauchung Dämmstoffdicke 20 mm einschließlich Anschluss am Bestand Dämmplatten als Ausgleichsdämmung und als Trittschalldämmung aus Polystyrol-Hartschaum Expandiertes Polystyrol (EPS) Dämmplatten EPS 045 DES sg 20 - 2 Druckfestigkeit 200 kPa bei 10% Stauchung Dämmstoffdicke 30 mm einschließlich Anschluss am Bestand Randdämmstreifen selbstklebenden PE Randstreifen (mit angeklebter Folie) mit kaschiertem Folienstreifen für einen dichten Anschluss der Trennschicht ohne Hohlkehle Randdämmstrefen FE 10/180 Estrich Estrich aus Werktrockenmörtel gemäß DIN 18560 der Festigkeitsklasse CT-C35-F5-S65 Estrichdicke 65 mm schwund- und spannungsarm gemäß den Technischen Richtlinien des Herstellers sorgfältig und homogen verdichten in richtiger Höhenlage ebenflächig nach den Anforderungen gemäß DIN 18202 Tab. 3, Zeile 3 Inklusive Oberfläche abreiben und glätten (egalisieren) einschließlich sämtlicher Nebenleistungen (Behelfe, Befestigungen, Verschnitt, Abdichtungen etc.) Ausführungsort: Kellergeschoss 01-KG-00200 Kellergeschoss 01-KG-00170 Kellergeschoss 01-KG-00160 Kellergeschoss 01-KG-F0030 Kellergeschoss 01-KG-00190 Kellergeschoss 01-KG-00180 Kellergeschoss 01-KG-00230 | E59: 12 | F59: m² | G59: =SUMPRODUCT((Kalkulation!A2:A50000=B59)*Kalkulation!D2:D50000) -> 0 | H59: =G59*E59 -> 0 | J59: =H59*(1-I59) -> 0 | K59: =B2 -> 0 | L59: 2bebe10b-a0bc-4d8a-ba3b-b747a44fe147 | M59: 85b0ad22-2a76-4074-9c69-94a8fec9d1f7
A60: Position | B60: 03.002.120. | C60: Bautrockner | D60: Bautrockner liefern und fachgerecht aufbauen. Umfang: Bautrockner liefern, fachgerecht aufbauen, in Betrieb nehmen und für die Dauer von 10 Tagen vorhalten. Einschließlich Wartung und Pflege (regelmäßiges Leeren, Beseitigung Kondensatwasser, Prüfen Filter etc.) und mehrfaches umstellen innerhalb des Gebäudes, je nach Anforderung und in Abstimmung mit der AG-Bauleitung. Anforderungen: Gerätetyp Bautrockner zur Miete Kondensationstrockner mit Energierückgewinnung Vibrationsfrei Abtauung automatisch, thermostatgesteuert (Heißgasabtauung) Kondensatabführung integrierter Auffangbehälter (überlaufgesichert, mit Kontrolllampe) Steuerung vollautomatisch, Bedien- und Kontrollfeld, Betriebsstundenzähler Anschlussart 1,8 m Netzkabel, gummiummantelt, mit Schuko-Stecker Entfeuchtungsleistung bei + 20 °C / 80 % rF: 32 Liter/Tag Kondensatbehältergröße 11 Liter Arbeitsbereich von + 3 °C bis + 30 °C / von 35 % rF bis 100 % rF Luftmenge 850 m³/Std. Versorgungsspannung 230 V / 50 Hz / 10 A Leistungsaufnahme (max.) 1.070 W einschließlich sämtlicher Nebenleistungen und inklusive rückstandsfreier Rückbau nach Nutzung Ausführungsort: Kellergeschoss 01-KG-00200 Kellergeschoss 01-KG-00170 Kellergeschoss 01-KG-00160 Kellergeschoss 01-KG-F0030 Kellergeschoss 01-KG-00190 Kellergeschoss 01-KG-00180 Kellergeschoss 01-KG-00230 | E60: 1 | F60: St | G60: =SUMPRODUCT((Kalkulation!A2:A50000=B60)*Kalkulation!D2:D50000) -> 0 | H60: =G60*E60 -> 0 | J60: =H60*(1-I60) -> 0 | K60: =B2 -> 0 | L60: 2bebe10b-a0bc-4d8a-ba3b-b747a44fe147 | M60: 8f82b797-376f-48e2-8ae8-c2364b148599
A61: Position | B61: 03.002.130. | C61: Adsorptionsentfeuchter | D61: Adsorptionstrockner liefern und fachgerecht aufbauen. Umfang: Adsorptionstrockner (Luftentfeuchter) liefern, fachgerecht aufbauen, in Betrieb nehmen und für die Dauer von 8 Tagen vorhalten. Einschließlich Wartung und Pflege (regelmäßiges Leeren, Beseitigung Kondensatwasser, Prüfen Filter etc.) und mehrfaches umstellen innerhalb des Gebäudes, je nach Anforderung und in Abstimmung mit der AG-Bauleitung. Anforderungen: Gerätetyp Adsorptionstrockner zur Miete Kondensatabführung über Abluftschlauch Vibrationsfrei Anschlussart Netzkabel, gummiummantelt, mit Schuko-Stecker Entfeuchtungsleistung bei + 20 °C / 60 % rF: 38,4 Liter/Tag Arbeitsbereich von - 20 °C bis + 35 °C Druckerhöhung 350 Pa Trockenluftvolumenstrom 310 m³/Std. Feuchtluftvolumenstrom 110 m³/Std. Versorgungsspannung 230 V / 50 Hz / 10 A Leistungsaufnahme (max.) 2.160 W einschließlich sämtlicher Nebenleistungen und inklusive rückstandsfreier Rückbau nach Nutzung Ausführungsort: Kellergeschoss 01-KG-00200 Kellergeschoss 01-KG-00170 Kellergeschoss 01-KG-00160 Kellergeschoss 01-KG-F0030 Kellergeschoss 01-KG-00190 Kellergeschoss 01-KG-00180 Kellergeschoss 01-KG-00230 | E61: 1 | F61: St | G61: =SUMPRODUCT((Kalkulation!A2:A50000=B61)*Kalkulation!D2:D50000) -> 0 | H61: =G61*E61 -> 0 | J61: =H61*(1-I61) -> 0 | K61: =B2 -> 0 | L61: 2bebe10b-a0bc-4d8a-ba3b-b747a44fe147 | M61: 89ff103d-14dc-460e-abd5-33f35afbac46
A62: Summe Gruppe | B62: 03.002. | C62: Böden | H62: =SUMIF(L:L,"2bebe10b-a0bc-4d8a-ba3b-b747a44fe147",J:J) -> 0 | J62: =H62*(1-I62) -> 0 | L62: 569847cc-caa6-419e-a984-b7ebaa522b0b | M62: 2bebe10b-a0bc-4d8a-ba3b-b747a44fe147
A63: Summe Gruppe | B63: 03. | C63: Kellergeschoss | H63: =SUMIF(L:L,"569847cc-caa6-419e-a984-b7ebaa522b0b",J:J) -> 0 | J63: =H63*(1-I63) -> 0 | L63: 6dc70e31-e96c-4610-bf73-f2ab9e6f1e90 | M63: 569847cc-caa6-419e-a984-b7ebaa522b0b
A64: Gruppe | B64: 04. | C64: Sockelgeschoss | K64: =""
A65: Gruppe | B65: 04.001. | C65: Wände | K65: =""
A66: Position | B66: 04.001.010. | C66: Aktionsbereich A | D66: Trennwand aus GK-Fireboardplatten fachgerecht herstellen. Umfang: Im Bereich der geplanten neuen Trennwände ist der vorhandene Estrichboden mit Trennlagen und Trittschalldämmung fachgerecht zu öffnen. Die Estrichkonstruktion ist entlang der geplanten Wandachsen zu schlitzen und aufzunehmen. Dabei sind sämtliche Schichten (Estrich, Trennlage, Trittschalldämmung) bis zur Rohdecke zu entfernen. Rückbau Estrich mit Unterbauten bis OK Betonrohboden. Abbruchstoffe fachgerecht als Bauabfall entsorgen Trennwand aus mit GK-Fireboardplatten beplanktem Metallständerwerk einschließlich integrierter Dämmung, fachgerecht herstellen und einbauen. beidseitig dreifache Beplankung mit Einlage Ausführung nach den Vorbemerkungen, Zeichnung und Details (u.a. W133.de) Anforderungen: Ausführungshinweise Rückbau Estrich, Trennlagen und Trittschalldämmung: Die Schnittführung erfolgt gemäß den Ausführungsplänen der neuen Trennwände Die Arbeiten sind staubarm und erschütterungsfrei durchzuführen, um angrenzende Bauteile nicht zu beeinträchtigen Die aufgenommenen Materialien sind sortenrein zu trennen und gemäß den geltenden Vorschriften als Bauabfälle zu entsorgen Nach dem Rückbau ist die Fläche für die Montage der Trennwände vorzubereiten (z. B. Reinigung, ggf. Grundierung) Besondere Anforderungen: Berücksichtigung von Schallschutzmaßnahmen: Die Trittschalldämmung darf nicht unkontrolliert unterbrochen werden. Trockenbauwand: Nichttragende innere Trennwand nach DIN 4103-1 Brandschutztechnische Anforderungen an die Bekleidung Feuerwiderstandsklasse 90 Minuten nach DIN 4102-2 Bewertetes Schalldämm-Maß Rw = 71,6 dB Wandhöhe bis circa 3,10 m (OKRB/OKRD bis UKRD) Umlaufende Anschlüsse starr Anforderungen an Befestigungen in den Hinweisen (Vorbemerkungen) Befestigungsuntergründe: Wand: Mauerwerk / Stahlbeton/ Metallständer Decke: Spannbetonhohlplattendecken (Betonwerkstoff) und oder Kassettendecken (Fertigbetonelemente) Schallentkopplung mittels Dämmstreifen Bauteilabtrennung durch Spezialpapierstreifen Breite 2 x 65 mm Ausführung mit Unterkonstruktion aus verzinkten Stahlblechprofilen DIN 18182-1 Wanddicke 150 mm beidseitige Beplankung nach DIN 18180 jeweils dreilagig Plattendicke 3*12,5 mm pro Seite Metallständer CW 75 Ständerachsabstand ≤ 312,5 mm Boden und Deckenanschlüsse mit Randprofilen UW 75/40/06 Befestigung mit bauaufsichtlich zugelassenen Befestigungsmitteln Dämmschicht aus Mineralwolle nach DIN EN 13162: Dämmschicht aus Mineralwolle nach DIN EN 13162 Baustoffklasse A1, nichtbrennbar nach DIN 4102 und EN 13501-1 Dämmschicht Dicke mindestens 60 mm Wärmeleitfähigkeit λ ≤ 0,040 W/(mK) längenbezogener Strömungswiderstand nach DIN EN 29053: r ≥ 5 kPa·s/m² R´w,R = 50,7 dB = erf. R´w = Rw = 71,6 dB Dämmschicht einlagig, dicht stoßen, abrutschsicher verlegen Beplankung beidseitig, dreilagig aus Gipsplatten GKF DIN 18180: 1. Seite: 1. (untere) und 2. (mittlere) Lage Beplankung aus Silentboard GKBF DIN 18180 bzw. Typ DF EN 520 zweilagig Plattendicke 2*12,5 mm Stahlblecheinlage je Wandseite Verzinktes Stahlblech als Platten oder Rollenware Stahlblechgüte DC01+ZE Materialstärke 0,5 mm Horizontale Verlegung mit Stoßüberlappung 100 mm Vertikale Stöße auf Ständern anordnen Verschraubung mit Schnellbauschrauben (nur zur Fixierung) 3. (obere) Lage Beplankung aus GKBF DIN 18180 Typ DFH2IR EN 520 (oder gleichwertig) einlagig Plattendicke 12,5 mm 2. Seite: 1. (untere) und 2. (mittlere) Lage Beplankung aus Silentboard GKBF DIN 18180 bzw. Typ DF EN 520 zweilagig Plattendicke 2*12,5 mm Stahlblecheinlage je Wandseite Verzinktes Stahlblech als Platten oder Rollenware Stahlblechgüte DC01+ZE Materialstärke 0,5 mm Horizontale Verlegung mit Stoßüberlappung 100 mm Vertikale Stöße auf Ständern anordnen Verschraubung mit Schnellbauschrauben (nur zur Fixierung) 3. (obere) Lage Beplankung aus GKBF DIN 18180 Typ DFH2IR EN 520 (oder gleichwertig) einlagig Plattendicke 12,5 mm Abmessungen: in circa (L*H) A=(1,10+0,97+1,46)*3,10 m A= 10,94 m² Verschraubung mit Schraubentyp XTN Verarbeitung gemäß DIN 18181 Verspachtelung der Gipsplatten gemäß Merkblatt Nr. 2 des Bundesverbandes der Gipsindustrie e.V. Qualitätsstufe Q3 Ausführung erfolgt unter Verwendung von DIN EN 13963, Spachtelmaterial Typ 4B oder alternativ Fügenfüller Typ 3B einschließlich sämtlicher Nebenleistungen (Behelfe, Aufstiegshilfen, Befestigungen, Trennstreifen, Verschnitt, Versiegelungen etc.) Abrechnung nach vollständiger Leistung nach Aufmaß in [m²] Hinweis: Die Ausführung ist eine Erweiterung zum Verwendbarkeitsnachweis Brandschutz Ausführungsort: Aktionsbereich A (Sockelgeschoss - vgl. Lageplan/Grundriss) | E66: 11 | F66: m² | G66: =SUMPRODUCT((Kalkulation!A2:A50000=B66)*Kalkulation!D2:D50000) -> 0 | H66: =G66*E66 -> 0 | J66: =H66*(1-I66) -> 0 | K66: =B2 -> 0 | L66: 73968f31-f719-4329-9ed9-50bbeafa2c92 | M66: 11933314-4b4e-4ecd-bc4b-67969df163d6
A67: Position | B67: 04.001.020. | C67: Aktionsbereich B | D67: Trockenbauwand liefern und fachgerecht einbauen. Umfang: Trockenbauwand aus Ständerwerk mit beidseitiger doppelter Beplankung 1. Seite Wasserschutzklasse W1 2. Seite Wasserschutzklasse W0 Oberflächen teilweise mit Fliesenbelag circa bis h=1,20 m Ausführung nach Zeichnungen und Details (u.a. W112.de) Anforderungen: Nichttragende innere Trennwand nach DIN 4103-1 Bewertetes Schalldämm-Maß Rw = 58,4 dB Wandhöhe bis circa 3,10 m (OKRB/OKRD bis UKRD) Umlaufende Anschlüsse starr Anforderungen an Befestigungen in den Hinweisen (Vorbemerkungen) Befestigungsuntergründe: Wand: Mauerwerk / Stahlbeton/ Metallständer Decke: Spannbetonhohlplattendecken (Betonwerkstoff) und oder Kassettendecken (Fertigbetonelemente) Schallentkopplung mittels Dämmstreifen Bauteilabtrennung durch Spezialpapierstreifen Breite 2 x 65 mm Ausführung mit Unterkonstruktion aus verzinkten Stahlblechprofilen DIN 18182-1 Wanddicke 150 mm beidseitige Beplankung nach DIN 18180 jeweils zweilagig Plattendicke 2*12,5 mm pro Seite Metallständer CW 100 Ständerachsabstand ≤ 625 mm Boden und Deckenanschlüsse mit Randprofilen UW 100/40/06 Befestigung mit bauaufsichtlich zugelassenen Befestigungsmitteln Dämmschicht aus Mineralwolle nach DIN EN 13162: Dämmschicht aus Mineralwolle nach DIN EN 13162 Baustoffklasse A1, nichtbrennbar nach DIN 4102 und EN 13501-1 Dämmschicht Dicke mindestens 100 mm Wärmeleitfähigkeit λ ≤ 0,040 W/(mK) längenbezogener Strömungswiderstand nach DIN EN 29053: r ≥ 5 kPa·s/m² Rw = 58,4 dB Dämmschicht einlagig, dicht stoßen, abrutschsicher verlegen beidseitige zweilagige Beplankung nachDIN 18180: 1. Seite: Beplankung aus Gipsplatten GKB-A DIN 18180 bzw. Typ A EN 520 zweilagig Plattendicke 2*12,5 mm 2. Seite: Beplankung aus Gipsplatten GKBI DIN 18180 bzw. Typ H2 EN 520 zweilagig Plattendicke 2*12,5 mm Abmessungen: in circa (L*H) A=2,88*3,10 m A= 8,93 m² Verschraubung mit Schraubentyp XTN Verarbeitung gemäß DIN 18181 Verspachtelung der Gipsplatten gemäß Merkblatt Nr. 2 des Bundesverbandes der Gipsindustrie e.V. Qualitätsstufe Q3 bei Oberflächen ohne Fliesen Ausführung erfolgt unter Verwendung von DIN EN 13963, Spachtelmaterial Typ 4B oder alternativ Fügenfüller Typ 3B (muss für GKBI geeignet sein) einschließlich sämtlicher Nebenleistungen (Behelfe, Aufstiegshilfen, Befestigungen, Trennstreifen, Versiegelungen etc.) Abrechnung nach vollständiger Leistung nach Aufmaß in [m²] Hinweis zur Trennwandmontage: Die Montage der Trennwand erfolgt direkt auf dem vorhandenen Estrichboden. Unterhalb des Estrichs befinden sich Trittschalldämmung und eine Fußbodenheizung (Bestandskonstruktion). Aufgrund der baulichen Gegebenheiten wurde durch den Bauherrn eine Ausnahmegenehmigung für die direkte Montage auf dem Estrich erteilt. Zur Vermeidung von Schäden an der Fußbodenheizung ist vorab eine thermografische Untersuchung mittels Wärmebildkamera vorgesehen. Ausführung der thermografischen Untersuchung durch das Gewerk TGA Die ermittelten Montagepunkte werden entsprechend von dem Gewerk TGA markiert - und sind bei der Ausführung zu berücksichtigen. Abstimmung vor den Ausführungen mit dem Gewerk TGA zwingend erforderlich Ausführungsort: Aktionsbereich B (Sockelgeschoss - vgl. Lageplan/Grundriss) | E67: 9 | F67: m² | G67: =SUMPRODUCT((Kalkulation!A2:A50000=B67)*Kalkulation!D2:D50000) -> 0 | H67: =G67*E67 -> 0 | J67: =H67*(1-I67) -> 0 | K67: =B2 -> 0 | L67: 73968f31-f719-4329-9ed9-50bbeafa2c92 | M67: f091b026-1b99-487e-826e-1d480798b295
A68: Position | B68: 04.001.030. | C68: Aktionsbereich B1 | D68: Trockenbauwand liefern und fachgerecht einbauen. Umfang: Trockenbauwand aus Ständerwerk mit einseitiger doppelter Beplankung Wasserschutzklasse W0 Ausführung nach Zeichnungen und Details (u.a. W112.de) Anforderungen: Nichttragende innere Trennwand nach DIN 4103-1 Bewertetes Schalldämm-Maß Rw = 58,4 dB Wandhöhe bis circa 3,10 m (OKRB/OKRD bis UKRD) Umlaufende Anschlüsse starr Anforderungen an Befestigungen in den Hinweisen (Vorbemerkungen) Befestigungsuntergründe: Wand: Mauerwerk / Stahlbeton/ Metallständer Decke: Spannbetonhohlplattendecken (Betonwerkstoff) und oder Kassettendecken (Fertigbetonelemente) Schallentkopplung mittels Dämmstreifen Bauteilabtrennung durch Spezialpapierstreifen Breite 2 x 65 mm Ausführung mit Unterkonstruktion aus verzinkten Stahlblechprofilen DIN 18182-1 Wanddicke 150 mm beidseitige Beplankung nach DIN 18180 zweilagig Plattendicke 2*12,5 mm Metallständer CW 100 Ständerachsabstand ≤ 625 mm Boden und Deckenanschlüsse mit Randprofilen UW 100/40/06 Befestigung mit bauaufsichtlich zugelassenen Befestigungsmitteln Dämmschicht aus Mineralwolle nach DIN EN 13162: Dämmschicht aus Mineralwolle nach DIN EN 13162 Baustoffklasse A1, nichtbrennbar nach DIN 4102 und EN 13501-1 Dämmschicht Dicke mindestens 100 mm Wärmeleitfähigkeit λ ≤ 0,040 W/(mK) längenbezogener Strömungswiderstand nach DIN EN 29053: r ≥ 5 kPa·s/m² Rw = 58,4 dB Dämmschicht einlagig, dicht stoßen, abrutschsicher verlegen einseitige zweilagige Beplankung nachDIN 18180: Seite: Beplankung aus Gipsplatten GKB-A DIN 18180 bzw. Typ A EN 520 zweilagig Plattendicke 2*12,5 mm Abmessungen: in circa (L*H) A=2,88*3,10 m A= 8,93 m² Verschraubung mit Schraubentyp XTN Verarbeitung gemäß DIN 18181 Verspachtelung der Gipsplatten gemäß Merkblatt Nr. 2 des Bundesverbandes der Gipsindustrie e.V. Qualitätsstufe Q3 bei Oberflächen ohne Fliesen Ausführung erfolgt unter Verwendung von DIN EN 13963, Spachtelmaterial Typ 4B oder alternativ Fügenfüller Typ 3B (muss für GKBI geeignet sein) einschließlich sämtlicher Nebenleistungen (Behelfe, Aufstiegshilfen, Befestigungen, Trennstreifen, Versiegelungen etc.) Abrechnung nach vollständiger Leistung nach Aufmaß in [m²] Hinweis zur Trennwandmontage: Die Montage der Trennwand erfolgt direkt auf dem vorhandenen Estrichboden. Unterhalb des Estrichs befinden sich Trittschalldämmung und eine Fußbodenheizung (Bestandskonstruktion). Aufgrund der baulichen Gegebenheiten wurde durch den Bauherrn eine Ausnahmegenehmigung für die direkte Montage auf dem Estrich erteilt. Zur Vermeidung von Schäden an der Fußbodenheizung ist vorab eine thermografische Untersuchung mittels Wärmebildkamera vorgesehen. Ausführung der thermografischen Untersuchung durch das Gewerk TGA Die ermittelten Montagepunkte werden entsprechend von dem Gewerk TGA markiert - und sind bei der Ausführung zu berücksichtigen. Abstimmung vor den Ausführungen mit dem Gewerk TGA zwingend erforderlich Ausführungsort: Aktionsbereich B1 (Sockelgeschoss - vgl. Lageplan/Grundriss) | E68: 9 | F68: m² | G68: =SUMPRODUCT((Kalkulation!A2:A50000=B68)*Kalkulation!D2:D50000) -> 0 | H68: =G68*E68 -> 0 | J68: =H68*(1-I68) -> 0 | K68: =B2 -> 0 | L68: 73968f31-f719-4329-9ed9-50bbeafa2c92 | M68: 0b164384-8800-4672-b426-05cb1a9dbbe6
A69: Position | B69: 04.001.040. | C69: Aktionsbereich B2 | D69: Trockenbauwand liefern und fachgerecht einbauen. Umfang: Ausführung wie Vorposition, jedoch mit einseitiger doppelter Beplankung Wasserschutzklasse W1 Ausführung nach Zeichnungen und Details (u.a. W112.de) Anforderungen: Wanddicke 150 mm beidseitige Beplankung nach DIN 18180 zweilagig Plattendicke 2*12,5 mm Metallständer CW 100 Ständerachsabstand ≤ 625 mm Boden und Deckenanschlüsse mit Randprofilen UW 100/40/06 Befestigung mit bauaufsichtlich zugelassenen Befestigungsmitteln Dämmschicht aus Mineralwolle nach DIN EN 13162: Dämmschicht aus Mineralwolle nach DIN EN 13162 Baustoffklasse A1, nichtbrennbar nach DIN 4102 und EN 13501-1 Dämmschicht Dicke mindestens 100 mm Wärmeleitfähigkeit λ ≤ 0,040 W/(mK) längenbezogener Strömungswiderstand nach DIN EN 29053: r ≥ 5 kPa·s/m² Rw = 58,4 dB Falls jedoch nur ein Estrich auf eine Trennlage oder ein Verbundestrich vorhanden ist, kann lediglich 38 dB erreicht werden. In diesem Fall ist die untere Flanke der maßgebende Teil der Trennwand. Dämmschicht einlagig, dicht stoßen, abrutschsicher verlegen einseitige zweilagige Beplankung nachDIN 18180: Seite: Beplankung aus Gipsplatten GKBI DIN 18180 bzw. Typ H2 EN 520 einlagig Plattendicke 1*12,5 mm Abmessungen: in circa (L*H) A=2,69*3,10 m A= 8,34 m² Verschraubung mit Schraubentyp XTN Verarbeitung gemäß DIN 18181 Verspachtelung der Gipsplatten gemäß Merkblatt Nr. 2 des Bundesverbandes der Gipsindustrie e.V. Qualitätsstufe Q3 bei Oberflächen ohne Fliesen Ausführung erfolgt unter Verwendung von DIN EN 13963, Spachtelmaterial Typ 4B oder alternativ Fügenfüller Typ 3B (muss für GKBI geeignet sein) einschließlich sämtlicher Nebenleistungen (Behelfe, Aufstiegshilfen, Befestigungen, Trennstreifen, Versiegelungen etc.) Abrechnung nach vollständiger Leistung nach Aufmaß in [m²] Hinweis zur Trennwandmontage: Die Montage der Trennwand erfolgt direkt auf dem vorhandenen Estrichboden. Unterhalb des Estrichs befinden sich Trittschalldämmung und eine Fußbodenheizung (Bestandskonstruktion). Aufgrund der baulichen Gegebenheiten wurde durch den Bauherrn eine Ausnahmegenehmigung für die direkte Montage auf dem Estrich erteilt. Zur Vermeidung von Schäden an der Fußbodenheizung ist vorab eine thermografische Untersuchung mittels Wärmebildkamera vorgesehen. Ausführung der thermografischen Untersuchung durch das Gewerk TGA Die ermittelten Montagepunkte werden entsprechend von dem Gewerk TGA markiert - und sind bei der Ausführung zu berücksichtigen. Abstimmung vor den Ausführungen mit dem Gewerk TGA zwingend erforderlich Ausführungsort: Aktionsbereich B2 (Sockelgeschoss - vgl. Lageplan/Grundriss) | E69: 8.5 | F69: m² | G69: =SUMPRODUCT((Kalkulation!A2:A50000=B69)*Kalkulation!D2:D50000) -> 0 | H69: =G69*E69 -> 0 | J69: =H69*(1-I69) -> 0 | K69: =B2 -> 0 | L69: 73968f31-f719-4329-9ed9-50bbeafa2c92 | M69: 25f079b9-4b25-4f91-b64d-ce44170ec1a1
A70: Position | B70: 04.001.050. | C70: Aktionsbereich H | D70: Schachtwand liefern und fachgerecht einbauen. Umfang: Schachtwand als Trockenbauwand Trockenbauwand aus Ständerwerk Raumhoch mit einseitiger doppelter Beplankung Wasserschutzklasse W0 Ausführung nach Zeichnungen und Details (u.a. W628B) Anforderungen: Nichttragende innere Schachtwand nach DIN 4103-1 Bewertetes Schalldämm-Maß Rw = 58,4 dB Wandhöhe bis circa 3,10 m (OKRB/OKRD bis UKRD) Umlaufende Anschlüsse starr Anforderungen an Befestigungen in den Hinweisen (Vorbemerkungen) Befestigungsuntergründe: Wand: Mauerwerk / Stahlbeton/ Metallständer Decke: Spannbetonhohlplattendecken (Betonwerkstoff) und oder Kassettendecken (Fertigbetonelemente) Schallentkopplung mittels Dämmstreifen Bauteilabtrennung durch Spezialpapierstreifen Breite 2 x 65 mm Ausführung mit Unterkonstruktion aus verzinkten Stahlblechprofilen DIN 18182-1 Wanddicke 75 mm einseitige Beplankung nach DIN 18180 zweilagig Plattendicke 2*12,5 mm Metallständer CW 50 Ständerachsabstand ≤ 625 mm Boden und Deckenanschlüsse mit Randprofilen UW 50/40/06 Befestigung mit bauaufsichtlich zugelassenen Befestigungsmitteln Dämmschicht aus Mineralwolle nach DIN EN 13162: Dämmschicht aus Mineralwolle nach DIN EN 13162 Baustoffklasse A1, nichtbrennbar nach DIN 4102 und EN 13501-1 Dämmschicht Dicke mindestens 50 mm Wärmeleitfähigkeit λ ≤ 0,040 W/(mK) längenbezogener Strömungswiderstand nach DIN EN 29053: r ≥ 5 kPa·s/m² Rw = 58,4 dB Dämmschicht einlagig, dicht stoßen, abrutschsicher verlegen einseitige zweilagige Beplankung nach DIN 18180: Seite: Beplankung aus Gipsplatten GKB-A DIN 18180 bzw. Typ A EN 520 zweilagig Plattendicke 2*12,5 mm Abmessungen: Schachtwand Raumhoch in circa (L+B*H) A=((0,15+0,15)*3,10)+((0,48+2,51)*3,10)+((0,74+1,30+0,74)*3,10)+((0,15+0,35)*3,10)+(2,89*3,10) A= 29,33 m² Verschraubung mit Schraubentyp XTN Verarbeitung gemäß DIN 18181 Verspachtelung der Gipsplatten gemäß Merkblatt Nr. 2 des Bundesverbandes der Gipsindustrie e.V. Qualitätsstufe Q3 bei Oberflächen ohne Fliesen Ausführung erfolgt unter Verwendung von DIN EN 13963, Spachtelmaterial Typ 4B oder alternativ Fügenfüller Typ 3B (muss für GKBI geeignet sein) einschließlich sämtlicher Nebenleistungen (Behelfe, Aufstiegshilfen, Befestigungen, Trennstreifen, Versiegelungen etc.) Abrechnung nach vollständiger Leistung nach Aufmaß in [m²] Ausführungsort: Aktionsbereich H (Sockelgeschoss - vgl. Lageplan/Grundriss) | E70: 30 | F70: m² | G70: =SUMPRODUCT((Kalkulation!A2:A50000=B70)*Kalkulation!D2:D50000) -> 0 | H70: =G70*E70 -> 0 | J70: =H70*(1-I70) -> 0 | K70: =B2 -> 0 | L70: 73968f31-f719-4329-9ed9-50bbeafa2c92 | M70: 7dc2e5d0-9195-4e5b-bb12-45c68e1b0014
A71: Position | B71: 04.001.060. | C71: Aktionsbereich H2 | D71: Schachtwand liefern und fachgerecht einbauen. Umfang: Ausführung wie Vorposition, jedoch mit einseitiger doppelter Beplankung Schachtwand als Trockenbauwand Trockenbauwand aus Ständerwerk Raumhoch mit einseitiger doppelter Beplankung Wasserschutzklasse W1 Ausführung nach Zeichnungen und Details (u.a. W628B) Anforderungen: Nichttragende innere Schachtwand nach DIN 4103-1 Bewertetes Schalldämm-Maß Rw = 58,4 dB Wandhöhe bis circa 3,10 m (OKRB/OKRD bis UKRD) Umlaufende Anschlüsse starr Anforderungen an Befestigungen in den Hinweisen (Vorbemerkungen) Befestigungsuntergründe: Wand: Mauerwerk / Stahlbeton/ Metallständer Decke: Spannbetonhohlplattendecken (Betonwerkstoff) und oder Kassettendecken (Fertigbetonelemente) Schallentkopplung mittels Dämmstreifen Bauteilabtrennung durch Spezialpapierstreifen Breite 2 x 65 mm Ausführung mit Unterkonstruktion aus verzinkten Stahlblechprofilen DIN 18182-1 Wanddicke 75 mm einseitige Beplankung nach DIN 18180 zweilagig Plattendicke 2*12,5 mm Metallständer CW 50 Ständerachsabstand ≤ 625 mm Boden und Deckenanschlüsse mit Randprofilen UW 50/40/06 Befestigung mit bauaufsichtlich zugelassenen Befestigungsmitteln Dämmschicht aus Mineralwolle nach DIN EN 13162: Dämmschicht aus Mineralwolle nach DIN EN 13162 Baustoffklasse A1, nichtbrennbar nach DIN 4102 und EN 13501-1 Dämmschicht Dicke mindestens 50 mm Wärmeleitfähigkeit λ ≤ 0,040 W/(mK) längenbezogener Strömungswiderstand nach DIN EN 29053: r ≥ 5 kPa·s/m² Rw = 58,4 dB Dämmschicht einlagig, dicht stoßen, abrutschsicher verlegen einseitige zweilagige Beplankung nach DIN 18180: Seite: Beplankung aus Gipsplatten GKBI DIN 18180 bzw. Typ H2 EN 520 einlagig Plattendicke 1*12,5 mm Abmessungen: Schachtwand Raumhoch in circa (L+B*H) A=(0,20+0,35)*3,10 m A= 1,71 m² Verschraubung mit Schraubentyp XTN Verarbeitung gemäß DIN 18181 Verspachtelung der Gipsplatten gemäß Merkblatt Nr. 2 des Bundesverbandes der Gipsindustrie e.V. Qualitätsstufe Q3 bei Oberflächen ohne Fliesen Ausführung erfolgt unter Verwendung von DIN EN 13963, Spachtelmaterial Typ 4B oder alternativ Fügenfüller Typ 3B (muss für GKBI geeignet sein) einschließlich sämtlicher Nebenleistungen (Behelfe, Aufstiegshilfen, Befestigungen, Trennstreifen, Versiegelungen etc.) Abrechnung nach vollständiger Leistung nach Aufmaß in [m²] Ausführungsort: Aktionsbereich H2 (Sockelgeschoss - vgl. Lageplan/Grundriss) | E71: 2 | F71: m² | G71: =SUMPRODUCT((Kalkulation!A2:A50000=B71)*Kalkulation!D2:D50000) -> 0 | H71: =G71*E71 -> 0 | J71: =H71*(1-I71) -> 0 | K71: =B2 -> 0 | L71: 73968f31-f719-4329-9ed9-50bbeafa2c92 | M71: 22c093ae-1a76-49b1-b930-0bd946af8401
A72: Position | B72: 04.001.070. | C72: Aktionsbereich H3 | D72: Abkofferung liefern und fachgerecht einbauen. Umfang: Trockenbauwand als Abkofferung Trockenbauwand aus Ständerwerk im Deckenixcel mit einseitiger doppelter Beplankung Wasserschutzklasse W0 Ausführung nach Zeichnungen und Details (u.a. W628B) Anforderungen: Nichttragende innere Abkofferung nach DIN 4103-1 Bewertetes Schalldämm-Maß Rw = 58,4 dB Wandhöhe bis circa 3,10 m (OKRB/OKRD bis UKRD) Umlaufende Anschlüsse starr Anforderungen an Befestigungen in den Hinweisen (Vorbemerkungen) Befestigungsuntergründe: Wand: Mauerwerk / Stahlbeton/ Metallständer Decke: Spannbetonhohlplattendecken (Betonwerkstoff) und oder Kassettendecken (Fertigbetonelemente) Schallentkopplung mittels Dämmstreifen Bauteilabtrennung durch Spezialpapierstreifen Breite 2 x 65 mm Ausführung mit Unterkonstruktion aus verzinkten Stahlblechprofilen DIN 18182-1 Wanddicke 75 mm einseitige Beplankung nach DIN 18180 zweilagig Plattendicke 2*12,5 mm Metallständer CW 50 Ständerachsabstand ≤ 625 mm Boden und Deckenanschlüsse mit Randprofilen UW 50/40/06 Befestigung mit bauaufsichtlich zugelassenen Befestigungsmitteln Dämmschicht aus Mineralwolle nach DIN EN 13162: Dämmschicht aus Mineralwolle nach DIN EN 13162 Baustoffklasse A1, nichtbrennbar nach DIN 4102 und EN 13501-1 Dämmschicht Dicke mindestens 50 mm Wärmeleitfähigkeit λ ≤ 0,040 W/(mK) längenbezogener Strömungswiderstand nach DIN EN 29053: r ≥ 5 kPa·s/m² Rw = 58,4 dB Dämmschicht einlagig, dicht stoßen, abrutschsicher verlegen einseitige zweilagige Beplankung nach DIN 18180: Seite: Beplankung aus Gipsplatten GKB-A DIN 18180 bzw. Typ A EN 520 zweilagig Plattendicke 2*12,5 mm Abmessungen: Abkofferung im Deckenixcel in circa (B+H+L) A=((0,4+0,3)*8,22)+((0,40+0,30)*0,50+1,89+2,02+5,36+3,97+0,25+4,91+5,13+1,62+3,80+1,54+0,75+0,79)+((0,30+0,30)*4,29) A= 40,71 m² Verschraubung mit Schraubentyp XTN Verarbeitung gemäß DIN 18181 Verspachtelung der Gipsplatten gemäß Merkblatt Nr. 2 des Bundesverbandes der Gipsindustrie e.V. Qualitätsstufe Q3 Ausführung erfolgt unter Verwendung von DIN EN 13963, Spachtelmaterial Typ 4B oder alternativ Fügenfüller Typ 3B (muss für GKBI geeignet sein) einschließlich sämtlicher Nebenleistungen (Behelfe, Aufstiegshilfen, Befestigungen, Trennstreifen, Versiegelungen etc.) Abrechnung nach vollständiger Leistung nach Aufmaß in [m²] Ausführungsort: Aktionsbereich H3 (Sockelgeschoss - vgl. Lageplan/Grundriss) | E72: 41 | F72: m² | G72: =SUMPRODUCT((Kalkulation!A2:A50000=B72)*Kalkulation!D2:D50000) -> 0 | H72: =G72*E72 -> 0 | J72: =H72*(1-I72) -> 0 | K72: =B2 -> 0 | L72: 73968f31-f719-4329-9ed9-50bbeafa2c92 | M72: fd1e4973-391e-4d89-8986-ceb0654792a2
A73: Position | B73: 04.001.080. | C73: Aktionsbereich M | D73: Verstärkung in den Trockenbauwänden (Vorpositionen) liefern und fachgerecht einbauen. Umfang: Verstärkungen zur Befestigung von Lasten in den Trockenbauwänden liefern und fachgerecht einbauen. aus Multiplexplatten Ausführung nach Zeichnungen und Detail Abstimmung der Abmessungen und Endeinbaulage mit dem Gewerk TGA und der AG-Bauleitung Anforderungen: Verstärkungen aus Multiplexplatten in Trockenbauwänden gem. DIN 68705 Teil 3 bzw. EN 636-2 / S Anforderungen E 05 nach EN 717-1 Holzwerkstoff Birke Verleimung WBP, Exterior (BFU 100) Mehrschichtholz beidseitig geschliffen Plattenstärke 22 mm in unterschiedlichen Breiten Höhen über 300 mm einschließlich Kantenversiegelung und sämtlicher Nebenleistungen (Behelfe, Aufstiegshilfen, Befestigungen, Verschnitt etc.) Ausführungsort: Aktionsbereich M (Sockelgeschoss - vgl. Lageplan/Grundriss) | E73: 8 | F73: m² | G73: =SUMPRODUCT((Kalkulation!A2:A50000=B73)*Kalkulation!D2:D50000) -> 0 | H73: =G73*E73 -> 0 | J73: =H73*(1-I73) -> 0 | K73: =B2 -> 0 | L73: 73968f31-f719-4329-9ed9-50bbeafa2c92 | M73: edf9687f-fdce-42cb-81c4-b51cabad21c4
A74: Summe Gruppe | B74: 04.001. | C74: Wände | H74: =SUMIF(L:L,"73968f31-f719-4329-9ed9-50bbeafa2c92",J:J) -> 0 | J74: =H74*(1-I74) -> 0 | L74: 7a73cc31-a7ce-4719-a6bd-a95cae11bc00 | M74: 73968f31-f719-4329-9ed9-50bbeafa2c92
A75: Gruppe | B75: 04.002. | C75: Decken | K75: =""
A76: Position | B76: 04.002.010. | C76: Abhang-Decke D131.de | D76: Freitragende Decke liefern und fachgerecht einbauen. Umfang: Freitragende Decke einschließlich Unterkonstruktion Bekleidung aus Gipsvliesplatten Wasserschutzklasse W1 Unterkonstuktion nach Abhangdeckenplan Ausführung nach Zeichnungen und Details Anforderungen: Unterdecke nach DIN 18168-1 freitragende Decke Einbauhöhe circa bis 3,20 m Raumbreite ≤ max. 1,70 m Befestigungsuntergründe: Wand: Mauerwerkswände / Stahlbetonwände / Metallständerwände Decke: Spannbetonhohlplattendecken (Betonwerkstoff) und oder Kassettendecken (Fertigbetonelemente) Ausführung der Unterkonstruktion aus verzinkten Stahlblechprofilen DIN 18182-1 Tragprofile als Einfachprofile UA 150 Randbefestigung mit UW 150 Verbindung mit Randprofil durch Anschluss- und Verbindungswinkel Befestigung mit für den Untergrund geeignetem Befestigungsmittel Befestigungsabstand max. 500 mm Decklage/Bekleidung aus Gipsvliesplatten GM-FH1IR nach DIN EN 15283-1 bzw. Typ DF EN 520 Schimmelresistenz Klasse 10 gem. ASTM D 3273 Wasseraufnahme ≤ 3% Plattendicke 12,5 mm (einlagig) Befestigung mit System-Schraube XTN Verarbeitung gemäß DIN 18181 Verspachtelung der Gipsplatten gemäß Merkblatt Nr. 2 des Bundesverbandes der Gipsindustrie e.V. Qualitätsstufe Q3 Verarbeitung gemäß DIN 18181 Ausführung erfolgt unter Verwendung von DIN EN 13963 Spachtelmaterial Typ 4B oder alternativ Fügenfüller Typ 3B einschließlich sämtlicher Nebenleistungen (Behelfe, Aufstiegshilfen, Befestigungen, Versiegelungen etc.) Abrechnung nach vollständiger Leistung nach Aufmaß in [m²] Ausführungsort: Bad 02-SG-00050 (4,18 m²) Hauswartwohnung | E76: 4.5 | F76: m² | G76: =SUMPRODUCT((Kalkulation!A2:A50000=B76)*Kalkulation!D2:D50000) -> 0 | H76: =G76*E76 -> 0 | J76: =H76*(1-I76) -> 0 | K76: =B2 -> 0 | L76: 75a64beb-2fe2-425b-bb32-e08721d7e4fa | M76: 33426d98-da40-46d5-b1fa-be1d24126986
A77: Position | B77: 04.002.020. | C77: Öffnungen in Decke bis Ø 125 mm | D77: Öffnungen für TGA in den Decken herstellen. Umfang: Öffnungen für die Installationen von Deckenbeleuchtungen und oder Lüftungselementen für die TGA herstellen. Einbau und Geräteanschluss ausschließlich durch das Gewerk TGA Leistungsposition nur für die Herstellung von Deckenöffnungen Anforderungen: Abmessungen rund bis circa 125 mm im Durchmesser Öffnungen herstellen einschließlich sämtlicher Nebenleistungen (Behelfe, Aufstiegshilfen, Befestigungen etc.) Ausführungen nur nach Abstimmung mit der TGA und der AG-Bauleitung Abrechnung nach vollständiger Ausführung und Aufmaß in [St] pro Durchführung in Trockenbauwand Ausführungsort: Bad 02-SG-00050 (4,18 m²) Hauswartwohnung | E77: 2 | F77: St | G77: =SUMPRODUCT((Kalkulation!A2:A50000=B77)*Kalkulation!D2:D50000) -> 0 | H77: =G77*E77 -> 0 | J77: =H77*(1-I77) -> 0 | K77: =B2 -> 0 | L77: 75a64beb-2fe2-425b-bb32-e08721d7e4fa | M77: 454c3bdd-0443-463d-b862-7cf0591be694
A78: Summe Gruppe | B78: 04.002. | C78: Decken | H78: =SUMIF(L:L,"75a64beb-2fe2-425b-bb32-e08721d7e4fa",J:J) -> 0 | J78: =H78*(1-I78) -> 0 | L78: 7a73cc31-a7ce-4719-a6bd-a95cae11bc00 | M78: 75a64beb-2fe2-425b-bb32-e08721d7e4fa
A79: Summe Gruppe | B79: 04. | C79: Sockelgeschoss | H79: =SUMIF(L:L,"7a73cc31-a7ce-4719-a6bd-a95cae11bc00",J:J) -> 0 | J79: =H79*(1-I79) -> 0 | L79: 6dc70e31-e96c-4610-bf73-f2ab9e6f1e90 | M79: 7a73cc31-a7ce-4719-a6bd-a95cae11bc00
A80: Gruppe | B80: 05. | C80: Erdgeschoss | K80: =""
A81: Gruppe | B81: 05.001. | C81: Wände | K81: =""
A82: Position | B82: 05.001.010. | C82: Aktionsbereich A | D82: Trennwand aus GK-Fireboardplatten fachgerecht herstellen. Umfang: Im Bereich der geplanten neuen Trennwände ist der vorhandene Estrichboden mit Trennlagen und Trittschalldämmung fachgerecht zu öffnen. Die Estrichkonstruktion ist entlang der geplanten Wandachsen zu schlitzen und aufzunehmen. Dabei sind sämtliche Schichten (Estrich, Trennlage, Trittschalldämmung) bis zur Rohdecke zu entfernen. Rückbau Estrich mit Unterbauten bis OK Betonrohboden. Abbruchstoffe fachgerecht als Bauabfall entsorgen Trennwand aus mit GK-Fireboardplatten beplanktem Metallständerwerk einschließlich integrierter Dämmung, fachgerecht herstellen und einbauen. beidseitig dreifache Beplankung mit Einlage Ausführung nach den Vorbemerkungen, Zeichnung und Details (u.a. W133.de) Anforderungen: Ausführungshinweise Rückbau Estrich, Trennlagen und Trittschalldämmung: Die Schnittführung erfolgt gemäß den Ausführungsplänen der neuen Trennwände Die Arbeiten sind staubarm und erschütterungsfrei durchzuführen, um angrenzende Bauteile nicht zu beeinträchtigen Die aufgenommenen Materialien sind sortenrein zu trennen und gemäß den geltenden Vorschriften als Bauabfälle zu entsorgen Nach dem Rückbau ist die Fläche für die Montage der Trennwände vorzubereiten (z. B. Reinigung, ggf. Grundierung) Besondere Anforderungen: Berücksichtigung von Schallschutzmaßnahmen: Die Trittschalldämmung darf nicht unkontrolliert unterbrochen werden. Trockenbauwand: Nichttragende innere Trennwand nach DIN 4103-1 Brandschutztechnische Anforderungen an die Bekleidung Feuerwiderstandsklasse 90 Minuten nach DIN 4102-2 Bewertetes Schalldämm-Maß Rw = 71,6 dB Wandhöhe bis circa 3,10 m (OKRB/OKRD bis UKRD) Umlaufende Anschlüsse starr Anforderungen an Befestigungen in den Hinweisen (Vorbemerkungen) Befestigungsuntergründe: Wand: Mauerwerk / Stahlbeton/ Metallständer Decke: Spannbetonhohlplattendecken (Betonwerkstoff) und oder Kassettendecken (Fertigbetonelemente) Schallentkopplung mittels Dämmstreifen Bauteilabtrennung durch Spezialpapierstreifen Breite 2 x 65 mm Ausführung mit Unterkonstruktion aus verzinkten Stahlblechprofilen DIN 18182-1 Wanddicke 150 mm beidseitige Beplankung nach DIN 18180 jeweils dreilagig Plattendicke 3*12,5 mm pro Seite Metallständer CW 75 Ständerachsabstand ≤ 312,5 mm Boden und Deckenanschlüsse mit Randprofilen UW 75/40/06 Befestigung mit bauaufsichtlich zugelassenen Befestigungsmitteln Dämmschicht aus Mineralwolle nach DIN EN 13162: Dämmschicht aus Mineralwolle nach DIN EN 13162 Baustoffklasse A1, nichtbrennbar nach DIN 4102 und EN 13501-1 Dämmschicht Dicke mindestens 60 mm Wärmeleitfähigkeit λ ≤ 0,040 W/(mK) längenbezogener Strömungswiderstand nach DIN EN 29053: r ≥ 5 kPa·s/m² R´w,R = 50,7 dB = erf. R´w = Rw = 71,6 dB Dämmschicht einlagig, dicht stoßen, abrutschsicher verlegen Beplankung beidseitig, dreilagig aus Gipsplatten GKF DIN 18180: 1. Seite: 1. (untere) und 2. (mittlere) Lage Beplankung aus Silentboard GKBF DIN 18180 bzw. Typ DF EN 520 zweilagig Plattendicke 2*12,5 mm Stahlblecheinlage je Wandseite Verzinktes Stahlblech als Platten oder Rollenware Stahlblechgüte DC01+ZE Materialstärke 0,5 mm Horizontale Verlegung mit Stoßüberlappung 100 mm Vertikale Stöße auf Ständern anordnen Verschraubung mit Schnellbauschrauben (nur zur Fixierung) 3. (obere) Lage Beplankung aus GKBF DIN 18180 Typ DFH2IR EN 520 (oder gleichwertig) einlagig Plattendicke 12,5 mm 2. Seite: 1. (untere) und 2. (mittlere) Lage Beplankung aus Silentboard GKBF DIN 18180 bzw. Typ DF EN 520 zweilagig Plattendicke 2*12,5 mm Stahlblecheinlage je Wandseite Verzinktes Stahlblech als Platten oder Rollenware Stahlblechgüte DC01+ZE Materialstärke 0,5 mm Horizontale Verlegung mit Stoßüberlappung 100 mm Vertikale Stöße auf Ständern anordnen Verschraubung mit Schnellbauschrauben (nur zur Fixierung) 3. (obere) Lage Beplankung aus GKBF DIN 18180 Typ DFH2IR EN 520 (oder gleichwertig) einlagig Plattendicke 12,5 mm Abmessungen: Abkastung TB Raumhoch und Deckenixcel Verschluss Bühnenzugang Durchgang verschließen in circa (L*B*H) A=((0,11+0,36+0,42+0,29)*3,10)+((0,30+0,30)*7,85)+(5,16*3,10)+(1,01*2,58) A= 26,67 m² Verschraubung mit Schraubentyp XTN Verarbeitung gemäß DIN 18181 Verspachtelung der Gipsplatten gemäß Merkblatt Nr. 2 des Bundesverbandes der Gipsindustrie e.V. Qualitätsstufe Q3 bei Oberflächen ohne Fliesen Ausführung erfolgt unter Verwendung von DIN EN 13963, Spachtelmaterial Typ 4B oder alternativ Fügenfüller Typ 3B einschließlich sämtlicher Nebenleistungen (Behelfe, Aufstiegshilfen, Befestigungen, Trennstreifen, Versiegelungen etc.) Abrechnung nach vollständiger Leistung nach Aufmaß in [m²] Hinweis: Die Ausführung ist eine Erweiterung zum Verwendbarkeitsnachweis Brandschutz Ausführungsort: Aktionsbereich A (Erdgeschoss - vgl. Lageplan/Grundriss) | E82: 27 | F82: m² | G82: =SUMPRODUCT((Kalkulation!A2:A50000=B82)*Kalkulation!D2:D50000) -> 0 | H82: =G82*E82 -> 0 | J82: =H82*(1-I82) -> 0 | K82: =B2 -> 0 | L82: da7efe4c-eaba-4e83-8dfc-14dc8326c6f2 | M82: b0e009da-bc58-4c45-85a1-d2bda4fa0502
A83: Position | B83: 05.001.020. | C83: Aktionsbereich B | D83: Trockenbauwand liefern und fachgerecht einbauen. Umfang: Trockenbauwand aus Ständerwerk mit beidseitiger doppelter Beplankung Küchenseitig Wasserschutzklasse W3 Cafeseitig Wasserschutzklasse W0 Ausführung nach Zeichnungen und Details (u.a. W112.de bzw. K913.de) Anforderungen: Nichttragende innere Trennwand nach DIN 4103-1 Bewertetes Schalldämm-Maß Rw = 58,4 dB Wandhöhe bis circa 3,10 m (OKRB/OKRD bis UKRD) Umlaufende Anschlüsse starr Anforderungen an Befestigungen in den Hinweisen (Vorbemerkungen) Befestigungsuntergründe: Wand: Mauerwerk / Stahlbeton/ Metallständer Decke: Spannbetonhohlplattendecken (Betonwerkstoff) und oder Kassettendecken (Fertigbetonelemente) Schallentkopplung mittels Dämmstreifen Bauteilabtrennung durch Spezialpapierstreifen Breite 2 x 65 mm Ausführung mit Unterkonstruktion aus verzinkten Stahlblechprofilen DIN 18182-1 Wanddicke 125 mm beidseitige Beplankung nach DIN 18180 jeweils zweilagig Plattendicke 2*12,5 mm pro Seite Metallständer CW 75 C3 Ständerachsabstand ≤ 625 mm Boden und Deckenanschlüsse mit Randprofilen UW 75/40/06 Befestigung mit bauaufsichtlich zugelassenen Befestigungsmitteln Dämmschicht aus Mineralwolle nach DIN EN 13162: Dämmschicht aus Mineralwolle nach DIN EN 13162 Baustoffklasse A1, nichtbrennbar nach DIN 4102 und EN 13501-1 Dämmschicht Dicke mindestens 60 mm Wärmeleitfähigkeit λ ≤ 0,040 W/(mK) längenbezogener Strömungswiderstand nach DIN EN 29053: r ≥ 5 kPa·s/m² Rw = 58,4 dB Falls jedoch nur ein Estrich auf eine Trennlage oder ein Verbundestrich vorhanden ist, kann lediglich 38 dB erreicht werden. In diesem Fall ist die untere Flanke der maßgebende Teil der Trennwand. Dämmschicht einlagig, dicht stoßen, abrutschsicher verlegen beidseitige zweilagige Beplankung nach DIN 18180: 1. Seite: Beplankung aus Gipsplatten GKB-A DIN 18180 bzw. Typ A EN 520 zweilagig Plattendicke 2*12,5 mm 2. Seite: Beplankung aus Zementbauplatten DIN EN 12467 bzw. Indoor 12,5 LEF DE zweilagig Plattendicke 2*12,5 mm Abmessungen: Küche 01-EG-001170 Theke 01-EG-00180 in circa (L*B*H) A=(0,71+2,14+1,79+0,80+1,56)*3,10 m A= 21,7 m² Verschraubung mit Schraubentyp XTN Verarbeitung gemäß DIN 18181 Verspachtelung der Gipsplatten gemäß Merkblatt Nr. 2 des Bundesverbandes der Gipsindustrie e.V. Qualitätsstufe Q3 bei Oberflächen ohne Fliesen Ausführung erfolgt unter Verwendung von DIN EN 13963, Spachtelmaterial Typ 4B oder alternativ Fügenfüller Typ 3B (muss für GKBI geeignet sein) einschließlich sämtlicher Nebenleistungen (Behelfe, Aufstiegshilfen, Befestigungen, Trennstreifen, Versiegelungen etc.) Abrechnung nach vollständiger Leistung nach Aufmaß in [m²] Hinweis zur Trennwandmontage: Die Montage der Trennwand erfolgt direkt auf dem vorhandenen Estrichboden. Unterhalb des Estrichs befinden sich Trittschalldämmung und eine Fußbodenheizung (Bestandskonstruktion). Aufgrund der baulichen Gegebenheiten wurde durch den Bauherrn eine Ausnahmegenehmigung für die direkte Montage auf dem Estrich erteilt. Zur Vermeidung von Schäden an der Fußbodenheizung ist vorab eine thermografische Untersuchung mittels Wärmebildkamera vorgesehen. Ausführung der thermografischen Untersuchung durch das Gewerk TGA Die ermittelten Montagepunkte werden entsprechend von dem Gewerk TGA markiert - und sind bei der Ausführung zu berücksichtigen. Abstimmung vor den Ausführungen mit dem Gewerk TGA zwingend erforderlich Ausführungsort: Aktionsbereich B (Erdgeschoss - vgl. Lageplan/Grundriss) | E83: 22 | F83: m² | G83: =SUMPRODUCT((Kalkulation!A2:A50000=B83)*Kalkulation!D2:D50000) -> 0 | H83: =G83*E83 -> 0 | J83: =H83*(1-I83) -> 0 | K83: =B2 -> 0 | L83: da7efe4c-eaba-4e83-8dfc-14dc8326c6f2 | M83: 1f24b384-9448-42ec-b03f-8469afe0fe5e
A84: Position | B84: 05.001.030. | C84: Aktionsbereich C | D84: Trockenbauwand liefern und fachgerecht einbauen. Umfang: Trockenbauwand aus Ständerwerk mit beidseitiger doppelter Beplankung Wasserschutzklasse W1 Oberflächen ohne Fliesenbelag Ausführung nach Zeichnungen und Details (u.a. W112.de) Anforderungen: Nichttragende innere Trennwand nach DIN 4103-1 Bewertetes Schalldämm-Maß Rw = 58,4 dB Wandhöhe bis circa 3,10 m (OKRB/OKRD bis UKRD) Umlaufende Anschlüsse starr Anforderungen an Befestigungen in den Hinweisen (Vorbemerkungen) Befestigungsuntergründe: Wand: Mauerwerk / Stahlbeton/ Metallständer Decke: Spannbetonhohlplattendecken (Betonwerkstoff) und oder Kassettendecken (Fertigbetonelemente) Schallentkopplung mittels Dämmstreifen Bauteilabtrennung durch Spezialpapierstreifen Breite 2 x 65 mm Ausführung mit Unterkonstruktion aus verzinkten Stahlblechprofilen DIN 18182-1 Wanddicke 125 mm beidseitige Beplankung nach DIN 18180 zweilagig Plattendicke 2*12,5 mm Metallständer CW 100 Ständerachsabstand ≤ 625 mm Boden und Deckenanschlüsse mit Randprofilen UW 100/40/06 Befestigung mit bauaufsichtlich zugelassenen Befestigungsmitteln Dämmschicht aus Mineralwolle nach DIN EN 13162: Dämmschicht aus Mineralwolle nach DIN EN 13162 Baustoffklasse A1, nichtbrennbar nach DIN 4102 und EN 13501-1 Dämmschicht Dicke mindestens 100 mm Wärmeleitfähigkeit λ ≤ 0,040 W/(mK) längenbezogener Strömungswiderstand nach DIN EN 29053: r ≥ 5 kPa·s/m² Rw = 58,4 dB Dämmschicht einlagig, dicht stoßen, abrutschsicher verlegen zweiseitige zweilagige Beplankung nachDIN 18180: 1. Seite: Beplankung aus Gipsplatten GKBI DIN 18180 bzw. Typ H2 EN 520 zweilagig Plattendicke 2*12,5 mm 2. Seite: Beplankung aus Gipsplatten GKBI DIN 18180 bzw. Typ H2 EN 520 zweilagig Plattendicke 2*12,5 mm Abmessungen: in circa (L*H) A=(3,03+3,19)*3,10 m A= 19,28 m² Verschraubung mit Schraubentyp XTN Verarbeitung gemäß DIN 18181 Verspachtelung der Gipsplatten gemäß Merkblatt Nr. 2 des Bundesverbandes der Gipsindustrie e.V. Qualitätsstufe Q3 bei Oberflächen ohne Fliesen Ausführung erfolgt unter Verwendung von DIN EN 13963, Spachtelmaterial Typ 4B oder alternativ Fügenfüller Typ 3B (muss für GKBI geeignet sein) einschließlich sämtlicher Nebenleistungen (Behelfe, Aufstiegshilfen, Befestigungen, Trennstreifen, Versiegelungen etc.) Abrechnung nach vollständiger Leistung nach Aufmaß in [m²] Ausführungsort: Aktionsbereich C (Sockelgeschoss - vgl. Lageplan/Grundriss) | E84: 19.5 | F84: m² | G84: =SUMPRODUCT((Kalkulation!A2:A50000=B84)*Kalkulation!D2:D50000) -> 0 | H84: =G84*E84 -> 0 | J84: =H84*(1-I84) -> 0 | K84: =B2 -> 0 | L84: da7efe4c-eaba-4e83-8dfc-14dc8326c6f2 | M84: fd1cf426-245a-47d6-9a3d-86dcc5a75168
A85: Position | B85: 05.001.040. | C85: Aktionsbereich D | D85: Trockenbauwand liefern und fachgerecht einbauen. Umfang: Trockenbauwand aus Ständerwerk mit beidseitiger doppelter Beplankung 1. Seite Wasserschutzklasse W1 2. Seite Wasserschutzklasse W0 Ausführung nach Zeichnungen und Details (u.a. W112.de) Anforderungen: Nichttragende innere Trennwand nach DIN 4103-1 Bewertetes Schalldämm-Maß Rw = 58,4 dB Wandhöhe bis circa 3,10 m (OKRB/OKRD bis UKRD) Umlaufende Anschlüsse starr Anforderungen an Befestigungen in den Hinweisen (Vorbemerkungen) Befestigungsuntergründe: Wand: Mauerwerk / Stahlbeton/ Metallständer Decke: Spannbetonhohlplattendecken (Betonwerkstoff) und oder Kassettendecken (Fertigbetonelemente) Schallentkopplung mittels Dämmstreifen Bauteilabtrennung durch Spezialpapierstreifen Breite 2 x 65 mm Ausführung mit Unterkonstruktion aus verzinkten Stahlblechprofilen DIN 18182-1 Wanddicke 125 mm beidseitige Beplankung nach DIN 18180 jeweils zweilagig Plattendicke 2*12,5 mm pro Seite Metallständer CW 75 Ständerachsabstand ≤ 625 mm Boden und Deckenanschlüsse mit Randprofilen UW 75/40/06 Befestigung mit bauaufsichtlich zugelassenen Befestigungsmitteln Dämmschicht aus Mineralwolle nach DIN EN 13162: Dämmschicht aus Mineralwolle nach DIN EN 13162 Baustoffklasse A1, nichtbrennbar nach DIN 4102 und EN 13501-1 Dämmschicht Dicke mindestens 70 mm Wärmeleitfähigkeit λ ≤ 0,040 W/(mK) längenbezogener Strömungswiderstand nach DIN EN 29053: r ≥ 5 kPa·s/m² Rw = 58,4 dB Dämmschicht einlagig, dicht stoßen, abrutschsicher verlegen beidseitige zweilagige Beplankung nachDIN 18180: 1. Seite: Beplankung aus Gipsplatten GKB-A DIN 18180 bzw. Typ A EN 520 zweilagig Plattendicke 2*12,5 mm 2. Seite: Beplankung aus Gipsplatten GKBI DIN 18180 bzw. Typ H2 EN 520 zweilagig Plattendicke 2*12,5 mm Abmessungen: in circa (L*H) A=(1,92+1,33+3,02+3,02+1,07+1,38)*3,10 m A= 36,39 m² Verschraubung mit Schraubentyp XTN Verarbeitung gemäß DIN 18181 Verspachtelung der Gipsplatten gemäß Merkblatt Nr. 2 des Bundesverbandes der Gipsindustrie e.V. Qualitätsstufe Q3 bei Oberflächen ohne Fliesen Ausführung erfolgt unter Verwendung von DIN EN 13963, Spachtelmaterial Typ 4B oder alternativ Fügenfüller Typ 3B (muss für GKBI geeignet sein) einschließlich sämtlicher Nebenleistungen (Behelfe, Aufstiegshilfen, Befestigungen, Trennstreifen, Versiegelungen etc.) Abrechnung nach vollständiger Leistung nach Aufmaß in [m²] Ausführungsort: Aktionsbereich D (Erdgeschoss - vgl. Lageplan/Grundriss) | E85: 36.5 | F85: m² | G85: =SUMPRODUCT((Kalkulation!A2:A50000=B85)*Kalkulation!D2:D50000) -> 0 | H85: =G85*E85 -> 0 | J85: =H85*(1-I85) -> 0 | K85: =B2 -> 0 | L85: da7efe4c-eaba-4e83-8dfc-14dc8326c6f2 | M85: 0f4a9f54-892f-4946-b5b9-90d5dd839d56
A86: Position | B86: 05.001.050. | C86: Aktionsbereich E | D86: Trockenbauwand liefern und fachgerecht einbauen. Umfang: Trockenbauwand aus Ständerwerk mit beidseitiger doppelter Beplankung 1. Seite Wasserschutzklasse W1 2. Seite Wasserschutzklasse W0 Ausführung nach Zeichnungen und Details (u.a. W112.de) Anforderungen: Nichttragende innere Trennwand nach DIN 4103-1 Bewertetes Schalldämm-Maß Rw = 58,4 dB Wandhöhe bis circa 3,10 m (OKRB/OKRD bis UKRD) Umlaufende Anschlüsse starr Anforderungen an Befestigungen in den Hinweisen (Vorbemerkungen) Befestigungsuntergründe: Wand: Mauerwerk / Stahlbeton/ Metallständer Decke: Spannbetonhohlplattendecken (Betonwerkstoff) und oder Kassettendecken (Fertigbetonelemente) Schallentkopplung mittels Dämmstreifen Bauteilabtrennung durch Spezialpapierstreifen Breite 2 x 65 mm Ausführung mit Unterkonstruktion aus verzinkten Stahlblechprofilen DIN 18182-1 Wanddicke 150 mm beidseitige Beplankung nach DIN 18180 jeweils zweilagig Plattendicke 2*12,5 mm pro Seite Metallständer CW 100 Ständerachsabstand ≤ 625 mm Boden und Deckenanschlüsse mit Randprofilen UW 100/40/06 Befestigung mit bauaufsichtlich zugelassenen Befestigungsmitteln Dämmschicht aus Mineralwolle nach DIN EN 13162: Dämmschicht aus Mineralwolle nach DIN EN 13162 Baustoffklasse A1, nichtbrennbar nach DIN 4102 und EN 13501-1 Dämmschicht Dicke mindestens 100 mm Wärmeleitfähigkeit λ ≤ 0,040 W/(mK) längenbezogener Strömungswiderstand nach DIN EN 29053: r ≥ 5 kPa·s/m² Rw = 58,4 dB Dämmschicht einlagig, dicht stoßen, abrutschsicher verlegen beidseitige zweilagige Beplankung nachDIN 18180: 1. Seite: Beplankung aus Gipsplatten GKB-A DIN 18180 bzw. Typ A EN 520 zweilagig Plattendicke 2*12,5 mm 2. Seite: Beplankung aus Gipsplatten GKBI DIN 18180 bzw. Typ H2 EN 520 zweilagig Plattendicke 2*12,5 mm Abmessungen: in circa (L*H) A=(2,62+4,16+2,90)*3,10 m A= 30,01 m² Verschraubung mit Schraubentyp XTN Verarbeitung gemäß DIN 18181 Verspachtelung der Gipsplatten gemäß Merkblatt Nr. 2 des Bundesverbandes der Gipsindustrie e.V. Qualitätsstufe Q3 bei Oberflächen ohne Fliesen Ausführung erfolgt unter Verwendung von DIN EN 13963, Spachtelmaterial Typ 4B oder alternativ Fügenfüller Typ 3B (muss für GKBI geeignet sein) einschließlich sämtlicher Nebenleistungen (Behelfe, Aufstiegshilfen, Befestigungen, Trennstreifen, Versiegelungen etc.) Abrechnung nach vollständiger Leistung nach Aufmaß in [m²] Ausführungsort: Aktionsbereich E (Erdgeschoss - vgl. Lageplan/Grundriss) | E86: 30.5 | F86: m² | G86: =SUMPRODUCT((Kalkulation!A2:A50000=B86)*Kalkulation!D2:D50000) -> 0 | H86: =G86*E86 -> 0 | J86: =H86*(1-I86) -> 0 | K86: =B2 -> 0 | L86: da7efe4c-eaba-4e83-8dfc-14dc8326c6f2 | M86: a76c5301-a653-4f0a-8b35-9d1452fa4671
